Workbook

Sheet Cover
B2: SITC International Holdings Co Ltd (1308.HK)
B3: Financial model - initiating coverage, 25 October 2026
B5: Key outputs (active scenario)
B6: Active scenario | C6: =Scenarios!D3 -> Base
B7: Share price (HK$) | C7: =Inputs!C6 -> 47.68
B8: Market cap (US$m) | C8: =Inputs!C16 -> 16487.785
B9: FY2026E diluted EPS (HK$) | C9: ='Income Statement'!H59 -> 4.2666165
B10: FY2027E diluted EPS (HK$) | C10: ='Income Statement'!I59 -> 3.4208878
B11: FY2026E P/E (x) | C11: =Inputs!C6/'Income Statement'!H59 -> 11.175131
B12: FY2027E P/E (x) | C12: =Inputs!C6/'Income Statement'!I59 -> 13.937902
B13: FY2026E DPS (HK$) | C13: ='Income Statement'!H60 -> 3.6192301
B14: FY2026E dividend yield | C14: ='Income Statement'!H60/Inputs!C6 -> 0.075906672
B15: Net cash excl. leases, YE2026E (US$m) | C15: ='Balance Sheet'!H53 -> 917.24481
B16: DCF value per share (HK$) | C16: =DCF!C53 -> 36.221802
B17: 12-month price target (HK$) | C17: ='Valuation Summary'!C20 -> 36.5
B18: Expected 12-month total return | C18: ='Valuation Summary'!C24 -> -0.15843555
B19: Rating | C19: ='Valuation Summary'!C25 -> SELL
B20: All checks pass | C20: =Checks!C47 -> TRUE
B22: Tabs
B23: Inputs | D23: Share price, FX, share count, declared dividends and opening balances.
B24: Scenarios | D24: Bull / Base / Bear drivers with selector (C3), common assumptions, and the stored scenario output table.
B25: Interim | D25: 1H25A, 2H25A, 1H26A, 2H26E, 9M and quarterly bridge; FY2026E volume and rate are 9M26 actuals plus a Q4 estimate.
B26: Revenue Model | D26: Fleet capacity, volume, freight rate and revenue streams (27 rows); revenue by geography (16 rows).
B27: Income Statement | D27: FY2021A-FY2030E, cost of sales by line, unit costs, EBIT/EBITDA, segment result, EPS and DPS.
B28: Cash Flow | D28: Indirect method; capex and newbuild instalments, dividends (declared vs paid), revolver and free cash flow.
B29: Balance Sheet | D29: Full statement of financial position; PPE, ROU, advances and lease roll-forwards; net cash; ROE.
B30: DCF Inputs | D30: Unlevered free cash flow after leases; bridge items; cycle reference per TEU.
B31: DCF | D31: WACC build, FY2027E-30E UFCF, Gordon terminal value, equity bridge and reverse DCF.
B32: Sensitivity | D32: WACC x g and revenue CAGR x EBITDA margin DCF grids; P/E x scenario EPS; FY2027E freight-rate sensitivity.
B33: Comps | D33: 12 listed container lines with statistical summary (max / 75th / median / 25th / min) and implied values.
B34: Valuation Summary | D34: Weighted price target, rating rule, cross-checks (DDM, justified P/B, scenarios) and probability weighting.
B35: Checks | D35: Balance, cash, tie-out of every historical total to the filings, scenario-store consistency.
B38: Conventions
B39: Blue | D39: Hard-coded input (reported historical figures and forecast assumptions)
B40: Black | D40: Formula
B41: Green | D41: Direct link to another tab
B42: Shaded columns | D42: Forecast periods (FY2026E-FY2030E; 2H26E and Q4 26E on Interim)
B44: Sources
B45: SITC annual reports 2022, 2023 and 2025; annual results announcements FY2018-FY2025; 2026 Interim Report (HKEX).
B46: Operating statistics for the nine months to 30-Sep-2026 and special dividend announcement (22-Oct-2026).
B47: Alphaliner Top 100 (25-Oct-2026) for fleet and order book; Yahoo Finance for price and FX (23-Oct-2026).
B48: Units: US$m unless stated (filings report US$'000). FY = year to 31 December.
B49: Prepared with AI assistance for professional review; not investment advice.

Sheet Inputs
A1: SITC International Holdings (1308.HK) - Inputs
A2: Market data and fixed inputs. Blue = input; black = formula; green = link to another tab.
A4: Item | B4: Unit | C4: Value | D4: Source / note
A5: Market data
A6: Share price (last close, 23-Oct-2026) | B6: HK$ | C6: 47.68 | D6: Yahoo Finance chart API, 1308.HK, close 23-Oct-2026
A7: HK$ per US$ | B7: HK$/US$ | C7: 7.8413 | D7: Yahoo Finance HKD=X, 23-Oct-2026
A8: 52-week high | B8: HK$ | C8: 52 | D8: Yahoo Finance, 1-year range
A9: 52-week low | B9: HK$ | C9: 26.22 | D9: Yahoo Finance, 1-year range
A10: Valuation date | B10: date | C10: 46320 | D10: Report date
A11: Share count
A12: Ordinary shares in issue | B12: m | C12: 2711.5282 | D12: HKEX monthly return for September 2026 (2,711,528,233 shares); includes ~34m held by the share-scheme trustee
A13: Dilution from outstanding share options | B13: m | C13: 0 | D13: 2026 Interim Report note 9: share options had no dilutive effect in 1H26
A14: Shares used for per-share value | B14: m | C14: =$C$12+$C$13 -> 2711.5282 | D14: Trustee-held scheme shares are deemed dilutive, so shares in issue is the diluted count
A15: Market capitalisation | B15: HK$m | C15: =$C$6*$C$14 -> 129285.67
A16: Market capitalisation | B16: US$m | C16: =$C$15/$C$7 -> 16487.785
A17: Dividends already declared
A18: FY2026 interim dividend (paid Sep-2026) | B18: HK$/sh | C18: 1.5 | D18: 2026 interim results announcement, 19-Aug-2026
A19: FY2026 special dividend (ex 4-Dec-2026, paid 17-Dec-2026) | B19: HK$/sh | C19: 1 | D19: Announcement 22-Oct-2026
A20: FY2026 dividends paid within 2026 | B20: HK$/sh | C20: =$C$18+$C$19 -> 2.5
A21: FY2025 final dividend paid in 2026 (cash) | B21: US$m | C21: 344.572 | D21: 1H26 dividends paid US$587.4m less the 2025 special payable of US$242.8m at 31-Dec-2025
A22: Opening balances for FY2021 growth rates
A23: Fleet capacity, 31-Dec-2020 | B23: TEU '000 | C23: 129.652 | D23: 2020 annual results announcement
A24: Container shipping volume, FY2020 | B24: TEU '000 | C24: 2614.203 | D24: 2020 annual results announcement
A25: Average freight rate excl. slot exchange, FY2020 | B25: US$/TEU | C25: 545.1 | D25: 2020 annual results announcement
A26: Cash and cash equivalents, 31-Dec-2020 | B26: US$m | C26: 61.139 | D26: 2022 Annual Report, consolidated statement of cash flows (2021 comparative)
A27: Financing policy
A28: Minimum cash and cash equivalents (revolver trigger) | B28: US$m | C28: 150 | D28: Our assumption; time deposits and FVTPL assets are set separately on Scenarios

Sheet Scenarios
A1: SITC International Holdings (1308.HK) - Scenarios
A2: Forecast drivers. Change C3 to switch the whole model between Bull (1), Base (2) and Bear (3).
A3: Active scenario (1 = Bull, 2 = Base, 3 = Bear) | C3: 2 | D3: =CHOOSE($C$3,"Bull","Base","Bear") -> Base
A4: Driver | B4: Unit | C4: FY2021A | D4: FY2022A | E4: FY2023A | F4: FY2024A | G4: FY2025A | H4: FY2026E | I4: FY2027E | J4: FY2028E | K4: FY2029E | L4: FY2030E | M4: Rationale / evidence
A5: Scenario drivers (Bull / Base / Bear; the Selected row feeds the model)
A6: Q4 2026 volume growth, year on year | B6: % | M6: 9M26 +5.9% YoY; Q4 2025 was a strong base (1.10m TEU)
A7: Bull | H7: 0.06
A8: Base | H8: 0.04
A9: Bear | H9: 0.01
A10: Selected | H10: =CHOOSE($C$3,H7,H8,H9) -> 0.04
A11: Q4 2026 average freight rate | B11: US$/TEU | M11: Q3 2026 implied US$865/TEU (Interim tab); Hormuz-related fuel and freight premium fading since July
A12: Bull | H12: 870
A13: Base | H13: 845
A14: Bear | H14: 810
A15: Selected | H15: =CHOOSE($C$3,H12,H13,H14) -> 845
A16: Container volume growth | B16: % | M16: FY2017-25 CAGR 6.3%; newbuild deliveries raise capacity ~10% a year in 2027-28
A17: Bull | I17: 0.07 | J17: 0.06 | K17: 0.05 | L17: 0.04
A18: Base | I18: 0.05 | J18: 0.05 | K18: 0.04 | L18: 0.035
A19: Bear | I19: 0.02 | J19: 0.03 | K19: 0.03 | L19: 0.03
A20: Selected | I20: =CHOOSE($C$3,I17,I18,I19) -> 0.05 | J20: =CHOOSE($C$3,J17,J18,J19) -> 0.05 | K20: =CHOOSE($C$3,K17,K18,K19) -> 0.04 | L20: =CHOOSE($C$3,L17,L18,L19) -> 0.035
A21: Average freight rate change | B21: % | M21: Base returns the rate to about the 2024-25 level by 2028; bear revisits the 2023 trough (US$623)
A22: Bull | I22: -0.03 | J22: 0 | K22: 0.01 | L22: 0.02
A23: Base | I23: -0.1 | J23: -0.05 | K23: 0 | L23: 0.01
A24: Bear | I24: -0.2 | J24: -0.08 | K24: 0 | L24: 0.02
A25: Selected | I25: =CHOOSE($C$3,I22,I23,I24) -> -0.1 | J25: =CHOOSE($C$3,J22,J23,J24) -> -0.05 | K25: =CHOOSE($C$3,K22,K23,K24) -> 0 | L25: =CHOOSE($C$3,L22,L23,L24) -> 0.01
A26: Vessel cost per average TEU slot, change | B26: % | M26: Charter-hire relief as global deliveries land; owned newbuilds carry depreciation instead
A27: Bull | I27: -0.03 | J27: -0.02 | K27: 0 | L27: 0.01
A28: Base | I28: -0.02 | J28: -0.01 | K28: 0.01 | L28: 0.015
A29: Bear | I29: 0 | J29: 0 | K29: 0.01 | L29: 0.02
A30: Selected | I30: =CHOOSE($C$3,I27,I28,I29) -> -0.02 | J30: =CHOOSE($C$3,J27,J28,J29) -> -0.01 | K30: =CHOOSE($C$3,K27,K28,K29) -> 0.01 | L30: =CHOOSE($C$3,L27,L28,L29) -> 0.015
A31: Other container logistics income growth | B31: % | M31: 1H26 +28.5% YoY
A32: Bull | H32: 0.25 | I32: 0.1 | J32: 0.08 | K32: 0.07 | L32: 0.06
A33: Base | H33: 0.22 | I33: 0.06 | J33: 0.05 | K33: 0.05 | L33: 0.04
A34: Bear | H34: 0.2 | I34: 0 | J34: 0.02 | K34: 0.03 | L34: 0.03
A35: Selected | H35: =CHOOSE($C$3,H32,H33,H34) -> 0.22 | I35: =CHOOSE($C$3,I32,I33,I34) -> 0.06 | J35: =CHOOSE($C$3,J32,J33,J34) -> 0.05 | K35: =CHOOSE($C$3,K32,K33,K34) -> 0.05 | L35: =CHOOSE($C$3,L32,L33,L34) -> 0.04
A36: Dividend payout (declared / attributable profit) | B36: % | M36: FY2021-25 payout 70-93% of EPS incl. specials; policy allows up to 100%
A37: Bull | H37: 0.9 | I37: 0.9 | J37: 0.9 | K37: 0.9 | L37: 0.9
A38: Base | H38: 0.85 | I38: 0.8 | J38: 0.8 | K38: 0.8 | L38: 0.8
A39: Bear | H39: 0.8 | I39: 0.7 | J39: 0.7 | K39: 0.7 | L39: 0.7
A40: Selected | H40: =CHOOSE($C$3,H37,H38,H39) -> 0.85 | I40: =CHOOSE($C$3,I37,I38,I39) -> 0.8 | J40: =CHOOSE($C$3,J37,J38,J39) -> 0.8 | K40: =CHOOSE($C$3,K37,K38,K39) -> 0.8 | L40: =CHOOSE($C$3,L37,L38,L39) -> 0.8
A42: Common assumptions (all scenarios)
A43: Fleet
A44: Newbuild deliveries | B44: TEU '000 | H44: 4 | I44: 26 | J44: 30 | K44: 6.2 | L44: 0 | M44: Alphaliner order book 66,232 TEU (25-Oct-2026), mostly for 2027-28 delivery; phasing is our estimate
A45: Disposals and charter redeliveries | B45: TEU '000 | H45: 1.7 | I45: 12 | J45: 15 | K45: 6 | L45: 4 | M45: Our estimate; fleet 187,297 TEU on Alphaliner 25-Oct-2026
A46: Average newbuild cost | B46: US$'000/TEU | H46: 13.4 | I46: 13.4 | J46: 13.4 | K46: 13.4 | L46: 13.4 | M46: US$763.3m commitments + US$124.3m advances at Jun-26 over ~66k TEU
A47: Revenue
A48: Slot exchange and other shipping income, % of freight revenue | B48: % | H48: 0.035 | I48: 0.035 | J48: 0.035 | K48: 0.035 | L48: 0.035 | M48: 1H26 3.5% (fewer lanes: 74 vs 82); FY2021-25 4-9%
A49: Other sources revenue | B49: US$m | H49: 2.6 | I49: 2.6 | J49: 2.6 | K49: 2.6 | L49: 2.6 | M49: FY2025 US$2.7m
A50: Greater China share of revenue | B50: % | H50: 0.48 | I50: 0.475 | J50: 0.47 | K50: 0.465 | L50: 0.46 | M50: FY2025 48.5%
A51: Southeast Asia share of revenue | B51: % | H51: 0.295 | I51: 0.3 | J51: 0.305 | K51: 0.31 | L51: 0.315 | M51: FY2025 28.8%; supply-chain relocation
A52: Japan share of revenue | B52: % | H52: 0.173 | I52: 0.172 | J52: 0.171 | K52: 0.17 | L52: 0.17 | M52: FY2025 17.5%
A53: Cost of sales
A54: Equipment and cargo transportation cost per TEU, FY2026E | B54: US$/TEU | H54: 276 | M54: 1H26 US$273.5; FY2025 US$284.1
A55: Equipment and cargo cost per TEU, growth | B55: % | I55: 0.015 | J55: 0.015 | K55: 0.015 | L55: 0.015 | M55: Port and trucking inflation
A56: Voyage cost per TEU, FY2026E | B56: US$/TEU | H56: 115.5 | M56: 1H26 US$115.0; 2H25 US$101.0; bunker up in 2026
A57: Voyage cost per TEU, change | B57: % | I57: -0.03 | J57: 0 | K57: 0.01 | L57: 0.01 | M57: Bunker normalisation, newer ships
A58: Vessel cost per average TEU slot, FY2026E | B58: US$/slot | H58: 1960 | M58: 1H26 annualised US$1,946; FY2025 US$1,804
A59: Other logistics costs, % of logistics income | B59: % | H59: 0.83 | I59: 0.83 | J59: 0.83 | K59: 0.83 | L59: 0.83 | M59: 1H26 83.4%; FY2025 82.9%
A60: Other costs, % of other sources revenue | B60: % | H60: 0.6 | I60: 0.6 | J60: 0.6 | K60: 0.6 | L60: 0.6 | M60: FY2025 61%
A61: Other income statement items
A62: Interest yield on opening cash, deposits and FVTPL | B62: % | H62: 0.035 | I62: 0.0325 | J62: 0.03 | K62: 0.03 | L62: 0.03 | M62: 1H26 US$16.6m on ~US$0.95bn; deposit rates falling
A63: Gain on disposal of vessels | B63: US$m | H63: 10 | I63: 5 | J63: 5 | K63: 5 | L63: 5 | M63: 1H26 US$6.2m (one vessel)
A64: Disposal proceeds | B64: US$m | H64: 30 | I64: 15 | J64: 15 | K64: 15 | L64: 15 | M64: 1H26 US$24.9m
A65: Other income and gains (excl. interest and disposals) | B65: US$m | H65: 12 | I65: 10 | J65: 10 | K65: 10 | L65: 10 | M65: FY2021-25 US$8-19m
A66: Administrative expenses growth | B66: % | H66: 0.13 | I66: 0.05 | J66: 0.04 | K66: 0.04 | L66: 0.04 | M66: 1H26 +17.1% (staff costs)
A67: Other expenses, net | B67: US$m | H67: 4 | I67: 4 | J67: 4 | K67: 4 | L67: 4 | M67: FY2021-25 US$1-6m
A68: Finance cost rate on opening leases and bank debt | B68: % | H68: 0.043 | I68: 0.043 | J68: 0.043 | K68: 0.043 | L68: 0.043 | M68: 1H26 annualised 4.3%
A69: Share of JV profits, growth | B69: % | H69: 0.16 | I69: 0.04 | J69: 0.03 | K69: 0.03 | L69: 0.03 | M69: 1H26 +25.9%
A70: Share of associates | B70: US$m | H70: 1.5 | I70: 1.5 | J70: 1.5 | K70: 1.5 | L70: 1.5 | M70: FY2025 US$1.7m
A71: JV dividends received, % of JV profit | B71: % | H71: 0.85 | I71: 0.85 | J71: 0.85 | K71: 0.85 | L71: 0.85 | M71: FY2025 89%
A72: Effective tax rate | B72: % | H72: 0.017 | I72: 0.017 | J72: 0.017 | K72: 0.017 | L72: 0.017 | M72: Shipping income largely exempt; FY2025 1.7%, 1H26 1.7%
A73: Non-controlling interests, % of profit | B73: % | H73: 0.006 | I73: 0.006 | J73: 0.006 | K73: 0.006 | L73: 0.006 | M73: FY2025 0.6%
A74: Share award expense | B74: US$m | H74: 25 | I74: 25 | J74: 25 | K74: 25 | L74: 25 | M74: FY2022-25 US$27-28m
A75: Fixed assets, leases and capex
A76: PPE depreciation, % of opening PPE | B76: % | H76: 0.064 | I76: 0.064 | J76: 0.064 | K76: 0.064 | L76: 0.064 | M76: FY2025 6.3%; 1H26 annualised 6.4%
A77: ROU depreciation, % of opening ROU assets | B77: % | H77: 0.21 | I77: 0.21 | J77: 0.21 | K77: 0.21 | L77: 0.21 | M77: 1H26 annualised 20.6%
A78: New leases (ROU additions) | B78: US$m | H78: 70 | I78: 75 | J78: 75 | K78: 75 | L78: 75 | M78: Keeps the chartered fleet roughly flat
A79: Lease principal paid, x ROU depreciation | B79: x | H79: 1.12 | I79: 1.12 | J79: 1.12 | K79: 1.12 | L79: 1.12 | M79: FY2023-25 1.08-1.21x; 1H26 1.10x
A80: Current share of lease liabilities | B80: % | H80: 0.225 | I80: 0.225 | J80: 0.225 | K80: 0.225 | L80: 0.225 | M80: Jun-26 22.8%
A81: Newbuild instalments (current order book) | B81: US$m | H81: 132 | I81: 330 | J81: 300 | K81: 73.1 | L81: 0 | M81: 1H26 US$71.9m paid; US$763.3m committed at Jun-26; phasing is our estimate
A82: Instalments on future fleet-renewal orders | B82: US$m | H82: 0 | I82: 0 | J82: 0 | K82: 75 | L82: 150 | M82: Our assumption: renewal ordering resumes from 2029
A83: Other capex (containers, equipment, dry-docking) | B83: US$m | H83: 30 | I83: 60 | J83: 60 | K83: 60 | L83: 60 | M83: 1H26 PPE purchases US$5.5m
A84: Working capital
A85: Trade receivables, days of revenue | B85: days | H85: 21 | I85: 21 | J85: 21 | K85: 21 | L85: 21 | M85: FY2025 19.7; Jun-26 23.4
A86: Bunkers, days of voyage costs | B86: days | H86: 45 | I86: 45 | J86: 45 | K86: 45 | L86: 45 | M86: FY2025 46.6
A87: Prepayments and other receivables, % of revenue | B87: % | H87: 0.013 | I87: 0.013 | J87: 0.013 | K87: 0.013 | L87: 0.013 | M87: FY2024-25 1.1-1.8%
A88: Trade payables, days of cost of sales | B88: days | H88: 41 | I88: 41 | J88: 41 | K88: 41 | L88: 41 | M88: FY2025 40.9
A89: Other payables and accruals, % of revenue | B89: % | H89: 0.047 | I89: 0.047 | J89: 0.047 | K89: 0.047 | L89: 0.047 | M89: FY2025 4.8%
A90: Income tax payable, % of tax charge | B90: % | H90: 0.2 | I90: 0.2 | J90: 0.2 | K90: 0.2 | L90: 0.2 | M90: FY2025 18.6%
A91: Treasury, shares and dividends
A92: Time deposits over three months (year end) | B92: US$m | H92: 650 | I92: 650 | J92: 650 | K92: 650 | L92: 650 | M92: Jun-26 US$720.2m
A93: Financial assets at FVTPL (year end) | B93: US$m | H93: 75 | I93: 75 | J93: 75 | K93: 75 | L93: 75 | M93: Jun-26 US$73.7m
A94: Existing bank loans (year end) | B94: US$m | H94: 30 | I94: 0 | J94: 0 | K94: 0 | L94: 0 | M94: Jun-26 US$33.1m
A95: Dividend payable at year end | B95: US$m | H95: 0 | I95: 0 | J95: 0 | K95: 0 | L95: 0 | M95: Only the Dec-2025 special was declared before and paid after a year end
A96: Share purchases for the share scheme | B96: US$m | H96: 5 | I96: 5 | J96: 5 | K96: 5 | L96: 5 | M96: FY2025 US$0.9m; FY2021-23 US$22-48m
A97: Dividends to NCI, % of NCI profit | B97: % | H97: 0.3 | I97: 0.3 | J97: 0.3 | K97: 0.3 | L97: 0.3 | M97: Our assumption
A98: Share of declared dividend paid within the year | B98: % | I98: 0.55 | J98: 0.55 | K98: 0.55 | L98: 0.55 | M98: Interim + specials; FY2026 uses the declared HK$2.50 (Inputs)
A99: Weighted average basic shares | B99: m | H99: 2672 | I99: 2680 | J99: 2688 | K99: 2696 | L99: 2704 | M99: 1H26 2,669.6m; scheme shares vest over time
A100: Dilutive shares (scheme shares held by trustee) | B100: m | H100: 34 | I100: 34 | J100: 34 | K100: 34 | L100: 34 | M100: 1H26 33.9m
A102: Scenario outputs: values stored from full model runs with C3 = 1, 2, 3; "Live" follows the active scenario
...

Sheet Interim
A1: SITC International Holdings (1308.HK) - Interim
A2: Half-year and quarterly bridge. 1H and 9M actuals from HKEX filings; 2H and Q4 derived; FY2026E links to the annual model.
A4: US$m unless stated | B4: Unit | C4: 1H25A | D4: 2H25A | E4: FY2025A | F4: 1H26A | G4: 2H26E | H4: FY2026E | I4: 9M25A | J4: 9M26A | K4: Q4 25A | L4: Q4 26E | M4: Q3 25A | N4: Q3 26A | O4: Note
A5: Operating statistics
A6: Container shipping volume | B6: TEU '000 | C6: 1829.665 | D6: =E6-C6 -> 2017.874 | E6: ='Revenue Model'!G12 -> 3847.539 | F6: 1971.942 | G6: =H6-F6 -> 2081.7778 | H6: =J6+L6 -> 4053.7198 | I6: 2749.844 | J6: 2912.117 | K6: =E6-I6 -> 1097.695 | L6: =K6*(1+Scenarios!H10) -> 1141.6028 | M6: =I6-C6 -> 920.179 | N6: =J6-F6 -> 940.175 | O6: Interim reports; 9M operating statistics announcements (22-Oct-2026)
A7: Volume growth, year on year | B7: % | F7: =F6/C6-1 -> 0.07776123 | G7: =G6/D6-1 -> 0.031668875 | H7: =H6/E6-1 -> 0.053587709 | J7: =J6/I6-1 -> 0.059011711 | L7: =L6/K6-1 -> 0.04 | N7: =N6/M6-1 -> 0.021730555
A8: Average freight rate (excl. slot exchange) | B8: US$/TEU | C8: 776.4 | D8: =(E8*E6-C8*C6)/D6 -> 732.35456 | E8: ='Revenue Model'!G15 -> 753.3 | F8: 807.2 | G8: =(H8*H6-F8*F6)/G6 -> 854.08741 | H8: =(J8*J6+L8*L6)/H6 -> 831.27891 | I8: 754.9 | J8: 825.9 | K8: =(E8*E6-I8*I6)/K6 -> 749.29183 | L8: =Scenarios!H15 -> 845 | M8: =(I8*I6-C8*C6)/M6 -> 712.14984 | N8: =(J8*J6-F8*F6)/N6 -> 865.12176 | O8: Q4 and Q3 rates derived from cumulative period averages
A9: Freight rate change, year on year | B9: % | F9: =F8/C8-1 -> 0.039670273 | G9: =G8/D8-1 -> 0.1662212 | H9: =H8/E8-1 -> 0.10351641 | J9: =J8/I8-1 -> 0.094052192 | L9: =L8/K8-1 -> 0.1277315 | N9: =N8/M8-1 -> 0.21480299
A10: Revenue | B10: US$m | C10: =C18 -> 1664.489 | D10: =D18 -> 1747.158 | E10: =E18 -> 3411.647 | F10: =F18 -> 1842.065 | G10: =G18 -> 2052.2664 | H10: =H18 -> 3894.3314 | I10: 2458.9 | J10: 2808.1 | K10: =E10-I10 -> 952.747 | L10: =H10-J10 -> 1086.2314 | M10: =I10-C10 -> 794.411 | N10: =J10-F10 -> 966.035 | O10: 9M figures are rounded to US$0.1m in the announcements
A11: Revenue growth, year on year | B11: % | F11: =F10/C10-1 -> 0.10668499 | G11: =G10/D10-1 -> 0.17463129 | H11: =H10/E10-1 -> 0.14148136 | J11: =J10/I10-1 -> 0.14201472 | L11: =L10/K10-1 -> 0.14010482 | N11: =N10/M10-1 -> 0.2160393
A12: Revenue per TEU lifted | B12: US$/TEU | C12: =C10/C6*1000 -> 909.72336 | D12: =D10/D6*1000 -> 865.84098 | E12: =E10/E6*1000 -> 886.70888 | F12: =F10/F6*1000 -> 934.13752 | G12: =G10/G6*1000 -> 985.82397 | H12: =H10/H6*1000 -> 960.68096 | I12: =I10/I6*1000 -> 894.19618 | J12: =J10/J6*1000 -> 964.28131 | ... N12: =N10/N6*1000 -> 1027.5055
A14: Half-year income statement
A15: Container shipping and supporting logistics income | B15: US$m | C15: 1512.689 | D15: =E15-C15 -> 1565.129 | E15: ='Income Statement'!G6 -> 3077.818 | F15: 1646.812 | G15: =H15-F15 -> 1840.9018 | H15: ='Income Statement'!H6 -> 3487.7138
A16: Other container logistics income | B16: US$m | C16: 150.696 | D16: =E16-C16 -> 180.466 | E16: ='Income Statement'!G7 -> 331.162 | F16: 193.678 | G16: =H16-F16 -> 210.33964 | H16: ='Income Statement'!H7 -> 404.01764
A17: Other sources | B17: US$m | C17: 1.104 | D17: =E17-C17 -> 1.563 | E17: ='Income Statement'!G8 -> 2.667 | F17: 1.575 | G17: =H17-F17 -> 1.025 | H17: ='Income Statement'!H8 -> 2.6
A18: Total revenue | B18: US$m | C18: =C15+C16+C17 -> 1664.489 | D18: =D15+D16+D17 -> 1747.158 | E18: =E15+E16+E17 -> 3411.647 | F18: =F15+F16+F17 -> 1842.065 | G18: =G15+G16+G17 -> 2052.2664 | H18: =H15+H16+H17 -> 3894.3314
A19: Equipment and cargo transportation costs | B19: US$m | C19: -520.451 | D19: =E19-C19 -> -572.715 | E19: ='Income Statement'!G12 -> -1093.166 | F19: -539.361 | G19: =H19-F19 -> -579.46566 | H19: ='Income Statement'!H12 -> -1118.8267
A20: Voyage costs | B20: US$m | C20: -198.651 | D20: =E20-C20 -> -203.795 | E20: ='Income Statement'!G13 -> -402.446 | F20: -226.702 | G20: =H20-F20 -> -241.50264 | H20: ='Income Statement'!H13 -> -468.20464
A21: Container shipping vessel costs | B21: US$m | C21: -151.911 | D21: =E21-C21 -> -177.515 | E21: ='Income Statement'!G14 -> -329.426 | F21: -180.231 | G21: =H21-F21 -> -184.54656 | H21: ='Income Statement'!H14 -> -364.77756
A22: Other container logistics costs | B22: US$m | C22: -123.697 | D22: =E22-C22 -> -150.831 | E22: ='Income Statement'!G15 -> -274.528 | F22: -161.511 | G22: =H22-F22 -> -173.82364 | H22: ='Income Statement'!H15 -> -335.33464
A23: Other costs | B23: US$m | C23: -0.348 | D23: =E23-C23 -> -1.267 | E23: ='Income Statement'!G16 -> -1.615 | F23: -1.027 | G23: =H23-F23 -> -0.533 | H23: ='Income Statement'!H16 -> -1.56
A24: Total cost of sales | B24: US$m | C24: =SUM(C19:C23) -> -995.058 | D24: =SUM(D19:D23) -> -1106.123 | E24: =SUM(E19:E23) -> -2101.181 | F24: =SUM(F19:F23) -> -1108.832 | G24: =SUM(G19:G23) -> -1179.8715 | H24: =SUM(H19:H23) -> -2288.7035
A25: Gross profit | B25: US$m | C25: =C18+C24 -> 669.431 | D25: =D18+D24 -> 641.035 | E25: =E18+E24 -> 1310.466 | F25: =F18+F24 -> 733.233 | G25: =G18+G24 -> 872.39495 | H25: =H18+H24 -> 1605.6279
A26: Gross margin | B26: % | C26: =C25/C18 -> 0.40218409 | D26: =D25/D18 -> 0.36690156 | E26: =E25/E18 -> 0.38411536 | F26: =F25/F18 -> 0.39804947 | G26: =G25/G18 -> 0.42508854 | H26: =H25/H18 -> 0.41229874
A27: Other income and gains (excl. interest) | B27: US$m | C27: 18.04 | D27: =E27-C27 -> 26.987 | E27: ='Income Statement'!G29+'Income Statement'!G30 -> 45.027 | F27: 13.511 | G27: =H27-F27 -> 8.489 | H27: ='Income Statement'!H29+'Income Statement'!H30 -> 22 | O27: 1H26 incl. US$6.2m vessel disposal gain (1H25 US$13.8m)
A28: Administrative expenses | B28: US$m | C28: -67.809 | D28: =E28-C28 -> -85.769 | E28: ='Income Statement'!G31 -> -153.578 | F28: -79.445 | G28: =H28-F28 -> -94.09814 | H28: ='Income Statement'!H31 -> -173.54314
A29: Other expenses, net | B29: US$m | C29: -1.673 | D29: =E29-C29 -> -4.013 | E29: ='Income Statement'!G33 -> -5.686 | F29: -1.804 | G29: =H29-F29 -> -2.196 | H29: ='Income Statement'!H33 -> -4
A30: Share of JV profits | B30: US$m | C30: 13.348 | D30: =E30-C30 -> 17.732 | E30: ='Income Statement'!G41 -> 31.08 | F30: 16.81 | G30: =H30-F30 -> 19.2428 | H30: ='Income Statement'!H41 -> 36.0528
A31: Share of associates | B31: US$m | C31: 0.954 | D31: =E31-C31 -> 0.725 | E31: ='Income Statement'!G42 -> 1.679 | F31: 0.525 | G31: =H31-F31 -> 0.975 | H31: ='Income Statement'!H42 -> 1.5
A32: Segment results | B32: US$m | C32: =C25+C27+C28+C29+C30+C31 -> 632.291 | D32: =D25+D27+D28+D29+D30+D31 -> 596.697 | E32: =E25+E27+E28+E29+E30+E31 -> 1228.988 | F32: =F25+F27+F28+F29+F30+F31 -> 682.83 | G32: =G25+G27+G28+G29+G30+G31 -> 804.80761 | H32: =H25+H27+H28+H29+H30+H31 -> 1487.6376
A33: Finance costs | B33: US$m | C33: -8.466 | D33: =E33-C33 -> -7.084 | E33: ='Income Statement'!G45 -> -15.55 | F33: -6.995 | G33: =H33-F33 -> -6.947578 | H33: ='Income Statement'!H45 -> -13.942578
A34: Bank interest income and FV gains | B34: US$m | C34: 19.782 | D34: =E34-C34 -> 18.049 | E34: ='Income Statement'!G44 -> 37.831 | F34: 16.569 | G34: =H34-F34 -> 16.63249 | H34: ='Income Statement'!H44 -> 33.20149
A35: Profit before tax | B35: US$m | C35: =C32+C33+C34 -> 643.607 | D35: =D32+D33+D34 -> 607.662 | E35: =E32+E33+E34 -> 1251.269 | F35: =F32+F33+F34 -> 692.404 | G35: =G32+G33+G34 -> 814.49252 | H35: =H32+H33+H34 -> 1506.8965
A36: Income tax | B36: US$m | C36: -10.159 | D36: =E36-C36 -> -10.708 | E36: ='Income Statement'!G47 -> -20.867 | F36: -11.935 | G36: =H36-F36 -> -13.682241 | H36: ='Income Statement'!H47 -> -25.617241
A37: Profit for the period | B37: US$m | C37: =C35+C36 -> 633.448 | D37: =D35+D36 -> 596.954 | E37: =E35+E36 -> 1230.402 | F37: =F35+F36 -> 680.469 | G37: =G35+G36 -> 800.81028 | H37: =H35+H36 -> 1481.2793
A38: Non-controlling interests | B38: US$m | C38: -3.453 | D38: =E38-C38 -> -4.062 | E38: ='Income Statement'!G51 -> -7.515 | F38: -3.928 | G38: =H38-F38 -> -4.9596757 | H38: ='Income Statement'!H51 -> -8.8876757
A39: Profit attributable to shareholders | B39: US$m | C39: =C37+C38 -> 629.995 | D39: =D37+D38 -> 592.892 | E39: =E37+E38 -> 1222.887 | F39: =F37+F38 -> 676.541 | G39: =G37+G38 -> 795.8506 | H39: =H37+H38 -> 1472.3916
A40: Depreciation of PPE (memo) | B40: US$m | C40: 57.211 | D40: =E40-C40 -> 58.803 | E40: ='Income Statement'!G36 -> 116.014 | F40: 57.516 | G40: =H40-F40 -> 57.25904 | H40: ='Income Statement'!H36 -> 114.77504
A41: Depreciation of ROU assets (memo) | B41: US$m | C41: 27.523 | D41: =E41-C41 -> 36.708 | E41: ='Income Statement'!G37 -> 64.231 | F41: 33.656 | G41: =H41-F41 -> 34.83424 | H41: ='Income Statement'!H37 -> 68.49024
A43: Half-year unit economics
A44: Equipment and cargo cost per TEU | B44: US$/TEU | C44: =-C19/C6*1000 -> 284.45153 | D44: =-D19/D6*1000 -> 283.82099 | E44: =-E19/E6*1000 -> 284.12084 | F44: =-F19/F6*1000 -> 273.51768 | G44: =-G19/G6*1000 -> 278.35135 | H44: =-H19/H6*1000 -> 276
A45: Voyage cost per TEU | B45: US$/TEU | C45: =-C20/C6*1000 -> 108.57233 | D45: =-D20/D6*1000 -> 100.99491 | E45: =-E20/E6*1000 -> 104.59829 | F45: =-F20/F6*1000 -> 114.96383 | G45: =-G20/G6*1000 -> 116.00788 | H45: =-H20/H6*1000 -> 115.5
A46: Total cost of sales per TEU | B46: US$/TEU | C46: =-C24/C6*1000 -> 543.8471 | D46: =-D24/D6*1000 -> 548.16257 | E46: =-E24/E6*1000 -> 546.11038 | F46: =-F24/F6*1000 -> 562.30457 | G46: =-G24/G6*1000 -> 566.7615 | H46: =-H24/H6*1000 -> 564.59341
A47: Gross profit per TEU | B47: US$/TEU | C47: =C25/C6*1000 -> 365.87627 | D47: =D25/D6*1000 -> 317.67841 | E47: =E25/E6*1000 -> 340.5985 | F47: =F25/F6*1000 -> 371.83294 | G47: =G25/G6*1000 -> 419.06247 | H47: =H25/H6*1000 -> 396.08755
A48: Segment result margin | B48: % | C48: =C32/C18 -> 0.37987094 | D48: =D32/D18 -> 0.34152435 | E48: =E32/E18 -> 0.36023305 | F48: =F32/F18 -> 0.37068725 | G48: =G32/G18 -> 0.39215551 | H48: =H32/H18 -> 0.38200077

Sheet Revenue Model
A1: SITC International Holdings (1308.HK) - Revenue Model
A2: Fleet, volume and freight-rate drivers; revenue by stream and by geography. US$m unless stated.
A4: US$m unless stated | B4: Unit | C4: FY2021A | D4: FY2022A | E4: FY2023A | F4: FY2024A | G4: FY2025A | H4: FY2026E | I4: FY2027E | J4: FY2028E | K4: FY2029E | L4: FY2030E | M4: Source / assumption
A5: A. Fleet, volume and freight rate
A6: Fleet capacity, start of year | B6: TEU '000 | C6: =Inputs!$C$23 -> 129.652 | D6: =C9 -> 143.115 | E6: =D9 -> 162.701 | F6: =E9 -> 162.851 | G6: =F9 -> 180.255 | H6: =G9 -> 184.961 | I6: =H9 -> 187.261 | J6: =I9 -> 201.261 | K6: =J9 -> 216.261 | L6: =K9 -> 216.461
A7: Newbuild deliveries | B7: TEU '000 | H7: =Scenarios!H44 -> 4 | I7: =Scenarios!I44 -> 26 | J7: =Scenarios!J44 -> 30 | K7: =Scenarios!K44 -> 6.2 | L7: =Scenarios!L44 -> 0
A8: Disposals and charter redeliveries | B8: TEU '000 | H8: =Scenarios!H45 -> 1.7 | I8: =Scenarios!I45 -> 12 | J8: =Scenarios!J45 -> 15 | K8: =Scenarios!K45 -> 6 | L8: =Scenarios!L45 -> 4
A9: Fleet capacity, year end | B9: TEU '000 | C9: 143.115 | D9: 162.701 | E9: 162.851 | F9: 180.255 | G9: 184.961 | H9: =H6+H7-H8 -> 187.261 | I9: =I6+I7-I8 -> 201.261 | J9: =J6+J7-J8 -> 216.261 | K9: =K6+K7-K8 -> 216.461 | L9: =L6+L7-L8 -> 212.461 | M9: Annual reports (operated fleet incl. chartered); 2025: 119 vessels
A10: Fleet capacity growth | B10: % | C10: =C9/C6-1 -> 0.10383951 | D10: =D9/D6-1 -> 0.13685498 | E10: =E9/E6-1 -> 0.00092193656 | F10: =F9/F6-1 -> 0.1068707 | G10: =G9/G6-1 -> 0.026107459 | H10: =H9/H6-1 -> 0.012435054 | I10: =I9/I6-1 -> 0.074761963 | J10: =J9/J6-1 -> 0.074530088 | ... L10: =L9/L6-1 -> -0.018479079
A11: Average fleet capacity | B11: TEU '000 | C11: =AVERAGE(C6,C9) -> 136.3835 | D11: =AVERAGE(D6,D9) -> 152.908 | E11: =AVERAGE(E6,E9) -> 162.776 | F11: =AVERAGE(F6,F9) -> 171.553 | G11: =AVERAGE(G6,G9) -> 182.608 | H11: =AVERAGE(H6,H9) -> 186.111 | I11: =AVERAGE(I6,I9) -> 194.261 | J11: =AVERAGE(J6,J9) -> 208.761 | ... L11: =AVERAGE(L6,L9) -> 214.461
A12: Container shipping volume | B12: TEU '000 | C12: 3142.118 | D12: 3261.939 | E12: 3224.498 | F12: 3570.184 | G12: 3847.539 | H12: =Interim!H6 -> 4053.7198 | I12: =H12*(1+Scenarios!I20) -> 4256.4058 | J12: =I12*(1+Scenarios!J20) -> 4469.2261 | K12: =J12*(1+Scenarios!K20) -> 4647.9951 | L12: =K12*(1+Scenarios!L20) -> 4810.675 | M12: Annual results; FY2026E = 9M26 actual + Q4 estimate (Interim tab)
A13: Volume growth | B13: % | C13: =C12/Inputs!$C$24-1 -> 0.20194109 | D13: =D12/C12-1 -> 0.038133832 | E13: =E12/D12-1 -> -0.011478142 | F13: =F12/E12-1 -> 0.10720614 | G13: =G12/F12-1 -> 0.077686472 | H13: =H12/G12-1 -> 0.053587709 | I13: =I12/H12-1 -> 0.05 | J13: =J12/I12-1 -> 0.05 | K13: =K12/J12-1 -> 0.04 | L13: =L12/K12-1 -> 0.035
A14: Liftings per average TEU slot | B14: x | C14: =C12/C11 -> 23.038843 | D14: =D12/D11 -> 21.33269 | E14: =E12/E11 -> 19.809419 | F14: =F12/F11 -> 20.810968 | G14: =G12/G11 -> 21.069937 | H14: =H12/H11 -> 21.781194 | I14: =I12/I11 -> 21.910758 | J14: =J12/J11 -> 21.408338 | ... L14: =L12/L11 -> 22.431468 | M14: Asset turns: volume / average capacity
A15: Average freight rate (excl. slot exchange) | B15: US$/TEU | C15: 826.9 | D15: 1099.6 | E15: 623.3 | F15: 721.1 | G15: 753.3 | H15: =Interim!H8 -> 831.27891 | I15: =H15*(1+Scenarios!I25) -> 748.15102 | J15: =I15*(1+Scenarios!J25) -> 710.74347 | K15: =J15*(1+Scenarios!K25) -> 710.74347 | L15: =K15*(1+Scenarios!L25) -> 717.85091
A16: Freight rate change | B16: % | C16: =C15/Inputs!$C$25-1 -> 0.51696936 | D16: =D15/C15-1 -> 0.32978595 | E16: =E15/D15-1 -> -0.43315751 | F16: =F15/E15-1 -> 0.15690679 | G16: =G15/F15-1 -> 0.044654001 | H16: =H15/G15-1 -> 0.10351641 | I16: =I15/H15-1 -> -0.1 | J16: =J15/I15-1 -> -0.05 | K16: =K15/J15-1 -> 0 | L16: =L15/K15-1 -> 0.01
A17: Freight revenue (volume x rate) | B17: US$m | C17: =C12*C15/1000 -> 2598.2174 | D17: =D12*D15/1000 -> 3586.8281 | E17: =E12*E15/1000 -> 2009.8296 | F17: =F12*F15/1000 -> 2574.4597 | G17: =G12*G15/1000 -> 2898.3511 | H17: =H12*H15/1000 -> 3369.7718 | I17: =I12*I15/1000 -> 3184.4343 | J17: =J12*J15/1000 -> 3176.4733 | ... L17: =L12*L15/1000 -> 3453.3474
A18: Slot exchange and other, % of freight revenue | B18: % | C18: =C19/C17 -> 0.040639643 | D18: =D19/D17 -> 0.062444273 | E18: =E19/E17 -> 0.093369307 | F18: =F19/F17 -> 0.062540625 | G18: =G19/G17 -> 0.061920334 | H18: =Scenarios!H48 -> 0.035 | I18: =Scenarios!I48 -> 0.035 | J18: =Scenarios!J48 -> 0.035 | K18: =Scenarios!K48 -> 0.035 | L18: =Scenarios!L48 -> 0.035
A19: Slot exchange, surcharges and other shipping income | B19: US$m | C19: =C20-C17 -> 105.59063 | D19: =D20-D17 -> 223.97688 | E19: =E20-E17 -> 187.6564 | F19: =F20-F17 -> 161.00832 | G19: =G20-G17 -> 179.46687 | H19: =H17*H18 -> 117.94201 | I19: =I17*I18 -> 111.4552 | J19: =J17*J18 -> 111.17656 | K19: =K17*K18 -> 115.62363 | L19: =L17*L18 -> 120.86716 | M19: Historical figures are the residual of reported shipping income
A20: Container shipping and supporting logistics income | B20: US$m | C20: 2703.808 | D20: 3810.805 | E20: 2197.486 | F20: 2735.468 | G20: 3077.818 | H20: =H17+H19 -> 3487.7138 | I20: =I17+I19 -> 3295.8895 | J20: =J17+J19 -> 3287.6498 | K20: =K17+K19 -> 3419.1558 | L20: =L17+L19 -> 3574.2145
A21: Growth | B21: % | D21: =D20/C20-1 -> 0.40942145 | E21: =E20/D20-1 -> -0.42335386 | F21: =F20/E20-1 -> 0.24481703 | G21: =G20/F20-1 -> 0.12515226 | H21: =H20/G20-1 -> 0.1331774 | I21: =I20/H20-1 -> -0.055 | J21: =J20/I20-1 -> -0.0025 | K21: =K20/J20-1 -> 0.04 | L21: =L20/K20-1 -> 0.04535
A22: Shipping income per TEU lifted | B22: US$/TEU | C22: =C20/C12*1000 -> 860.50492 | D22: =D20/D12*1000 -> 1168.2637 | E22: =E20/E12*1000 -> 681.49709 | F22: =F20/F12*1000 -> 766.19804 | G22: =G20/G12*1000 -> 799.94459 | H22: =H20/H12*1000 -> 860.37368 | I22: =I20/I12*1000 -> 774.33631 | J22: =J20/J12*1000 -> 735.61949 | ... L22: =L20/L12*1000 -> 742.97569
A23: Other container logistics income | B23: US$m | C23: 279.422 | D23: 291.418 | E23: 224.682 | F23: 320.394 | G23: 331.162 | H23: =G23*(1+Scenarios!H35) -> 404.01764 | I23: =H23*(1+Scenarios!I35) -> 428.2587 | J23: =I23*(1+Scenarios!J35) -> 449.67163 | K23: =J23*(1+Scenarios!K35) -> 472.15521 | L23: =K23*(1+Scenarios!L35) -> 491.04142 | M23: Freight forwarding, depots, warehousing, trucking
A24: Growth | B24: % | D24: =D23/C23-1 -> 0.04293148 | E24: =E23/D23-1 -> -0.22900439 | F24: =F23/E23-1 -> 0.42598873 | G24: =G23/F23-1 -> 0.033608619 | H24: =H23/G23-1 -> 0.22 | I24: =I23/H23-1 -> 0.06 | J24: =J23/I23-1 -> 0.05 | K24: =K23/J23-1 -> 0.05 | L24: =L23/K23-1 -> 0.04
A25: Logistics income per TEU lifted | B25: US$/TEU | C25: =C23/C12*1000 -> 88.927914 | D25: =D23/D12*1000 -> 89.338887 | E25: =E23/E12*1000 -> 69.679683 | F25: =F23/F12*1000 -> 89.741593 | G25: =G23/G12*1000 -> 86.071122 | H25: =H23/H12*1000 -> 99.665902 | I25: =I23/I12*1000 -> 100.6151 | J25: =J23/J12*1000 -> 100.6151 | ... L25: =L23/L12*1000 -> 102.07329
A26: Other sources (dry bulk and other) | B26: US$m | C26: 29.217 | D26: 10.732 | E26: 6.791 | F26: 2.197 | G26: 2.667 | H26: =Scenarios!H49 -> 2.6 | I26: =Scenarios!I49 -> 2.6 | J26: =Scenarios!J49 -> 2.6 | K26: =Scenarios!K49 -> 2.6 | L26: =Scenarios!L49 -> 2.6
A27: Total revenue | B27: US$m | C27: =C20+C23+C26 -> 3012.447 | D27: =D20+D23+D26 -> 4112.955 | E27: =E20+E23+E26 -> 2428.959 | F27: =F20+F23+F26 -> 3058.059 | G27: =G20+G23+G26 -> 3411.647 | H27: =H20+H23+H26 -> 3894.3314 | I27: =I20+I23+I26 -> 3726.7482 | J27: =J20+J23+J26 -> 3739.9215 | ... L27: =L20+L23+L26 -> 4067.856
A28: Revenue growth | B28: % | D28: =D27/C27-1 -> 0.36532029 | E28: =E27/D27-1 -> -0.40943701 | F28: =F27/E27-1 -> 0.25899984 | G28: =G27/F27-1 -> 0.11562498 | H28: =H27/G27-1 -> 0.14148136 | I28: =I27/H27-1 -> -0.043032598 | J28: =J27/I27-1 -> 0.0035347735 | K28: =K27/J27-1 -> 0.041174548 | L28: =L27/K27-1 -> 0.044671006
A29: Mix: container shipping | B29: % | C29: =C20/C27 -> 0.89754542 | D29: =D20/D27 -> 0.926537 | E29: =E20/E27 -> 0.9047028 | F29: =F20/F27 -> 0.89451119 | G29: =G20/G27 -> 0.90215019 | H29: =H20/H27 -> 0.89558731 | I29: =I20/I27 -> 0.8843875 | J29: =J20/J27 -> 0.87906922 | ... L29: =L20/L27 -> 0.87864825
A30: Mix: other container logistics | B30: % | C30: =C23/C27 -> 0.092755823 | D30: =D23/D27 -> 0.070853681 | E30: =E23/E27 -> 0.092501356 | F30: =F23/F27 -> 0.10477038 | G30: =G23/G27 -> 0.097068073 | H30: =H23/H27 -> 0.10374506 | I30: =I23/I27 -> 0.11491485 | J30: =J23/J27 -> 0.12023558 | ... L30: =L23/L27 -> 0.12071259
A31: Mix: other sources | B31: % | C31: =C26/C27 -> 0.0096987598 | D31: =D26/D27 -> 0.0026093162 | E31: =E26/E27 -> 0.0027958479 | F31: =F26/F27 -> 0.00071842957 | G31: =G26/G27 -> 0.00078173387 | H31: =H26/H27 -> 0.00066763706 | I31: =I26/I27 -> 0.00069765915 | J31: =J26/J27 -> 0.00069520177 | ... L31: =L26/L27 -> 0.00063915734
A32: Revenue per average TEU slot | B32: US$'000 | C32: =C27/C11 -> 22.088061 | D32: =D27/D11 -> 26.898233 | E32: =E27/E11 -> 14.922095 | F32: =F27/F11 -> 17.825739 | G32: =G27/G11 -> 18.6829 | H32: =H27/H11 -> 20.924778 | I32: =I27/I11 -> 19.184233 | J32: =J27/J11 -> 17.914847 | ... L32: =L27/L11 -> 18.967812
A34: B. Revenue by geography (location of service)
A35: Greater China | B35: US$m | C35: 1414.641 | D35: 1980.749 | E35: 942.529 | F35: 1473.885 | G35: 1653.596 | H35: =H27*H41 -> 1869.2791 | I35: =I27*I41 -> 1770.2054 | J35: =J27*J41 -> 1757.7631 | K35: =K27*K41 -> 1810.6686 | L35: =L27*L41 -> 1871.2137 | M35: Annual reports, geographical information
A36: Southeast Asia | B36: US$m | C36: 898.233 | D36: 1159.406 | E36: 790.401 | F36: 879.335 | G36: 983.042 | H36: =H27*H42 -> 1148.8278 | I36: =I27*I42 -> 1118.0245 | J36: =J27*J42 -> 1140.676 | K36: =K27*K42 -> 1207.1124 | L36: =L27*L42 -> 1281.3746
A37: Japan | B37: US$m | C37: 579.265 | D37: 742.682 | E37: 527.012 | F37: 520.96 | G37: 596.799 | H37: =H27*H43 -> 673.71934 | I37: =I27*I43 -> 641.0007 | J37: =J27*J43 -> 639.52657 | K37: =K27*K43 -> 661.96488 | L37: =L27*L43 -> 691.53551
A38: Others | B38: US$m | C38: 120.308 | D38: 230.118 | E38: 169.017 | F38: 183.879 | G38: 178.21 | H38: =H27*H44 -> 202.50524 | I38: =I27*I44 -> 197.51766 | J38: =J27*J44 -> 201.95576 | K38: =K27*K44 -> 214.16511 | L38: =L27*L44 -> 223.73208
A39: Total revenue by geography | B39: US$m | C39: =C35+C36+C37+C38 -> 3012.447 | D39: =D35+D36+D37+D38 -> 4112.955 | E39: =E35+E36+E37+E38 -> 2428.959 | F39: =F35+F36+F37+F38 -> 3058.059 | G39: =G35+G36+G37+G38 -> 3411.647 | H39: =H35+H36+H37+H38 -> 3894.3314 | I39: =I35+I36+I37+I38 -> 3726.7482 | J39: =J35+J36+J37+J38 -> 3739.9215 | ... L39: =L35+L36+L37+L38 -> 4067.856
A40: Difference to total revenue | B40: US$m | C40: =ROUND(C39-C27,3) -> 0 | D40: =ROUND(D39-D27,3) -> 0 | E40: =ROUND(E39-E27,3) -> 0 | F40: =ROUND(F39-F27,3) -> 0 | G40: =ROUND(G39-G27,3) -> 0 | H40: =ROUND(H39-H27,3) -> 0 | I40: =ROUND(I39-I27,3) -> 0 | J40: =ROUND(J39-J27,3) -> 0 | ... L40: =ROUND(L39-L27,3) -> 0
A41: Greater China share | B41: % | C41: =C35/C39 -> 0.46959864 | D41: =D35/D39 -> 0.48158781 | E41: =E35/E39 -> 0.38803825 | F41: =F35/F39 -> 0.48196748 | G41: =G35/G39 -> 0.48469141 | H41: =Scenarios!H50 -> 0.48 | I41: =Scenarios!I50 -> 0.475 | J41: =Scenarios!J50 -> 0.47 | K41: =Scenarios!K50 -> 0.465 | L41: =Scenarios!L50 -> 0.46
A42: Southeast Asia share | B42: % | C42: =C36/C39 -> 0.29817388 | D42: =D36/D39 -> 0.28189124 | E42: =E36/E39 -> 0.3254073 | F42: =F36/F39 -> 0.28754677 | G42: =G36/G39 -> 0.28814294 | H42: =Scenarios!H51 -> 0.295 | I42: =Scenarios!I51 -> 0.3 | J42: =Scenarios!J51 -> 0.305 | K42: =Scenarios!K51 -> 0.31 | L42: =Scenarios!L51 -> 0.315
A43: Japan share | B43: % | C43: =C37/C39 -> 0.19229052 | D43: =D37/D39 -> 0.18057139 | E43: =E37/E39 -> 0.21697032 | F43: =F37/F39 -> 0.17035643 | G43: =G37/G39 -> 0.17492988 | H43: =Scenarios!H52 -> 0.173 | I43: =Scenarios!I52 -> 0.172 | J43: =Scenarios!J52 -> 0.171 | K43: =Scenarios!K52 -> 0.17 | L43: =Scenarios!L52 -> 0.17
A44: Others share | B44: % | C44: =C38/C39 -> 0.039936968 | D44: =D38/D39 -> 0.055949555 | E44: =E38/E39 -> 0.06958413 | F44: =F38/F39 -> 0.060129317 | G44: =G38/G39 -> 0.052235768 | H44: =1-H41-H42-H43 -> 0.052 | I44: =1-I41-I42-I43 -> 0.053 | J44: =1-J41-J42-J43 -> 0.054 | K44: =1-K41-K42-K43 -> 0.055 | L44: =1-L41-L42-L43 -> 0.055
A45: Greater China growth | B45: % | D45: =D35/C35-1 -> 0.40017785 | E45: =E35/D35-1 -> -0.52415526 | F45: =F35/E35-1 -> 0.5637556 | G45: =G35/F35-1 -> 0.12193014 | H45: =H35/G35-1 -> 0.13043276 | I45: =I35/H35-1 -> -0.053001009 | J45: =J35/I35-1 -> -0.0070287504 | K45: =K35/J35-1 -> 0.030098223 | L45: =L35/K35-1 -> 0.033437985
A46: Southeast Asia growth | B46: % | D46: =D36/C36-1 -> 0.29076309 | E46: =E36/D36-1 -> -0.31827074 | F46: =F36/E36-1 -> 0.11251757 | G46: =G36/F36-1 -> 0.11793799 | H46: =H36/G36-1 -> 0.16864567 | I46: =I36/H36-1 -> -0.026812812 | J46: =J36/I36-1 -> 0.020260353 | K46: =K36/J36-1 -> 0.058242983 | L46: =L36/K36-1 -> 0.061520539
A47: Japan growth | B47: % | D47: =D37/C37-1 -> 0.28211095 | E47: =E37/D37-1 -> -0.29039347 | F47: =F37/E37-1 -> -0.011483609 | G47: =G37/F37-1 -> 0.14557548 | H47: =H37/G37-1 -> 0.12888819 | I47: =I37/H37-1 -> -0.048564202 | J47: =J37/I37-1 -> -0.002299731 | K47: =K37/J37-1 -> 0.035085808 | L47: =L37/K37-1 -> 0.044671006
A48: Others growth | B48: % | D48: =D38/C38-1 -> 0.91274063 | E48: =E38/D38-1 -> -0.2655203 | F48: =F38/E38-1 -> 0.087931983 | G48: =G38/F38-1 -> -0.030830057 | H48: =H38/G38-1 -> 0.13632925 | I48: =I38/H38-1 -> -0.024629379 | J48: =J38/I38-1 -> 0.022469392 | K48: =K38/J38-1 -> 0.060455558 | L48: =L38/K38-1 -> 0.044671006
A49: Revenue outside Greater China | B49: US$m | C49: =C36+C37+C38 -> 1597.806 | D49: =D36+D37+D38 -> 2132.206 | E49: =E36+E37+E38 -> 1486.43 | F49: =F36+F37+F38 -> 1584.174 | G49: =G36+G37+G38 -> 1758.051 | H49: =H36+H37+H38 -> 2025.0524 | I49: =I36+I37+I38 -> 1956.5428 | J49: =J36+J37+J38 -> 1982.1584 | ... L49: =L36+L37+L38 -> 2196.6422
A50: Share outside Greater China | B50: % | C50: =C49/C39 -> 0.53040136 | D50: =D49/D39 -> 0.51841219 | E50: =E49/E39 -> 0.61196175 | F50: =F49/F39 -> 0.51803252 | G50: =G49/G39 -> 0.51530859 | H50: =H49/H39 -> 0.52 | I50: =I49/I39 -> 0.525 | J50: =J49/J39 -> 0.53 | ... L50: =L49/L39 -> 0.54

Sheet Income Statement
A1: SITC International Holdings (1308.HK) - Income Statement
A2: Consolidated income statement, FY2021A-FY2030E. US$m unless stated; costs negative.
A4: US$m unless stated | B4: Unit | C4: FY2021A | D4: FY2022A | E4: FY2023A | F4: FY2024A | G4: FY2025A | H4: FY2026E | I4: FY2027E | J4: FY2028E | K4: FY2029E | L4: FY2030E | M4: Source / assumption
A5: Revenue
A6: Container shipping and supporting logistics income | B6: US$m | C6: ='Revenue Model'!C20 -> 2703.808 | D6: ='Revenue Model'!D20 -> 3810.805 | E6: ='Revenue Model'!E20 -> 2197.486 | F6: ='Revenue Model'!F20 -> 2735.468 | G6: ='Revenue Model'!G20 -> 3077.818 | H6: ='Revenue Model'!H20 -> 3487.7138 | I6: ='Revenue Model'!I20 -> 3295.8895 | J6: ='Revenue Model'!J20 -> 3287.6498 | ... L6: ='Revenue Model'!L20 -> 3574.2145
A7: Other container logistics income | B7: US$m | C7: ='Revenue Model'!C23 -> 279.422 | D7: ='Revenue Model'!D23 -> 291.418 | E7: ='Revenue Model'!E23 -> 224.682 | F7: ='Revenue Model'!F23 -> 320.394 | G7: ='Revenue Model'!G23 -> 331.162 | H7: ='Revenue Model'!H23 -> 404.01764 | I7: ='Revenue Model'!I23 -> 428.2587 | J7: ='Revenue Model'!J23 -> 449.67163 | ... L7: ='Revenue Model'!L23 -> 491.04142
A8: Other sources | B8: US$m | C8: ='Revenue Model'!C26 -> 29.217 | D8: ='Revenue Model'!D26 -> 10.732 | E8: ='Revenue Model'!E26 -> 6.791 | F8: ='Revenue Model'!F26 -> 2.197 | G8: ='Revenue Model'!G26 -> 2.667 | H8: ='Revenue Model'!H26 -> 2.6 | I8: ='Revenue Model'!I26 -> 2.6 | J8: ='Revenue Model'!J26 -> 2.6 | ... L8: ='Revenue Model'!L26 -> 2.6
A9: Total revenue | B9: US$m | C9: =C6+C7+C8 -> 3012.447 | D9: =D6+D7+D8 -> 4112.955 | E9: =E6+E7+E8 -> 2428.959 | F9: =F6+F7+F8 -> 3058.059 | G9: =G6+G7+G8 -> 3411.647 | H9: =H6+H7+H8 -> 3894.3314 | I9: =I6+I7+I8 -> 3726.7482 | J9: =J6+J7+J8 -> 3739.9215 | ... L9: =L6+L7+L8 -> 4067.856
A10: Growth | B10: % | D10: =D9/C9-1 -> 0.36532029 | E10: =E9/D9-1 -> -0.40943701 | F10: =F9/E9-1 -> 0.25899984 | G10: =G9/F9-1 -> 0.11562498 | H10: =H9/G9-1 -> 0.14148136 | I10: =I9/H9-1 -> -0.043032598 | J10: =J9/I9-1 -> 0.0035347735 | K10: =K9/J9-1 -> 0.041174548 | L10: =L9/K9-1 -> 0.044671006
A11: Cost of sales
A12: Equipment and cargo transportation costs | B12: US$m | C12: -853.83 | D12: -1010.115 | E12: -925.542 | F12: -973.133 | G12: -1093.166 | H12: =-'Revenue Model'!H12*H21/1000 -> -1118.8267 | I12: =-'Revenue Model'!I12*I21/1000 -> -1192.3895 | J12: =-'Revenue Model'!J12*J21/1000 -> -1270.7891 | K12: =-'Revenue Model'!K12*K21/1000 -> -1341.445 | L12: =-'Revenue Model'!L12*L21/1000 -> -1409.2215 | M12: Annual results; FY2023 derived as total cost of sales less the other lines
A13: Voyage costs (bunker, port charges) | B13: US$m | C13: -350.506 | D13: -542.194 | E13: -408.463 | F13: -422.468 | G13: -402.446 | H13: =-'Revenue Model'!H12*H22/1000 -> -468.20464 | I13: =-'Revenue Model'!I12*I22/1000 -> -476.86642 | J13: =-'Revenue Model'!J12*J22/1000 -> -500.70974 | K13: =-'Revenue Model'!K12*K22/1000 -> -525.94551 | L13: =-'Revenue Model'!L12*L22/1000 -> -549.79714
A14: Container shipping vessel costs (depreciation, charter hire, crew) | B14: US$m | C14: -258.686 | D14: -355.962 | E14: -296.734 | F14: -257.47 | G14: -329.426 | H14: =-'Revenue Model'!H11*H23/1000 -> -364.77756 | I14: =-'Revenue Model'!I11*I23/1000 -> -373.13653 | J14: =-'Revenue Model'!J11*J23/1000 -> -396.97825 | K14: =-'Revenue Model'!K11*K23/1000 -> -415.54465 | L14: =-'Revenue Model'!L11*L23/1000 -> -418.07393
A15: Other container logistics costs | B15: US$m | C15: -212.26 | D15: -219.389 | E15: -172.472 | F15: -261.46 | G15: -274.528 | H15: =-'Revenue Model'!H23*H24 -> -335.33464 | I15: =-'Revenue Model'!I23*I24 -> -355.45472 | J15: =-'Revenue Model'!J23*J24 -> -373.22746 | K15: =-'Revenue Model'!K23*K24 -> -391.88883 | L15: =-'Revenue Model'!L23*L24 -> -407.56438
A16: Other costs | B16: US$m | C16: -17.792 | D16: -6.213 | E16: -2.714 | F16: -0.711 | G16: -1.615 | H16: =-'Revenue Model'!H26*H25 -> -1.56 | I16: =-'Revenue Model'!I26*I25 -> -1.56 | J16: =-'Revenue Model'!J26*J25 -> -1.56 | K16: =-'Revenue Model'!K26*K25 -> -1.56 | L16: =-'Revenue Model'!L26*L25 -> -1.56 | M16: FY2021-22: dry bulk cost of sales
A17: Total cost of sales | B17: US$m | C17: =SUM(C12:C16) -> -1693.074 | D17: =SUM(D12:D16) -> -2133.873 | E17: =SUM(E12:E16) -> -1805.925 | F17: =SUM(F12:F16) -> -1915.242 | G17: =SUM(G12:G16) -> -2101.181 | H17: =SUM(H12:H16) -> -2288.7035 | I17: =SUM(I12:I16) -> -2399.4072 | J17: =SUM(J12:J16) -> -2543.2646 | ... L17: =SUM(L12:L16) -> -2786.217
A18: Gross profit | B18: US$m | C18: =C9+C17 -> 1319.373 | D18: =D9+D17 -> 1979.082 | E18: =E9+E17 -> 623.034 | F18: =F9+F17 -> 1142.817 | G18: =G9+G17 -> 1310.466 | H18: =H9+H17 -> 1605.6279 | I18: =I9+I17 -> 1327.3411 | J18: =J9+J17 -> 1196.6569 | ... L18: =L9+L17 -> 1281.639
A19: Gross margin | B19: % | C19: =C18/C9 -> 0.43797385 | D19: =D18/D9 -> 0.48118251 | E19: =E18/E9 -> 0.25650248 | F19: =F18/F9 -> 0.37370666 | G19: =G18/G9 -> 0.38411536 | H19: =H18/H9 -> 0.41229874 | I19: =I18/I9 -> 0.35616601 | J19: =J18/J9 -> 0.31996845 | ... L19: =L18/L9 -> 0.31506499
A20: Unit costs (memo)
A21: Equipment and cargo cost per TEU | B21: US$/TEU | C21: =-C12/'Revenue Model'!C12*1000 -> 271.73709 | D21: =-D12/'Revenue Model'!D12*1000 -> 309.66704 | E21: =-E12/'Revenue Model'!E12*1000 -> 287.03445 | F21: =-F12/'Revenue Model'!F12*1000 -> 272.57223 | G21: =-G12/'Revenue Model'!G12*1000 -> 284.12084 | H21: =Scenarios!H54 -> 276 | I21: =H21*(1+Scenarios!I55) -> 280.14 | J21: =I21*(1+Scenarios!J55) -> 284.3421 | K21: =J21*(1+Scenarios!K55) -> 288.60723 | L21: =K21*(1+Scenarios!L55) -> 292.93634
A22: Voyage cost per TEU | B22: US$/TEU | C22: =-C13/'Revenue Model'!C12*1000 -> 111.55087 | D22: =-D13/'Revenue Model'!D12*1000 -> 166.21831 | E22: =-E13/'Revenue Model'!E12*1000 -> 126.67491 | F22: =-F13/'Revenue Model'!F12*1000 -> 118.33228 | G22: =-G13/'Revenue Model'!G12*1000 -> 104.59829 | H22: =Scenarios!H56 -> 115.5 | I22: =H22*(1+Scenarios!I57) -> 112.035 | J22: =I22*(1+Scenarios!J57) -> 112.035 | K22: =J22*(1+Scenarios!K57) -> 113.15535 | L22: =K22*(1+Scenarios!L57) -> 114.2869
A23: Vessel cost per average TEU slot | B23: US$/slot | C23: =-C14/'Revenue Model'!C11*1000 -> 1896.7544 | D23: =-D14/'Revenue Model'!D11*1000 -> 2327.9488 | E23: =-E14/'Revenue Model'!E11*1000 -> 1822.9592 | F23: =-F14/'Revenue Model'!F11*1000 -> 1500.819 | G23: =-G14/'Revenue Model'!G11*1000 -> 1804.0064 | H23: =Scenarios!H58 -> 1960 | I23: =H23*(1+Scenarios!I30) -> 1920.8 | J23: =I23*(1+Scenarios!J30) -> 1901.592 | K23: =J23*(1+Scenarios!K30) -> 1920.6079 | L23: =K23*(1+Scenarios!L30) -> 1949.417
A24: Other logistics costs, % of logistics income | B24: % | C24: =-C15/C7 -> 0.75963954 | D24: =-D15/D7 -> 0.7528327 | E24: =-E15/E7 -> 0.76762714 | F24: =-F15/F7 -> 0.81605773 | G24: =-G15/G7 -> 0.828984 | H24: =Scenarios!H59 -> 0.83 | I24: =Scenarios!I59 -> 0.83 | J24: =Scenarios!J59 -> 0.83 | K24: =Scenarios!K59 -> 0.83 | L24: =Scenarios!L59 -> 0.83
A25: Other costs, % of other sources revenue | B25: % | C25: =-C16/C8 -> 0.60896054 | D25: =-D16/D8 -> 0.57892285 | E25: =-E16/E8 -> 0.39964659 | F25: =-F16/F8 -> 0.32362312 | G25: =-G16/G8 -> 0.60554931 | H25: =Scenarios!H60 -> 0.6 | I25: =Scenarios!I60 -> 0.6 | J25: =Scenarios!J60 -> 0.6 | K25: =Scenarios!K60 -> 0.6 | L25: =Scenarios!L60 -> 0.6
A26: Total cost of sales per TEU lifted | B26: US$/TEU | C26: =-C17/'Revenue Model'!C12*1000 -> 538.83209 | D26: =-D17/'Revenue Model'!D12*1000 -> 654.17318 | E26: =-E17/'Revenue Model'!E12*1000 -> 560.06392 | F26: =-F17/'Revenue Model'!F12*1000 -> 536.4547 | G26: =-G17/'Revenue Model'!G12*1000 -> 546.11038 | H26: =-H17/'Revenue Model'!H12*1000 -> 564.59341 | I26: =-I17/'Revenue Model'!I12*1000 -> 563.71674 | J26: =-J17/'Revenue Model'!J12*1000 -> 569.06152 | ... L26: =-L17/'Revenue Model'!L12*1000 -> 579.17382
A27: Gross profit per TEU lifted | B27: US$/TEU | C27: =C18/'Revenue Model'!C12*1000 -> 419.89925 | D27: =D18/'Revenue Model'!D12*1000 -> 606.7195 | E27: =E18/'Revenue Model'!E12*1000 -> 193.21891 | F27: =F18/'Revenue Model'!F12*1000 -> 320.10031 | G27: =G18/'Revenue Model'!G12*1000 -> 340.5985 | H27: =H18/'Revenue Model'!H12*1000 -> 396.08755 | I27: =I18/'Revenue Model'!I12*1000 -> 311.84552 | J27: =J18/'Revenue Model'!J12*1000 -> 267.75483 | ... L27: =L18/'Revenue Model'!L12*1000 -> 266.41563
A28: Operating items
A29: Gain on disposal of vessels and equipment | B29: US$m | C29: 3.141 | D29: 119.072 | E29: 22.05 | F29: 9.524 | G29: 35.527 | H29: =Scenarios!H63 -> 10 | I29: =Scenarios!I63 -> 5 | J29: =Scenarios!J63 -> 5 | K29: =Scenarios!K63 -> 5 | L29: =Scenarios!L63 -> 5
A30: Other income and gains | B30: US$m | C30: 14.588 | D30: 18.72 | E30: 16.125 | F30: 8.451 | G30: 9.5 | H30: =Scenarios!H65 -> 12 | I30: =Scenarios!I65 -> 10 | J30: =Scenarios!J65 -> 10 | K30: =Scenarios!K65 -> 10 | L30: =Scenarios!L65 -> 10 | M30: Residual of reported other income and gains
A31: Administrative expenses | B31: US$m | C31: -154.764 | D31: -165.651 | E31: -136.047 | F31: -143.998 | G31: -153.578 | H31: =G31*(1+Scenarios!H66) -> -173.54314 | I31: =H31*(1+Scenarios!I66) -> -182.2203 | J31: =I31*(1+Scenarios!J66) -> -189.50911 | K31: =J31*(1+Scenarios!K66) -> -197.08947 | L31: =K31*(1+Scenarios!L66) -> -204.97305
A32: Administrative expenses, % of revenue | B32: % | C32: =-C31/C9 -> 0.051374846 | D32: =-D31/D9 -> 0.040275422 | E32: =-E31/E9 -> 0.056010414 | F32: =-F31/F9 -> 0.047088039 | G32: =-G31/G9 -> 0.045015794 | H32: =-H31/H9 -> 0.044563012 | I32: =-I31/I9 -> 0.048895253 | J32: =-J31/J9 -> 0.050671949 | ... L32: =-L31/L9 -> 0.050388473
A33: Other expenses, net | B33: US$m | C33: -4.493 | D33: -5.383 | E33: -4.085 | F33: -0.952 | G33: -5.686 | H33: =-Scenarios!H67 -> -4 | I33: =-Scenarios!I67 -> -4 | J33: =-Scenarios!J67 -> -4 | K33: =-Scenarios!K67 -> -4 | L33: =-Scenarios!L67 -> -4
A34: EBIT (excl. JVs, associates and interest income) | B34: US$m | C34: =C18+C29+C30+C31+C33 -> 1177.845 | D34: =D18+D29+D30+D31+D33 -> 1945.84 | E34: =E18+E29+E30+E31+E33 -> 521.077 | F34: =F18+F29+F30+F31+F33 -> 1015.842 | G34: =G18+G29+G30+G31+G33 -> 1196.229 | H34: =H18+H29+H30+H31+H33 -> 1450.0848 | I34: =I18+I29+I30+I31+I33 -> 1156.1208 | J34: =J18+J29+J30+J31+J33 -> 1018.1478 | ... L34: =L18+L29+L30+L31+L33 -> 1087.6659
A35: EBIT margin | B35: % | C35: =C34/C9 -> 0.39099277 | D35: =D34/D9 -> 0.47310024 | E35: =E34/E9 -> 0.21452688 | F35: =F34/F9 -> 0.33218522 | G35: =G34/G9 -> 0.35063094 | H35: =H34/H9 -> 0.37235783 | I35: =I34/I9 -> 0.31022239 | J35: =J34/J9 -> 0.27223774 | ... L35: =L34/L9 -> 0.26738064
A36: Depreciation of PPE | B36: US$m | C36: 79.239 | D36: 88.312 | E36: 99.973 | F36: 110.999 | G36: 116.014 | H36: =Scenarios!H76*'Balance Sheet'!G6 -> 114.77504 | I36: =Scenarios!I76*'Balance Sheet'!H6 -> 111.49984 | J36: =Scenarios!J76*'Balance Sheet'!I6 -> 129.86145 | K36: =Scenarios!K76*'Balance Sheet'!J6 -> 150.47832 | L36: =Scenarios!L76*'Balance Sheet'!K6 -> 149.36482 | M36: Mostly within vessel costs in cost of sales
A37: Depreciation of right-of-use assets | B37: US$m | C37: 52.135 | D37: 57.332 | E37: 58.788 | F37: 52.913 | G37: 64.231 | H37: =Scenarios!H77*'Balance Sheet'!G7 -> 68.49024 | I37: =Scenarios!I77*'Balance Sheet'!H7 -> 68.80729 | J37: =Scenarios!J77*'Balance Sheet'!I7 -> 70.107759 | K37: =Scenarios!K77*'Balance Sheet'!J7 -> 71.135129 | L37: =Scenarios!L77*'Balance Sheet'!K7 -> 71.946752
A38: Depreciation and amortisation | B38: US$m | C38: =C36+C37 -> 131.374 | D38: =D36+D37 -> 145.644 | E38: =E36+E37 -> 158.761 | F38: =F36+F37 -> 163.912 | G38: =G36+G37 -> 180.245 | H38: =H36+H37 -> 183.26528 | I38: =I36+I37 -> 180.30713 | J38: =J36+J37 -> 199.96921 | ... L38: =L36+L37 -> 221.31158
A39: EBITDA | B39: US$m | C39: =C34+C38 -> 1309.219 | D39: =D34+D38 -> 2091.484 | E39: =E34+E38 -> 679.838 | F39: =F34+F38 -> 1179.754 | G39: =G34+G38 -> 1376.474 | H39: =H34+H38 -> 1633.3501 | I39: =I34+I38 -> 1336.4279 | J39: =J34+J38 -> 1218.117 | ... L39: =L34+L38 -> 1308.9775
A40: EBITDA margin | B40: % | C40: =C39/C9 -> 0.43460316 | D40: =D39/D9 -> 0.50851128 | E40: =E39/E9 -> 0.27988863 | F40: =F39/F9 -> 0.38578523 | G40: =G39/G9 -> 0.4034632 | H40: =H39/H9 -> 0.41941733 | I40: =I39/I9 -> 0.35860428 | J40: =J39/J9 -> 0.32570657 | ... L40: =L39/L9 -> 0.32178561
A41: Share of profits of joint ventures | B41: US$m | C41: 15.578 | D41: 21.706 | E41: 20.013 | F41: 24.503 | G41: 31.08 | H41: =G41*(1+Scenarios!H69) -> 36.0528 | I41: =H41*(1+Scenarios!I69) -> 37.494912 | J41: =I41*(1+Scenarios!J69) -> 38.619759 | K41: =J41*(1+Scenarios!K69) -> 39.778352 | L41: =K41*(1+Scenarios!L69) -> 40.971703
A42: Share of profits of associates | B42: US$m | C42: 0.368 | D42: 0.461 | E42: -0.213 | F42: 1.878 | G42: 1.679 | H42: =Scenarios!H70 -> 1.5 | I42: =Scenarios!I70 -> 1.5 | J42: =Scenarios!J70 -> 1.5 | K42: =Scenarios!K70 -> 1.5 | L42: =Scenarios!L70 -> 1.5
A43: Segment results (company definition) | B43: US$m | C43: =C34+C41+C42 -> 1193.791 | D43: =D34+D41+D42 -> 1968.007 | E43: =E34+E41+E42 -> 540.877 | F43: =F34+F41+F42 -> 1042.223 | G43: =G34+G41+G42 -> 1228.988 | H43: =H34+H41+H42 -> 1487.6376 | I43: =I34+I41+I42 -> 1195.1157 | J43: =J34+J41+J42 -> 1058.2675 | ... L43: =L34+L41+L42 -> 1130.1376 | M43: Ties to the reported segment result in every historical year (Checks)
A44: Bank interest, investment income and FV gains | B44: US$m | C44: 6.538 | D44: 22.527 | E44: 31.29 | F44: 27.027 | G44: 37.831 | H44: =Scenarios!H62*('Balance Sheet'!G22+'Balance Sheet'!G21+'Balance Sheet'!G20) -> 33.20149 | I44: =Scenarios!I62*('Balance Sheet'!H22+'Balance Sheet'!H21+'Balance Sheet'!H20) -> 30.785456 | J44: =Scenarios!J62*('Balance Sheet'!I22+'Balance Sheet'!I21+'Balance Sheet'!I20) -> 28.460915 | K44: =Scenarios!K62*('Balance Sheet'!J22+'Balance Sheet'!J21+'Balance Sheet'!J20) -> 27.334054 | L44: =Scenarios!L62*('Balance Sheet'!K22+'Balance Sheet'!K21+'Balance Sheet'!K20) -> 32.925389
A45: Finance costs (leases and bank loans) | B45: US$m | C45: -15.663 | D45: -17.492 | E45: -18.753 | F45: -15.676 | G45: -15.55 | H45: =-Scenarios!H68*('Balance Sheet'!G51+'Balance Sheet'!G29+'Balance Sheet'!G35) -> -13.942578 | I45: =-Scenarios!I68*('Balance Sheet'!H51+'Balance Sheet'!H29+'Balance Sheet'!H35) -> -14.129711 | J45: =-Scenarios!J68*('Balance Sheet'!I51+'Balance Sheet'!I29+'Balance Sheet'!I35) -> -12.750952 | K45: =-Scenarios!K68*('Balance Sheet'!J51+'Balance Sheet'!J29+'Balance Sheet'!J35) -> -12.599562 | L45: =-Scenarios!L68*('Balance Sheet'!K51+'Balance Sheet'!K29+'Balance Sheet'!K35) -> -12.398694
A46: Profit before tax | B46: US$m | C46: =C43+C44+C45 -> 1184.666 | D46: =D43+D44+D45 -> 1973.042 | E46: =E43+E44+E45 -> 553.414 | F46: =F43+F44+F45 -> 1053.574 | G46: =G43+G44+G45 -> 1251.269 | H46: =H43+H44+H45 -> 1506.8965 | I46: =I43+I44+I45 -> 1211.7714 | J46: =J43+J44+J45 -> 1073.9775 | ... L46: =L43+L44+L45 -> 1150.6643
A47: Income tax | B47: US$m | C47: -17.487 | D47: -23.235 | E47: -17.24 | F47: -19.232 | G47: -20.867 | H47: =-H46*Scenarios!H72 -> -25.617241 | I47: =-I46*Scenarios!I72 -> -20.600114 | J47: =-J46*Scenarios!J72 -> -18.257617 | K47: =-K46*Scenarios!K72 -> -18.486657 | L47: =-L46*Scenarios!L72 -> -19.561294
A48: Effective tax rate | B48: % | C48: =-C47/C46 -> 0.014761123 | D48: =-D47/D46 -> 0.011776232 | E48: =-E47/E46 -> 0.031152085 | F48: =-F47/F46 -> 0.018254057 | G48: =-G47/G46 -> 0.01667667 | H48: =-H47/H46 -> 0.017 | I48: =-I47/I46 -> 0.017 | J48: =-J47/J46 -> 0.017 | ... L48: =-L47/L46 -> 0.017
A49: Profit for the year | B49: US$m | C49: =C46+C47 -> 1167.179 | D49: =D46+D47 -> 1949.807 | E49: =E46+E47 -> 536.174 | F49: =F46+F47 -> 1034.342 | G49: =G46+G47 -> 1230.402 | H49: =H46+H47 -> 1481.2793 | I49: =I46+I47 -> 1191.1713 | J49: =J46+J47 -> 1055.7199 | ... L49: =L46+L47 -> 1131.103
A50: Net margin | B50: % | C50: =C49/C9 -> 0.38745213 | D50: =D49/D9 -> 0.47406475 | E50: =E49/E9 -> 0.2207423 | F50: =F49/F9 -> 0.33823481 | G50: =G49/G9 -> 0.36064751 | H50: =H49/H9 -> 0.38036805 | I50: =I49/I9 -> 0.31962752 | J50: =J49/J9 -> 0.28228397 | ... L50: =L49/L9 -> 0.27805877
A51: Non-controlling interests | B51: US$m | C51: -4.465 | D51: -5.382 | E51: -4.781 | F51: -6.017 | G51: -7.515 | H51: =-H49*Scenarios!H73 -> -8.8876757 | I51: =-I49*Scenarios!I73 -> -7.1470278 | J51: =-J49*Scenarios!J73 -> -6.3343193 | K51: =-K49*Scenarios!K73 -> -6.4137825 | L51: =-L49*Scenarios!L73 -> -6.7866183
A52: Profit attributable to shareholders | B52: US$m | C52: =C49+C51 -> 1162.714 | D52: =D49+D51 -> 1944.425 | E52: =E49+E51 -> 531.393 | F52: =F49+F51 -> 1028.325 | G52: =G49+G51 -> 1222.887 | H52: =H49+H51 -> 1472.3916 | I52: =I49+I51 -> 1184.0243 | J52: =J49+J51 -> 1049.3856 | ... L52: =L49+L51 -> 1124.3164
A53: Growth | B53: % | D53: =D52/C52-1 -> 0.67231581 | E53: =E52/D52-1 -> -0.72670944 | F53: =F52/E52-1 -> 0.93514969 | G53: =G52/F52-1 -> 0.18920283 | H53: =H52/G52-1 -> 0.20402916 | I53: =I52/H52-1 -> -0.19584961 | J53: =J52/I52-1 -> -0.1137128 | K53: =K52/J52-1 -> 0.012544871 | L53: =L52/K52-1 -> 0.058130404
A54: Per share
A55: Weighted average shares, basic | B55: m | C55: 2660.792 | D55: 2654.356 | E55: 2647.319 | F55: 2645.299 | G55: 2655.241 | H55: =Scenarios!H99 -> 2672 | I55: =Scenarios!I99 -> 2680 | J55: =Scenarios!J99 -> 2688 | K55: =Scenarios!K99 -> 2696 | L55: =Scenarios!L99 -> 2704 | M55: Excludes shares held by the scheme trustee
A56: Weighted average shares, diluted | B56: m | C56: 2683.105 | D56: 2683.157 | E56: 2683.11 | F56: 2684.192 | G56: 2695.624 | H56: =H55+Scenarios!H100 -> 2706 | I56: =I55+Scenarios!I100 -> 2714 | J56: =J55+Scenarios!J100 -> 2722 | K56: =K55+Scenarios!K100 -> 2730 | L56: =L55+Scenarios!L100 -> 2738
A57: Basic EPS | B57: US$ | C57: =C52/C55 -> 0.43698042 | D57: =D52/D55 -> 0.73254115 | E57: =E52/E55 -> 0.20072874 | F57: =F52/F55 -> 0.38873677 | G57: =G52/G55 -> 0.46055593 | H57: =H52/H55 -> 0.55104476 | I57: =I52/I55 -> 0.4418001 | J57: =J52/J55 -> 0.39039641 | ... L57: =L52/L55 -> 0.41579749
A58: Diluted EPS | B58: US$ | C58: =C52/C56 -> 0.43334644 | D58: =D52/D56 -> 0.72467806 | E58: =E52/E56 -> 0.19805114 | F58: =F52/F56 -> 0.38310411 | G58: =G52/G56 -> 0.45365637 | H58: =H52/H56 -> 0.54412106 | I58: =I52/I56 -> 0.43626539 | J58: =J52/J56 -> 0.38552004 | ... L58: =L52/L56 -> 0.41063419
A59: Diluted EPS at current HK$/US$ | B59: HK$ | C59: =C58*Inputs!$C$7 -> 3.3979994 | D59: =D58*Inputs!$C$7 -> 5.682418 | E59: =E58*Inputs!$C$7 -> 1.5529784 | F59: =F58*Inputs!$C$7 -> 3.0040343 | G59: =G58*Inputs!$C$7 -> 3.5572557 | H59: =H58*Inputs!$C$7 -> 4.2666165 | I59: =I58*Inputs!$C$7 -> 3.4208878 | J59: =J58*Inputs!$C$7 -> 3.0229783 | ... L59: =L58*Inputs!$C$7 -> 3.2199059
A60: Dividend per share declared for the year | B60: HK$ | C60: 3.2 | D60: 4 | E60: 1.1 | F60: 2.52 | G60: 3 | H60: ='Cash Flow'!H47/Inputs!$C$12*Inputs!$C$7 -> 3.6192301 | I60: ='Cash Flow'!I47/Inputs!$C$12*Inputs!$C$7 -> 2.739205 | J60: ='Cash Flow'!J47/Inputs!$C$12*Inputs!$C$7 -> 2.4277223 | K60: ='Cash Flow'!K47/Inputs!$C$12*Inputs!$C$7 -> 2.4581778 | L60: ='Cash Flow'!L47/Inputs!$C$12*Inputs!$C$7 -> 2.6010726 | M60: Incl. specials. FY2021 3.20; FY2022 4.00; FY2023 1.10; FY2024 2.52; FY2025 3.00
A61: Payout ratio | B61: % | C61: =C60/C59 -> 0.94173058 | D61: =D60/D59 -> 0.70392568 | E61: =E60/E59 -> 0.70831635 | F61: =F60/F59 -> 0.83887191 | G61: =G60/G59 -> 0.84334674 | H61: =Scenarios!H40 -> 0.85 | I61: =Scenarios!I40 -> 0.8 | J61: =Scenarios!J40 -> 0.8 | K61: =Scenarios!K40 -> 0.8 | L61: =Scenarios!L40 -> 0.8 | M61: Historical payout on current FX (approximation)
A62: Share award expense (memo, within admin) | B62: US$m | C62: 8.444 | D62: 27.747 | E62: 28.429 | F62: 27.829 | G62: 26.952 | H62: =Scenarios!H74 -> 25 | I62: =Scenarios!I74 -> 25 | J62: =Scenarios!J74 -> 25 | K62: =Scenarios!K74 -> 25 | L62: =Scenarios!L74 -> 25

Sheet Cash Flow
A1: SITC International Holdings (1308.HK) - Cash Flow
A2: Consolidated cash flow statement; outflows negative. US$m.
A4: US$m unless stated | B4: Unit | C4: FY2021A | D4: FY2022A | E4: FY2023A | F4: FY2024A | G4: FY2025A | H4: FY2026E | I4: FY2027E | J4: FY2028E | K4: FY2029E | L4: FY2030E | M4: Source / assumption
A5: Operating activities
A6: Profit for the year | B6: US$m | C6: ='Income Statement'!C49 -> 1167.179 | D6: ='Income Statement'!D49 -> 1949.807 | E6: ='Income Statement'!E49 -> 536.174 | F6: ='Income Statement'!F49 -> 1034.342 | G6: ='Income Statement'!G49 -> 1230.402 | H6: ='Income Statement'!H49 -> 1481.2793 | I6: ='Income Statement'!I49 -> 1191.1713 | J6: ='Income Statement'!J49 -> 1055.7199 | ... L6: ='Income Statement'!L49 -> 1131.103
A7: Depreciation and amortisation | B7: US$m | C7: ='Income Statement'!C38 -> 131.374 | D7: ='Income Statement'!D38 -> 145.644 | E7: ='Income Statement'!E38 -> 158.761 | F7: ='Income Statement'!F38 -> 163.912 | G7: ='Income Statement'!G38 -> 180.245 | H7: ='Income Statement'!H38 -> 183.26528 | I7: ='Income Statement'!I38 -> 180.30713 | J7: ='Income Statement'!J38 -> 199.96921 | ... L7: ='Income Statement'!L38 -> 221.31158
A8: Share award expense | B8: US$m | C8: ='Income Statement'!C62 -> 8.444 | D8: ='Income Statement'!D62 -> 27.747 | E8: ='Income Statement'!E62 -> 28.429 | F8: ='Income Statement'!F62 -> 27.829 | G8: ='Income Statement'!G62 -> 26.952 | H8: ='Income Statement'!H62 -> 25 | I8: ='Income Statement'!I62 -> 25 | J8: ='Income Statement'!J62 -> 25 | ... L8: ='Income Statement'!L62 -> 25
A9: Share of JV and associate profits | B9: US$m | C9: =-('Income Statement'!C41+'Income Statement'!C42) -> -15.946 | D9: =-('Income Statement'!D41+'Income Statement'!D42) -> -22.167 | E9: =-('Income Statement'!E41+'Income Statement'!E42) -> -19.8 | F9: =-('Income Statement'!F41+'Income Statement'!F42) -> -26.381 | G9: =-('Income Statement'!G41+'Income Statement'!G42) -> -32.759 | H9: =-('Income Statement'!H41+'Income Statement'!H42) -> -37.5528 | I9: =-('Income Statement'!I41+'Income Statement'!I42) -> -38.994912 | J9: =-('Income Statement'!J41+'Income Statement'!J42) -> -40.119759 | ... L9: =-('Income Statement'!L41+'Income Statement'!L42) -> -42.471703
A10: Gain on disposal of vessels and equipment | B10: US$m | C10: =-'Income Statement'!C29 -> -3.141 | D10: =-'Income Statement'!D29 -> -119.072 | E10: =-'Income Statement'!E29 -> -22.05 | F10: =-'Income Statement'!F29 -> -9.524 | G10: =-'Income Statement'!G29 -> -35.527 | H10: =-'Income Statement'!H29 -> -10 | I10: =-'Income Statement'!I29 -> -5 | J10: =-'Income Statement'!J29 -> -5 | ... L10: =-'Income Statement'!L29 -> -5
A11: Change in bunkers | B11: US$m | H11: ='Balance Sheet'!G16-'Balance Sheet'!H16 -> -6.3698593 | I11: ='Balance Sheet'!H16-'Balance Sheet'!I16 -> -1.0678914 | J11: ='Balance Sheet'!I16-'Balance Sheet'!J16 -> -2.9395875 | K11: ='Balance Sheet'!J16-'Balance Sheet'!K16 -> -3.1112594 | L11: ='Balance Sheet'!K16-'Balance Sheet'!L16 -> -2.9406118
A12: Change in trade receivables | B12: US$m | H12: ='Balance Sheet'!G17-'Balance Sheet'!H17 -> -39.995426 | I12: ='Balance Sheet'!H17-'Balance Sheet'!I17 -> 9.6417732 | J12: ='Balance Sheet'!I17-'Balance Sheet'!J17 -> -0.75791077 | K12: ='Balance Sheet'!J17-'Balance Sheet'!K17 -> -8.8596742 | L12: ='Balance Sheet'!K17-'Balance Sheet'!L17 -> -10.00779
A13: Change in prepayments and other receivables | B13: US$m | H13: ='Balance Sheet'!G18-'Balance Sheet'!H18 -> -11.608309 | I13: ='Balance Sheet'!H18-'Balance Sheet'!I18 -> 2.1785816 | J13: ='Balance Sheet'!I18-'Balance Sheet'!J18 -> -0.17125174 | K13: ='Balance Sheet'!J18-'Balance Sheet'!K18 -> -2.0018645 | L13: ='Balance Sheet'!K18-'Balance Sheet'!L18 -> -2.261284
A14: Change in trade payables | B14: US$m | H14: ='Balance Sheet'!H26-'Balance Sheet'!G26 -> 21.843243 | I14: ='Balance Sheet'!I26-'Balance Sheet'!H26 -> 12.435209 | J14: ='Balance Sheet'!J26-'Balance Sheet'!I26 -> 16.159323 | K14: ='Balance Sheet'!K26-'Balance Sheet'!J26 -> 14.953141 | L14: ='Balance Sheet'!L26-'Balance Sheet'!K26 -> 12.337402
A15: Change in other payables and accruals | B15: US$m | H15: ='Balance Sheet'!H27-'Balance Sheet'!G27 -> 18.101578 | I15: ='Balance Sheet'!I27-'Balance Sheet'!H27 -> -7.8764105 | J15: ='Balance Sheet'!J27-'Balance Sheet'!I27 -> 0.61914092 | K15: ='Balance Sheet'!K27-'Balance Sheet'!J27 -> 7.23751 | L15: ='Balance Sheet'!L27-'Balance Sheet'!K27 -> 8.1754115
A16: Change in income tax payable | B16: US$m | H16: ='Balance Sheet'!H31-'Balance Sheet'!G31 -> 1.2424482 | I16: ='Balance Sheet'!I31-'Balance Sheet'!H31 -> -1.0034253 | J16: ='Balance Sheet'!J31-'Balance Sheet'!I31 -> -0.46849934 | K16: ='Balance Sheet'!K31-'Balance Sheet'!J31 -> 0.045807893 | L16: ='Balance Sheet'!L31-'Balance Sheet'!K31 -> 0.21492737
A17: Working capital and other items (historical residual) | B17: US$m | C17: 47.299 | D17: 20.606 | E17: -9.301 | F17: -31.844 | G17: 31.724 | M17: Reported operating cash flow less the lines above
A18: Net cash from operating activities | B18: US$m | C18: =SUM(C6:C17) -> 1335.209 | D18: =SUM(D6:D17) -> 2002.565 | E18: =SUM(E6:E17) -> 672.213 | F18: =SUM(F6:F17) -> 1158.334 | G18: =SUM(G6:G17) -> 1401.037 | H18: =SUM(H6:H17) -> 1625.2054 | I18: =SUM(I6:I17) -> 1366.7914 | J18: =SUM(J6:J17) -> 1248.0105 | ... L18: =SUM(L6:L17) -> 1335.461
A19: Investing activities
A20: Purchases of PPE (FY2026E on: containers, equipment, dry-docking) | B20: US$m | C20: -67.996 | D20: -412.832 | E20: -260.645 | F20: -242.939 | G20: -100.207 | H20: =-Scenarios!H83 -> -30 | I20: =-Scenarios!I83 -> -60 | J20: =-Scenarios!J83 -> -60 | K20: =-Scenarios!K83 -> -60 | L20: =-Scenarios!L83 -> -60
A21: Advance payments for vessels (newbuild instalments) | B21: US$m | C21: -121.103 | D21: -75.34 | E21: -48.511 | F21: -18.087 | G21: -35.122 | H21: =-(Scenarios!H81+Scenarios!H82) -> -132 | I21: =-(Scenarios!I81+Scenarios!I82) -> -330 | J21: =-(Scenarios!J81+Scenarios!J82) -> -300 | K21: =-(Scenarios!K81+Scenarios!K82) -> -148.1 | L21: =-(Scenarios!L81+Scenarios!L82) -> -150
A22: Proceeds from disposal of vessels and equipment | B22: US$m | C22: 20.978 | D22: 241.744 | E22: 44.067 | F22: 32.374 | G22: 70.732 | H22: =Scenarios!H64 -> 30 | I22: =Scenarios!I64 -> 15 | J22: =Scenarios!J64 -> 15 | K22: =Scenarios!K64 -> 15 | L22: =Scenarios!L64 -> 15
A23: Dividends from joint ventures | B23: US$m | C23: 2.986 | D23: 12.239 | E23: 15.246 | F23: 17.316 | G23: 27.603 | H23: ='Income Statement'!H41*Scenarios!H71 -> 30.64488 | I23: ='Income Statement'!I41*Scenarios!I71 -> 31.870675 | J23: ='Income Statement'!J41*Scenarios!J71 -> 32.826795 | K23: ='Income Statement'!K41*Scenarios!K71 -> 33.811599 | L23: ='Income Statement'!L41*Scenarios!L71 -> 34.825947
A24: Change in time deposits and FVTPL assets | B24: US$m | H24: =('Balance Sheet'!G21+'Balance Sheet'!G20)-('Balance Sheet'!H21+'Balance Sheet'!H20) -> -19.97 | I24: =('Balance Sheet'!H21+'Balance Sheet'!H20)-('Balance Sheet'!I21+'Balance Sheet'!I20) -> 0 | J24: =('Balance Sheet'!I21+'Balance Sheet'!I20)-('Balance Sheet'!J21+'Balance Sheet'!J20) -> 0 | K24: =('Balance Sheet'!J21+'Balance Sheet'!J20)-('Balance Sheet'!K21+'Balance Sheet'!K20) -> 0 | L24: =('Balance Sheet'!K21+'Balance Sheet'!K20)-('Balance Sheet'!L21+'Balance Sheet'!L20) -> 0
A25: Deposits, investments and other (historical residual) | B25: US$m | C25: 218.954 | D25: -195.006 | E25: 100.658 | F25: -298.212 | G25: -91.455
A26: Net cash from investing activities | B26: US$m | C26: =SUM(C20:C25) -> 53.819 | D26: =SUM(D20:D25) -> -429.195 | E26: =SUM(E20:E25) -> -149.185 | F26: =SUM(F20:F25) -> -509.548 | G26: =SUM(G20:G25) -> -128.449 | H26: =SUM(H20:H25) -> -121.32512 | I26: =SUM(I20:I25) -> -343.12932 | J26: =SUM(J20:J25) -> -312.1732 | ... L26: =SUM(L20:L25) -> -160.17405
A27: Financing activities
A28: Dividends paid to shareholders | B28: US$m | C28: -551.911 | D28: -1574.077 | E28: -751.971 | F28: -557.55 | G28: -937.716 | H28: =-(H50+'Balance Sheet'!G32-'Balance Sheet'!H32) -> -1451.9051 | I28: =-(I50+'Balance Sheet'!H32-'Balance Sheet'!I32) -> -908.00141 | J28: =-(J50+'Balance Sheet'!I32-'Balance Sheet'!J32) -> -887.97839 | K28: =-(K50+'Balance Sheet'!J32-'Balance Sheet'!K32) -> -845.30079 | L28: =-(L50+'Balance Sheet'!K32-'Balance Sheet'!L32) -> -877.21722
A29: Dividends paid to non-controlling interests | B29: US$m | H29: ='Income Statement'!H51*Scenarios!H97 -> -2.6663027 | I29: ='Income Statement'!I51*Scenarios!I97 -> -2.1441083 | J29: ='Income Statement'!J51*Scenarios!J97 -> -1.9002958 | K29: ='Income Statement'!K51*Scenarios!K97 -> -1.9241347 | L29: ='Income Statement'!L51*Scenarios!L97 -> -2.0359855
A30: Principal portion of lease payments | B30: US$m | C30: -56.129 | D30: -63.028 | E30: -63.728 | F30: -61.237 | G30: -77.909 | H30: =-'Income Statement'!H37*Scenarios!H79 -> -76.709069 | I30: =-'Income Statement'!I37*Scenarios!I79 -> -77.064164 | J30: =-'Income Statement'!J37*Scenarios!J79 -> -78.52069 | K30: =-'Income Statement'!K37*Scenarios!K79 -> -79.671345 | L30: =-'Income Statement'!L37*Scenarios!L79 -> -80.580363
A31: New bank loans | B31: US$m | C31: 70.7 | D31: 110.067 | E31: 95.171 | F31: 31.132 | G31: 19.766
A32: Repayment of bank loans | B32: US$m | C32: -167.661 | D32: -166.336 | E32: -198.313 | F32: -33.136 | G32: -168.26
A33: Net change in existing bank loans | B33: US$m | H33: ='Balance Sheet'!H29-'Balance Sheet'!G29 -> 11.061 | I33: ='Balance Sheet'!I29-'Balance Sheet'!H29 -> -30 | J33: ='Balance Sheet'!J29-'Balance Sheet'!I29 -> 0 | K33: ='Balance Sheet'!K29-'Balance Sheet'!J29 -> 0 | L33: ='Balance Sheet'!L29-'Balance Sheet'!K29 -> 0
A34: Purchase of shares for the share scheme | B34: US$m | C34: -48.112 | D34: -22.013 | E34: -23.753 | F34: -5.083 | G34: -0.914 | H34: =-Scenarios!H96 -> -5 | I34: =-Scenarios!I96 -> -5 | J34: =-Scenarios!J96 -> -5 | K34: =-Scenarios!K96 -> -5 | L34: =-Scenarios!L96 -> -5
A35: Other financing (historical residual: NCI dividends, option proceeds) | B35: US$m | C35: -1.097 | D35: -2.862 | E35: -2.018 | F35: -7.665 | G35: -5.735
A36: Financing cash flow before revolver | B36: US$m | C36: =SUM(C28:C35) -> -754.21 | D36: =SUM(D28:D35) -> -1718.249 | E36: =SUM(E28:E35) -> -944.612 | F36: =SUM(F28:F35) -> -633.539 | G36: =SUM(G28:G35) -> -1170.768 | H36: =SUM(H28:H35) -> -1525.2195 | I36: =SUM(I28:I35) -> -1022.2097 | J36: =SUM(J28:J35) -> -973.39937 | ... L36: =SUM(L28:L35) -> -964.83356
A37: Revolver drawdown / (repayment) | B37: US$m | H37: =H45-G45 -> 0 | I37: =I45-H45 -> 0 | J37: =J45-I45 -> 0 | K37: =K45-J45 -> 0 | L37: =L45-K45 -> 0
A38: Net cash from financing activities | B38: US$m | C38: =C36+C37 -> -754.21 | D38: =D36+D37 -> -1718.249 | E38: =E36+E37 -> -944.612 | F38: =F36+F37 -> -633.539 | G38: =G36+G37 -> -1170.768 | H38: =H36+H37 -> -1525.2195 | I38: =I36+I37 -> -1022.2097 | J38: =J36+J37 -> -973.39937 | ... L38: =L36+L37 -> -964.83356
A39: Effect of exchange rate changes (historical) | B39: US$m | C39: -1.693 | D39: -4.722 | E39: -0.869 | F39: -1.364 | G39: 5.671
A40: Net change in cash and cash equivalents | B40: US$m | C40: =C18+C26+C38+C39 -> 633.125 | D40: =D18+D26+D38+D39 -> -149.601 | E40: =E18+E26+E38+E39 -> -422.453 | F40: =F18+F26+F38+F39 -> 13.883 | G40: =G18+G26+G38+G39 -> 107.491 | H40: =H18+H26+H38+H39 -> -21.339193 | I40: =I18+I26+I38+I39 -> 1.4523492 | J40: =J18+J26+J38+J39 -> -37.562035 | ... L40: =L18+L26+L38+L39 -> 210.45335
A41: Cash and cash equivalents, start of year | B41: US$m | C41: =Inputs!$C$26 -> 61.139 | D41: =C42 -> 694.264 | E41: =D42 -> 544.663 | F41: =E42 -> 122.21 | G41: =F42 -> 136.093 | H41: =G42 -> 243.584 | I41: =H42 -> 222.24481 | J41: =I42 -> 223.69716 | K41: =J42 -> 186.13512 | L41: =K42 -> 372.51296
A42: Cash and cash equivalents, end of year | B42: US$m | C42: =C41+C40 -> 694.264 | D42: =D41+D40 -> 544.663 | E42: =E41+E40 -> 122.21 | F42: =F41+F40 -> 136.093 | G42: =G41+G40 -> 243.584 | H42: =H41+H40 -> 222.24481 | I42: =I41+I40 -> 223.69716 | J42: =J41+J40 -> 186.13512 | ... L42: =L41+L40 -> 582.96631
A43: Revolver
A44: Cash before revolver | B44: US$m | H44: =H41+H18+H26+H36+H39 -> 222.24481 | I44: =I41+I18+I26+I36+I39 -> 223.69716 | J44: =J41+J18+J26+J36+J39 -> 186.13512 | K44: =K41+K18+K26+K36+K39 -> 372.51296 | L44: =L41+L18+L26+L36+L39 -> 582.96631
A45: Revolver balance, year end | B45: US$m | G45: ='Balance Sheet'!G35 -> 0 | H45: =MAX(0,G45+Inputs!$C$28-H44) -> 0 | I45: =MAX(0,H45+Inputs!$C$28-I44) -> 0 | J45: =MAX(0,I45+Inputs!$C$28-J44) -> 0 | K45: =MAX(0,J45+Inputs!$C$28-K44) -> 0 | L45: =MAX(0,K45+Inputs!$C$28-L44) -> 0 | M45: Draws only if cash would fall below the minimum
A46: Dividends
A47: Dividends declared for the year | B47: US$m | H47: ='Income Statement'!H52*Scenarios!H40 -> 1251.5329 | I47: ='Income Statement'!I52*Scenarios!I40 -> 947.21942 | J47: ='Income Statement'!J52*Scenarios!J40 -> 839.50845 | K47: ='Income Statement'!K52*Scenarios!K40 -> 850.03997 | L47: ='Income Statement'!L52*Scenarios!L40 -> 899.45314
A48: Paid within the year (interim and specials) | B48: US$m | H48: =Inputs!$C$20*Inputs!$C$12/Inputs!$C$7 -> 864.50213 | I48: =I47*Scenarios!I98 -> 520.97068 | J48: =J47*Scenarios!J98 -> 461.72965 | K48: =K47*Scenarios!K98 -> 467.52199 | L48: =L47*Scenarios!L98 -> 494.69923
A49: Final dividend paid the following year | B49: US$m | G49: =Inputs!$C$21 -> 344.572 | H49: =MAX(0,H47-H48) -> 387.03073 | I49: =MAX(0,I47-I48) -> 426.24874 | J49: =MAX(0,J47-J48) -> 377.7788 | K49: =MAX(0,K47-K48) -> 382.51799 | L49: =MAX(0,L47-L48) -> 404.75391
A50: Dividends recognised in equity during the year | B50: US$m | H50: =H48+G49 -> 1209.0741 | I50: =I48+H49 -> 908.00141 | J50: =J48+I49 -> 887.97839 | K50: =K48+J49 -> 845.30079 | L50: =L48+K49 -> 877.21722
A51: Free cash flow (memo)
A52: Total capex (PPE + vessel instalments) | B52: US$m | C52: =C20+C21 -> -189.099 | D52: =D20+D21 -> -488.172 | E52: =E20+E21 -> -309.156 | F52: =F20+F21 -> -261.026 | G52: =G20+G21 -> -135.329 | H52: =H20+H21 -> -162 | I52: =I20+I21 -> -390 | J52: =J20+J21 -> -360 | ... L52: =L20+L21 -> -210
A53: Free cash flow after leases | B53: US$m | C53: =C18+C52+C22+C23+C30 -> 1113.945 | D53: =D18+D52+D22+D23+D30 -> 1705.348 | E53: =E18+E52+E22+E23+E30 -> 358.642 | F53: =F18+F52+F22+F23+F30 -> 885.761 | G53: =G18+G52+G22+G23+G30 -> 1286.134 | H53: =H18+H52+H22+H23+H30 -> 1447.1412 | I53: =I18+I52+I22+I23+I30 -> 946.59787 | J53: =J18+J52+J22+J23+J30 -> 857.31665 | ... L53: =L18+L52+L22+L23+L30 -> 1094.7066 | M53: Operating cash flow - capex + disposals + JV dividends - lease principal
A54: Free cash flow per diluted share (current FX) | B54: HK$ | C54: =C53/'Income Statement'!C56*Inputs!$C$7 -> 3.2554734 | D54: =D53/'Income Statement'!D56*Inputs!$C$7 -> 4.9837357 | E54: =E53/'Income Statement'!E56*Inputs!$C$7 -> 1.0481194 | F54: =F53/'Income Statement'!F56*Inputs!$C$7 -> 2.5875637 | G54: =G53/'Income Statement'!G56*Inputs!$C$7 -> 3.7412349 | H54: =H53/'Income Statement'!H56*Inputs!$C$7 -> 4.1934474 | I54: =I53/'Income Statement'!I56*Inputs!$C$7 -> 2.7349145 | J54: =J53/'Income Statement'!J56*Inputs!$C$7 -> 2.469683 | ... L54: =L53/'Income Statement'!L56*Inputs!$C$7 -> 3.1351068
A55: Free cash flow yield on current market cap | B55: % | C55: =C53/Inputs!$C$16 -> 0.067561836 | D55: =D53/Inputs!$C$16 -> 0.103431 | E55: =E53/Inputs!$C$16 -> 0.021751982 | F55: =F53/Inputs!$C$16 -> 0.053722257 | G55: =G53/Inputs!$C$16 -> 0.078005264 | H55: =H53/Inputs!$C$16 -> 0.087770508 | I55: =I53/Inputs!$C$16 -> 0.057412071 | J55: =J53/Inputs!$C$16 -> 0.051997079 | ... L55: =L53/Inputs!$C$16 -> 0.066395005
A56: Cash dividends as % of free cash flow | B56: % | C56: =-C28/C53 -> 0.49545624 | D56: =-D28/D53 -> 0.92302392 | E56: =-E28/E53 -> 2.0967176 | F56: =-F28/F53 -> 0.62945874 | G56: =-G28/G53 -> 0.72909666 | H56: =-H28/H53 -> 1.0032919 | I56: =-I28/I53 -> 0.95922613 | J56: =-J28/J53 -> 1.0357648 | ... L56: =-L28/L53 -> 0.80132636

Sheet Balance Sheet
A1: SITC International Holdings (1308.HK) - Balance Sheet
A2: Consolidated statement of financial position at 31 December. US$m.
A4: US$m unless stated | B4: Unit | C4: FY2021A | D4: FY2022A | E4: FY2023A | F4: FY2024A | G4: FY2025A | H4: FY2026E | I4: FY2027E | J4: FY2028E | K4: FY2029E | L4: FY2030E | M4: Source / assumption
A5: Non-current assets
A6: Property, plant and equipment | B6: US$m | C6: 1087.704 | D6: 1396.647 | E6: 1661.852 | F6: 1827.726 | G6: 1793.36 | H6: =G6+Scenarios!H83+H50-'Income Statement'!H36-(Scenarios!H64-Scenarios!H63) -> 1742.185 | I6: =H6+Scenarios!I83+I50-'Income Statement'!I36-(Scenarios!I64-Scenarios!I63) -> 2029.0851 | J6: =I6+Scenarios!J83+J50-'Income Statement'!J36-(Scenarios!J64-Scenarios!J63) -> 2351.2237 | K6: =J6+Scenarios!K83+K50-'Income Statement'!K36-(Scenarios!K64-Scenarios!K63) -> 2333.8254 | L6: =K6+Scenarios!L83+L50-'Income Statement'!L36-(Scenarios!L64-Scenarios!L63) -> 2234.4605 | M6: Opening + other capex + newbuilds delivered - depreciation - NBV of disposals
A7: Right-of-use assets | B7: US$m | C7: 233.189 | D7: 262.923 | E7: 215.463 | F7: 235.841 | G7: 326.144 | H7: =G7+Scenarios!H78-'Income Statement'!H37 -> 327.65376 | I7: =H7+Scenarios!I78-'Income Statement'!I37 -> 333.84647 | J7: =I7+Scenarios!J78-'Income Statement'!J37 -> 338.73871 | K7: =J7+Scenarios!K78-'Income Statement'!K37 -> 342.60358 | L7: =K7+Scenarios!L78-'Income Statement'!L37 -> 345.65683
A8: Advance payments for vessels | B8: US$m | C8: 145.152 | D8: 111.722 | E8: 70.833 | F8: 30.873 | G8: 52.467 | H8: =G8+Scenarios!H81+Scenarios!H82-H50 -> 130.867 | I8: =H8+Scenarios!I81+Scenarios!I82-I50 -> 112.467 | J8: =I8+Scenarios!J81+Scenarios!J82-J50 -> 10.467 | K8: =J8+Scenarios!K81+Scenarios!K82-K50 -> 75.487 | L8: =K8+Scenarios!L81+Scenarios!L82-L50 -> 225.487
A9: Goodwill | B9: US$m | C9: 1.111 | D9: 1.019 | E9: 0.998 | F9: 0.971 | G9: 1.014 | H9: =G9 -> 1.014 | I9: =H9 -> 1.014 | J9: =I9 -> 1.014 | K9: =J9 -> 1.014 | L9: =K9 -> 1.014
A10: Other intangible assets | B10: US$m | C10: 1.579 | D10: 1.579 | E10: 1.579 | F10: 1.579 | G10: 1.579 | H10: =G10 -> 1.579 | I10: =H10 -> 1.579 | J10: =I10 -> 1.579 | K10: =J10 -> 1.579 | L10: =K10 -> 1.579
A11: Investments in joint ventures | B11: US$m | C11: 49.929 | D11: 57.777 | E11: 57.965 | F11: 60.666 | G11: 65.686 | H11: =G11+'Income Statement'!H41-'Cash Flow'!H23 -> 71.09392 | I11: =H11+'Income Statement'!I41-'Cash Flow'!I23 -> 76.718157 | J11: =I11+'Income Statement'!J41-'Cash Flow'!J23 -> 82.511121 | K11: =J11+'Income Statement'!K41-'Cash Flow'!K23 -> 88.477874 | L11: =K11+'Income Statement'!L41-'Cash Flow'!L23 -> 94.623629
A12: Investments in associates | B12: US$m | C12: 10.494 | D12: 9.63 | E12: 12.604 | F12: 13.892 | G12: 13.885 | H12: =G12+'Income Statement'!H42 -> 15.385 | I12: =H12+'Income Statement'!I42 -> 16.885 | J12: =I12+'Income Statement'!J42 -> 18.385 | K12: =J12+'Income Statement'!K42 -> 19.885 | L12: =K12+'Income Statement'!L42 -> 21.385
A13: Derivative financial instruments | B13: US$m | C13: 1.907 | D13: 12.589 | E13: 4.584 | F13: 3.006 | G13: 0 | H13: =G13 -> 0 | I13: =H13 -> 0 | J13: =I13 -> 0 | K13: =J13 -> 0 | L13: =K13 -> 0
A14: Total non-current assets | B14: US$m | C14: =SUM(C6:C13) -> 1531.065 | D14: =SUM(D6:D13) -> 1853.886 | E14: =SUM(E6:E13) -> 2025.878 | F14: =SUM(F6:F13) -> 2174.554 | G14: =SUM(G6:G13) -> 2254.135 | H14: =SUM(H6:H13) -> 2289.7776 | I14: =SUM(I6:I13) -> 2571.5947 | J14: =SUM(J6:J13) -> 2803.9185 | ... L14: =SUM(L6:L13) -> 2924.206
A15: Current assets
A16: Bunkers | B16: US$m | C16: 41.476 | D16: 53.205 | E16: 43.324 | F16: 46.98 | G16: 51.354 | H16: =-'Income Statement'!H13*Scenarios!H86/365 -> 57.723859 | I16: =-'Income Statement'!I13*Scenarios!I86/365 -> 58.791751 | J16: =-'Income Statement'!J13*Scenarios!J86/365 -> 61.731338 | K16: =-'Income Statement'!K13*Scenarios!K86/365 -> 64.842598 | L16: =-'Income Statement'!L13*Scenarios!L86/365 -> 67.78321
A17: Trade receivables | B17: US$m | C17: 157.038 | D17: 139.051 | E17: 113.333 | F17: 174.671 | G17: 184.062 | H17: ='Income Statement'!H9*Scenarios!H85/365 -> 224.05743 | I17: ='Income Statement'!I9*Scenarios!I85/365 -> 214.41565 | J17: ='Income Statement'!J9*Scenarios!J85/365 -> 215.17356 | K17: ='Income Statement'!K9*Scenarios!K85/365 -> 224.03324 | L17: ='Income Statement'!L9*Scenarios!L85/365 -> 234.04103
A18: Prepayments, deposits and other receivables | B18: US$m | C18: 34.929 | D18: 34.487 | E18: 37.34 | F18: 54.396 | G18: 39.018 | H18: ='Income Statement'!H9*Scenarios!H87 -> 50.626309 | I18: ='Income Statement'!I9*Scenarios!I87 -> 48.447727 | J18: ='Income Statement'!J9*Scenarios!J87 -> 48.618979 | K18: ='Income Statement'!K9*Scenarios!K87 -> 50.620843 | L18: ='Income Statement'!L9*Scenarios!L87 -> 52.882127
A19: Derivative financial instruments | B19: US$m | C19: 0.329 | D19: 5.116 | E19: 1.485 | F19: 2.288 | G19: 0.387 | H19: =G19 -> 0.387 | I19: =H19 -> 0.387 | J19: =I19 -> 0.387 | K19: =J19 -> 0.387 | L19: =K19 -> 0.387
A20: Financial assets at FVTPL | B20: US$m | C20: 32.105 | D20: 15.58 | E20: 14.78 | F20: 0.69 | G20: 167.386 | H20: =Scenarios!H93 -> 75 | I20: =Scenarios!I93 -> 75 | J20: =Scenarios!J93 -> 75 | K20: =Scenarios!K93 -> 75 | L20: =Scenarios!L93 -> 75
A21: Time deposits over three months | B21: US$m | C21: 225.217 | D21: 436.868 | E21: 294.113 | F21: 608.401 | G21: 537.644 | H21: =Scenarios!H92 -> 650 | I21: =Scenarios!I92 -> 650 | J21: =Scenarios!J92 -> 650 | K21: =Scenarios!K92 -> 650 | L21: =Scenarios!L92 -> 650 | M21: FY2021-23 split from "cash and bank balances" using cash equivalents in the cash flow statement
A22: Cash and cash equivalents | B22: US$m | C22: 694.264 | D22: 544.663 | E22: 122.21 | F22: 136.093 | G22: 243.584 | H22: ='Cash Flow'!H42 -> 222.24481 | I22: ='Cash Flow'!I42 -> 223.69716 | J22: ='Cash Flow'!J42 -> 186.13512 | K22: ='Cash Flow'!K42 -> 372.51296 | L22: ='Cash Flow'!L42 -> 582.96631
A23: Total current assets | B23: US$m | C23: =SUM(C16:C22) -> 1185.358 | D23: =SUM(D16:D22) -> 1228.97 | E23: =SUM(E16:E22) -> 626.585 | F23: =SUM(F16:F22) -> 1023.519 | G23: =SUM(G16:G22) -> 1223.435 | H23: =SUM(H16:H22) -> 1280.0394 | I23: =SUM(I16:I22) -> 1270.7393 | J23: =SUM(J16:J22) -> 1237.046 | ... L23: =SUM(L16:L22) -> 1663.0597
A24: Total assets | B24: US$m | C24: =C14+C23 -> 2716.423 | D24: =D14+D23 -> 3082.856 | E24: =E14+E23 -> 2652.463 | F24: =F14+F23 -> 3198.073 | G24: =G14+G23 -> 3477.57 | H24: =H14+H23 -> 3569.817 | I24: =I14+I23 -> 3842.334 | J24: =J14+J23 -> 4040.9645 | ... L24: =L14+L23 -> 4587.2657
A25: Current liabilities
A26: Trade payables | B26: US$m | C26: 201.857 | D26: 209.102 | E26: 203.514 | F26: 233.68 | G26: 235.244 | H26: =-'Income Statement'!H17*Scenarios!H88/365 -> 257.08724 | I26: =-'Income Statement'!I17*Scenarios!I88/365 -> 269.52245 | J26: =-'Income Statement'!J17*Scenarios!J88/365 -> 285.68177 | K26: =-'Income Statement'!K17*Scenarios!K88/365 -> 300.63491 | L26: =-'Income Statement'!L17*Scenarios!L88/365 -> 312.97232
A27: Other payables and accruals | B27: US$m | C27: 173.445 | D27: 177.092 | E27: 137.265 | F27: 143.332 | G27: 164.932 | H27: ='Income Statement'!H9*Scenarios!H89 -> 183.03358 | I27: ='Income Statement'!I9*Scenarios!I89 -> 175.15717 | J27: ='Income Statement'!J9*Scenarios!J89 -> 175.77631 | K27: ='Income Statement'!K9*Scenarios!K89 -> 183.01382 | L27: ='Income Statement'!L9*Scenarios!L89 -> 191.18923
A28: Derivative financial instruments | B28: US$m | C28: 0.051 | D28: 2.992 | E28: 0 | F28: 1.001 | G28: 0 | H28: =G28 -> 0 | I28: =H28 -> 0 | J28: =I28 -> 0 | K28: =J28 -> 0 | L28: =K28 -> 0
A29: Bank borrowings | B29: US$m | C29: 83.211 | D29: 34.829 | E29: 104.219 | F29: 114.981 | G29: 18.939 | H29: =Scenarios!H94 -> 30 | I29: =Scenarios!I94 -> 0 | J29: =Scenarios!J94 -> 0 | K29: =Scenarios!K94 -> 0 | L29: =Scenarios!L94 -> 0
A30: Lease liabilities | B30: US$m | C30: 48.186 | D30: 54.841 | E30: 50.937 | F30: 45.98 | G30: 59.265 | H30: =H51*Scenarios!H80 -> 67.184535 | I30: =I51*Scenarios!I80 -> 66.720098 | J30: =J51*Scenarios!J80 -> 65.927942 | K30: =K51*Scenarios!K80 -> 64.87689 | L30: =L51*Scenarios!L80 -> 63.621308
A31: Income tax payable | B31: US$m | C31: 7.695 | D31: 9.508 | E31: 7.065 | F31: 5.782 | G31: 3.881 | H31: =-'Income Statement'!H47*Scenarios!H90 -> 5.1234482 | I31: =-'Income Statement'!I47*Scenarios!I90 -> 4.1200228 | J31: =-'Income Statement'!J47*Scenarios!J90 -> 3.6515235 | K31: =-'Income Statement'!K47*Scenarios!K90 -> 3.6973314 | L31: =-'Income Statement'!L47*Scenarios!L90 -> 3.9122587
A32: Dividend payable | B32: US$m | C32: 270.829 | D32: 0 | E32: 0 | F32: 0 | G32: 242.831 | H32: =Scenarios!H95 -> 0 | I32: =Scenarios!I95 -> 0 | J32: =Scenarios!J95 -> 0 | K32: =Scenarios!K95 -> 0 | L32: =Scenarios!L95 -> 0
A33: Total current liabilities | B33: US$m | C33: =SUM(C26:C32) -> 785.274 | D33: =SUM(D26:D32) -> 488.364 | E33: =SUM(E26:E32) -> 503 | F33: =SUM(F26:F32) -> 544.756 | G33: =SUM(G26:G32) -> 725.092 | H33: =SUM(H26:H32) -> 542.4288 | I33: =SUM(I26:I32) -> 515.51974 | J33: =SUM(J26:J32) -> 531.03755 | ... L33: =SUM(L26:L32) -> 571.69511
A34: Non-current liabilities
A35: Bank borrowings (FY2026E on: revolver) | B35: US$m | C35: 244.06 | D35: 236.609 | E35: 64.815 | F35: 51.876 | G35: 0 | H35: ='Cash Flow'!H45 -> 0 | I35: ='Cash Flow'!I45 -> 0 | J35: ='Cash Flow'!J45 -> 0 | K35: ='Cash Flow'!K45 -> 0 | L35: ='Cash Flow'!L45 -> 0
A36: Lease liabilities | B36: US$m | C36: 168.409 | D36: 189.758 | E36: 150.733 | F36: 175.984 | G36: 246.042 | H36: =H51-H30 -> 231.4134 | I36: =I51-I30 -> 229.81367 | J36: =J51-J30 -> 227.08513 | K36: =K51-K30 -> 223.46484 | L36: =L51-L30 -> 219.14006
A37: Derivative financial instruments | B37: US$m | C37: 0.195 | D37: 0 | E37: 0 | F37: 0 | G37: 0 | H37: =G37 -> 0 | I37: =H37 -> 0 | J37: =I37 -> 0 | K37: =J37 -> 0 | L37: =K37 -> 0
A38: Provision for reinstatement costs | B38: US$m | C38: 2.801 | D38: 3.114 | E38: 2.857 | F38: 3.953 | G38: 5.23 | H38: =G38 -> 5.23 | I38: =H38 -> 5.23 | J38: =I38 -> 5.23 | K38: =J38 -> 5.23 | L38: =K38 -> 5.23
A39: Total non-current liabilities | B39: US$m | C39: =SUM(C35:C38) -> 415.465 | D39: =SUM(D35:D38) -> 429.481 | E39: =SUM(E35:E38) -> 218.405 | F39: =SUM(F35:F38) -> 231.813 | G39: =SUM(G35:G38) -> 251.272 | H39: =SUM(H35:H38) -> 236.6434 | I39: =SUM(I35:I38) -> 235.04367 | J39: =SUM(J35:J38) -> 232.31513 | ... L39: =SUM(L35:L38) -> 224.37006
A40: Total liabilities | B40: US$m | C40: =C33+C39 -> 1200.739 | D40: =D33+D39 -> 917.845 | E40: =E33+E39 -> 721.405 | F40: =F33+F39 -> 776.569 | G40: =G33+G39 -> 976.364 | H40: =H33+H39 -> 779.0722 | I40: =I33+I39 -> 750.56341 | J40: =J33+J39 -> 763.35268 | ... L40: =L33+L39 -> 796.06518
A41: Equity
A42: Issued capital | B42: US$m | C42: 34.581 | D42: 34.582 | E42: 34.583 | F42: 34.641 | G42: 34.806 | H42: =G42 -> 34.806 | I42: =H42 -> 34.806 | J42: =I42 -> 34.806 | K42: =J42 -> 34.806 | L42: =K42 -> 34.806
A43: Reserves | B43: US$m | C43: =C44-C42 -> 1467.106 | D43: =D44-D42 -> 2115.958 | E43: =E44-E42 -> 1879.953 | F43: =F44-F42 -> 2369.595 | G43: =G44-G42 -> 2443.732 | H43: =H44-H42 -> 2727.0495 | I43: =I44-I42 -> 3023.0723 | J43: =J44-J42 -> 3204.4795 | ... L43: =L44-L42 -> 3708.8279
A44: Equity attributable to shareholders | B44: US$m | C44: 1501.687 | D44: 2150.54 | E44: 1914.536 | F44: 2404.236 | G44: 2478.538 | H44: =G44+'Income Statement'!H52-'Cash Flow'!H50+'Income Statement'!H62-Scenarios!H96 -> 2761.8555 | I44: =H44+'Income Statement'!I52-'Cash Flow'!I50+'Income Statement'!I62-Scenarios!I96 -> 3057.8783 | J44: =I44+'Income Statement'!J52-'Cash Flow'!J50+'Income Statement'!J62-Scenarios!J96 -> 3239.2855 | K44: =J44+'Income Statement'!K52-'Cash Flow'!K50+'Income Statement'!K62-Scenarios!K96 -> 3476.5347 | L44: =K44+'Income Statement'!L52-'Cash Flow'!L50+'Income Statement'!L62-Scenarios!L96 -> 3743.6339 | M44: Opening + profit - dividends recognised + share awards - scheme share purchases
A45: Non-controlling interests | B45: US$m | C45: 13.997 | D45: 14.471 | E45: 16.522 | F45: 17.268 | G45: 22.668 | H45: =G45-'Income Statement'!H51+'Cash Flow'!H29 -> 28.889373 | I45: =H45-'Income Statement'!I51+'Cash Flow'!I29 -> 33.892292 | J45: =I45-'Income Statement'!J51+'Cash Flow'!J29 -> 38.326316 | K45: =J45-'Income Statement'!K51+'Cash Flow'!K29 -> 42.815964 | L45: =K45-'Income Statement'!L51+'Cash Flow'!L29 -> 47.566596
A46: Total equity | B46: US$m | C46: =C44+C45 -> 1515.684 | D46: =D44+D45 -> 2165.011 | E46: =E44+E45 -> 1931.058 | F46: =F44+F45 -> 2421.504 | G46: =G44+G45 -> 2501.206 | H46: =H44+H45 -> 2790.7448 | I46: =I44+I45 -> 3091.7706 | J46: =J44+J45 -> 3277.6118 | ... L46: =L44+L45 -> 3791.2005
A47: Total liabilities and equity | B47: US$m | C47: =C40+C46 -> 2716.423 | D47: =D40+D46 -> 3082.856 | E47: =E40+E46 -> 2652.463 | F47: =F40+F46 -> 3198.073 | G47: =G40+G46 -> 3477.57 | H47: =H40+H46 -> 3569.817 | I47: =I40+I46 -> 3842.334 | J47: =J40+J46 -> 4040.9645 | ... L47: =L40+L46 -> 4587.2657
A48: Balance check (assets - liabilities - equity) | B48: US$m | C48: =ROUND(C24-C47,3) -> 0 | D48: =ROUND(D24-D47,3) -> 0 | E48: =ROUND(E24-E47,3) -> 0 | F48: =ROUND(F24-F47,3) -> 0 | G48: =ROUND(G24-G47,3) -> 0 | H48: =ROUND(H24-H47,3) -> 0 | I48: =ROUND(I24-I47,3) -> 0 | J48: =ROUND(J24-J47,3) -> 0 | ... L48: =ROUND(L24-L47,3) -> 0
A49: Memo
A50: Newbuilds delivered (transfer from advances to PPE) | B50: US$m | H50: ='Revenue Model'!H7*Scenarios!H46 -> 53.6 | I50: ='Revenue Model'!I7*Scenarios!I46 -> 348.4 | J50: ='Revenue Model'!J7*Scenarios!J46 -> 402 | K50: ='Revenue Model'!K7*Scenarios!K46 -> 83.08 | L50: ='Revenue Model'!L7*Scenarios!L46 -> 0
A51: Total lease liabilities | B51: US$m | C51: =C30+C36 -> 216.595 | D51: =D30+D36 -> 244.599 | E51: =E30+E36 -> 201.67 | F51: =F30+F36 -> 221.964 | G51: =G30+G36 -> 305.307 | H51: =G51+Scenarios!H78+'Cash Flow'!H30 -> 298.59793 | I51: =H51+Scenarios!I78+'Cash Flow'!I30 -> 296.53377 | J51: =I51+Scenarios!J78+'Cash Flow'!J30 -> 293.01308 | K51: =J51+Scenarios!K78+'Cash Flow'!K30 -> 288.34173 | L51: =K51+Scenarios!L78+'Cash Flow'!L30 -> 282.76137
A52: Cash, time deposits and FVTPL assets | B52: US$m | C52: =C22+C21+C20 -> 951.586 | D52: =D22+D21+D20 -> 997.111 | E52: =E22+E21+E20 -> 431.103 | F52: =F22+F21+F20 -> 745.184 | G52: =G22+G21+G20 -> 948.614 | H52: =H22+H21+H20 -> 947.24481 | I52: =I22+I21+I20 -> 948.69716 | J52: =J22+J21+J20 -> 911.13512 | ... L52: =L22+L21+L20 -> 1307.9663
A53: Net cash excl. leases | B53: US$m | C53: =C52-C29-C35 -> 624.315 | D53: =D52-D29-D35 -> 725.673 | E53: =E52-E29-E35 -> 262.069 | F53: =F52-F29-F35 -> 578.327 | G53: =G52-G29-G35 -> 929.675 | H53: =H52-H29-H35 -> 917.24481 | I53: =I52-I29-I35 -> 948.69716 | J53: =J52-J29-J35 -> 911.13512 | ... L53: =L52-L29-L35 -> 1307.9663
A54: Net cash incl. lease liabilities | B54: US$m | C54: =C53-C51 -> 407.72 | D54: =D53-D51 -> 481.074 | E54: =E53-E51 -> 60.399 | F54: =F53-F51 -> 356.363 | G54: =G53-G51 -> 624.368 | H54: =H53-H51 -> 618.64688 | I54: =I53-I51 -> 652.16339 | J54: =J53-J51 -> 618.12204 | ... L54: =L53-L51 -> 1025.2049
A55: Return on average shareholders equity | B55: % | D55: ='Income Statement'!D52/AVERAGE(D44,C44) -> 1.0647887 | E55: ='Income Statement'!E52/AVERAGE(E44,D44) -> 0.26144308 | F55: ='Income Statement'!F52/AVERAGE(F44,E44) -> 0.47621176 | G55: ='Income Statement'!G52/AVERAGE(G44,F44) -> 0.50089846 | H55: ='Income Statement'!H52/AVERAGE(H44,G44) -> 0.56193933 | I55: ='Income Statement'!I52/AVERAGE(I44,H44) -> 0.40689981 | J55: ='Income Statement'!J52/AVERAGE(J44,I44) -> 0.33328831 | K55: ='Income Statement'!K52/AVERAGE(K44,J44) -> 0.31643193 | L55: ='Income Statement'!L52/AVERAGE(L44,K44) -> 0.31143772
A56: Book value per share (shares in issue, current FX) | B56: HK$ | C56: =C44/Inputs!$C$12*Inputs!$C$7 -> 4.3426353 | D56: =D44/Inputs!$C$12*Inputs!$C$7 -> 6.219013 | E56: =E44/Inputs!$C$12*Inputs!$C$7 -> 5.5365277 | F56: =F44/Inputs!$C$12*Inputs!$C$7 -> 6.9526607 | G56: =G44/Inputs!$C$12*Inputs!$C$7 -> 7.16753 | H56: =H44/Inputs!$C$12*Inputs!$C$7 -> 7.9868382 | I56: =I44/Inputs!$C$12*Inputs!$C$7 -> 8.8428883 | J56: =J44/Inputs!$C$12*Inputs!$C$7 -> 9.3674885 | ... L56: =L44/Inputs!$C$12*Inputs!$C$7 -> 10.825982
A57: Trade working capital (bunkers + receivables + prepayments - payables) | B57: US$m | C57: =C16+C17+C18-C26-C27 -> -141.859 | D57: =D16+D17+D18-D26-D27 -> -159.451 | E57: =E16+E17+E18-E26-E27 -> -146.782 | F57: =F16+F17+F18-F26-F27 -> -100.965 | G57: =G16+G17+G18-G26-G27 -> -125.742 | H57: =H16+H17+H18-H26-H27 -> -107.71323 | I57: =I16+I17+I18-I26-I27 -> -123.02449 | J57: =J16+J17+J18-J26-J27 -> -135.9342 | ... L57: =L16+L17+L18-L26-L27 -> -149.45518

Sheet DCF Inputs
A1: SITC International Holdings (1308.HK) - DCF Inputs
A2: Unlevered free cash flow build for the DCF tab. Leases are operating costs, so lease liabilities are not deducted in the bridge.
A4: US$m unless stated | B4: Unit | C4: FY2021A | D4: FY2022A | E4: FY2023A | F4: FY2024A | G4: FY2025A | H4: FY2026E | I4: FY2027E | J4: FY2028E | K4: FY2029E | L4: FY2030E | M4: Source / assumption
A5: Unlevered free cash flow (leases treated as operating costs)
A6: Revenue | B6: US$m | C6: ='Income Statement'!C9 -> 3012.447 | D6: ='Income Statement'!D9 -> 4112.955 | E6: ='Income Statement'!E9 -> 2428.959 | F6: ='Income Statement'!F9 -> 3058.059 | G6: ='Income Statement'!G9 -> 3411.647 | H6: ='Income Statement'!H9 -> 3894.3314 | I6: ='Income Statement'!I9 -> 3726.7482 | J6: ='Income Statement'!J9 -> 3739.9215 | ... L6: ='Income Statement'!L9 -> 4067.856
A7: EBITDA | B7: US$m | C7: ='Income Statement'!C39 -> 1309.219 | D7: ='Income Statement'!D39 -> 2091.484 | E7: ='Income Statement'!E39 -> 679.838 | F7: ='Income Statement'!F39 -> 1179.754 | G7: ='Income Statement'!G39 -> 1376.474 | H7: ='Income Statement'!H39 -> 1633.3501 | I7: ='Income Statement'!I39 -> 1336.4279 | J7: ='Income Statement'!J39 -> 1218.117 | ... L7: ='Income Statement'!L39 -> 1308.9775
A8: EBIT excl. disposal gains | B8: US$m | C8: ='Income Statement'!C34-'Income Statement'!C29 -> 1174.704 | D8: ='Income Statement'!D34-'Income Statement'!D29 -> 1826.768 | E8: ='Income Statement'!E34-'Income Statement'!E29 -> 499.027 | F8: ='Income Statement'!F34-'Income Statement'!F29 -> 1006.318 | G8: ='Income Statement'!G34-'Income Statement'!G29 -> 1160.702 | H8: ='Income Statement'!H34-'Income Statement'!H29 -> 1440.0848 | I8: ='Income Statement'!I34-'Income Statement'!I29 -> 1151.1208 | J8: ='Income Statement'!J34-'Income Statement'!J29 -> 1013.1478 | ... L8: ='Income Statement'!L34-'Income Statement'!L29 -> 1082.6659
A9: Tax rate | B9: % | C9: ='Income Statement'!C48 -> 0.014761123 | D9: ='Income Statement'!D48 -> 0.011776232 | E9: ='Income Statement'!E48 -> 0.031152085 | F9: ='Income Statement'!F48 -> 0.018254057 | G9: ='Income Statement'!G48 -> 0.01667667 | H9: =Scenarios!H72 -> 0.017 | I9: =Scenarios!I72 -> 0.017 | J9: =Scenarios!J72 -> 0.017 | K9: =Scenarios!K72 -> 0.017 | L9: =Scenarios!L72 -> 0.017
A10: NOPAT | B10: US$m | C10: =C8*(1-C9) -> 1157.3641 | D10: =D8*(1-D9) -> 1805.2556 | E10: =E8*(1-E9) -> 483.48127 | F10: =F8*(1-F9) -> 987.94861 | G10: =G8*(1-G9) -> 1141.3454 | H10: =H8*(1-H9) -> 1415.6034 | I10: =I8*(1-I9) -> 1131.5517 | J10: =J8*(1-J9) -> 995.92426 | ... L10: =L8*(1-L9) -> 1064.2606
A11: Add: depreciation and amortisation | B11: US$m | C11: ='Income Statement'!C38 -> 131.374 | D11: ='Income Statement'!D38 -> 145.644 | E11: ='Income Statement'!E38 -> 158.761 | F11: ='Income Statement'!F38 -> 163.912 | G11: ='Income Statement'!G38 -> 180.245 | H11: ='Income Statement'!H38 -> 183.26528 | I11: ='Income Statement'!I38 -> 180.30713 | J11: ='Income Statement'!J38 -> 199.96921 | ... L11: ='Income Statement'!L38 -> 221.31158
A12: Less: capex incl. newbuild instalments | B12: US$m | C12: ='Cash Flow'!C52 -> -189.099 | D12: ='Cash Flow'!D52 -> -488.172 | E12: ='Cash Flow'!E52 -> -309.156 | F12: ='Cash Flow'!F52 -> -261.026 | G12: ='Cash Flow'!G52 -> -135.329 | H12: ='Cash Flow'!H52 -> -162 | I12: ='Cash Flow'!I52 -> -390 | J12: ='Cash Flow'!J52 -> -360 | ... L12: ='Cash Flow'!L52 -> -210
A13: Add: disposal proceeds | B13: US$m | C13: ='Cash Flow'!C22 -> 20.978 | D13: ='Cash Flow'!D22 -> 241.744 | E13: ='Cash Flow'!E22 -> 44.067 | F13: ='Cash Flow'!F22 -> 32.374 | G13: ='Cash Flow'!G22 -> 70.732 | H13: ='Cash Flow'!H22 -> 30 | I13: ='Cash Flow'!I22 -> 15 | J13: ='Cash Flow'!J22 -> 15 | ... L13: ='Cash Flow'!L22 -> 15
A14: Less: increase in working capital | B14: US$m | C14: ='Cash Flow'!C17 -> 47.299 | D14: ='Cash Flow'!D17 -> 20.606 | E14: ='Cash Flow'!E17 -> -9.301 | F14: ='Cash Flow'!F17 -> -31.844 | G14: ='Cash Flow'!G17 -> 31.724 | H14: =SUM('Cash Flow'!H11:H16) -> -16.786325 | I14: =SUM('Cash Flow'!I11:I16) -> 14.307836 | J14: =SUM('Cash Flow'!J11:J16) -> 12.441214 | K14: =SUM('Cash Flow'!K11:K16) -> 8.2636604 | L14: =SUM('Cash Flow'!L11:L16) -> 5.5180547 | M14: Historical: residual operating items incl. working capital
A15: Less: lease principal | B15: US$m | C15: ='Cash Flow'!C30 -> -56.129 | D15: ='Cash Flow'!D30 -> -63.028 | E15: ='Cash Flow'!E30 -> -63.728 | F15: ='Cash Flow'!F30 -> -61.237 | G15: ='Cash Flow'!G30 -> -77.909 | H15: ='Cash Flow'!H30 -> -76.709069 | I15: ='Cash Flow'!I30 -> -77.064164 | J15: ='Cash Flow'!J30 -> -78.52069 | ... L15: ='Cash Flow'!L30 -> -80.580363
A16: Less: lease interest | B16: US$m | C16: ='Income Statement'!C45 -> -15.663 | D16: ='Income Statement'!D45 -> -17.492 | E16: ='Income Statement'!E45 -> -18.753 | F16: ='Income Statement'!F45 -> -15.676 | G16: ='Income Statement'!G45 -> -15.55 | H16: =-Scenarios!H68*'Balance Sheet'!G51 -> -13.128201 | I16: =-Scenarios!I68*'Balance Sheet'!H51 -> -12.839711 | J16: =-Scenarios!J68*'Balance Sheet'!I51 -> -12.750952 | K16: =-Scenarios!K68*'Balance Sheet'!J51 -> -12.599562 | L16: =-Scenarios!L68*'Balance Sheet'!K51 -> -12.398694 | M16: Historical: total finance costs (mostly leases)
A17: Unlevered free cash flow after leases | B17: US$m | C17: =C10+C11+C12+C13+C14+C15+C16 -> 1096.1241 | D17: =D10+D11+D12+D13+D14+D15+D16 -> 1644.5576 | E17: =E10+E11+E12+E13+E14+E15+E16 -> 285.37127 | F17: =F10+F11+F12+F13+F14+F15+F16 -> 814.45161 | G17: =G10+G11+G12+G13+G14+G15+G16 -> 1195.2584 | H17: =H10+H11+H12+H13+H14+H15+H16 -> 1360.245 | I17: =I10+I11+I12+I13+I14+I15+I16 -> 861.2628 | J17: =J10+J11+J12+J13+J14+J15+J16 -> 772.06304 | ... L17: =L10+L11+L12+L13+L14+L15+L16 -> 1003.1112
A18: UFCF margin | B18: % | C18: =C17/C6 -> 0.36386501 | D18: =D17/D6 -> 0.39984818 | E18: =E17/E6 -> 0.11748707 | F18: =F17/F6 -> 0.26632959 | G18: =G17/G6 -> 0.35034643 | H18: =H17/H6 -> 0.34928846 | I18: =I17/I6 -> 0.23110303 | J18: =J17/J6 -> 0.2064383 | ... L18: =L17/L6 -> 0.24659457
A19: UFCF / NOPAT | B19: % | C19: =C17/C10 -> 0.94708666 | D19: =D17/D10 -> 0.91098324 | E19: =E17/E10 -> 0.59024266 | F19: =F17/F10 -> 0.82438662 | G19: =G17/G10 -> 1.0472364 | H19: =H17/H10 -> 0.96089419 | I19: =I17/I10 -> 0.76113428 | J19: =J17/J10 -> 0.77522265 | ... L19: =L17/L10 -> 0.94254281
A20: Bridge items (year end)
A21: Net cash excl. leases | B21: US$m | C21: ='Balance Sheet'!C53 -> 624.315 | D21: ='Balance Sheet'!D53 -> 725.673 | E21: ='Balance Sheet'!E53 -> 262.069 | F21: ='Balance Sheet'!F53 -> 578.327 | G21: ='Balance Sheet'!G53 -> 929.675 | H21: ='Balance Sheet'!H53 -> 917.24481 | I21: ='Balance Sheet'!I53 -> 948.69716 | J21: ='Balance Sheet'!J53 -> 911.13512 | ... L21: ='Balance Sheet'!L53 -> 1307.9663
A22: Investments in JVs and associates (book) | B22: US$m | C22: ='Balance Sheet'!C11+'Balance Sheet'!C12 -> 60.423 | D22: ='Balance Sheet'!D11+'Balance Sheet'!D12 -> 67.407 | E22: ='Balance Sheet'!E11+'Balance Sheet'!E12 -> 70.569 | F22: ='Balance Sheet'!F11+'Balance Sheet'!F12 -> 74.558 | G22: ='Balance Sheet'!G11+'Balance Sheet'!G12 -> 79.571 | H22: ='Balance Sheet'!H11+'Balance Sheet'!H12 -> 86.47892 | I22: ='Balance Sheet'!I11+'Balance Sheet'!I12 -> 93.603157 | J22: ='Balance Sheet'!J11+'Balance Sheet'!J12 -> 100.89612 | ... L22: ='Balance Sheet'!L11+'Balance Sheet'!L12 -> 116.00863
A23: Non-controlling interests (book) | B23: US$m | C23: ='Balance Sheet'!C45 -> 13.997 | D23: ='Balance Sheet'!D45 -> 14.471 | E23: ='Balance Sheet'!E45 -> 16.522 | F23: ='Balance Sheet'!F45 -> 17.268 | G23: ='Balance Sheet'!G45 -> 22.668 | H23: ='Balance Sheet'!H45 -> 28.889373 | I23: ='Balance Sheet'!I45 -> 33.892292 | J23: ='Balance Sheet'!J45 -> 38.326316 | ... L23: ='Balance Sheet'!L45 -> 47.566596
A24: JV dividends received | B24: US$m | C24: ='Cash Flow'!C23 -> 2.986 | D24: ='Cash Flow'!D23 -> 12.239 | E24: ='Cash Flow'!E23 -> 15.246 | F24: ='Cash Flow'!F23 -> 17.316 | G24: ='Cash Flow'!G23 -> 27.603 | H24: ='Cash Flow'!H23 -> 30.64488 | I24: ='Cash Flow'!I23 -> 31.870675 | J24: ='Cash Flow'!J23 -> 32.826795 | ... L24: ='Cash Flow'!L23 -> 34.825947
A25: Cycle reference
A26: Average freight rate | B26: US$/TEU | C26: ='Revenue Model'!C15 -> 826.9 | D26: ='Revenue Model'!D15 -> 1099.6 | E26: ='Revenue Model'!E15 -> 623.3 | F26: ='Revenue Model'!F15 -> 721.1 | G26: ='Revenue Model'!G15 -> 753.3 | H26: ='Revenue Model'!H15 -> 831.27891 | I26: ='Revenue Model'!I15 -> 748.15102 | J26: ='Revenue Model'!J15 -> 710.74347 | ... L26: ='Revenue Model'!L15 -> 717.85091
A27: Container volume | B27: TEU '000 | C27: ='Revenue Model'!C12 -> 3142.118 | D27: ='Revenue Model'!D12 -> 3261.939 | E27: ='Revenue Model'!E12 -> 3224.498 | F27: ='Revenue Model'!F12 -> 3570.184 | G27: ='Revenue Model'!G12 -> 3847.539 | H27: ='Revenue Model'!H12 -> 4053.7198 | I27: ='Revenue Model'!I12 -> 4256.4058 | J27: ='Revenue Model'!J12 -> 4469.2261 | ... L27: ='Revenue Model'!L12 -> 4810.675
A28: EBIT per TEU lifted | B28: US$/TEU | C28: =C8/C27*1000 -> 373.85738 | D28: =D8/D27*1000 -> 560.02519 | E28: =E8/E27*1000 -> 154.76114 | F28: =F8/F27*1000 -> 281.86727 | G28: =G8/G27*1000 -> 301.67388 | H28: =H8/H27*1000 -> 355.25021 | I28: =I8/I27*1000 -> 270.44432 | J28: =J8/J27*1000 -> 226.69423 | ... L28: =L8/L27*1000 -> 225.05489
A29: UFCF per TEU lifted | B29: US$/TEU | C29: =C17/C27*1000 -> 348.84879 | D29: =D17/D27*1000 -> 504.16564 | E29: =E17/E27*1000 -> 88.500991 | F29: =F17/F27*1000 -> 228.12595 | G29: =G17/G27*1000 -> 310.65529 | H29: =H17/H27*1000 -> 335.55478 | I29: =I17/I27*1000 -> 202.34509 | J29: =J17/J27*1000 -> 172.75095 | ... L29: =L17/L27*1000 -> 208.51777

Sheet DCF
A1: SITC International Holdings (1308.HK) - DCF
A2: Unlevered free cash flow after lease payments, discounted at the cost of equity (net-cash company). US$m unless stated.
A5: Discount rate
A6: Risk-free rate (US 10-year Treasury yield) | B6: % | C6: 0.05 | H6: Yahoo Finance ^TNX close 23-Oct-2026: 4.99%
A7: Equity beta, raw (5-year) | B7: x | C7: 1.03 | H7: stockanalysis.com (S&P Global MI), 24-Oct-2026
A8: Blume adjustment weight on raw beta | B8: x | C8: 0.67 | H8: Adjusted beta = w x raw + (1 - w) x 1.0
A9: Equity beta, adjusted | B9: x | C9: =$C$8*$C$7+(1-$C$8) -> 1.0201
A10: Equity risk premium (incl. China/HK country premium) | B10: % | C10: 0.05 | H10: Mature-market ERP ~4.3% + ~0.7% country premium (our assumption)
A11: Cost of equity | B11: % | C11: =$C$6+$C$9*$C$10 -> 0.101005 | H11: CAPM
A12: Pre-tax cost of debt (lease and bank rate) | B12: % | C12: =Scenarios!H68 -> 0.043
A13: Tax rate | B13: % | C13: =Scenarios!H72 -> 0.017
A14: Target debt / (debt + equity) | B14: % | C14: 0 | H14: Net cash balance sheet; leases are inside FCF, so no lease debt in the WACC
A15: WACC | B15: % | C15: =$C$11*(1-$C$14)+$C$12*(1-$C$13)*$C$14 -> 0.101005
A16: Terminal growth rate | B16: % | C16: 0.02 | H16: Below intra-Asia trade growth (3-4%) to allow for cyclical pricing pressure
A17: Valuation base date | C17: 31-Dec-2026 | H17: Cash flows from FY2027E; mid-year discounting; YE2026E net cash in the bridge
A19: Unlevered free cash flow | D19: FY2027E | E19: FY2028E | F19: FY2029E | G19: FY2030E
A20: Years from base date | D20: 1 | E20: =D20+1 -> 2 | F20: =E20+1 -> 3 | G20: =F20+1 -> 4
A21: Revenue | B21: US$m | D21: ='DCF Inputs'!I6 -> 3726.7482 | E21: ='DCF Inputs'!J6 -> 3739.9215 | F21: ='DCF Inputs'!K6 -> 3893.911 | G21: ='DCF Inputs'!L6 -> 4067.856
A22: EBITDA excl. disposal gains | B22: US$m | D22: ='DCF Inputs'!I8+'DCF Inputs'!I11 -> 1331.4279 | E22: ='DCF Inputs'!J8+'DCF Inputs'!J11 -> 1213.117 | F22: ='DCF Inputs'!K8+'DCF Inputs'!K11 -> 1248.051 | G22: ='DCF Inputs'!L8+'DCF Inputs'!L11 -> 1303.9775 | H22: Disposal gains excluded; proceeds counted in capex net
A23: Depreciation and amortisation | B23: US$m | D23: ='DCF Inputs'!I11 -> 180.30713 | E23: ='DCF Inputs'!J11 -> 199.96921 | F23: ='DCF Inputs'!K11 -> 221.61344 | G23: ='DCF Inputs'!L11 -> 221.31158
A24: EBIT excl. disposal gains | B24: US$m | D24: =D22-D23 -> 1151.1208 | E24: =E22-E23 -> 1013.1478 | F24: =F22-F23 -> 1026.4376 | G24: =G22-G23 -> 1082.6659
A25: Tax rate | B25: % | D25: ='DCF Inputs'!I9 -> 0.017 | E25: ='DCF Inputs'!J9 -> 0.017 | F25: ='DCF Inputs'!K9 -> 0.017 | G25: ='DCF Inputs'!L9 -> 0.017
A26: NOPAT | B26: US$m | D26: =D24*(1-D25) -> 1131.5517 | E26: =E24*(1-E25) -> 995.92426 | F26: =F24*(1-F25) -> 1008.9881 | G26: =G24*(1-G25) -> 1064.2606
A27: Capex net of disposal proceeds | B27: US$m | D27: ='DCF Inputs'!I12+'DCF Inputs'!I13 -> -375 | E27: ='DCF Inputs'!J12+'DCF Inputs'!J13 -> -345 | F27: ='DCF Inputs'!K12+'DCF Inputs'!K13 -> -193.1 | G27: ='DCF Inputs'!L12+'DCF Inputs'!L13 -> -195
A28: Change in working capital | B28: US$m | D28: ='DCF Inputs'!I14 -> 14.307836 | E28: ='DCF Inputs'!J14 -> 12.441214 | F28: ='DCF Inputs'!K14 -> 8.2636604 | G28: ='DCF Inputs'!L14 -> 5.5180547
A29: Lease payments (principal + interest) | B29: US$m | D29: ='DCF Inputs'!I15+'DCF Inputs'!I16 -> -89.903875 | E29: ='DCF Inputs'!J15+'DCF Inputs'!J16 -> -91.271642 | F29: ='DCF Inputs'!K15+'DCF Inputs'!K16 -> -92.270907 | G29: ='DCF Inputs'!L15+'DCF Inputs'!L16 -> -92.979057
A30: Other cash items (capex, working capital, leases) | B30: US$m | D30: =D27+D28+D29 -> -450.59604 | E30: =E27+E28+E29 -> -423.83043 | F30: =F27+F28+F29 -> -277.10725 | G30: =G27+G28+G29 -> -282.461
A31: Unlevered free cash flow | B31: US$m | D31: =D26+D23+D30 -> 861.2628 | E31: =E26+E23+E30 -> 772.06304 | F31: =F26+F23+F30 -> 953.49432 | G31: =G26+G23+G30 -> 1003.1112 | H31: Ties to 'DCF Inputs' UFCF; Checks tab
A32: Discount factor (mid-year) | B32: x | D32: =1/(1+$C$15)^(D20-0.5) -> 0.95302733 | E32: =1/(1+$C$15)^(E20-0.5) -> 0.86559764 | F32: =1/(1+$C$15)^(F20-0.5) -> 0.78618865 | G32: =1/(1+$C$15)^(G20-0.5) -> 0.71406456
A33: Present value of UFCF | B33: US$m | D33: =D31*D32 -> 820.80698 | E33: =E31*E32 -> 668.29595 | F33: =F31*F32 -> 749.62642 | G33: =G31*G32 -> 716.28615
A35: Terminal value (Gordon growth on FY2030E UFCF)
A36: Terminal-year UFCF (FY2030E) | B36: US$m | C36: =G31 -> 1003.1112 | H36: FY2030E freight rate ~US$720/TEU, close to the FY2023-25 average (US$699)
A37: Terminal value at end-FY2030 | B37: US$m | C37: =$C$36*(1+$C$16)/($C$15-$C$16) -> 12630.991
A38: Discount factor (end of FY2030) | B38: x | C38: =1/(1+$C$15)^G20 -> 0.68052304
A39: Present value of terminal value | B39: US$m | C39: =$C$37*$C$38 -> 8595.6803
A40: Implied terminal EV / FY2030E EBITDA | B40: x | C40: =$C$37/G22 -> 9.6865097
A42: Equity bridge at 31-Dec-2026E
A43: Sum of PV of UFCF, FY2027E-30E | B43: US$m | C43: =SUM(D33:G33) -> 2955.0155
A44: PV of terminal value | B44: US$m | C44: =$C$39 -> 8595.6803
A45: Enterprise value (leases treated as operating) | B45: US$m | C45: =$C$43+$C$44 -> 11550.696
A46: Terminal value share of EV | B46: % | C46: =$C$44/$C$45 -> 0.74416991
A47: Add: net cash excl. leases, YE2026E | B47: US$m | C47: ='Balance Sheet'!H53 -> 917.24481 | H47: After the HK$1.00 special dividend paid 17-Dec-2026
A48: Add: JVs and associates at book | B48: US$m | C48: ='DCF Inputs'!H22 -> 86.47892
A49: Less: non-controlling interests at book | B49: US$m | C49: =-'DCF Inputs'!H23 -> -28.889373
A50: Equity value | B50: US$m | C50: =$C$45+$C$47+$C$48+$C$49 -> 12525.53
A51: Shares in issue (diluted) | B51: m | C51: =Inputs!$C$14 -> 2711.5282
A52: Equity value per share | B52: US$ | C52: =$C$50/$C$51 -> 4.6193619
A53: DCF value per share | B53: HK$ | C53: =$C$52*Inputs!$C$7 -> 36.221802 | H53: Value at end-2026, after the December special dividend
A54: vs current share price | B54: % | C54: =$C$53/Inputs!$C$6-1 -> -0.24031455
A55: Implied FY2027E P/E at DCF value | B55: x | C55: =$C$53/'Income Statement'!I59 -> 10.588422
A56: Implied FY2027E EV/EBITDA at DCF value | B56: x | C56: =$C$45/'Income Statement'!I39 -> 8.6429623
A58: Reverse DCF: what the share price implies
A59: Share price less the Dec-2026 special dividend | B59: HK$ | C59: =Inputs!$C$6-Inputs!$C$19 -> 46.68 | H59: The stock trades cum the HK$1.00 special until 4-Dec-2026
A60: Market equity value on that basis | B60: US$m | C60: =$C$59*$C$51/Inputs!$C$7 -> 16141.984
A61: Market-implied enterprise value | B61: US$m | C61: =$C$60-$C$47-$C$48-$C$49 -> 15167.149
A62: Market-implied PV of terminal value | B62: US$m | C62: =$C$61-$C$43 -> 12212.134
A63: Implied terminal-year UFCF | B63: US$m | C63: =$C$62/$C$38*($C$15-$C$16)/(1+$C$16) -> 1425.1494 | H63: Holding our FY2027E-30E cash flows, WACC and g
A64: Implied terminal UFCF vs our FY2030E | B64: % | C64: =$C$63/$C$36-1 -> 0.42072919
A65: Implied terminal UFCF per TEU lifted | B65: US$/TEU | C65: =$C$63/'DCF Inputs'!L27*1000 -> 296.24728
A66: Model UFCF per TEU: FY2030E (memo: FY2026E in note) | B66: US$/TEU | C66: ='DCF Inputs'!L29 -> 208.51777 | H66: Compare with FY2026E on the DCF Inputs tab

Sheet Sensitivity
A1: SITC International Holdings (1308.HK) - Sensitivity
A2: DCF value per share (HK$) recomputed in every cell; P/E and freight-rate grids use model EPS. Base case boxed.
A5: Table 1. DCF value per share (HK$): WACC vs terminal growth
A6: WACC \ terminal growth | B6: =DCF!$C$16+(-0.01) -> 0.01 | C6: =DCF!$C$16+(-0.005) -> 0.015 | D6: =DCF!$C$16+(0) -> 0.02 | E6: =DCF!$C$16+(0.005) -> 0.025 | F6: =DCF!$C$16+(0.01) -> 0.03
A7: =DCF!$C$15+(-0.02) -> 0.081005 | B7: =(SUMPRODUCT(DCF!$D$31:$G$31/(1+$A7)^(DCF!$D$20:$G$20-0.5))+DCF!$G$31*(1+B$6)/($A7-B$6)/(1+$A7)^DCF!$G$20+(DCF!$C$47+DCF!$C$48+DCF!$C$49))/DCF!$C$51*Inputs!$C$7 -> 41.895686 | C7: =(SUMPRODUCT(DCF!$D$31:$G$31/(1+$A7)^(DCF!$D$20:$G$20-0.5))+DCF!$G$31*(1+C$6)/($A7-C$6)/(1+$A7)^DCF!$G$20+(DCF!$C$47+DCF!$C$48+DCF!$C$49))/DCF!$C$51*Inputs!$C$7 -> 44.345562 | D7: =(SUMPRODUCT(DCF!$D$31:$G$31/(1+$A7)^(DCF!$D$20:$G$20-0.5))+DCF!$G$31*(1+D$6)/($A7-D$6)/(1+$A7)^DCF!$G$20+(DCF!$C$47+DCF!$C$48+DCF!$C$49))/DCF!$C$51*Inputs!$C$7 -> 47.197025 | E7: =(SUMPRODUCT(DCF!$D$31:$G$31/(1+$A7)^(DCF!$D$20:$G$20-0.5))+DCF!$G$31*(1+E$6)/($A7-E$6)/(1+$A7)^DCF!$G$20+(DCF!$C$47+DCF!$C$48+DCF!$C$49))/DCF!$C$51*Inputs!$C$7 -> 50.557631 | F7: =(SUMPRODUCT(DCF!$D$31:$G$31/(1+$A7)^(DCF!$D$20:$G$20-0.5))+DCF!$G$31*(1+F$6)/($A7-F$6)/(1+$A7)^DCF!$G$20+(DCF!$C$47+DCF!$C$48+DCF!$C$49))/DCF!$C$51*Inputs!$C$7 -> 54.577116
A8: =DCF!$C$15+(-0.015) -> 0.086005 | B8: =(SUMPRODUCT(DCF!$D$31:$G$31/(1+$A8)^(DCF!$D$20:$G$20-0.5))+DCF!$G$31*(1+B$6)/($A8-B$6)/(1+$A8)^DCF!$G$20+(DCF!$C$47+DCF!$C$48+DCF!$C$49))/DCF!$C$51*Inputs!$C$7 -> 39.310961 | C8: =(SUMPRODUCT(DCF!$D$31:$G$31/(1+$A8)^(DCF!$D$20:$G$20-0.5))+DCF!$G$31*(1+C$6)/($A8-C$6)/(1+$A8)^DCF!$G$20+(DCF!$C$47+DCF!$C$48+DCF!$C$49))/DCF!$C$51*Inputs!$C$7 -> 41.409256 | D8: =(SUMPRODUCT(DCF!$D$31:$G$31/(1+$A8)^(DCF!$D$20:$G$20-0.5))+DCF!$G$31*(1+D$6)/($A8-D$6)/(1+$A8)^DCF!$G$20+(DCF!$C$47+DCF!$C$48+DCF!$C$49))/DCF!$C$51*Inputs!$C$7 -> 43.825449 | E8: =(SUMPRODUCT(DCF!$D$31:$G$31/(1+$A8)^(DCF!$D$20:$G$20-0.5))+DCF!$G$31*(1+E$6)/($A8-E$6)/(1+$A8)^DCF!$G$20+(DCF!$C$47+DCF!$C$48+DCF!$C$49))/DCF!$C$51*Inputs!$C$7 -> 46.637708 | F8: =(SUMPRODUCT(DCF!$D$31:$G$31/(1+$A8)^(DCF!$D$20:$G$20-0.5))+DCF!$G$31*(1+F$6)/($A8-F$6)/(1+$A8)^DCF!$G$20+(DCF!$C$47+DCF!$C$48+DCF!$C$49))/DCF!$C$51*Inputs!$C$7 -> 49.952111
A9: =DCF!$C$15+(-0.01) -> 0.091005 | B9: =(SUMPRODUCT(DCF!$D$31:$G$31/(1+$A9)^(DCF!$D$20:$G$20-0.5))+DCF!$G$31*(1+B$6)/($A9-B$6)/(1+$A9)^DCF!$G$20+(DCF!$C$47+DCF!$C$48+DCF!$C$49))/DCF!$C$51*Inputs!$C$7 -> 37.047724 | C9: =(SUMPRODUCT(DCF!$D$31:$G$31/(1+$A9)^(DCF!$D$20:$G$20-0.5))+DCF!$G$31*(1+C$6)/($A9-C$6)/(1+$A9)^DCF!$G$20+(DCF!$C$47+DCF!$C$48+DCF!$C$49))/DCF!$C$51*Inputs!$C$7 -> 38.861814 | D9: =(SUMPRODUCT(DCF!$D$31:$G$31/(1+$A9)^(DCF!$D$20:$G$20-0.5))+DCF!$G$31*(1+D$6)/($A9-D$6)/(1+$A9)^DCF!$G$20+(DCF!$C$47+DCF!$C$48+DCF!$C$49))/DCF!$C$51*Inputs!$C$7 -> 40.931391 | E9: =(SUMPRODUCT(DCF!$D$31:$G$31/(1+$A9)^(DCF!$D$20:$G$20-0.5))+DCF!$G$31*(1+E$6)/($A9-E$6)/(1+$A9)^DCF!$G$20+(DCF!$C$47+DCF!$C$48+DCF!$C$49))/DCF!$C$51*Inputs!$C$7 -> 43.314517 | F9: =(SUMPRODUCT(DCF!$D$31:$G$31/(1+$A9)^(DCF!$D$20:$G$20-0.5))+DCF!$G$31*(1+F$6)/($A9-F$6)/(1+$A9)^DCF!$G$20+(DCF!$C$47+DCF!$C$48+DCF!$C$49))/DCF!$C$51*Inputs!$C$7 -> 46.088288
A10: =DCF!$C$15+(-0.005) -> 0.096005 | B10: =(SUMPRODUCT(DCF!$D$31:$G$31/(1+$A10)^(DCF!$D$20:$G$20-0.5))+DCF!$G$31*(1+B$6)/($A10-B$6)/(1+$A10)^DCF!$G$20+(DCF!$C$47+DCF!$C$48+DCF!$C$49))/DCF!$C$51*Inputs!$C$7 -> 35.049825 | C10: =(SUMPRODUCT(DCF!$D$31:$G$31/(1+$A10)^(DCF!$D$20:$G$20-0.5))+DCF!$G$31*(1+C$6)/($A10-C$6)/(1+$A10)^DCF!$G$20+(DCF!$C$47+DCF!$C$48+DCF!$C$49))/DCF!$C$51*Inputs!$C$7 -> 36.631146 | D10: =(SUMPRODUCT(DCF!$D$31:$G$31/(1+$A10)^(DCF!$D$20:$G$20-0.5))+DCF!$G$31*(1+D$6)/($A10-D$6)/(1+$A10)^DCF!$G$20+(DCF!$C$47+DCF!$C$48+DCF!$C$49))/DCF!$C$51*Inputs!$C$7 -> 38.420521 | E10: =(SUMPRODUCT(DCF!$D$31:$G$31/(1+$A10)^(DCF!$D$20:$G$20-0.5))+DCF!$G$31*(1+E$6)/($A10-E$6)/(1+$A10)^DCF!$G$20+(DCF!$C$47+DCF!$C$48+DCF!$C$49))/DCF!$C$51*Inputs!$C$7 -> 40.461903 | F10: =(SUMPRODUCT(DCF!$D$31:$G$31/(1+$A10)^(DCF!$D$20:$G$20-0.5))+DCF!$G$31*(1+F$6)/($A10-F$6)/(1+$A10)^DCF!$G$20+(DCF!$C$47+DCF!$C$48+DCF!$C$49))/DCF!$C$51*Inputs!$C$7 -> 42.812562
A11: =DCF!$C$15+(0) -> 0.101005 | B11: =(SUMPRODUCT(DCF!$D$31:$G$31/(1+$A11)^(DCF!$D$20:$G$20-0.5))+DCF!$G$31*(1+B$6)/($A11-B$6)/(1+$A11)^DCF!$G$20+(DCF!$C$47+DCF!$C$48+DCF!$C$49))/DCF!$C$51*Inputs!$C$7 -> 33.273459 | C11: =(SUMPRODUCT(DCF!$D$31:$G$31/(1+$A11)^(DCF!$D$20:$G$20-0.5))+DCF!$G$31*(1+C$6)/($A11-C$6)/(1+$A11)^DCF!$G$20+(DCF!$C$47+DCF!$C$48+DCF!$C$49))/DCF!$C$51*Inputs!$C$7 -> 34.661928 | D11: =(SUMPRODUCT(DCF!$D$31:$G$31/(1+$A11)^(DCF!$D$20:$G$20-0.5))+DCF!$G$31*(1+D$6)/($A11-D$6)/(1+$A11)^DCF!$G$20+(DCF!$C$47+DCF!$C$48+DCF!$C$49))/DCF!$C$51*Inputs!$C$7 -> 36.221802 | E11: =(SUMPRODUCT(DCF!$D$31:$G$31/(1+$A11)^(DCF!$D$20:$G$20-0.5))+DCF!$G$31*(1+E$6)/($A11-E$6)/(1+$A11)^DCF!$G$20+(DCF!$C$47+DCF!$C$48+DCF!$C$49))/DCF!$C$51*Inputs!$C$7 -> 37.98691 | F11: =(SUMPRODUCT(DCF!$D$31:$G$31/(1+$A11)^(DCF!$D$20:$G$20-0.5))+DCF!$G$31*(1+F$6)/($A11-F$6)/(1+$A11)^DCF!$G$20+(DCF!$C$47+DCF!$C$48+DCF!$C$49))/DCF!$C$51*Inputs!$C$7 -> 40.000607
A12: =DCF!$C$15+(0.005) -> 0.106005 | B12: =(SUMPRODUCT(DCF!$D$31:$G$31/(1+$A12)^(DCF!$D$20:$G$20-0.5))+DCF!$G$31*(1+B$6)/($A12-B$6)/(1+$A12)^DCF!$G$20+(DCF!$C$47+DCF!$C$48+DCF!$C$49))/DCF!$C$51*Inputs!$C$7 -> 31.683947 | C12: =(SUMPRODUCT(DCF!$D$31:$G$31/(1+$A12)^(DCF!$D$20:$G$20-0.5))+DCF!$G$31*(1+C$6)/($A12-C$6)/(1+$A12)^DCF!$G$20+(DCF!$C$47+DCF!$C$48+DCF!$C$49))/DCF!$C$51*Inputs!$C$7 -> 32.910998 | D12: =(SUMPRODUCT(DCF!$D$31:$G$31/(1+$A12)^(DCF!$D$20:$G$20-0.5))+DCF!$G$31*(1+D$6)/($A12-D$6)/(1+$A12)^DCF!$G$20+(DCF!$C$47+DCF!$C$48+DCF!$C$49))/DCF!$C$51*Inputs!$C$7 -> 34.280721 | E12: =(SUMPRODUCT(DCF!$D$31:$G$31/(1+$A12)^(DCF!$D$20:$G$20-0.5))+DCF!$G$31*(1+E$6)/($A12-E$6)/(1+$A12)^DCF!$G$20+(DCF!$C$47+DCF!$C$48+DCF!$C$49))/DCF!$C$51*Inputs!$C$7 -> 35.819536 | F12: =(SUMPRODUCT(DCF!$D$31:$G$31/(1+$A12)^(DCF!$D$20:$G$20-0.5))+DCF!$G$31*(1+F$6)/($A12-F$6)/(1+$A12)^DCF!$G$20+(DCF!$C$47+DCF!$C$48+DCF!$C$49))/DCF!$C$51*Inputs!$C$7 -> 37.560812
A13: =DCF!$C$15+(0.01) -> 0.111005 | B13: =(SUMPRODUCT(DCF!$D$31:$G$31/(1+$A13)^(DCF!$D$20:$G$20-0.5))+DCF!$G$31*(1+B$6)/($A13-B$6)/(1+$A13)^DCF!$G$20+(DCF!$C$47+DCF!$C$48+DCF!$C$49))/DCF!$C$51*Inputs!$C$7 -> 30.25348 | C13: =(SUMPRODUCT(DCF!$D$31:$G$31/(1+$A13)^(DCF!$D$20:$G$20-0.5))+DCF!$G$31*(1+C$6)/($A13-C$6)/(1+$A13)^DCF!$G$20+(DCF!$C$47+DCF!$C$48+DCF!$C$49))/DCF!$C$51*Inputs!$C$7 -> 31.344188 | D13: =(SUMPRODUCT(DCF!$D$31:$G$31/(1+$A13)^(DCF!$D$20:$G$20-0.5))+DCF!$G$31*(1+D$6)/($A13-D$6)/(1+$A13)^DCF!$G$20+(DCF!$C$47+DCF!$C$48+DCF!$C$49))/DCF!$C$51*Inputs!$C$7 -> 32.554747 | E13: =(SUMPRODUCT(DCF!$D$31:$G$31/(1+$A13)^(DCF!$D$20:$G$20-0.5))+DCF!$G$31*(1+E$6)/($A13-E$6)/(1+$A13)^DCF!$G$20+(DCF!$C$47+DCF!$C$48+DCF!$C$49))/DCF!$C$51*Inputs!$C$7 -> 33.90606 | F13: =(SUMPRODUCT(DCF!$D$31:$G$31/(1+$A13)^(DCF!$D$20:$G$20-0.5))+DCF!$G$31*(1+F$6)/($A13-F$6)/(1+$A13)^DCF!$G$20+(DCF!$C$47+DCF!$C$48+DCF!$C$49))/DCF!$C$51*Inputs!$C$7 -> 35.424192
A14: =DCF!$C$15+(0.015) -> 0.116005 | B14: =(SUMPRODUCT(DCF!$D$31:$G$31/(1+$A14)^(DCF!$D$20:$G$20-0.5))+DCF!$G$31*(1+B$6)/($A14-B$6)/(1+$A14)^DCF!$G$20+(DCF!$C$47+DCF!$C$48+DCF!$C$49))/DCF!$C$51*Inputs!$C$7 -> 28.959498 | C14: =(SUMPRODUCT(DCF!$D$31:$G$31/(1+$A14)^(DCF!$D$20:$G$20-0.5))+DCF!$G$31*(1+C$6)/($A14-C$6)/(1+$A14)^DCF!$G$20+(DCF!$C$47+DCF!$C$48+DCF!$C$49))/DCF!$C$51*Inputs!$C$7 -> 29.934096 | D14: =(SUMPRODUCT(DCF!$D$31:$G$31/(1+$A14)^(DCF!$D$20:$G$20-0.5))+DCF!$G$31*(1+D$6)/($A14-D$6)/(1+$A14)^DCF!$G$20+(DCF!$C$47+DCF!$C$48+DCF!$C$49))/DCF!$C$51*Inputs!$C$7 -> 31.010209 | E14: =(SUMPRODUCT(DCF!$D$31:$G$31/(1+$A14)^(DCF!$D$20:$G$20-0.5))+DCF!$G$31*(1+E$6)/($A14-E$6)/(1+$A14)^DCF!$G$20+(DCF!$C$47+DCF!$C$48+DCF!$C$49))/DCF!$C$51*Inputs!$C$7 -> 32.20457 | F14: =(SUMPRODUCT(DCF!$D$31:$G$31/(1+$A14)^(DCF!$D$20:$G$20-0.5))+DCF!$G$31*(1+F$6)/($A14-F$6)/(1+$A14)^DCF!$G$20+(DCF!$C$47+DCF!$C$48+DCF!$C$49))/DCF!$C$51*Inputs!$C$7 -> 33.537802
A15: =DCF!$C$15+(0.02) -> 0.121005 | B15: =(SUMPRODUCT(DCF!$D$31:$G$31/(1+$A15)^(DCF!$D$20:$G$20-0.5))+DCF!$G$31*(1+B$6)/($A15-B$6)/(1+$A15)^DCF!$G$20+(DCF!$C$47+DCF!$C$48+DCF!$C$49))/DCF!$C$51*Inputs!$C$7 -> 27.783508 | C15: =(SUMPRODUCT(DCF!$D$31:$G$31/(1+$A15)^(DCF!$D$20:$G$20-0.5))+DCF!$G$31*(1+C$6)/($A15-C$6)/(1+$A15)^DCF!$G$20+(DCF!$C$47+DCF!$C$48+DCF!$C$49))/DCF!$C$51*Inputs!$C$7 -> 28.658494 | D15: =(SUMPRODUCT(DCF!$D$31:$G$31/(1+$A15)^(DCF!$D$20:$G$20-0.5))+DCF!$G$31*(1+D$6)/($A15-D$6)/(1+$A15)^DCF!$G$20+(DCF!$C$47+DCF!$C$48+DCF!$C$49))/DCF!$C$51*Inputs!$C$7 -> 29.620109 | E15: =(SUMPRODUCT(DCF!$D$31:$G$31/(1+$A15)^(DCF!$D$20:$G$20-0.5))+DCF!$G$31*(1+E$6)/($A15-E$6)/(1+$A15)^DCF!$G$20+(DCF!$C$47+DCF!$C$48+DCF!$C$49))/DCF!$C$51*Inputs!$C$7 -> 30.681887 | F15: =(SUMPRODUCT(DCF!$D$31:$G$31/(1+$A15)^(DCF!$D$20:$G$20-0.5))+DCF!$G$31*(1+F$6)/($A15-F$6)/(1+$A15)^DCF!$G$20+(DCF!$C$47+DCF!$C$48+DCF!$C$49))/DCF!$C$51*Inputs!$C$7 -> 31.860337
A16: Centre cell equals the DCF tab value; rows and columns move with the DCF inputs.
A19: Table 2. DCF value per share (HK$): FY2025A-30E revenue CAGR vs FY2030E EBITDA margin
A20: Revenue CAGR \ EBITDA margin | B20: =(DCF!$G$22/DCF!$G$21)+(-0.08) -> 0.24055646 | C20: =(DCF!$G$22/DCF!$G$21)+(-0.04) -> 0.28055646 | D20: =(DCF!$G$22/DCF!$G$21)+(0) -> 0.32055646 | E20: =(DCF!$G$22/DCF!$G$21)+(0.04) -> 0.36055646 | F20: =(DCF!$G$22/DCF!$G$21)+(0.08) -> 0.40055646
A21: =((DCF!$G$21/'Income Statement'!$G$9)^(1/5)-1)+(-0.03) -> 0.0058104675 | B21: =(SUMPRODUCT(DCF!$D$31:$F$31/(1+DCF!$C$15)^(DCF!$D$20:$F$20-0.5))+(('Income Statement'!$G$9*(1+$A21)^5*B$20-DCF!$G$23)*(1-DCF!$G$25)+DCF!$G$23+DCF!$G$30)*(1/(1+DCF!$C$15)^(DCF!$G$20-0.5)+(1+DCF!$C$16)/(DCF!$C$15-DCF!$C$16)/(1+DCF!$C$15)^DCF!$G$20)+(DCF!$C$47+DCF!$C$48+DCF!$C$49))/DCF!$C$51*Inputs!$C$7 -> 24.105064 | C21: =(SUMPRODUCT(DCF!$D$31:$F$31/(1+DCF!$C$15)^(DCF!$D$20:$F$20-0.5))+(('Income Statement'!$G$9*(1+$A21)^5*C$20-DCF!$G$23)*(1-DCF!$G$25)+DCF!$G$23+DCF!$G$30)*(1/(1+DCF!$C$15)^(DCF!$G$20-0.5)+(1+DCF!$C$16)/(DCF!$C$15-DCF!$C$16)/(1+DCF!$C$15)^DCF!$G$20)+(DCF!$C$47+DCF!$C$48+DCF!$C$49))/DCF!$C$51*Inputs!$C$7 -> 27.812081 | D21: =(SUMPRODUCT(DCF!$D$31:$F$31/(1+DCF!$C$15)^(DCF!$D$20:$F$20-0.5))+(('Income Statement'!$G$9*(1+$A21)^5*D$20-DCF!$G$23)*(1-DCF!$G$25)+DCF!$G$23+DCF!$G$30)*(1/(1+DCF!$C$15)^(DCF!$G$20-0.5)+(1+DCF!$C$16)/(DCF!$C$15-DCF!$C$16)/(1+DCF!$C$15)^DCF!$G$20)+(DCF!$C$47+DCF!$C$48+DCF!$C$49))/DCF!$C$51*Inputs!$C$7 -> 31.519098 | E21: =(SUMPRODUCT(DCF!$D$31:$F$31/(1+DCF!$C$15)^(DCF!$D$20:$F$20-0.5))+(('Income Statement'!$G$9*(1+$A21)^5*E$20-DCF!$G$23)*(1-DCF!$G$25)+DCF!$G$23+DCF!$G$30)*(1/(1+DCF!$C$15)^(DCF!$G$20-0.5)+(1+DCF!$C$16)/(DCF!$C$15-DCF!$C$16)/(1+DCF!$C$15)^DCF!$G$20)+(DCF!$C$47+DCF!$C$48+DCF!$C$49))/DCF!$C$51*Inputs!$C$7 -> 35.226116 | F21: =(SUMPRODUCT(DCF!$D$31:$F$31/(1+DCF!$C$15)^(DCF!$D$20:$F$20-0.5))+(('Income Statement'!$G$9*(1+$A21)^5*F$20-DCF!$G$23)*(1-DCF!$G$25)+DCF!$G$23+DCF!$G$30)*(1/(1+DCF!$C$15)^(DCF!$G$20-0.5)+(1+DCF!$C$16)/(DCF!$C$15-DCF!$C$16)/(1+DCF!$C$15)^DCF!$G$20)+(DCF!$C$47+DCF!$C$48+DCF!$C$49))/DCF!$C$51*Inputs!$C$7 -> 38.933133
A22: =((DCF!$G$21/'Income Statement'!$G$9)^(1/5)-1)+(-0.015) -> 0.020810467 | B22: =(SUMPRODUCT(DCF!$D$31:$F$31/(1+DCF!$C$15)^(DCF!$D$20:$F$20-0.5))+(('Income Statement'!$G$9*(1+$A22)^5*B$20-DCF!$G$23)*(1-DCF!$G$25)+DCF!$G$23+DCF!$G$30)*(1/(1+DCF!$C$15)^(DCF!$G$20-0.5)+(1+DCF!$C$16)/(DCF!$C$15-DCF!$C$16)/(1+DCF!$C$15)^DCF!$G$20)+(DCF!$C$47+DCF!$C$48+DCF!$C$49))/DCF!$C$51*Inputs!$C$7 -> 25.817758 | C22: =(SUMPRODUCT(DCF!$D$31:$F$31/(1+DCF!$C$15)^(DCF!$D$20:$F$20-0.5))+(('Income Statement'!$G$9*(1+$A22)^5*C$20-DCF!$G$23)*(1-DCF!$G$25)+DCF!$G$23+DCF!$G$30)*(1/(1+DCF!$C$15)^(DCF!$G$20-0.5)+(1+DCF!$C$16)/(DCF!$C$15-DCF!$C$16)/(1+DCF!$C$15)^DCF!$G$20)+(DCF!$C$47+DCF!$C$48+DCF!$C$49))/DCF!$C$51*Inputs!$C$7 -> 29.809564 | D22: =(SUMPRODUCT(DCF!$D$31:$F$31/(1+DCF!$C$15)^(DCF!$D$20:$F$20-0.5))+(('Income Statement'!$G$9*(1+$A22)^5*D$20-DCF!$G$23)*(1-DCF!$G$25)+DCF!$G$23+DCF!$G$30)*(1/(1+DCF!$C$15)^(DCF!$G$20-0.5)+(1+DCF!$C$16)/(DCF!$C$15-DCF!$C$16)/(1+DCF!$C$15)^DCF!$G$20)+(DCF!$C$47+DCF!$C$48+DCF!$C$49))/DCF!$C$51*Inputs!$C$7 -> 33.80137 | E22: =(SUMPRODUCT(DCF!$D$31:$F$31/(1+DCF!$C$15)^(DCF!$D$20:$F$20-0.5))+(('Income Statement'!$G$9*(1+$A22)^5*E$20-DCF!$G$23)*(1-DCF!$G$25)+DCF!$G$23+DCF!$G$30)*(1/(1+DCF!$C$15)^(DCF!$G$20-0.5)+(1+DCF!$C$16)/(DCF!$C$15-DCF!$C$16)/(1+DCF!$C$15)^DCF!$G$20)+(DCF!$C$47+DCF!$C$48+DCF!$C$49))/DCF!$C$51*Inputs!$C$7 -> 37.793176 | F22: =(SUMPRODUCT(DCF!$D$31:$F$31/(1+DCF!$C$15)^(DCF!$D$20:$F$20-0.5))+(('Income Statement'!$G$9*(1+$A22)^5*F$20-DCF!$G$23)*(1-DCF!$G$25)+DCF!$G$23+DCF!$G$30)*(1/(1+DCF!$C$15)^(DCF!$G$20-0.5)+(1+DCF!$C$16)/(DCF!$C$15-DCF!$C$16)/(1+DCF!$C$15)^DCF!$G$20)+(DCF!$C$47+DCF!$C$48+DCF!$C$49))/DCF!$C$51*Inputs!$C$7 -> 41.784983
A23: =((DCF!$G$21/'Income Statement'!$G$9)^(1/5)-1)+(0) -> 0.035810467 | B23: =(SUMPRODUCT(DCF!$D$31:$F$31/(1+DCF!$C$15)^(DCF!$D$20:$F$20-0.5))+(('Income Statement'!$G$9*(1+$A23)^5*B$20-DCF!$G$23)*(1-DCF!$G$25)+DCF!$G$23+DCF!$G$30)*(1/(1+DCF!$C$15)^(DCF!$G$20-0.5)+(1+DCF!$C$16)/(DCF!$C$15-DCF!$C$16)/(1+DCF!$C$15)^DCF!$G$20)+(DCF!$C$47+DCF!$C$48+DCF!$C$49))/DCF!$C$51*Inputs!$C$7 -> 27.634133 | C23: =(SUMPRODUCT(DCF!$D$31:$F$31/(1+DCF!$C$15)^(DCF!$D$20:$F$20-0.5))+(('Income Statement'!$G$9*(1+$A23)^5*C$20-DCF!$G$23)*(1-DCF!$G$25)+DCF!$G$23+DCF!$G$30)*(1/(1+DCF!$C$15)^(DCF!$G$20-0.5)+(1+DCF!$C$16)/(DCF!$C$15-DCF!$C$16)/(1+DCF!$C$15)^DCF!$G$20)+(DCF!$C$47+DCF!$C$48+DCF!$C$49))/DCF!$C$51*Inputs!$C$7 -> 31.927968 | D23: =(SUMPRODUCT(DCF!$D$31:$F$31/(1+DCF!$C$15)^(DCF!$D$20:$F$20-0.5))+(('Income Statement'!$G$9*(1+$A23)^5*D$20-DCF!$G$23)*(1-DCF!$G$25)+DCF!$G$23+DCF!$G$30)*(1/(1+DCF!$C$15)^(DCF!$G$20-0.5)+(1+DCF!$C$16)/(DCF!$C$15-DCF!$C$16)/(1+DCF!$C$15)^DCF!$G$20)+(DCF!$C$47+DCF!$C$48+DCF!$C$49))/DCF!$C$51*Inputs!$C$7 -> 36.221802 | E23: =(SUMPRODUCT(DCF!$D$31:$F$31/(1+DCF!$C$15)^(DCF!$D$20:$F$20-0.5))+(('Income Statement'!$G$9*(1+$A23)^5*E$20-DCF!$G$23)*(1-DCF!$G$25)+DCF!$G$23+DCF!$G$30)*(1/(1+DCF!$C$15)^(DCF!$G$20-0.5)+(1+DCF!$C$16)/(DCF!$C$15-DCF!$C$16)/(1+DCF!$C$15)^DCF!$G$20)+(DCF!$C$47+DCF!$C$48+DCF!$C$49))/DCF!$C$51*Inputs!$C$7 -> 40.515637 | F23: =(SUMPRODUCT(DCF!$D$31:$F$31/(1+DCF!$C$15)^(DCF!$D$20:$F$20-0.5))+(('Income Statement'!$G$9*(1+$A23)^5*F$20-DCF!$G$23)*(1-DCF!$G$25)+DCF!$G$23+DCF!$G$30)*(1/(1+DCF!$C$15)^(DCF!$G$20-0.5)+(1+DCF!$C$16)/(DCF!$C$15-DCF!$C$16)/(1+DCF!$C$15)^DCF!$G$20)+(DCF!$C$47+DCF!$C$48+DCF!$C$49))/DCF!$C$51*Inputs!$C$7 -> 44.809472
A24: =((DCF!$G$21/'Income Statement'!$G$9)^(1/5)-1)+(0.015) -> 0.050810467 | B24: =(SUMPRODUCT(DCF!$D$31:$F$31/(1+DCF!$C$15)^(DCF!$D$20:$F$20-0.5))+(('Income Statement'!$G$9*(1+$A24)^5*B$20-DCF!$G$23)*(1-DCF!$G$25)+DCF!$G$23+DCF!$G$30)*(1/(1+DCF!$C$15)^(DCF!$G$20-0.5)+(1+DCF!$C$16)/(DCF!$C$15-DCF!$C$16)/(1+DCF!$C$15)^DCF!$G$20)+(DCF!$C$47+DCF!$C$48+DCF!$C$49))/DCF!$C$51*Inputs!$C$7 -> 29.558825 | C24: =(SUMPRODUCT(DCF!$D$31:$F$31/(1+DCF!$C$15)^(DCF!$D$20:$F$20-0.5))+(('Income Statement'!$G$9*(1+$A24)^5*C$20-DCF!$G$23)*(1-DCF!$G$25)+DCF!$G$23+DCF!$G$30)*(1/(1+DCF!$C$15)^(DCF!$G$20-0.5)+(1+DCF!$C$16)/(DCF!$C$15-DCF!$C$16)/(1+DCF!$C$15)^DCF!$G$20)+(DCF!$C$47+DCF!$C$48+DCF!$C$49))/DCF!$C$51*Inputs!$C$7 -> 34.1727 | D24: =(SUMPRODUCT(DCF!$D$31:$F$31/(1+DCF!$C$15)^(DCF!$D$20:$F$20-0.5))+(('Income Statement'!$G$9*(1+$A24)^5*D$20-DCF!$G$23)*(1-DCF!$G$25)+DCF!$G$23+DCF!$G$30)*(1/(1+DCF!$C$15)^(DCF!$G$20-0.5)+(1+DCF!$C$16)/(DCF!$C$15-DCF!$C$16)/(1+DCF!$C$15)^DCF!$G$20)+(DCF!$C$47+DCF!$C$48+DCF!$C$49))/DCF!$C$51*Inputs!$C$7 -> 38.786575 | E24: =(SUMPRODUCT(DCF!$D$31:$F$31/(1+DCF!$C$15)^(DCF!$D$20:$F$20-0.5))+(('Income Statement'!$G$9*(1+$A24)^5*E$20-DCF!$G$23)*(1-DCF!$G$25)+DCF!$G$23+DCF!$G$30)*(1/(1+DCF!$C$15)^(DCF!$G$20-0.5)+(1+DCF!$C$16)/(DCF!$C$15-DCF!$C$16)/(1+DCF!$C$15)^DCF!$G$20)+(DCF!$C$47+DCF!$C$48+DCF!$C$49))/DCF!$C$51*Inputs!$C$7 -> 43.40045 | F24: =(SUMPRODUCT(DCF!$D$31:$F$31/(1+DCF!$C$15)^(DCF!$D$20:$F$20-0.5))+(('Income Statement'!$G$9*(1+$A24)^5*F$20-DCF!$G$23)*(1-DCF!$G$25)+DCF!$G$23+DCF!$G$30)*(1/(1+DCF!$C$15)^(DCF!$G$20-0.5)+(1+DCF!$C$16)/(DCF!$C$15-DCF!$C$16)/(1+DCF!$C$15)^DCF!$G$20)+(DCF!$C$47+DCF!$C$48+DCF!$C$49))/DCF!$C$51*Inputs!$C$7 -> 48.014325
A25: =((DCF!$G$21/'Income Statement'!$G$9)^(1/5)-1)+(0.03) -> 0.065810467 | B25: =(SUMPRODUCT(DCF!$D$31:$F$31/(1+DCF!$C$15)^(DCF!$D$20:$F$20-0.5))+(('Income Statement'!$G$9*(1+$A25)^5*B$20-DCF!$G$23)*(1-DCF!$G$25)+DCF!$G$23+DCF!$G$30)*(1/(1+DCF!$C$15)^(DCF!$G$20-0.5)+(1+DCF!$C$16)/(DCF!$C$15-DCF!$C$16)/(1+DCF!$C$15)^DCF!$G$20)+(DCF!$C$47+DCF!$C$48+DCF!$C$49))/DCF!$C$51*Inputs!$C$7 -> 31.596609 | C25: =(SUMPRODUCT(DCF!$D$31:$F$31/(1+DCF!$C$15)^(DCF!$D$20:$F$20-0.5))+(('Income Statement'!$G$9*(1+$A25)^5*C$20-DCF!$G$23)*(1-DCF!$G$25)+DCF!$G$23+DCF!$G$30)*(1/(1+DCF!$C$15)^(DCF!$G$20-0.5)+(1+DCF!$C$16)/(DCF!$C$15-DCF!$C$16)/(1+DCF!$C$15)^DCF!$G$20)+(DCF!$C$47+DCF!$C$48+DCF!$C$49))/DCF!$C$51*Inputs!$C$7 -> 36.549329 | D25: =(SUMPRODUCT(DCF!$D$31:$F$31/(1+DCF!$C$15)^(DCF!$D$20:$F$20-0.5))+(('Income Statement'!$G$9*(1+$A25)^5*D$20-DCF!$G$23)*(1-DCF!$G$25)+DCF!$G$23+DCF!$G$30)*(1/(1+DCF!$C$15)^(DCF!$G$20-0.5)+(1+DCF!$C$16)/(DCF!$C$15-DCF!$C$16)/(1+DCF!$C$15)^DCF!$G$20)+(DCF!$C$47+DCF!$C$48+DCF!$C$49))/DCF!$C$51*Inputs!$C$7 -> 41.502049 | E25: =(SUMPRODUCT(DCF!$D$31:$F$31/(1+DCF!$C$15)^(DCF!$D$20:$F$20-0.5))+(('Income Statement'!$G$9*(1+$A25)^5*E$20-DCF!$G$23)*(1-DCF!$G$25)+DCF!$G$23+DCF!$G$30)*(1/(1+DCF!$C$15)^(DCF!$G$20-0.5)+(1+DCF!$C$16)/(DCF!$C$15-DCF!$C$16)/(1+DCF!$C$15)^DCF!$G$20)+(DCF!$C$47+DCF!$C$48+DCF!$C$49))/DCF!$C$51*Inputs!$C$7 -> 46.454769 | F25: =(SUMPRODUCT(DCF!$D$31:$F$31/(1+DCF!$C$15)^(DCF!$D$20:$F$20-0.5))+(('Income Statement'!$G$9*(1+$A25)^5*F$20-DCF!$G$23)*(1-DCF!$G$25)+DCF!$G$23+DCF!$G$30)*(1/(1+DCF!$C$15)^(DCF!$G$20-0.5)+(1+DCF!$C$16)/(DCF!$C$15-DCF!$C$16)/(1+DCF!$C$15)^DCF!$G$20)+(DCF!$C$47+DCF!$C$48+DCF!$C$49))/DCF!$C$51*Inputs!$C$7 -> 51.407489
A26: Varies the terminal year only: FY2027E-29E cash flows, D&A, capex, working capital and leases stay at model values.
A30: Table 3. Value per share (HK$): target P/E vs FY2027E EPS by scenario
A31: Target P/E \ FY2027E EPS | B31: Bear | C31: Base | D31: Bull | E31: Live model
A32: FY2027E diluted EPS (HK$) | B32: =Scenarios!E118 -> 2.122262 | C32: =Scenarios!D118 -> 3.4208878 | D32: =Scenarios!C118 -> 4.3918818 | E32: ='Income Statement'!I59 -> 3.4208878
A33: 7 | B33: =$A33*B$32 -> 14.855834 | C33: =$A33*C$32 -> 23.946215 | D33: =$A33*D$32 -> 30.743173 | E33: =$A33*E$32 -> 23.946215
A34: 8 | B34: =$A34*B$32 -> 16.978096 | C34: =$A34*C$32 -> 27.367103 | D34: =$A34*D$32 -> 35.135054 | E34: =$A34*E$32 -> 27.367103
A35: 9 | B35: =$A35*B$32 -> 19.100358 | C35: =$A35*C$32 -> 30.78799 | D35: =$A35*D$32 -> 39.526936 | E35: =$A35*E$32 -> 30.78799
A36: 10 | B36: =$A36*B$32 -> 21.22262 | C36: =$A36*C$32 -> 34.208878 | D36: =$A36*D$32 -> 43.918818 | E36: =$A36*E$32 -> 34.208878
A37: 11 | B37: =$A37*B$32 -> 23.344882 | C37: =$A37*C$32 -> 37.629766 | D37: =$A37*D$32 -> 48.3107 | E37: =$A37*E$32 -> 37.629766
A38: 12 | B38: =$A38*B$32 -> 25.467144 | C38: =$A38*C$32 -> 41.050654 | D38: =$A38*D$32 -> 52.702581 | E38: =$A38*E$32 -> 41.050654
A39: 13 | B39: =$A39*B$32 -> 27.589406 | C39: =$A39*C$32 -> 44.471542 | D39: =$A39*D$32 -> 57.094463 | E39: =$A39*E$32 -> 44.471542
A40: 14 | B40: =$A40*B$32 -> 29.711668 | C40: =$A40*C$32 -> 47.89243 | D40: =$A40*D$32 -> 61.486345 | E40: =$A40*E$32 -> 47.89243
A42: Table 4. FY2027E freight rate vs base case: EPS and P/E at the current price (costs held)
A43: Rate vs base | B43: Rate (US$/TEU) | C43: Revenue chg (US$m) | D43: Profit chg (US$m) | E43: EPS (HK$) | F43: EPS chg | G43: P/E at price
A44: -0.2 | B44: ='Revenue Model'!$I$15*(1+A44) -> 598.52082 | C44: ='Revenue Model'!$I$12*'Revenue Model'!$I$15*A44*(1+'Revenue Model'!$I$18)/1000 -> -659.17791 | D44: =C44*(1-Scenarios!$I$72)*(1-Scenarios!$I$73) -> -644.08405 | E44: ='Income Statement'!$I$59+D44/'Income Statement'!$I$56*Inputs!$C$7 -> 1.5599975 | F44: =E44/'Income Statement'!$I$59-1 -> -0.54397876 | G44: =Inputs!$C$6/E44 -> 30.564151
A45: -0.15 | B45: ='Revenue Model'!$I$15*(1+A45) -> 635.92837 | C45: ='Revenue Model'!$I$12*'Revenue Model'!$I$15*A45*(1+'Revenue Model'!$I$18)/1000 -> -494.38343 | D45: =C45*(1-Scenarios!$I$72)*(1-Scenarios!$I$73) -> -483.06304 | E45: ='Income Statement'!$I$59+D45/'Income Statement'!$I$56*Inputs!$C$7 -> 2.0252201 | F45: =E45/'Income Statement'!$I$59-1 -> -0.40798407 | G45: =Inputs!$C$6/E45 -> 23.54312
A46: -0.1 | B46: ='Revenue Model'!$I$15*(1+A46) -> 673.33592 | C46: ='Revenue Model'!$I$12*'Revenue Model'!$I$15*A46*(1+'Revenue Model'!$I$18)/1000 -> -329.58895 | D46: =C46*(1-Scenarios!$I$72)*(1-Scenarios!$I$73) -> -322.04203 | E46: ='Income Statement'!$I$59+D46/'Income Statement'!$I$56*Inputs!$C$7 -> 2.4904427 | F46: =E46/'Income Statement'!$I$59-1 -> -0.27198938 | G46: =Inputs!$C$6/E46 -> 19.145191
A47: -0.05 | B47: ='Revenue Model'!$I$15*(1+A47) -> 710.74347 | C47: ='Revenue Model'!$I$12*'Revenue Model'!$I$15*A47*(1+'Revenue Model'!$I$18)/1000 -> -164.79448 | D47: =C47*(1-Scenarios!$I$72)*(1-Scenarios!$I$73) -> -161.02101 | E47: ='Income Statement'!$I$59+D47/'Income Statement'!$I$56*Inputs!$C$7 -> 2.9556653 | F47: =E47/'Income Statement'!$I$59-1 -> -0.13599469 | G47: =Inputs!$C$6/E47 -> 16.131732
A48: 0 | B48: ='Revenue Model'!$I$15*(1+A48) -> 748.15102 | C48: ='Revenue Model'!$I$12*'Revenue Model'!$I$15*A48*(1+'Revenue Model'!$I$18)/1000 -> 0 | D48: =C48*(1-Scenarios!$I$72)*(1-Scenarios!$I$73) -> 0 | E48: ='Income Statement'!$I$59+D48/'Income Statement'!$I$56*Inputs!$C$7 -> 3.4208878 | F48: =E48/'Income Statement'!$I$59-1 -> 0 | G48: =Inputs!$C$6/E48 -> 13.937902
A49: 0.05 | B49: ='Revenue Model'!$I$15*(1+A49) -> 785.55857 | C49: ='Revenue Model'!$I$12*'Revenue Model'!$I$15*A49*(1+'Revenue Model'!$I$18)/1000 -> 164.79448 | D49: =C49*(1-Scenarios!$I$72)*(1-Scenarios!$I$73) -> 161.02101 | E49: ='Income Statement'!$I$59+D49/'Income Statement'!$I$56*Inputs!$C$7 -> 3.8861104 | F49: =E49/'Income Statement'!$I$59-1 -> 0.13599469 | G49: =Inputs!$C$6/E49 -> 12.269337
A50: 0.1 | B50: ='Revenue Model'!$I$15*(1+A50) -> 822.96613 | C50: ='Revenue Model'!$I$12*'Revenue Model'!$I$15*A50*(1+'Revenue Model'!$I$18)/1000 -> 329.58895 | D50: =C50*(1-Scenarios!$I$72)*(1-Scenarios!$I$73) -> 322.04203 | E50: ='Income Statement'!$I$59+D50/'Income Statement'!$I$56*Inputs!$C$7 -> 4.351333 | F50: =E50/'Income Statement'!$I$59-1 -> 0.27198938 | G50: =Inputs!$C$6/E50 -> 10.957562
A51: 0.15 | B51: ='Revenue Model'!$I$15*(1+A51) -> 860.37368 | C51: ='Revenue Model'!$I$12*'Revenue Model'!$I$15*A51*(1+'Revenue Model'!$I$18)/1000 -> 494.38343 | D51: =C51*(1-Scenarios!$I$72)*(1-Scenarios!$I$73) -> 483.06304 | E51: ='Income Statement'!$I$59+D51/'Income Statement'!$I$56*Inputs!$C$7 -> 4.8165556 | F51: =E51/'Income Statement'!$I$59-1 -> 0.40798407 | G51: =Inputs!$C$6/E51 -> 9.8991903
A52: Each US$10/TEU on the FY2027E average rate moves revenue by about | E52: ='Revenue Model'!$I$12*10*(1+'Revenue Model'!$I$18)/1000 -> 44.0538 | F52: US$m

Sheet Comps
A1: SITC International Holdings (1308.HK) - Comparable companies
A2: Listed container lines. Market data and LTM/forward multiples from stockanalysis.com (S&P Global Market Intelligence), 24-25 Oct 2026. Forward P/E is the source's consensus-based figure; NTM EV multiples were not available from public sources.
A5: Company | B5: Ticker | C5: Group | D5: Ccy | E5: Local per US$ | F5: Mkt cap (local bn) | G5: EV (local bn) | H5: Mkt cap (US$bn) | I5: EV (US$bn) | J5: EV/Sales LTM | K5: EV/EBITDA LTM | L5: P/E LTM | M5: P/E fwd | N5: P/B | O5: Div. yield | P5: ROE | Q5: EBITDA margin | R5: Rev. growth fcst 3Y | S5: EPS growth fcst 3Y
A6: COSCO Shipping Holdings | B6: 1919.HK | C6: Asia | D6: HKD | E6: 7.8413 | F6: 273.94 | G6: 252.57 | H6: =F6/E6 -> 34.935534 | I6: =G6/E6 -> 32.21022 | J6: 0.98 | K6: 4.2 | L6: 7.98 | M6: 7.8 | N6: 0.83 | O6: 0.0725 | P6: 0.1081 | Q6: 0.1816 | R6: 0.0185 | S6: -0.1805
A7: Orient Overseas (OOIL) | B7: 0316.HK | C7: Asia | D7: HKD | E7: 7.8413 | F7: 99.25 | G7: 63.7 | H7: =F7/E7 -> 12.65734 | I7: =G7/E7 -> 8.123653 | J7: 0.81 | K7: 4.15 | L7: 9.83 | M7: 7.83 | N7: 0.91 | O7: 0.0595 | P7: 0.0948 | Q7: 0.146 | R7: 0.0376 | S7: -0.3582
A8: Evergreen Marine | B8: 2603.TW | C8: Asia | D8: TWD | E8: 32.57 | F8: 562.91 | G8: 595.82 | H8: =F8/E8 -> 17.283083 | I8: =G8/E8 -> 18.293522 | J8: 1.59 | K8: 5.6 | L8: 10.32 | M8: 5.3 | N8: 0.96 | O8: 0.0615 | P8: 0.1017 | Q8: 0.2343 | R8: 0.0228 | S8: -0.0952
A9: Yang Ming Marine | B9: 2609.TW | C9: Asia | D9: TWD | E9: 32.57 | F9: 216.16 | G9: 106.16 | H9: =F9/E9 -> 6.6367823 | I9: =G9/E9 -> 3.2594412 | J9: 0.65 | K9: 3.51 | L9: 13.94 | M9: 7.13 | N9: 0.66 | O9: 0.0323 | P9: 0.0495 | Q9: 0.1164 | R9: 0.0286 | S9: -0.1944
A10: Wan Hai Lines | B10: 2615.TW | C10: Asia | D10: TWD | E10: 32.57 | F10: 335.33 | G10: 269.18 | H10: =F10/E10 -> 10.295671 | I10: =G10/E10 -> 8.2646607 | J10: 1.86 | K10: 5.68 | L10: 8.21 | M10: 6.5 | N10: 1.16 | O10: 0.0293 | P10: 0.1549 | Q10: 0.307 | R10: 0.0578 | S10: 0.0064
A11: HMM | B11: 011200.KS | C11: Asia | D11: KRW | E11: 1325.4 | F11: 21360 | G11: 14820 | H11: =F11/E11 -> 16.11589 | I11: =G11/E11 -> 11.18153 | J11: 1.29 | K11: 5.73 | L11: 15.19 | M11: 12.02 | N11: 0.74 | O11: 0.0309 | P11: 0.052 | Q11: 0.2177 | R11: 0.023 | S11: -0.1306
A12: T.S. Lines | B12: 2510.HK | C12: Asia | D12: HKD | E12: 7.8413 | F12: 20.5 | G12: 17.42 | H12: =F12/E12 -> 2.6143624 | I12: =G12/E12 -> 2.2215704 | J12: 1.7 | K12: 4.34 | L12: 7.01 | M12: 6.16 | N12: 1.2 | O12: 0.0892 | P12: 0.1789 | Q12: 0.3419 | R12: 0.0556 | S12: 0.0675
A13: Regional Container Lines | B13: RCL.BK | C13: Asia | D13: THB | E13: 33.74 | F13: 39.16 | G13: 37.29 | H13: =F13/E13 -> 1.1606402 | I13: =G13/E13 -> 1.1052164 | J13: 1 | K13: 3.06 | L13: 5.05 | M13: n/a | N13: 0.67 | O13: 0.0529 | P13: 0.1407 | Q13: 0.3106 | R13: n/a | S13: n/a
A14: A.P. Moller-Maersk | B14: MAERSK-B.CO | C14: Global | D14: DKK | E14: 6.6714 | F14: 324.19 | G14: 324.95 | H14: =F14/E14 -> 48.593998 | I14: =G14/E14 -> 48.707917 | J14: 0.88 | K14: 5.09 | L14: 22.62 | M14: 9.7 | N14: 0.88 | O14: 0.021 | P14: 0.0437 | Q14: 0.1049 | R14: 0.0232 | S14: -0.2085
A15: Hapag-Lloyd | B15: HLAG.DE | C15: Global | D15: EUR | E15: 0.89253838 | F15: 22.57 | G15: 24.38 | H15: =F15/E15 -> 25.287428 | I15: =G15/E15 -> 27.315352 | J15: 1.34 | K15: 9.72 | L15: 389.19 | M15: 23.95 | N15: 1.24 | O15: 0.0234 | P15: 0.0038 | Q15: 0.0724 | R15: 0.0149 | S15: n/a
A16: ZIM Integrated Shipping | B16: ZIM | C16: Global | D16: USD | E16: 1 | F16: 3.54 | G16: 7.21 | H16: =F16/E16 -> 3.54 | I16: =G16/E16 -> 7.21 | J16: 1.12 | K16: 15.45 | L16: 25.52 | M16: 3.22 | N16: 0.91 | O16: 0.0406 | P16: 0.0358 | Q16: 0.0725 | R16: -0.0376 | S16: n/a
A17: Matson | B17: MATX | C17: Global | D17: USD | E17: 1 | F17: 6.84 | G17: 7.43 | H17: =F17/E17 -> 6.84 | I17: =G17/E17 -> 7.43 | J17: 2.15 | K17: 11.02 | L17: 15.31 | M17: 12.7 | N17: 2.47 | O17: 0.0066 | P17: 0.1721 | Q17: 0.195 | R17: 0.0497 | S17: 0.0849
A19: Statistical summary (12 peers)
A20: Maximum | H20: =MAX(H6:H17) -> 48.593998 | I20: =MAX(I6:I17) -> 48.707917 | J20: =MAX(J6:J17) -> 2.15 | K20: =MAX(K6:K17) -> 15.45 | L20: =MAX(L6:L17) -> 389.19 | M20: =MAX(M6:M17) -> 23.95 | N20: =MAX(N6:N17) -> 2.47 | O20: =MAX(O6:O17) -> 0.0892 | ... S20: =MAX(S6:S17) -> 0.0849
A21: 75th percentile | H21: =QUARTILE(H6:H17,3) -> 19.284169 | I21: =QUARTILE(I6:I17,3) -> 20.548979 | J21: =QUARTILE(J6:J17,3) -> 1.6175 | K21: =QUARTILE(K6:K17,3) -> 6.7275 | L21: =QUARTILE(L6:L17,3) -> 17.1375 | M21: =QUARTILE(M6:M17,3) -> 10.86 | N21: =QUARTILE(N6:N17,3) -> 1.17 | O21: =QUARTILE(O6:O17,3) -> 0.06 | ... S21: =QUARTILE(S6:S17,3) -> 0.0064
A22: Median | H22: =MEDIAN(H6:H17) -> 11.476505 | I22: =MEDIAN(I6:I17) -> 8.1941568 | J22: =MEDIAN(J6:J17) -> 1.205 | K22: =MEDIAN(K6:K17) -> 5.345 | L22: =MEDIAN(L6:L17) -> 12.13 | M22: =MEDIAN(M6:M17) -> 7.8 | N22: =MEDIAN(N6:N17) -> 0.91 | O22: =MEDIAN(O6:O17) -> 0.03645 | ... S22: =MEDIAN(S6:S17) -> -0.1306
A23: 25th percentile | H23: =QUARTILE(H6:H17,1) -> 5.8625867 | I23: =QUARTILE(I6:I17,1) -> 6.2223603 | J23: =QUARTILE(J6:J17,1) -> 0.955 | K23: =QUARTILE(K6:K17,1) -> 4.1875 | L23: =QUARTILE(L6:L17,1) -> 8.1525 | M23: =QUARTILE(M6:M17,1) -> 6.33 | N23: =QUARTILE(N6:N17,1) -> 0.8075 | O23: =QUARTILE(O6:O17,1) -> 0.027825 | ... S23: =QUARTILE(S6:S17,1) -> -0.1944
A24: Minimum | H24: =MIN(H6:H17) -> 1.1606402 | I24: =MIN(I6:I17) -> 1.1052164 | J24: =MIN(J6:J17) -> 0.65 | K24: =MIN(K6:K17) -> 3.06 | L24: =MIN(L6:L17) -> 5.05 | M24: =MIN(M6:M17) -> 3.22 | N24: =MIN(N6:N17) -> 0.66 | O24: =MIN(O6:O17) -> 0.0066 | ... S24: =MIN(S6:S17) -> -0.3582
A26: SITC International (1308.HK)
A27: SITC International (market data) | B27: 1308.HK | C27: Target | D27: HKD | E27: 7.8413 | F27: 129.29 | G27: 124.17 | H27: =F27/E27 -> 16.488337 | I27: =G27/E27 -> 15.835384 | J27: 4.41 | K27: 11.1 | L27: 12.94 | M27: 11.69 | N27: 5.77 | O27: 0.0675 | P27: 0.4692 | Q27: 0.3677 | R27: 0.0393 | S27: -0.0199
A28: SITC, our FY2026E at current price | B28: 1308.HK | C28: Our est. | D28: HKD | E28: =Inputs!$C$7 -> 7.8413 | F28: =Inputs!$C$15/1000 -> 129.28567 | G28: =I28*E28 -> 121.6417 | H28: =F28/E28 -> 16.487785 | I28: =(Inputs!$C$16-'Balance Sheet'!H53-'DCF Inputs'!H22+'Balance Sheet'!H45)/1000 -> 15.51295 | J28: =I28*1000/'Income Statement'!H9 -> 3.9834694 | K28: =I28*1000/'Income Statement'!H39 -> 9.4976273 | M28: =Inputs!$C$6/'Income Statement'!H59 -> 11.175131 | N28: =Inputs!$C$6/'Balance Sheet'!H56 -> 5.9698217 | O28: ='Income Statement'!H60/Inputs!$C$6 -> 0.075906672 | P28: ='Balance Sheet'!H55 -> 0.56193933 | Q28: ='Income Statement'!H40 -> 0.41941733 | T28: EV = market cap - YE net cash - JVs + NCI; the P/E fwd column shows that year's P/E
A29: SITC, our FY2027E at current price | B29: 1308.HK | C29: Our est. | D29: HKD | E29: =Inputs!$C$7 -> 7.8413 | F29: =Inputs!$C$15/1000 -> 129.28567 | G29: =I29*E29 -> 121.37844 | H29: =F29/E29 -> 16.487785 | I29: =(Inputs!$C$16-'Balance Sheet'!I53-'DCF Inputs'!I22+'Balance Sheet'!I45)/1000 -> 15.479377 | J29: =I29*1000/'Income Statement'!I9 -> 4.153588 | K29: =I29*1000/'Income Statement'!I39 -> 11.58265 | M29: =Inputs!$C$6/'Income Statement'!I59 -> 13.937902 | N29: =Inputs!$C$6/'Balance Sheet'!I56 -> 5.3919034 | O29: ='Income Statement'!I60/Inputs!$C$6 -> 0.057449769 | P29: ='Balance Sheet'!I55 -> 0.40689981 | Q29: ='Income Statement'!I40 -> 0.35860428
A31: Applying peer multiples to SITC (HK$ per share) | B31: Peer stat | C31: Multiple | D31: SITC metric | E31: Metric value | F31: Value / share | G31: vs price
A32: P/E on FY2027E EPS | B32: Median fwd P/E | C32: =M22 -> 7.8 | D32: FY2027E EPS (HK$) | E32: ='Income Statement'!I59 -> 3.4208878 | F32: =C32*E32 -> 26.682925 | G32: =F32/Inputs!$C$6-1 -> -0.44037489
A33: P/E on FY2027E EPS | B33: 75th pct fwd P/E | C33: =M21 -> 10.86 | D33: FY2027E EPS (HK$) | E33: ='Income Statement'!I59 -> 3.4208878 | F33: =C33*E33 -> 37.150842 | G33: =F33/Inputs!$C$6-1 -> -0.22082966
A34: EV/EBITDA on FY2026E | B34: Median LTM EV/EBITDA | C34: =K22 -> 5.345 | D34: FY2026E EBITDA (US$m) | E34: ='Income Statement'!H39 -> 1633.3501 | F34: =(C34*E34+('Balance Sheet'!H53+'DCF Inputs'!H22-'Balance Sheet'!H45))/Inputs!$C$14*Inputs!$C$7 -> 28.065548 | G34: =F34/Inputs!$C$6-1 -> -0.41137692
A35: P/B on YE2026E book | B35: Median P/B | C35: =N22 -> 0.91 | D35: BVPS YE2026E (HK$) | E35: ='Balance Sheet'!H56 -> 7.9868382 | F35: =C35*E35 -> 7.2680228 | G35: =F35/Inputs!$C$6-1 -> -0.84756664
A36: P/B scaled by ROE | B36: Median P/B x (SITC ROE / median ROE) | C36: =N22*'Balance Sheet'!I55/P22 -> 3.7687412 | D36: BVPS YE2026E (HK$) | E36: ='Balance Sheet'!H56 -> 7.9868382 | F36: =C36*E36 -> 30.100326 | G36: =F36/Inputs!$C$6-1 -> -0.36870121

Sheet Valuation Summary
A1: SITC International Holdings (1308.HK) - Valuation summary
A2: Price target, rating and cross-checks. HK$ per share unless stated.
A5: Valuation methods | B5: Low | C5: Base | D5: High | E5: Weight | F5: Weighted | G5: Base vs price
A6: DCF (FCF after leases; WACC +/-1pp, g -/+0.5pp) | B6: =(SUMPRODUCT(DCF!$D$31:$G$31/(1+(DCF!$C$15+(0.01)))^(DCF!$D$20:$G$20-0.5))+DCF!$G$31*(1+(DCF!$C$16+(-0.005)))/((DCF!$C$15+(0.01))-(DCF!$C$16+(-0.005)))/(1+(DCF!$C$15+(0.01)))^DCF!$G$20+DCF!$C$47+DCF!$C$48+DCF!$C$49)/Inputs!$C$14*Inputs!$C$7 -> 31.344188 | C6: =DCF!$C$53 -> 36.221802 | D6: =(SUMPRODUCT(DCF!$D$31:$G$31/(1+(DCF!$C$15+(-0.01)))^(DCF!$D$20:$G$20-0.5))+DCF!$G$31*(1+(DCF!$C$16+(0.005)))/((DCF!$C$15+(-0.01))-(DCF!$C$16+(0.005)))/(1+(DCF!$C$15+(-0.01)))^DCF!$G$20+DCF!$C$47+DCF!$C$48+DCF!$C$49)/Inputs!$C$14*Inputs!$C$7 -> 43.314517 | E6: 0.6 | F6: =C6*E6 -> 21.733081 | G6: =C6/Inputs!$C$6-1 -> -0.24031455 | H6: Primary: captures the newbuild capex cycle and the fall in freight rates to mid-cycle
A7: P/E on FY2027E EPS (peer median / 75th pct / 13x) | B7: =Comps!$F$32 -> 26.682925 | C7: =Comps!$F$33 -> 37.150842 | D7: =13*'Income Statement'!I59 -> 44.471542 | E7: 0.4 | F7: =C7*E7 -> 14.860337 | G7: =C7/Inputs!$C$6-1 -> -0.22082966 | H7: Top-quartile peer multiple for the highest ROE and payout in the group; high end = SITC trailing P/E ~13x
A8: Blended value | B8: =SUMPRODUCT(B6:B7,$E6:$E7) -> 29.479683 | C8: =F6+F7 -> 36.593418 | D8: =SUMPRODUCT(D6:D7,$E6:$E7) -> 43.777327 | E8: =E6+E7 -> 1 | F8: =C8 -> 36.593418 | G8: =C8/Inputs!$C$6-1 -> -0.23252059
A10: Cross-checks (not weighted) | B10: Low | C10: Base | D10: High
A11: Dividend discount (cost of equity +/-1pp) | B11: =('Income Statement'!I60/(1+DCF!$C$11+(0.01))^1+'Income Statement'!J60/(1+DCF!$C$11+(0.01))^2+'Income Statement'!K60/(1+DCF!$C$11+(0.01))^3+('Income Statement'!L60+'Income Statement'!L60*(1+DCF!$C$16)/(DCF!$C$11+(0.01)-DCF!$C$16))/(1+DCF!$C$11+(0.01))^4+'Cash Flow'!H49/Inputs!$C$14*Inputs!$C$7/(1+DCF!$C$11+(0.01))^0.5) -> 28.128712 | C11: =('Income Statement'!I60/(1+DCF!$C$11+(0))^1+'Income Statement'!J60/(1+DCF!$C$11+(0))^2+'Income Statement'!K60/(1+DCF!$C$11+(0))^3+('Income Statement'!L60+'Income Statement'!L60*(1+DCF!$C$16)/(DCF!$C$11+(0)-DCF!$C$16))/(1+DCF!$C$11+(0))^4+'Cash Flow'!H49/Inputs!$C$14*Inputs!$C$7/(1+DCF!$C$11+(0))^0.5) -> 31.457838 | D11: =('Income Statement'!I60/(1+DCF!$C$11+(-0.01))^1+'Income Statement'!J60/(1+DCF!$C$11+(-0.01))^2+'Income Statement'!K60/(1+DCF!$C$11+(-0.01))^3+('Income Statement'!L60+'Income Statement'!L60*(1+DCF!$C$16)/(DCF!$C$11+(-0.01)-DCF!$C$16))/(1+DCF!$C$11+(-0.01))^4+'Cash Flow'!H49/Inputs!$C$14*Inputs!$C$7/(1+DCF!$C$11+(-0.01))^0.5) -> 35.723494 | G11: =IF(C11="","",C11/Inputs!$C$6-1) -> -0.3402299 | H11: FY2026 final + FY2027E-30E DPS + Gordon terminal; DPS discounted one year after the fiscal year on average
A12: Justified P/B = (ROE - g) / (ke - g), FY2027E ROE | C12: =('Balance Sheet'!I55-DCF!$C$16)/(DCF!$C$11-DCF!$C$16)*'Balance Sheet'!H56 -> 38.147104 | G12: =IF(C12="","",C12/Inputs!$C$6-1) -> -0.1999349 | H12: Gordon-consistent P/B on YE2026E book value
A13: EV/EBITDA, peer median LTM on FY2026E EBITDA | C13: =Comps!$F$34 -> 28.065548 | G13: =IF(C13="","",C13/Inputs!$C$6-1) -> -0.41137692 | H13: Peers carry lower margins and returns; shown for reference
A14: DCF by scenario: bear / base / bull | B14: =Scenarios!E125 -> 16.104944 | C14: =Scenarios!D125 -> 36.221802 | D14: =Scenarios!C125 -> 59.402046 | G14: =IF(C14="","",C14/Inputs!$C$6-1) -> -0.24031455 | H14: Stored full-model runs (Scenarios tab)
A15: 52-week trading range | B15: =Inputs!$C$9 -> 26.22 | D15: =Inputs!$C$8 -> 52 | H15: Yahoo Finance
A16: Consensus price target (9 analysts; consensus rating Buy) | C16: 46.2 | G16: =IF(C16="","",C16/Inputs!$C$6-1) -> -0.031040268 | H16: stockanalysis.com (S&P Global MI), 24-Oct-2026; not our estimate
A18: Price target and rating
A19: Blended value (HK$) | C19: =C8 -> 36.593418
A20: 12-month price target (rounded to HK$0.50) | C20: =ROUND(C19*2,0)/2 -> 36.5
A21: Share price, 23-Oct-2026 close (HK$) | C21: =Inputs!$C$6 -> 47.68
A22: Price upside / (downside) to target | C22: =C20/C21-1 -> -0.23447987
A23: Dividends expected in the next 12 months (HK$) | C23: =Inputs!$C$19+'Cash Flow'!H49/Inputs!$C$14*Inputs!$C$7+'Cash Flow'!I48/Inputs!$C$14*Inputs!$C$7 -> 3.6257929 | H23: Dec-2026 special HK$1.00 + FY2026E final (mid-2027) + FY2027E in-year dividends
A24: Expected 12-month total return | C24: =(C20+C23)/C21-1 -> -0.15843555
A25: Rating | C25: =IF(C24>=C26,"BUY",IF(C24<=C27,"SELL","HOLD")) -> SELL
A26: BUY threshold (expected total return) | C26: 0.15 | H26: House framework: BUY above +15%, SELL below -10%, otherwise HOLD
A27: SELL threshold (expected total return) | C27: -0.1
A29: What the target implies
A30: P/E FY2026E at target | C30: =$C$20/'Income Statement'!H59 -> 8.5547881
A31: P/E FY2027E at target | C31: =$C$20/'Income Statement'!I59 -> 10.669745
A32: EV/EBITDA FY2027E at target | C32: =($C$20*Inputs!$C$14/Inputs!$C$7-'Balance Sheet'!H53-'DCF Inputs'!H22+'Balance Sheet'!H45)/'Income Statement'!I39 -> 8.7149459
A33: P/B on YE2026E book at target | C33: =$C$20/'Balance Sheet'!H56 -> 4.5700187
A34: FY2027E dividend yield at target | C34: ='Income Statement'!I60/$C$20 -> 0.075046712
A35: EPS the current price implies at the base-case P/E (HK$) | C35: =Inputs!$C$6/Comps!$C$33 -> 4.3904236 | H35: Compare with our FY2027E-28E EPS on the Income Statement
A37: Scenario values (stored full-model runs) and probability weighting
A38: Scenario | B38: Probability | C38: Rate FY28E | D38: EPS FY27E | E38: DCF value | F38: vs price | G38: Definition
A39: Bear | B39: 0.25 | C39: =Scenarios!E109 -> 604.63564 | D39: =Scenarios!E118 -> 2.122262 | E39: =Scenarios!E125 -> 16.104944 | F39: =E39/Inputs!$C$6-1 -> -0.66222853 | G39: FY2027E rate falls by more than 15%
A40: Base | B40: 0.5 | C40: =Scenarios!D109 -> 710.74347 | D40: =Scenarios!D118 -> 3.4208878 | E40: =Scenarios!D125 -> 36.221802 | F40: =E40/Inputs!$C$6-1 -> -0.24031455 | G40: FY2027E rate falls by 5-15%
A41: Bull | B41: 0.25 | C41: =Scenarios!C109 -> 813.33533 | D41: =Scenarios!C118 -> 4.3918818 | E41: =Scenarios!C125 -> 59.402046 | F41: =E41/Inputs!$C$6-1 -> 0.24584827 | G41: FY2027E rate falls by less than 5%
A42: Probability-weighted DCF value | B42: =SUM(B39:B41) -> 1 | E42: =IF(ABS(B42-1)<0.0001,SUMPRODUCT(B39:B41,E39:E41),"n/a") -> 36.987648 | F42: =IF(ISNUMBER(E42),E42/Inputs!$C$6-1,"") -> -0.22425234 | G42: Buckets are exclusive and cover all FY2027E rate outcomes; weights must sum to 100%

Sheet Checks
A1: SITC International Holdings (1308.HK) - Checks
A2: TRUE = pass. AllChecksPass (C47) must be TRUE.
A4: Check | B4: Unit | C4: FY2021A | D4: FY2022A | E4: FY2023A | F4: FY2024A | G4: FY2025A | H4: FY2026E | I4: FY2027E | J4: FY2028E | K4: FY2029E | L4: FY2030E | M4: Note
A5: Balance sheet and cash
A6: Balance sheet balances | C6: =ABS('Balance Sheet'!C48)<0.01 -> TRUE | D6: =ABS('Balance Sheet'!D48)<0.01 -> TRUE | E6: =ABS('Balance Sheet'!E48)<0.01 -> TRUE | F6: =ABS('Balance Sheet'!F48)<0.01 -> TRUE | G6: =ABS('Balance Sheet'!G48)<0.01 -> TRUE | H6: =ABS('Balance Sheet'!H48)<0.01 -> TRUE | I6: =ABS('Balance Sheet'!I48)<0.01 -> TRUE | J6: =ABS('Balance Sheet'!J48)<0.01 -> TRUE | ... L6: =ABS('Balance Sheet'!L48)<0.01 -> TRUE
A7: Cash flow closing cash = balance sheet cash | C7: =ABS('Cash Flow'!C42-'Balance Sheet'!C22)<0.01 -> TRUE | D7: =ABS('Cash Flow'!D42-'Balance Sheet'!D22)<0.01 -> TRUE | E7: =ABS('Cash Flow'!E42-'Balance Sheet'!E22)<0.01 -> TRUE | F7: =ABS('Cash Flow'!F42-'Balance Sheet'!F22)<0.01 -> TRUE | G7: =ABS('Cash Flow'!G42-'Balance Sheet'!G22)<0.01 -> TRUE | H7: =ABS('Cash Flow'!H42-'Balance Sheet'!H22)<0.01 -> TRUE | I7: =ABS('Cash Flow'!I42-'Balance Sheet'!I22)<0.01 -> TRUE | J7: =ABS('Cash Flow'!J42-'Balance Sheet'!J22)<0.01 -> TRUE | ... L7: =ABS('Cash Flow'!L42-'Balance Sheet'!L22)<0.01 -> TRUE
A8: Geographic revenue sums to total revenue | C8: =ABS('Revenue Model'!C40)<0.01 -> TRUE | D8: =ABS('Revenue Model'!D40)<0.01 -> TRUE | E8: =ABS('Revenue Model'!E40)<0.01 -> TRUE | F8: =ABS('Revenue Model'!F40)<0.01 -> TRUE | G8: =ABS('Revenue Model'!G40)<0.01 -> TRUE | H8: =ABS('Revenue Model'!H40)<0.01 -> TRUE | I8: =ABS('Revenue Model'!I40)<0.01 -> TRUE | J8: =ABS('Revenue Model'!J40)<0.01 -> TRUE | ... L8: =ABS('Revenue Model'!L40)<0.01 -> TRUE
A9: Vessel advances not negative | H9: ='Balance Sheet'!H8>-0.01 -> TRUE | I9: ='Balance Sheet'!I8>-0.01 -> TRUE | J9: ='Balance Sheet'!J8>-0.01 -> TRUE | K9: ='Balance Sheet'!K8>-0.01 -> TRUE | L9: ='Balance Sheet'!L8>-0.01 -> TRUE
A10: Cash at or above minimum | H10: ='Balance Sheet'!H22>=Inputs!$C$28-0.01 -> TRUE | I10: ='Balance Sheet'!I22>=Inputs!$C$28-0.01 -> TRUE | J10: ='Balance Sheet'!J22>=Inputs!$C$28-0.01 -> TRUE | K10: ='Balance Sheet'!K22>=Inputs!$C$28-0.01 -> TRUE | L10: ='Balance Sheet'!L22>=Inputs!$C$28-0.01 -> TRUE
A11: Revolver not negative | H11: ='Cash Flow'!H45>=0 -> TRUE | I11: ='Cash Flow'!I45>=0 -> TRUE | J11: ='Cash Flow'!J45>=0 -> TRUE | K11: ='Cash Flow'!K45>=0 -> TRUE | L11: ='Cash Flow'!L45>=0 -> TRUE
A12: Historical tie-out to reported figures (US$m)
A13: Total non-current assets, reported | B13: US$m | C13: 1531.065 | D13: 1853.886 | E13: 2025.878 | F13: 2174.554 | G13: 2254.135
A14: Total non-current assets ties | C14: =ABS('Balance Sheet'!C14-C13)<0.01 -> TRUE | D14: =ABS('Balance Sheet'!D14-D13)<0.01 -> TRUE | E14: =ABS('Balance Sheet'!E14-E13)<0.01 -> TRUE | F14: =ABS('Balance Sheet'!F14-F13)<0.01 -> TRUE | G14: =ABS('Balance Sheet'!G14-G13)<0.01 -> TRUE
A15: Total current assets, reported | B15: US$m | C15: 1185.358 | D15: 1228.97 | E15: 626.585 | F15: 1023.519 | G15: 1223.435
A16: Total current assets ties | C16: =ABS('Balance Sheet'!C23-C15)<0.01 -> TRUE | D16: =ABS('Balance Sheet'!D23-D15)<0.01 -> TRUE | E16: =ABS('Balance Sheet'!E23-E15)<0.01 -> TRUE | F16: =ABS('Balance Sheet'!F23-F15)<0.01 -> TRUE | G16: =ABS('Balance Sheet'!G23-G15)<0.01 -> TRUE
A17: Total current liabilities, reported | B17: US$m | C17: 785.274 | D17: 488.364 | E17: 503 | F17: 544.756 | G17: 725.092
A18: Total current liabilities ties | C18: =ABS('Balance Sheet'!C33-C17)<0.01 -> TRUE | D18: =ABS('Balance Sheet'!D33-D17)<0.01 -> TRUE | E18: =ABS('Balance Sheet'!E33-E17)<0.01 -> TRUE | F18: =ABS('Balance Sheet'!F33-F17)<0.01 -> TRUE | G18: =ABS('Balance Sheet'!G33-G17)<0.01 -> TRUE
A19: Total non-current liabilities, reported | B19: US$m | C19: 415.465 | D19: 429.481 | E19: 218.405 | F19: 231.813 | G19: 251.272
A20: Total non-current liabilities ties | C20: =ABS('Balance Sheet'!C39-C19)<0.01 -> TRUE | D20: =ABS('Balance Sheet'!D39-D19)<0.01 -> TRUE | E20: =ABS('Balance Sheet'!E39-E19)<0.01 -> TRUE | F20: =ABS('Balance Sheet'!F39-F19)<0.01 -> TRUE | G20: =ABS('Balance Sheet'!G39-G19)<0.01 -> TRUE
A21: Total equity, reported | B21: US$m | C21: 1515.684 | D21: 2165.011 | E21: 1931.058 | F21: 2421.504 | G21: 2501.206
A22: Total equity ties | C22: =ABS('Balance Sheet'!C46-C21)<0.01 -> TRUE | D22: =ABS('Balance Sheet'!D46-D21)<0.01 -> TRUE | E22: =ABS('Balance Sheet'!E46-E21)<0.01 -> TRUE | F22: =ABS('Balance Sheet'!F46-F21)<0.01 -> TRUE | G22: =ABS('Balance Sheet'!G46-G21)<0.01 -> TRUE
A23: Revenue, reported | B23: US$m | C23: 3012.447 | D23: 4112.955 | E23: 2428.959 | F23: 3058.059 | G23: 3411.647
A24: Revenue ties | C24: =ABS('Income Statement'!C9-C23)<0.01 -> TRUE | D24: =ABS('Income Statement'!D9-D23)<0.01 -> TRUE | E24: =ABS('Income Statement'!E9-E23)<0.01 -> TRUE | F24: =ABS('Income Statement'!F9-F23)<0.01 -> TRUE | G24: =ABS('Income Statement'!G9-G23)<0.01 -> TRUE
A25: Cost of sales, reported | B25: US$m | C25: -1693.074 | D25: -2133.873 | E25: -1805.925 | F25: -1915.242 | G25: -2101.181
A26: Cost of sales ties | C26: =ABS('Income Statement'!C17-C25)<0.01 -> TRUE | D26: =ABS('Income Statement'!D17-D25)<0.01 -> TRUE | E26: =ABS('Income Statement'!E17-E25)<0.01 -> TRUE | F26: =ABS('Income Statement'!F17-F25)<0.01 -> TRUE | G26: =ABS('Income Statement'!G17-G25)<0.01 -> TRUE
A27: Segment results, reported | B27: US$m | C27: 1193.791 | D27: 1968.007 | E27: 540.877 | F27: 1042.223 | G27: 1228.988
A28: Segment results ties | C28: =ABS('Income Statement'!C43-C27)<0.01 -> TRUE | D28: =ABS('Income Statement'!D43-D27)<0.01 -> TRUE | E28: =ABS('Income Statement'!E43-E27)<0.01 -> TRUE | F28: =ABS('Income Statement'!F43-F27)<0.01 -> TRUE | G28: =ABS('Income Statement'!G43-G27)<0.01 -> TRUE
A29: Profit before tax, reported | B29: US$m | C29: 1184.666 | D29: 1973.042 | E29: 553.414 | F29: 1053.574 | G29: 1251.269
A30: Profit before tax ties | C30: =ABS('Income Statement'!C46-C29)<0.01 -> TRUE | D30: =ABS('Income Statement'!D46-D29)<0.01 -> TRUE | E30: =ABS('Income Statement'!E46-E29)<0.01 -> TRUE | F30: =ABS('Income Statement'!F46-F29)<0.01 -> TRUE | G30: =ABS('Income Statement'!G46-G29)<0.01 -> TRUE
A31: Profit attributable to shareholders, reported | B31: US$m | C31: 1162.714 | D31: 1944.425 | E31: 531.393 | F31: 1028.325 | G31: 1222.887
A32: Profit attributable to shareholders ties | C32: =ABS('Income Statement'!C52-C31)<0.01 -> TRUE | D32: =ABS('Income Statement'!D52-D31)<0.01 -> TRUE | E32: =ABS('Income Statement'!E52-E31)<0.01 -> TRUE | F32: =ABS('Income Statement'!F52-F31)<0.01 -> TRUE | G32: =ABS('Income Statement'!G52-G31)<0.01 -> TRUE
A33: Operating cash flow, reported | B33: US$m | C33: 1335.209 | D33: 2002.565 | E33: 672.213 | F33: 1158.334 | G33: 1401.037
A34: Operating cash flow ties | C34: =ABS('Cash Flow'!C18-C33)<0.01 -> TRUE | D34: =ABS('Cash Flow'!D18-D33)<0.01 -> TRUE | E34: =ABS('Cash Flow'!E18-E33)<0.01 -> TRUE | F34: =ABS('Cash Flow'!F18-F33)<0.01 -> TRUE | G34: =ABS('Cash Flow'!G18-G33)<0.01 -> TRUE
A35: Investing cash flow, reported | B35: US$m | C35: 53.819 | D35: -429.195 | E35: -149.185 | F35: -509.548 | G35: -128.449
A36: Investing cash flow ties | C36: =ABS('Cash Flow'!C26-C35)<0.01 -> TRUE | D36: =ABS('Cash Flow'!D26-D35)<0.01 -> TRUE | E36: =ABS('Cash Flow'!E26-E35)<0.01 -> TRUE | F36: =ABS('Cash Flow'!F26-F35)<0.01 -> TRUE | G36: =ABS('Cash Flow'!G26-G35)<0.01 -> TRUE
A37: Financing cash flow, reported | B37: US$m | C37: -754.21 | D37: -1718.249 | E37: -944.612 | F37: -633.539 | G37: -1170.768
A38: Financing cash flow ties | C38: =ABS('Cash Flow'!C38-C37)<0.01 -> TRUE | D38: =ABS('Cash Flow'!D38-D37)<0.01 -> TRUE | E38: =ABS('Cash Flow'!E38-E37)<0.01 -> TRUE | F38: =ABS('Cash Flow'!F38-F37)<0.01 -> TRUE | G38: =ABS('Cash Flow'!G38-G37)<0.01 -> TRUE
A39: Diluted EPS, reported (US$, 2 dp) | B39: US$ | C39: 0.43 | D39: 0.72 | E39: 0.2 | F39: 0.38 | G39: 0.45
A40: Diluted EPS ties at 2 dp | C40: =ROUND('Income Statement'!C58,2)=C39 -> TRUE | D40: =ROUND('Income Statement'!D58,2)=D39 -> TRUE | E40: =ROUND('Income Statement'!E58,2)=E39 -> TRUE | F40: =ROUND('Income Statement'!F58,2)=F39 -> TRUE | G40: =ROUND('Income Statement'!G58,2)=G39 -> TRUE
A42: Scenario outputs: live = stored for active scenario | C42: =Scenarios!G128 -> TRUE
A43: DCF tab UFCF = DCF Inputs UFCF (FY2027E-30E) | C43: =ABS(SUM(DCF!D31:G31)-SUM('DCF Inputs'!I17:L17))<0.01 -> TRUE
A44: Sensitivity table 1 centre = DCF value per share | C44: =ABS(Sensitivity!D11-DCF!C53)<0.005 -> TRUE
A45: Sensitivity table 2 centre = DCF value per share | C45: =ABS(Sensitivity!D23-DCF!C53)<0.005 -> TRUE
A47: ALL CHECKS PASS | C47: =AND(C6:L6,C7:L7,C8:L8,C9:L9,C10:L10,C11:L11,C14:L14,C16:L16,C18:L18,C20:L20,C22:L22,C24:L24,C26:L26,C28:L28,C30:L30,C32:L32,C34:L34,C36:L36,C38:L38,C40:L40,C42:C45) -> TRUE
