Workbook

Sheet Cover
A1: SHEIN Global Holdings Ltd (0625.HK) - Cover
A2: Initiation of coverage - earnings and valuation model. Prepared 30-Sep-2026. Not investment advice.
A4: Recommendation
A5: Rating | C5: ='Valuation Summary'!C11 -> BUY
A6: 12-month price target (HK$) | C6: ='Valuation Summary'!C9 -> 45
A7: Share price (HK$, 30-Sep-2026) | C7: =Inputs!$C$5 -> 30.84
A8: Upside / (downside) | C8: ='Valuation Summary'!C10 -> 0.45914397
A9: Market cap, fully diluted (US$m) | C9: =Inputs!$C$20 -> 17372.748
A10: Pro forma unrestricted cash & investments (US$m) | C10: =Inputs!$C$30 -> 13485.398
A11: Active scenario | C11: =Scenarios!D4 -> Base
A12: Model integrity (Checks tab) | C12: =IF(Checks!C20,"ALL CHECKS PASS","CHECK ERRORS") -> ALL CHECKS PASS
A14: Tabs
A15: Inputs | C15: Market data, share count, pro forma cash bridge, WACC, price-target weights
A16: Scenarios | C16: Bull / Base / Bear drivers FY2027E-31E with live selector; scenario comparison
A17: Interim | C17: Quarterly / half-year actuals (1Q25-2Q26), 2H26E build, 30-Jun-2026 balance sheet
A18: Revenue Model | C18: Customers x frequency = orders; revenue by region, business model and category
A19: Income Statement | C19: IFRS P&L FY2023A-FY2031E, non-IFRS adjusted earnings, per-share data
A20: Balance Sheet | C20: Full balance sheet, equity roll-forward (IPO conversion), working-capital drivers
A21: Cash Flow | C21: Cash-flow statement in company presentation; free cash flow
A22: DCF Inputs | C22: Unlevered FCF build incl. 2H26E stub
A23: DCF | C23: WACC, discounting, terminal value, EV-to-equity bridge
A24: Sensitivity | C24: WACC x g, growth x margin, P/E x EPS tables
A25: Comps | C25: 11 listed peers with statistical summary and implied values
A26: Valuation Summary | C26: Price target, rating, football field, key financials
A27: Checks | C27: Balance, cash and tie-out checks
A29: Colour legend
A30: Blue | C30: Hard-coded historical data or assumption (change me)
A31: Black | C31: Formula / calculation
A32: Green | C32: Direct link to another tab
A34: Sources
A35: [1] | C35: SHEIN Global Holdings Ltd Global Offering prospectus, 24-Aug-2026 (HKEX: 2026082400019)
A36: [2] | C36: Announcement of final offer price and allotment results, 31-Aug-2026 (HKEX: 2026083102409)
A37: [3] | C37: Stabilising actions and lapse of over-allotment option, 27-Sep-2026 (HKEX: 2026092700013)
A38: [4] | C38: 2026 Interim Report, 28-Sep-2026 (HKEX: 2026092801831)
A39: [5] | C39: Market prices and peer multiples: stockanalysis.com, 29/30-Sep-2026 closes; FX approximate
A40: [6] | C40: All forecasts are analyst estimates; units US$m unless stated; fiscal year ends 31 December

Sheet Inputs
A1: SHEIN Global Holdings Ltd (0625.HK) - Inputs
A2: Market data, capital structure and valuation inputs. Blue = input.
A4: Market data (close of 30-Sep-2026)
A5: Share price | B5: HK$ | C5: 30.84 | D5: Close 30-Sep-2026 (stockanalysis.com / HKEX)
A6: HK$ per US$ | B6: HK$/US$ | C6: 7.845 | D6: HK$48.56 = US$6.19 per 2026 Interim Report note 28
A7: IPO offer price (1-Sep-2026 listing) | B7: HK$ | C7: 48.56 | D7: Allotment results announcement, 31-Aug-2026
A8: IPO indicative range - low | B8: HK$ | C8: 47.6 | D8: Prospectus cover
A9: IPO indicative range - high | B9: HK$ | C9: 49.5 | D9: Prospectus cover
A10: High since listing | B10: HK$ | C10: 48.56 | D10: 1-Sep-2026 open
A11: Low since listing | B11: HK$ | C11: 29.9 | D11: 30-Sep-2026 intraday low
A12: Valuation date | B12: date | C12: 46295
A13: Share count (m shares)
A14: Shares in issue at listing (Class A + Class B) | B14: m | C14: 4246.2026 | D14: Allotment results; over-allotment option lapsed 26-Sep-2026
A15: Pre-IPO ESOP options outstanding (near-nil strike) | B15: m | C15: 157.0826 | D15: 2026 Interim Report - Share Schemes
A16: Pre-IPO ESOP RSUs outstanding | B16: m | C16: 15.9497 | D16: 2026 Interim Report - Share Schemes
A17: Fully diluted shares | B17: m | C17: =C14+C15+C16 -> 4419.2349 | D17: Treasury method ~ full count given near-nil strikes
A18: Annual dilution from post-IPO share scheme | B18: % | C18: 0.005 | D18: Analyst assumption
A19: Market cap (fully diluted) | B19: HK$m | C19: =C5*C17 -> 136289.2
A20: Market cap (fully diluted) | B20: US$m | C20: =C19/C6 -> 17372.748
A21: Pro forma cash bridge at listing (US$m)
A22: Cash resources, 30-Jun-2026 (cash, restricted, ST inv.) | B22: US$m | C22: =Interim!I87 -> 15248 | D22: 2026 Interim Report
A23: Less: restricted cash (current + non-current) | B23: US$m | C23: =Interim!I64+Interim!I65 -> 660
A24: IPO net proceeds | B24: HK$m | C24: 13214.1 | D24: Allotment results announcement
A25: IPO net proceeds | B25: US$m | C25: =C24/C6 -> 1684.3977
A26: Conversion Adjustment cash paid to Series Pre-D/D/D+ holders | B26: US$m | C26: 2200 | D26: Interim Report note 15 (paid at listing)
A27: 8% p.a. distribution to preferred holders (total, 2026) | B27: US$m | C27: 1082 | D27: US$725m paid 1H26 + US$357m in 2H26
A28: of which unpaid at 30-Jun-2026 | B28: US$m | C28: 357 | D28: Accrued at 30-Jun-2026
A29: 12% p.a. distribution (5-Mar-2026 to listing) | B29: US$m | C29: 230 | D29: Prospectus: est. US$230.4m; paid Sep-2026
A30: Pro forma unrestricted cash & investments | B30: US$m | C30: =C22-C23+C25-C26-C28-C29 -> 13485.398
A31: Less: minimum operating cash (analyst) | B31: US$m | C31: 1500 | D31: ~3.5% of revenue; supports negative working-capital model
A32: Less: regulatory contingency reserve (analyst) | B32: US$m | C32: 1000 | D32: EU DSA, FTC, CNIL appeal, Irish DPC exposure
A33: Plus: associates & FVTPL investments (book) | B33: US$m | C33: =Interim!I73+Interim!I74 -> 411
A34: Memo: lease liabilities (not deducted; lease cost in FCFF) | B34: US$m | C34: =Interim!I83 -> 1145
A35: Net cash used in valuation | B35: US$m | C35: =C30-C31-C32+C33 -> 11396.398
A36: Preferred-share conversion at listing (1-Sep-2026)
A37: Ordinary shares in issue before IPO (post 1:50 split) | B37: m | C37: 2568.5058 | D37: 51,370,116 pre-split (Interim Report note 14)
A38: New Class B shares issued in the Global Offering | B38: m | C38: 279.9925 | D38: Allotment results
A39: Class B shares issued on conversion (incl. 19.6m adjustment shares) | B39: m | C39: =C14-C37-C38 -> 1397.7043
A40: Carrying value of preferred shares, 30-Jun-2026 | B40: US$m | C40: =Interim!I82 -> 15105 | D40: Interim Report
A41: Fair value at conversion: shares at IPO price + cash compensation + 12% distribution | B41: US$m | C41: =C39*C7/C6+C26+C29 -> 11081.692
A42: Estimated 2H26 non-cash FV gain on remeasurement at conversion | B42: US$m | C42: =C40-C41 -> 4023.3083 | D42: Analyst estimate; excluded from adjusted earnings
A43: Discount rate
A44: Risk-free rate | B44: % | C44: 0.04 | D44: Matches 4.00% used in 30-Jun-2026 preferred-share valuation
A45: Equity beta | B45: x | C45: 1.2 | D45: HK-listed consumer internet peers; 40% implied vol.
A46: Equity risk premium (incl. China/geo-policy premium) | B46: % | C46: 0.06
A47: Cost of equity | B47: % | C47: =C44+C45*C46 -> 0.112 | D47: CAPM
A48: Target debt / capital | B48: % | C48: 0 | D48: Debt-free balance sheet
A49: After-tax cost of debt | B49: % | C49: 0.045 | D49: Not used at 0% gearing
A50: WACC | B50: % | C50: =C47*(1-C48)+C49*C48 -> 0.112
A51: Terminal growth rate | B51: % | C51: 0.025 | D51: Global online fashion market 2025-30E CAGR 5.5% (CIC); nominal GDP-like
A52: Tax rate on EBIT (DCF) | B52: % | C52: 0.22 | D52: Pillar 2 floor 15%; US/EU higher; FY25 core ETR 20.6%
A53: Price target methodology
A54: Target P/E on FY2027E adj. EPS | B54: x | C54: 14 | D54: Between China platforms (~7x) and global apparel (~21x)
A55: Weight: DCF | B55: % | C55: 0.5
A56: Weight: P/E | B56: % | C56: =1-C55 -> 0.5
A57: BUY if 12m upside above | B57: % | C57: 0.15
A58: SELL if 12m upside below | B58: % | C58: -0.1
A59: Capital return
A60: Dividend payout (% of adj. net income, paid following year) | B60: % | C60: 0.5 | D60: Policy: >=50% of net profit (Prospectus)

Sheet Scenarios
A1: SHEIN Global Holdings Ltd (0625.HK) - Scenarios
A2: Operating drivers by scenario for FY2027E-FY2031E. Change C4 to switch the whole model.
A4: Active scenario (1 = Bull, 2 = Base, 3 = Bear) | C4: 2 | D4: =CHOOSE(C4,"Bull","Base","Bear") -> Base
B6: Case | C6: FY2027E | D6: FY2028E | E6: FY2029E | F6: FY2030E | G6: FY2031E
A7: US net revenue growth (YoY)
B8: Bull | C8: 0.05 | D8: 0.06 | E8: 0.06 | F8: 0.05 | G8: 0.05
B9: Base | C9: 0.02 | D9: 0.04 | E9: 0.04 | F9: 0.04 | G9: 0.035
B10: Bear | C10: -0.04 | D10: 0 | E10: 0.02 | F10: 0.02 | G10: 0.02
B11: Selected | C11: =CHOOSE($C$4,C8,C9,C10) -> 0.02 | D11: =CHOOSE($C$4,D8,D9,D10) -> 0.04 | E11: =CHOOSE($C$4,E8,E9,E10) -> 0.04 | F11: =CHOOSE($C$4,F8,F9,F10) -> 0.04 | G11: =CHOOSE($C$4,G8,G9,G10) -> 0.035 | H11: Base: 1H26 -9.9%; de minimis base effect fades 2027; Everlane consolidated
A12: Europe net revenue growth (YoY)
B13: Bull | C13: 0.02 | D13: 0.07 | E13: 0.07 | F13: 0.06 | G13: 0.06
B14: Base | C14: -0.04 | D14: 0.04 | E14: 0.05 | F14: 0.05 | G14: 0.045
B15: Bear | C15: -0.1 | D15: -0.02 | E15: 0.02 | F15: 0.03 | G15: 0.03
B16: Selected | C16: =CHOOSE($C$4,C13,C14,C15) -> -0.04 | D16: =CHOOSE($C$4,D13,D14,D15) -> 0.04 | E16: =CHOOSE($C$4,E13,E14,E15) -> 0.05 | F16: =CHOOSE($C$4,F13,F14,F15) -> 0.05 | G16: =CHOOSE($C$4,G13,G14,G15) -> 0.045 | H16: EUR 3/item duty from 1-Jul-2026 + handling fee; 2Q26 -13.9%; 1H27 laps pre-duty base
A17: Rest of world net revenue growth (YoY)
B18: Bull | C18: 0.16 | D18: 0.13 | E18: 0.11 | F18: 0.1 | G18: 0.09
B19: Base | C19: 0.12 | D19: 0.1 | E19: 0.09 | F19: 0.08 | G19: 0.07
B20: Bear | C20: 0.08 | D20: 0.07 | E20: 0.06 | F20: 0.05 | G20: 0.04
B21: Selected | C21: =CHOOSE($C$4,C18,C19,C20) -> 0.12 | D21: =CHOOSE($C$4,D18,D19,D20) -> 0.1 | E21: =CHOOSE($C$4,E18,E19,E20) -> 0.09 | F21: =CHOOSE($C$4,F18,F19,F20) -> 0.08 | G21: =CHOOSE($C$4,G18,G19,G20) -> 0.07 | H21: 2Q26 +21.6% (LatAm-led) despite Middle East drag
A22: Service (marketplace) revenue % of net revenues
B23: Bull | C23: 0.145 | D23: 0.15 | E23: 0.155 | F23: 0.16 | G23: 0.163
B24: Base | C24: 0.145 | D24: 0.15 | E24: 0.155 | F24: 0.16 | G24: 0.163
B25: Bear | C25: 0.145 | D25: 0.15 | E25: 0.155 | F25: 0.16 | G25: 0.163
B26: Selected | C26: =CHOOSE($C$4,C23,C24,C25) -> 0.145 | D26: =CHOOSE($C$4,D23,D24,D25) -> 0.15 | E26: =CHOOSE($C$4,E23,E24,E25) -> 0.155 | F26: =CHOOSE($C$4,F23,F24,F25) -> 0.16 | G26: =CHOOSE($C$4,G23,G24,G25) -> 0.163 | H26: Mgmt: 1P remains core; marketplace mix 13.4% in 1H26
A27: Cost of sales % of product revenue
B28: Bull | C28: 0.34 | D28: 0.338 | E28: 0.336 | F28: 0.335 | G28: 0.335
B29: Base | C29: 0.343 | D29: 0.342 | E29: 0.341 | F29: 0.34 | G29: 0.34
B30: Bear | C30: 0.346 | D30: 0.346 | E30: 0.346 | F30: 0.346 | G30: 0.346
B31: Selected | C31: =CHOOSE($C$4,C28,C29,C30) -> 0.343 | D31: =CHOOSE($C$4,D28,D29,D30) -> 0.342 | E31: =CHOOSE($C$4,E28,E29,E30) -> 0.341 | F31: =CHOOSE($C$4,F28,F29,F30) -> 0.34 | G31: =CHOOSE($C$4,G28,G29,G30) -> 0.34 | H31: 1H26 34.6%; FY25 36.2%; higher price-point brands a partial offset
A32: Fulfilment expenses % of net revenues
B33: Bull | C33: 0.498 | D33: 0.495 | E33: 0.493 | F33: 0.493 | G33: 0.493
B34: Base | C34: 0.505 | D34: 0.502 | E34: 0.5 | F34: 0.5 | G34: 0.5
B35: Bear | C35: 0.512 | D35: 0.51 | E35: 0.508 | F35: 0.508 | G35: 0.508
B36: Selected | C36: =CHOOSE($C$4,C33,C34,C35) -> 0.505 | D36: =CHOOSE($C$4,D33,D34,D35) -> 0.502 | E36: =CHOOSE($C$4,E33,E34,E35) -> 0.5 | F36: =CHOOSE($C$4,F33,F34,F35) -> 0.5 | G36: =CHOOSE($C$4,G33,G34,G35) -> 0.5 | H36: Duties booked in fulfilment; freight normalises; local inventory adds cost near term
A37: Marketing expenses % of net revenues
B38: Bull | C38: 0.133 | D38: 0.13 | E38: 0.128 | F38: 0.128 | G38: 0.128
B39: Base | C39: 0.135 | D39: 0.133 | E39: 0.132 | F39: 0.132 | G39: 0.132
B40: Bear | C40: 0.138 | D40: 0.138 | E40: 0.136 | F40: 0.136 | G40: 0.136
B41: Selected | C41: =CHOOSE($C$4,C38,C39,C40) -> 0.135 | D41: =CHOOSE($C$4,D38,D39,D40) -> 0.133 | E41: =CHOOSE($C$4,E38,E39,E40) -> 0.132 | F41: =CHOOSE($C$4,F38,F39,F40) -> 0.132 | G41: =CHOOSE($C$4,G38,G39,G40) -> 0.132 | H41: FY25 14.8%; 1H26 14.6%; IPO proceeds 40% earmarked for brand
A42: Technology & content % of net revenues
B43: Bull | C43: 0.023 | D43: 0.023 | E43: 0.023 | F43: 0.023 | G43: 0.023
B44: Base | C44: 0.024 | D44: 0.024 | E44: 0.024 | F44: 0.024 | G44: 0.024
B45: Bear | C45: 0.025 | D45: 0.025 | E45: 0.025 | F45: 0.025 | G45: 0.025
B46: Selected | C46: =CHOOSE($C$4,C43,C44,C45) -> 0.024 | D46: =CHOOSE($C$4,D43,D44,D45) -> 0.024 | E46: =CHOOSE($C$4,E43,E44,E45) -> 0.024 | F46: =CHOOSE($C$4,F43,F44,F45) -> 0.024 | G46: =CHOOSE($C$4,G43,G44,G45) -> 0.024 | H46: IPO proceeds 40% earmarked for tech
A47: G&A % of net revenues
B48: Bull | C48: 0.012 | D48: 0.012 | E48: 0.012 | F48: 0.012 | G48: 0.012
B49: Base | C49: 0.013 | D49: 0.013 | E49: 0.013 | F49: 0.013 | G49: 0.013
B50: Bear | C50: 0.014 | D50: 0.014 | E50: 0.014 | F50: 0.014 | G50: 0.014
B51: Selected | C51: =CHOOSE($C$4,C48,C49,C50) -> 0.013 | D51: =CHOOSE($C$4,D48,D49,D50) -> 0.013 | E51: =CHOOSE($C$4,E48,E49,E50) -> 0.013 | F51: =CHOOSE($C$4,F48,F49,F50) -> 0.013 | G51: =CHOOSE($C$4,G48,G49,G50) -> 0.013 | H51: Public-company costs
A52: Active customer growth (YoY)
B53: Bull | C53: 0.08 | D53: 0.07 | E53: 0.06 | F53: 0.05 | G53: 0.05
B54: Base | C54: 0.06 | D54: 0.05 | E54: 0.04 | F54: 0.04 | G54: 0.035
B55: Bear | C55: 0.03 | D55: 0.02 | E55: 0.02 | F55: 0.02 | G55: 0.02
B56: Selected | C56: =CHOOSE($C$4,C53,C54,C55) -> 0.06 | D56: =CHOOSE($C$4,D53,D54,D55) -> 0.05 | E56: =CHOOSE($C$4,E53,E54,E55) -> 0.04 | F56: =CHOOSE($C$4,F53,F54,F55) -> 0.04 | G56: =CHOOSE($C$4,G53,G54,G55) -> 0.035 | H56: LTM Jun-26: 291m (+14.6%)
A57: Orders per active customer (x)
B58: Bull | C58: 3.9 | D58: 3.95 | E58: 4 | F58: 4.05 | G58: 4.1
B59: Base | C59: 3.85 | D59: 3.9 | E59: 3.95 | F59: 4 | G59: 4
B60: Bear | C60: 3.8 | D60: 3.8 | E60: 3.8 | F60: 3.8 | G60: 3.8
B61: Selected | C61: =CHOOSE($C$4,C58,C59,C60) -> 3.85 | D61: =CHOOSE($C$4,D58,D59,D60) -> 3.9 | E61: =CHOOSE($C$4,E58,E59,E60) -> 3.95 | F61: =CHOOSE($C$4,F58,F59,F60) -> 4 | G61: =CHOOSE($C$4,G58,G59,G60) -> 4 | H61: FY23 3.8 / FY24 4.0 / FY25 4.0 / LTM Mar-26 3.9
A63: Scenario comparison (full-model outputs)
C64: Bull | D64: Base | E64: Bear | F64: Selected (live)
A65: FY2027E net revenues (US$m) | C65: 45735.306 | D65: 43889.542 | E65: 41767.901 | F65: ='Income Statement'!G6 -> 43889.542
A66: FY2031E net revenues (US$m) | C66: 63310.673 | D66: 56375.645 | E66: 48063.112 | F66: ='Income Statement'!K6 -> 56375.645
A67: Revenue CAGR FY2026E-31E | C67: 0.086147233 | D67: 0.061235132 | E67: 0.027911423 | F67: =('Income Statement'!K6/'Income Statement'!F6)^(1/5)-1 -> 0.061235132
A68: FY2027E adj. EBIT margin | C68: 0.045486495 | D68: 0.032013447 | E68: 0.017564183 | F68: ='Income Statement'!G34 -> 0.032013447
A69: FY2031E adj. EBIT margin | C69: 0.065500415 | D69: 0.048548579 | E69: 0.029894717 | F69: ='Income Statement'!K34 -> 0.048548579
A70: FY2027E adj. net income (US$m) | C70: 1981.9119 | D70: 1457.3506 | E70: 936.11243 | F70: ='Income Statement'!G58 -> 1457.3506
A71: FY2027E adj. EPS (HK$) | C71: 3.5007746 | D71: 2.5742091 | E71: 1.6535138 | F71: ='Income Statement'!G66 -> 2.5742091
A72: FY2031E adj. net income (US$m) | C72: 3749.2184 | D72: 2588.6824 | E72: 1513.5114 | F72: ='Income Statement'!K58 -> 2588.6824
A73: Cumulative FCFF 2H26E-FY2031E (US$m) | C73: 12843.023 | D73: 8081.6541 | E73: 3369.9397 | F73: =SUM(DCF!D16:I16) -> 8081.6541
A74: DCF value per share (HK$) | C74: 73.638406 | D74: 54.352438 | E74: 36.127901 | F74: =DCF!C49 -> 54.352438
A75: P/E value per share (HK$) @ target P/E | C75: 49.010845 | D75: 36.038928 | E75: 23.149193 | F75: ='Valuation Summary'!C7 -> 36.038928
A76: Blended value per share (HK$) | C76: 61.324625 | D76: 45.195683 | E76: 29.638547 | F76: ='Valuation Summary'!C8 -> 45.195683
A77: vs. current price | C77: 0.98847682 | D77: 0.46548907 | E77: -0.038957629 | F77: ='Valuation Summary'!C8/Inputs!$C$5-1 -> 0.46548907
A78: Bull / Base / Bear columns are values recorded by re-running the full model with the selector set to 1 / 2 / 3; the 'Selected (live)' column recalculates.

Sheet Interim
A1: SHEIN Global Holdings Ltd (0625.HK) - Interim
A2: Quarterly and half-year actuals (unaudited except FY/3M audited), 2H26E build, balance sheet at 30-Jun-2026.
A4: US$m unless stated | B4: 1Q25A | C4: 2Q25A | D4: 1H25A | E4: 2H25A | F4: FY2025A | G4: 1Q26A | H4: 2Q26A | I4: 1H26A | J4: 2H26E | K4: FY2026E | L4: 2H26E driver
A5: Net revenues by region (US$m)
A6: United States | B6: 2380 | C6: 2632 | D6: =B6+C6 -> 5012 | E6: =F6-D6 -> 5089 | F6: ='Revenue Model'!E15 -> 10101 | G6: 2040 | H6: 2474 | I6: =G6+H6 -> 4514 | J6: =E6*(1+L6) -> 4681.88 | K6: =I6+J6 -> 9195.88 | L6: -0.08 | M6: 2H26E: 2Q26 -6.0%; early-3Q US sales >10% lower (Jefferies)
A7: Europe | B7: 2843 | C7: 4379 | D7: =B7+C7 -> 7222 | E7: =F7-D7 -> 7580 | F7: ='Revenue Model'!E18 -> 14802 | G7: 2908 | H7: 3770 | I7: =G7+H7 -> 6678 | J7: =E7*(1+L7) -> 6443 | K7: =I7+J7 -> 13121 | L7: -0.15 | M7: 2H26E: EUR 150 exemption removed 1-Jul-2026; price rises + lower ad spend
A8: Rest of world | B8: 3729 | C8: 3977 | D8: =B8+C8 -> 7706 | E8: =F8-D8 -> 9238 | F8: ='Revenue Model'!E21 -> 16944 | G8: 4104 | H8: 4838 | I8: =G8+H8 -> 8942 | J8: =E8*(1+L8) -> 10623.7 | K8: =I8+J8 -> 19565.7 | L8: 0.15 | M8: 2H26E: LatAm strength; Middle East still soft
A9: Total net revenues | B9: =B6+B7+B8 -> 8952 | C9: =C6+C7+C8 -> 10988 | D9: =D6+D7+D8 -> 19940 | E9: =E6+E7+E8 -> 21907 | F9: =F6+F7+F8 -> 41847 | G9: =G6+G7+G8 -> 9052 | H9: =H6+H7+H8 -> 11082 | I9: =I6+I7+I8 -> 20134 | ... K9: =K6+K7+K8 -> 41882.58
A10: US YoY | G10: =IFERROR(G6/B6-1,0) -> -0.14285714 | H10: =IFERROR(H6/C6-1,0) -> -0.060030395 | I10: =IFERROR(I6/D6-1,0) -> -0.099361532 | J10: =IFERROR(J6/E6-1,0) -> -0.08 | K10: =IFERROR(K6/F6-1,0) -> -0.08960697
A11: Europe YoY | G11: =IFERROR(G7/B7-1,0) -> 0.022863173 | H11: =IFERROR(H7/C7-1,0) -> -0.13907285 | I11: =IFERROR(I7/D7-1,0) -> -0.075325395 | J11: =IFERROR(J7/E7-1,0) -> -0.15 | K11: =IFERROR(K7/F7-1,0) -> -0.11356573
A12: Rest of world YoY | G12: =IFERROR(G8/B8-1,0) -> 0.10056315 | H12: =IFERROR(H8/C8-1,0) -> 0.21649485 | I12: =IFERROR(I8/D8-1,0) -> 0.1603945 | J12: =IFERROR(J8/E8-1,0) -> 0.15 | K12: =IFERROR(K8/F8-1,0) -> 0.15472734
A13: Total YoY | G13: =IFERROR(G9/B9-1,0) -> 0.011170688 | H13: =IFERROR(H9/C9-1,0) -> 0.008554787 | I13: =IFERROR(I9/D9-1,0) -> 0.0097291876 | J13: =IFERROR(J9/E9-1,0) -> -0.0072314785 | K13: =IFERROR(K9/F9-1,0) -> 0.00085024016
A14: Net revenues by type (US$m)
A15: Product revenues (first-party) | B15: 7765 | C15: 10013 | D15: =B15+C15 -> 17778 | E15: =F15-D15 -> 19329 | F15: ='Revenue Model'!E32 -> 37107 | G15: 7757 | H15: 9676 | I15: =G15+H15 -> 17433 | J15: =J9-J16 -> 18812.522 | K15: =I15+J15 -> 36245.522
A16: Service revenues (marketplace & brand enablement) | B16: 1187 | C16: 975 | D16: =B16+C16 -> 2162 | E16: =F16-D16 -> 2578 | F16: ='Revenue Model'!E30 -> 4740 | G16: 1295 | H16: 1406 | I16: =G16+H16 -> 2701 | J16: =J9*L17 -> 2936.0583 | K16: =I16+J16 -> 5637.0583
A17: Service % of net revenues | B17: =IFERROR(B16/B9,0) -> 0.13259607 | C17: =IFERROR(C16/C9,0) -> 0.088733163 | D17: =IFERROR(D16/D9,0) -> 0.10842528 | E17: =IFERROR(E16/E9,0) -> 0.11767928 | F17: =IFERROR(F16/F9,0) -> 0.11326977 | G17: =IFERROR(G16/G9,0) -> 0.14306231 | H17: =IFERROR(H16/H9,0) -> 0.12687241 | I17: =IFERROR(I16/I9,0) -> 0.13415119 | ... K17: =IFERROR(K16/K9,0) -> 0.13459195 | L17: 0.135
A18: Product revenues YoY | G18: =IFERROR(G15/B15-1,0) -> -0.001030264 | H18: =IFERROR(H15/C15-1,0) -> -0.033656247 | I18: =IFERROR(I15/D15-1,0) -> -0.019406007 | J18: =IFERROR(J15/E15-1,0) -> -0.026720384 | K18: =IFERROR(K15/F15-1,0) -> -0.023216059
A19: Service revenues YoY | G19: =IFERROR(G16/B16-1,0) -> 0.090985678 | H19: =IFERROR(H16/C16-1,0) -> 0.44205128 | I19: =IFERROR(I16/D16-1,0) -> 0.2493062 | J19: =IFERROR(J16/E16-1,0) -> 0.13888995 | K19: =IFERROR(K16/F16-1,0) -> 0.18925281
A20: Operating KPIs
A21: Total orders (m) | B21: 240 | C21: 277 | D21: =B21+C21 -> 517 | E21: =F21-D21 -> 561 | F21: ='Revenue Model'!E9 -> 1078 | G21: 251 | H21: 298 | I21: =G21+H21 -> 549 | J21: =E21*(1+L22) -> 594.66 | K21: =I21+J21 -> 1143.66
A22: Orders YoY | G22: =IFERROR(G21/B21-1,0) -> 0.045833333 | H22: =IFERROR(H21/C21-1,0) -> 0.075812274 | I22: =IFERROR(I21/D21-1,0) -> 0.061895551 | J22: =IFERROR(J21/E21-1,0) -> 0.06 | K22: =IFERROR(K21/F21-1,0) -> 0.060909091 | L22: 0.06 | M22: 1H26 +6.4%, 2Q26 +7.6%
A23: Net revenue per order (US$) | B23: =IFERROR(B9/B21,0) -> 37.3 | C23: =IFERROR(C9/C21,0) -> 39.66787 | D23: =IFERROR(D9/D21,0) -> 38.568665 | E23: =IFERROR(E9/E21,0) -> 39.049911 | F23: =IFERROR(F9/F21,0) -> 38.819109 | G23: =IFERROR(G9/G21,0) -> 36.063745 | H23: =IFERROR(H9/H21,0) -> 37.187919 | I23: =IFERROR(I9/I21,0) -> 36.673953 | ... K23: =IFERROR(K9/K21,0) -> 36.621531
A24: Active customers, trailing 12 months (m) | B24: 241 | C24: 254 | F24: 273 | G24: 281 | H24: 291 | I24: 291
A25: Income statement (US$m)
A26: Cost of sales | B26: 3339 | C26: 3628 | D26: =B26+C26 -> 6967 | E26: =F26-D26 -> 6466 | F26: ='Income Statement'!E11 -> 13433 | G26: 2679 | H26: 3347 | I26: =G26+H26 -> 6026 | J26: =J15*L27 -> 6396.2574 | K26: =I26+J26 -> 12422.257
A27: % of product revenues | B27: =IFERROR(B26/B15,0) -> 0.43000644 | C27: =IFERROR(C26/C15,0) -> 0.36232897 | D27: =IFERROR(D26/D15,0) -> 0.39188885 | E27: =IFERROR(E26/E15,0) -> 0.33452326 | F27: =IFERROR(F26/F15,0) -> 0.36200717 | G27: =IFERROR(G26/G15,0) -> 0.34536548 | H27: =IFERROR(H26/H15,0) -> 0.3459074 | I27: =IFERROR(I26/I15,0) -> 0.34566627 | ... K27: =IFERROR(K26/K15,0) -> 0.3427253 | L27: 0.34
A28: Gross profit | B28: =B9-B26 -> 5613 | C28: =C9-C26 -> 7360 | D28: =D9-D26 -> 12973 | E28: =E9-E26 -> 15441 | F28: =F9-F26 -> 28414 | G28: =G9-G26 -> 6373 | H28: =H9-H26 -> 7735 | I28: =I9-I26 -> 14108 | ... K28: =K9-K26 -> 29460.323
A29: Gross margin | B29: =IFERROR(B28/B9,0) -> 0.62701072 | C29: =IFERROR(C28/C9,0) -> 0.66982162 | D29: =IFERROR(D28/D9,0) -> 0.65060181 | E29: =IFERROR(E28/E9,0) -> 0.7048432 | F29: =IFERROR(F28/F9,0) -> 0.6789973 | G29: =IFERROR(G28/G9,0) -> 0.70404331 | H29: =IFERROR(H28/H9,0) -> 0.6979787 | I29: =IFERROR(I28/I9,0) -> 0.70070527 | ... K29: =IFERROR(K28/K9,0) -> 0.70340277
A30: Fulfilment expenses | B30: 3831 | C30: 4730 | D30: =B30+C30 -> 8561 | E30: =F30-D30 -> 10511 | F30: ='Income Statement'!E16 -> 19072 | G30: 4322 | H30: 5587 | I30: =G30+H30 -> 9909 | J30: =J9*L31 -> 11091.776 | K30: =I30+J30 -> 21000.776
A31: % of net revenues | B31: =IFERROR(B30/B9,0) -> 0.42794906 | C31: =IFERROR(C30/C9,0) -> 0.4304696 | D31: =IFERROR(D30/D9,0) -> 0.42933801 | E31: =IFERROR(E30/E9,0) -> 0.47980098 | F31: =IFERROR(F30/F9,0) -> 0.45575549 | G31: =IFERROR(G30/G9,0) -> 0.47746354 | H31: =IFERROR(H30/H9,0) -> 0.50415088 | I31: =IFERROR(I30/I9,0) -> 0.49215258 | ... K31: =IFERROR(K30/K9,0) -> 0.5014203 | L31: 0.51
A32: per order (US$) | B32: =IFERROR(B30/B21,0) -> 15.9625 | C32: =IFERROR(C30/C21,0) -> 17.075812 | D32: =IFERROR(D30/D21,0) -> 16.558994 | E32: =IFERROR(E30/E21,0) -> 18.736185 | F32: =IFERROR(F30/F21,0) -> 17.692022 | G32: =IFERROR(G30/G21,0) -> 17.219124 | H32: =IFERROR(H30/H21,0) -> 18.748322 | I32: =IFERROR(I30/I21,0) -> 18.04918 | ... K32: =IFERROR(K30/K21,0) -> 18.362779
A33: Marketing expenses | B33: 1088 | C33: 1576 | D33: =B33+C33 -> 2664 | E33: =F33-D33 -> 3527 | F33: ='Income Statement'!E21 -> 6191 | G33: 1430 | H33: 1511 | I33: =G33+H33 -> 2941 | J33: =J9*L34 -> 2936.0583 | K33: =I33+J33 -> 5877.0583
A34: % of net revenues | B34: =IFERROR(B33/B9,0) -> 0.12153709 | C34: =IFERROR(C33/C9,0) -> 0.1434292 | D34: =IFERROR(D33/D9,0) -> 0.1336008 | E34: =IFERROR(E33/E9,0) -> 0.16099877 | F34: =IFERROR(F33/F9,0) -> 0.1479437 | G34: =IFERROR(G33/G9,0) -> 0.15797614 | H34: =IFERROR(H33/H9,0) -> 0.13634723 | I34: =IFERROR(I33/I9,0) -> 0.14607132 | ... K34: =IFERROR(K33/K9,0) -> 0.14032226 | L34: 0.135
A35: Technology & content | B35: 220 | C35: 221 | D35: =B35+C35 -> 441 | E35: =F35-D35 -> 455 | F35: ='Income Statement'!E23 -> 896 | G35: 241 | H35: 258 | I35: =G35+H35 -> 499 | J35: =J9*L36 -> 500.21734 | K35: =I35+J35 -> 999.21734
A36: % of net revenues | B36: =IFERROR(B35/B9,0) -> 0.024575514 | C36: =IFERROR(C35/C9,0) -> 0.02011285 | D36: =IFERROR(D35/D9,0) -> 0.022116349 | E36: =IFERROR(E35/E9,0) -> 0.020769617 | F36: =IFERROR(F35/F9,0) -> 0.021411332 | G36: =IFERROR(G35/G9,0) -> 0.026623951 | H36: =IFERROR(H35/H9,0) -> 0.023280996 | I36: =IFERROR(I35/I9,0) -> 0.024783948 | ... K36: =IFERROR(K35/K9,0) -> 0.023857588 | L36: 0.023
A37: General & administrative | B37: 126 | C37: 135 | D37: =B37+C37 -> 261 | E37: =F37-D37 -> 287 | F37: ='Income Statement'!E25 -> 548 | G37: 122 | H37: 144 | I37: =G37+H37 -> 266 | J37: =J9*L38 -> 282.73154 | K37: =I37+J37 -> 548.73154
A38: % of net revenues | B38: =IFERROR(B37/B9,0) -> 0.014075067 | C38: =IFERROR(C37/C9,0) -> 0.01228613 | D38: =IFERROR(D37/D9,0) -> 0.013089268 | E38: =IFERROR(E37/E9,0) -> 0.013100835 | F38: =IFERROR(F37/F9,0) -> 0.013095323 | G38: =IFERROR(G37/G9,0) -> 0.013477684 | H38: =IFERROR(H37/H9,0) -> 0.012994044 | I38: =IFERROR(I37/I9,0) -> 0.013211483 | ... K38: =IFERROR(K37/K9,0) -> 0.013101665 | L38: 0.013
A39: Operating income | B39: =B28-B30-B33-B35-B37 -> 348 | C39: =C28-C30-C33-C35-C37 -> 698 | D39: =D28-D30-D33-D35-D37 -> 1046 | E39: =E28-E30-E33-E35-E37 -> 661 | F39: =F28-F30-F33-F35-F37 -> 1707 | G39: =G28-G30-G33-G35-G37 -> 258 | H39: =H28-H30-H33-H35-H37 -> 235 | I39: =I28-I30-I33-I35-I37 -> 493 | ... K39: =K28-K30-K33-K35-K37 -> 1034.5396
A40: Operating margin | B40: =IFERROR(B39/B9,0) -> 0.038873995 | C40: =IFERROR(C39/C9,0) -> 0.063523844 | D40: =IFERROR(D39/D9,0) -> 0.052457372 | E40: =IFERROR(E39/E9,0) -> 0.030173004 | F40: =IFERROR(F39/F9,0) -> 0.040791455 | G40: =IFERROR(G39/G9,0) -> 0.028501989 | H40: =IFERROR(H39/H9,0) -> 0.021205559 | I40: =IFERROR(I39/I9,0) -> 0.024485944 | ... K40: =IFERROR(K39/K9,0) -> 0.024700953
A41: Share-based compensation (in opex) | B41: 22 | C41: 17 | D41: =B41+C41 -> 39 | E41: =F41-D41 -> 46 | F41: ='Income Statement'!E32 -> 85 | G41: 26 | H41: 19 | I41: =G41+H41 -> 45 | J41: =L41 -> 45 | K41: =I41+J41 -> 90 | L41: 45
A42: Adjusted EBIT (non-IFRS) | B42: =B39+B41 -> 370 | C42: =C39+C41 -> 715 | D42: =D39+D41 -> 1085 | E42: =E39+E41 -> 707 | F42: =F39+F41 -> 1792 | G42: =G39+G41 -> 284 | H42: =H39+H41 -> 254 | I42: =I39+I41 -> 538 | ... K42: =K39+K41 -> 1124.5396
A43: Adjusted EBIT margin | B43: =IFERROR(B42/B9,0) -> 0.041331546 | C43: =IFERROR(C42/C9,0) -> 0.065070987 | D43: =IFERROR(D42/D9,0) -> 0.05441324 | E43: =IFERROR(E42/E9,0) -> 0.03227279 | F43: =IFERROR(F42/F9,0) -> 0.042822664 | G43: =IFERROR(G42/G9,0) -> 0.031374282 | H43: =IFERROR(H42/H9,0) -> 0.022920051 | I43: =IFERROR(I42/I9,0) -> 0.02672097 | ... K43: =IFERROR(K42/K9,0) -> 0.026849818
A44: FV changes of convertible redeemable preferred shares | B44: 0 | C44: 0 | D44: =B44+C44 -> 0 | E44: =F44-D44 -> 328 | F44: ='Income Statement'!E44 -> 328 | G44: -328 | H44: 2189 | I44: =G44+H44 -> 1861 | J44: =Inputs!$C$42 -> 4023.3083 | K44: =I44+J44 -> 5884.3083 | M44: 2H26E: remeasurement to conversion value at listing (Inputs); non-cash, excluded from adj. NI
A45: Share of income/(losses) from associates | B45: -21 | C45: 25 | D45: =B45+C45 -> 4 | E45: =F45-D45 -> -1 | F45: ='Income Statement'!E45 -> 3 | G45: -16 | H45: 1 | I45: =G45+H45 -> -15 | J45: =L45 -> 0 | K45: =I45+J45 -> -15 | L45: 0
A46: Interest yield on cash resources (annualised, 2H26E driver) | L46: 0.039
A47: Interest income | B47: 135 | C47: 156 | D47: =B47+C47 -> 291 | E47: =F47-D47 -> 330 | F47: ='Income Statement'!E47 -> 621 | G47: 150 | H47: 159 | I47: =G47+H47 -> 309 | J47: =L46*0.5*(Inputs!$C$22+Inputs!$C$25-Inputs!$C$26-Inputs!$C$28-Inputs!$C$29) -> 275.83526 | K47: =I47+J47 -> 584.83526
A48: Exchange gain/(loss) | B48: 47 | C48: -23 | D48: =B48+C48 -> 24 | E48: =F48-D48 -> -119 | F48: ='Income Statement'!E48 -> -95 | G48: -72 | H48: -79 | I48: =G48+H48 -> -151 | J48: =L48 -> 0 | K48: =I48+J48 -> -151 | L48: 0
A49: Others, net (incl. lease interest) | B49: -14 | C49: -11 | D49: =B49+C49 -> -25 | E49: =F49-D49 -> -25 | F49: ='Income Statement'!E50 -> -50 | G49: -12 | H49: -28 | I49: =G49+H49 -> -40 | J49: =L49 -> -30 | K49: =I49+J49 -> -70 | L49: -30
A50: Income before income taxes | B50: =B39+B44+B45+B47+B48+B49 -> 495 | C50: =C39+C44+C45+C47+C48+C49 -> 845 | D50: =D39+D44+D45+D47+D48+D49 -> 1340 | E50: =E39+E44+E45+E47+E48+E49 -> 1174 | F50: =F39+F44+F45+F47+F48+F49 -> 2514 | G50: =G39+G44+G45+G47+G48+G49 -> -20 | H50: =H39+H44+H45+H47+H48+H49 -> 2477 | I50: =I39+I44+I45+I47+I48+I49 -> 2457 | ... K50: =K39+K44+K45+K47+K48+K49 -> 7267.6832
A51: Income tax expense | B51: 100 | C51: 154 | D51: =B51+C51 -> 254 | E51: =F51-D51 -> 196 | F51: ='Income Statement'!E52 -> 450 | G51: 79 | H51: 79 | I51: =G51+H51 -> 158 | J51: =L52*(J50-J44-J45) -> 181.09623 | K51: =I51+J51 -> 339.09623
A52: Effective tax rate (ex FV changes & associates) | B52: =IFERROR(B51/(B50-B44-B45),0) -> 0.19379845 | C52: =IFERROR(C51/(C50-C44-C45),0) -> 0.18780488 | D52: =IFERROR(D51/(D50-D44-D45),0) -> 0.19011976 | E52: =IFERROR(E51/(E50-E44-E45),0) -> 0.23140496 | F52: =IFERROR(F51/(F50-F44-F45),0) -> 0.20613834 | G52: =IFERROR(G51/(G50-G44-G45),0) -> 0.24382716 | H52: =IFERROR(H51/(H50-H44-H45),0) -> 0.27526132 | I52: =IFERROR(I51/(I50-I44-I45),0) -> 0.25859247 | ... K52: =IFERROR(K51/(K50-K44-K45),0) -> 0.24249307 | L52: 0.23
A53: Net income (IFRS) | B53: =B50-B51 -> 395 | C53: =C50-C51 -> 691 | D53: =D50-D51 -> 1086 | E53: =E50-E51 -> 978 | F53: =F50-F51 -> 2064 | G53: =G50-G51 -> -99 | H53: =H50-H51 -> 2398 | I53: =I50-I51 -> 2299 | ... K53: =K50-K51 -> 6928.587
A54: Other non-IFRS adjustments (impairment / FV on LT investments) | B54: 2 | C54: 0 | D54: =B54+C54 -> 2 | E54: =F54-D54 -> -4 | F54: ='Income Statement'!E57 -> -2 | G54: 0 | H54: 1 | I54: =G54+H54 -> 1 | J54: =L54 -> 0 | K54: =I54+J54 -> 1 | L54: 0
A55: Adjusted net income (non-IFRS) | B55: =B53+B41-B44-B45+B54 -> 440 | C55: =C53+C41-C44-C45+C54 -> 683 | D55: =D53+D41-D44-D45+D54 -> 1123 | E55: =E53+E41-E44-E45+E54 -> 693 | F55: =F53+F41-F44-F45+F54 -> 1816 | G55: =G53+G41-G44-G45+G54 -> 271 | H55: =H53+H41-H44-H45+H54 -> 228 | I55: =I53+I41-I44-I45+I54 -> 499 | ... K55: =K53+K41-K44-K45+K54 -> 1150.2787
A56: Adjusted net margin | B56: =IFERROR(B55/B9,0) -> 0.049151028 | C56: =IFERROR(C55/C9,0) -> 0.062158719 | D56: =IFERROR(D55/D9,0) -> 0.056318957 | E56: =IFERROR(E55/E9,0) -> 0.031633724 | F56: =IFERROR(F55/F9,0) -> 0.043396181 | G56: =IFERROR(G55/G9,0) -> 0.029938135 | H56: =IFERROR(H55/H9,0) -> 0.020573904 | I56: =IFERROR(I55/I9,0) -> 0.024783948 | ... K56: =IFERROR(K55/K9,0) -> 0.02746437
A57: Half-year cash flow items (US$m)
A58: D&A of property, equipment & intangibles | D58: 76 | E58: =F58-D58 -> 75 | F58: ='Income Statement'!E36 -> 151 | I58: 87 | J58: =K58-I58 -> 93.095094 | K58: ='Income Statement'!F36 -> 180.09509
A59: Depreciation of right-of-use assets | D59: 122 | E59: =F59-D59 -> 125 | F59: ='Income Statement'!E38 -> 247 | I59: 139 | J59: =K59-I59 -> 145.80154 | K59: ='Income Statement'!F38 -> 284.80154
A60: Capital expenditure (PP&E and land use rights) | D60: 103 | E60: =F60-D60 -> 119 | F60: =-'Cash Flow'!E27 -> 222 | I60: 140 | J60: =K60-I60 -> 153.17806 | K60: =-'Cash Flow'!F27 -> 293.17806
A61: Net cash from operating activities (reported) | D61: 2877 | E61: =F61-D61 -> -39 | F61: ='Cash Flow'!E24 -> 2838 | I61: 1205
A62: Balance sheet (US$m): column F = 31-Dec-2025 (audited), column I = 30-Jun-2026 (unaudited)
A63: Cash and cash equivalents | F63: 4481 | I63: 3043
A64: Restricted cash (current) | F64: 550 | I64: 622
A65: Restricted cash (non-current) | F65: 32 | I65: 38
A66: Short-term investments | F66: 9723 | I66: 11545
A67: Receivables from payment platforms & service providers | F67: 718 | I67: 1223
A68: Other receivables and prepayments | F68: 534 | I68: 598
A69: Inventories | F69: 1261 | I69: 1540
A70: Other current assets | F70: 326 | I70: 450
A71: Intangible assets (incl. Everlane goodwill) | F71: 38 | I71: 135
A72: Deferred tax assets | F72: 102 | I72: 125
A73: Investments in associates | F73: 266 | I73: 249
A74: Investments at FVTPL | F74: 158 | I74: 162
... A86: Total shareholders' deficit | F86: -6897 | I86: -4514
A87: Cash resources (cash + restricted + ST investments) | F87: =F63+F64+F65+F66 -> 14786 | I87: =I63+I64+I65+I66 -> 15248
A88: Operating net working capital | F88: =F67+F68+F69+F70-F76-(F77-F78-F79)-F80 -> -4004 | I88: =I67+I68+I69+I70-I76-(I77-I78-I79)-I80 -> -4974 | M88: Excludes tax payable, lease liabilities and preferred-share distributions

Sheet Revenue Model
A1: SHEIN Global Holdings Ltd (0625.HK) - Revenue Model
A2: Revenue build: customers x order frequency; revenue by region, business model and category.
A4: US$m unless stated | C4: FY2023A | D4: FY2024A | E4: FY2025A | F4: FY2026E | G4: FY2027E | H4: FY2028E | I4: FY2029E | J4: FY2030E | K4: FY2031E
A5: Customer & order KPIs
A6: Active customers (m) | C6: 186 | D6: 230 | E6: 273 | F6: 300 | G6: =F6*(1+G7) -> 318 | H6: =G6*(1+H7) -> 333.9 | I6: =H6*(1+I7) -> 347.256 | J6: =I6*(1+J7) -> 361.14624 | K6: =J6*(1+K7) -> 373.78636 | M6: FY26E: LTM Jun-26 already 291m
A7: YoY growth | D7: =IFERROR(D6/C6-1,0) -> 0.23655914 | E7: =IFERROR(E6/D6-1,0) -> 0.18695652 | F7: =IFERROR(F6/E6-1,0) -> 0.098901099 | G7: =Scenarios!C56 -> 0.06 | H7: =Scenarios!D56 -> 0.05 | I7: =Scenarios!E56 -> 0.04 | J7: =Scenarios!F56 -> 0.04 | K7: =Scenarios!G56 -> 0.035
A8: Orders per active customer (x) | C8: =C9/C6 -> 3.844086 | D8: =D9/D6 -> 3.9956522 | E8: =E9/E6 -> 3.9487179 | F8: =F9/F6 -> 3.8122 | G8: =Scenarios!C61 -> 3.85 | H8: =Scenarios!D61 -> 3.9 | I8: =Scenarios!E61 -> 3.95 | J8: =Scenarios!F61 -> 4 | K8: =Scenarios!G61 -> 4
A9: Total orders (m) | C9: 715 | D9: 919 | E9: 1078 | F9: =Interim!K21 -> 1143.66 | G9: =G6*G8 -> 1224.3 | H9: =H6*H8 -> 1302.21 | I9: =I6*I8 -> 1371.6612 | J9: =J6*J8 -> 1444.585 | K9: =K6*K8 -> 1495.1454
A10: YoY growth | D10: =IFERROR(D9/C9-1,0) -> 0.28531469 | E10: =IFERROR(E9/D9-1,0) -> 0.17301415 | F10: =IFERROR(F9/E9-1,0) -> 0.060909091 | G10: =IFERROR(G9/F9-1,0) -> 0.070510466 | H10: =IFERROR(H9/G9-1,0) -> 0.063636364 | I10: =IFERROR(I9/H9-1,0) -> 0.053333333 | J10: =IFERROR(J9/I9-1,0) -> 0.053164557 | K10: =IFERROR(K9/J9-1,0) -> 0.035
A11: Net revenue per order (US$) | C11: =C24/C9 -> 44.899301 | D11: =D24/D9 -> 42.163221 | E11: =E24/E9 -> 38.819109 | F11: =F24/F9 -> 36.621531 | G11: =G24/G9 -> 35.848682 | H11: =H24/H9 -> 36.061725 | I11: =I24/I9 -> 36.579429 | J11: =J24/J9 -> 36.944931 | K11: =K24/K9 -> 37.705793
A12: YoY growth | D12: =IFERROR(D11/C11-1,0) -> -0.060938139 | E12: =IFERROR(E11/D11-1,0) -> -0.079313472 | F12: =IFERROR(F11/E11-1,0) -> -0.056610742 | G12: =IFERROR(G11/F11-1,0) -> -0.02110367 | H12: =IFERROR(H11/G11-1,0) -> 0.0059428223 | I12: =IFERROR(I11/H11-1,0) -> 0.014356056 | J12: =IFERROR(J11/I11-1,0) -> 0.0099920229 | K12: =IFERROR(K11/J11-1,0) -> 0.020594491 | M12: Diluted by marketplace mix (service revenue = take rate only)
A13: Net revenue per active customer (US$) | C13: =C24/C6 -> 172.59677 | D13: =D24/D6 -> 168.46957 | E13: =E24/E6 -> 153.28571 | F13: =F24/F6 -> 139.6086 | G13: =G24/G6 -> 138.01743 | H13: =H24/H6 -> 140.64073 | I13: =I24/I6 -> 144.48874 | J13: =J24/J6 -> 147.77972 | K13: =K24/K6 -> 150.82317
A14: Net revenues by geography (US$m)
A15: United States | C15: 9454 | D15: 10464 | E15: 10101 | F15: =Interim!K6 -> 9195.88 | G15: =F15*(1+G16) -> 9379.7976 | H15: =G15*(1+H16) -> 9754.9895 | I15: =H15*(1+I16) -> 10145.189 | J15: =I15*(1+J16) -> 10550.997 | K15: =J15*(1+K16) -> 10920.282
A16: YoY growth | D16: =IFERROR(D15/C15-1,0) -> 0.10683309 | E16: =IFERROR(E15/D15-1,0) -> -0.034690367 | F16: =IFERROR(F15/E15-1,0) -> -0.08960697 | G16: =Scenarios!C11 -> 0.02 | H16: =Scenarios!D11 -> 0.04 | I16: =Scenarios!E11 -> 0.04 | J16: =Scenarios!F11 -> 0.04 | K16: =Scenarios!G11 -> 0.035
A17: % of net revenues | C17: =IFERROR(C15/C24,0) -> 0.29448961 | D17: =IFERROR(D15/D24,0) -> 0.27005265 | E17: =IFERROR(E15/E24,0) -> 0.24137931 | F17: =IFERROR(F15/F24,0) -> 0.21956336 | G17: =IFERROR(G15/G24,0) -> 0.21371373 | H17: =IFERROR(H15/H24,0) -> 0.20773003 | I17: =IFERROR(I15/I24,0) -> 0.20219778 | J17: =IFERROR(J15/J24,0) -> 0.19769493 | K17: =IFERROR(K15/K24,0) -> 0.19370566
A18: Europe | C18: 10214 | D18: 13603 | E18: 14802 | F18: =Interim!K7 -> 13121 | G18: =F18*(1+G19) -> 12596.16 | H18: =G18*(1+H19) -> 13100.006 | I18: =H18*(1+I19) -> 13755.007 | J18: =I18*(1+J19) -> 14442.757 | K18: =J18*(1+K19) -> 15092.681
A19: YoY growth | D19: =IFERROR(D18/C18-1,0) -> 0.33179949 | E19: =IFERROR(E18/D18-1,0) -> 0.088142322 | F19: =IFERROR(F18/E18-1,0) -> -0.11356573 | G19: =Scenarios!C16 -> -0.04 | H19: =Scenarios!D16 -> 0.04 | I19: =Scenarios!E16 -> 0.05 | J19: =Scenarios!F16 -> 0.05 | K19: =Scenarios!G16 -> 0.045
A20: % of net revenues | C20: =IFERROR(C18/C24,0) -> 0.31816341 | D20: =IFERROR(D18/D24,0) -> 0.35106328 | E20: =IFERROR(E18/E24,0) -> 0.35371711 | F20: =IFERROR(F18/F24,0) -> 0.3132806 | G20: =IFERROR(G18/G24,0) -> 0.28699685 | H20: =IFERROR(H18/H24,0) -> 0.27896132 | I20: =IFERROR(I18/I24,0) -> 0.27414292 | J20: =IFERROR(J18/J24,0) -> 0.27061518 | K20: =IFERROR(K18/K24,0) -> 0.26771634
A21: Rest of world (LatAm, Middle East, APAC & other) | C21: 12435 | D21: 14681 | E21: 16944 | F21: =Interim!K8 -> 19565.7 | G21: =F21*(1+G22) -> 21913.584 | H21: =G21*(1+H22) -> 24104.942 | I21: =H21*(1+I22) -> 26274.387 | J21: =I21*(1+J22) -> 28376.338 | K21: =J21*(1+K22) -> 30362.682
A22: YoY growth | D22: =IFERROR(D21/C21-1,0) -> 0.18061922 | E22: =IFERROR(E21/D21-1,0) -> 0.15414481 | F22: =IFERROR(F21/E21-1,0) -> 0.15472734 | G22: =Scenarios!C21 -> 0.12 | H22: =Scenarios!D21 -> 0.1 | I22: =Scenarios!E21 -> 0.09 | J22: =Scenarios!F21 -> 0.08 | K22: =Scenarios!G21 -> 0.07
A23: % of net revenues | C23: =IFERROR(C21/C24,0) -> 0.38734698 | D23: =IFERROR(D21/D24,0) -> 0.37888407 | E23: =IFERROR(E21/E24,0) -> 0.40490358 | F23: =IFERROR(F21/F24,0) -> 0.46715603 | G23: =IFERROR(G21/G24,0) -> 0.49928943 | H23: =IFERROR(H21/H24,0) -> 0.51330865 | I23: =IFERROR(I21/I24,0) -> 0.5236593 | J23: =IFERROR(J21/J24,0) -> 0.53168989 | K23: =IFERROR(K21/K24,0) -> 0.538578
A24: Total net revenues | C24: =C15+C18+C21 -> 32103 | D24: =D15+D18+D21 -> 38748 | E24: =E15+E18+E21 -> 41847 | F24: =F15+F18+F21 -> 41882.58 | G24: =G15+G18+G21 -> 43889.542 | H24: =H15+H18+H21 -> 46959.938 | I24: =I15+I18+I21 -> 50174.583 | J24: =J15+J18+J21 -> 53370.092 | K24: =K15+K18+K21 -> 56375.645
A25: YoY growth | D25: =IFERROR(D24/C24-1,0) -> 0.20699 | E25: =IFERROR(E24/D24-1,0) -> 0.079978321 | F25: =IFERROR(F24/E24-1,0) -> 0.00085024016 | G25: =IFERROR(G24/F24-1,0) -> 0.047918767 | H25: =IFERROR(H24/G24-1,0) -> 0.069957366 | I25: =IFERROR(I24/H24-1,0) -> 0.068455046 | J25: =IFERROR(J24/I24-1,0) -> 0.063687801 | K25: =IFERROR(K24/J24-1,0) -> 0.056315298
A26: Memo: net revenues outside the US | C26: =C18+C21 -> 22649 | D26: =D18+D21 -> 28284 | E26: =E18+E21 -> 31746 | F26: =F18+F21 -> 32686.7 | G26: =G18+G21 -> 34509.744 | H26: =H18+H21 -> 37204.949 | I26: =I18+I21 -> 40029.394 | J26: =J18+J21 -> 42819.095 | K26: =K18+K21 -> 45455.363
A27: YoY growth | D27: =IFERROR(D26/C26-1,0) -> 0.24879686 | E27: =IFERROR(E26/D26-1,0) -> 0.12240136 | F27: =IFERROR(F26/E26-1,0) -> 0.02963208 | G27: =IFERROR(G26/F26-1,0) -> 0.055773266 | H27: =IFERROR(H26/G26-1,0) -> 0.07809982 | I27: =IFERROR(I26/H26-1,0) -> 0.075915845 | J27: =IFERROR(J26/I26-1,0) -> 0.06969132 | K27: =IFERROR(K26/J26-1,0) -> 0.061567572
A28: Net revenues by business model (US$m)
A29: Service revenues % of total | C29: =IFERROR(C30/C24,0) -> 0.027037972 | D29: =IFERROR(D30/D24,0) -> 0.087669041 | E29: =IFERROR(E30/E24,0) -> 0.11326977 | F29: =IFERROR(F30/F24,0) -> 0.13459195 | G29: =Scenarios!C26 -> 0.145 | H29: =Scenarios!D26 -> 0.15 | I29: =Scenarios!E26 -> 0.155 | J29: =Scenarios!F26 -> 0.16 | K29: =Scenarios!G26 -> 0.163
A30: Service revenues (marketplace commissions, fulfilment & brand-enablement fees) | C30: 868 | D30: 3397 | E30: 4740 | F30: =Interim!K16 -> 5637.0583 | G30: =G24*G29 -> 6363.9835 | H30: =H24*H29 -> 7043.9907 | I30: =I24*I29 -> 7777.0604 | J30: =J24*J29 -> 8539.2147 | K30: =K24*K29 -> 9189.2301
A31: YoY growth | D31: =IFERROR(D30/C30-1,0) -> 2.9135945 | E31: =IFERROR(E30/D30-1,0) -> 0.39534884 | F31: =IFERROR(F30/E30-1,0) -> 0.18925281 | G31: =IFERROR(G30/F30-1,0) -> 0.12895471 | H31: =IFERROR(H30/G30-1,0) -> 0.10685245 | I31: =IFERROR(I30/H30-1,0) -> 0.10407021 | J31: =IFERROR(J30/I30-1,0) -> 0.098000311 | K31: =IFERROR(K30/J30-1,0) -> 0.07612121
A32: Product revenues (first-party, own & partner brands) | C32: 31235 | D32: 35351 | E32: 37107 | F32: =Interim!K15 -> 36245.522 | G32: =G24-G30 -> 37525.558 | H32: =H24-H30 -> 39915.948 | I32: =I24-I30 -> 42397.523 | J32: =J24-J30 -> 44830.877 | K32: =K24-K30 -> 47186.414
A33: YoY growth | D33: =IFERROR(D32/C32-1,0) -> 0.13177525 | E33: =IFERROR(E32/D32-1,0) -> 0.049673277 | F33: =IFERROR(F32/E32-1,0) -> -0.023216059 | G33: =IFERROR(G32/F32-1,0) -> 0.035315711 | H33: =IFERROR(H32/G32-1,0) -> 0.063700305 | I33: =IFERROR(I32/H32-1,0) -> 0.062170016 | J33: =IFERROR(J32/I32-1,0) -> 0.057393791 | K33: =IFERROR(K32/J32-1,0) -> 0.052542743
A34: % of net revenues | C34: =IFERROR(C32/C24,0) -> 0.97296203 | D34: =IFERROR(D32/D24,0) -> 0.91233096 | E34: =IFERROR(E32/E24,0) -> 0.88673023 | F34: =IFERROR(F32/F24,0) -> 0.86540805 | G34: =IFERROR(G32/G24,0) -> 0.855 | H34: =IFERROR(H32/H24,0) -> 0.85 | I34: =IFERROR(I32/I24,0) -> 0.845 | J34: =IFERROR(J32/J24,0) -> 0.84 | K34: =IFERROR(K32/K24,0) -> 0.837
A35: Total net revenues | C35: =C32+C30 -> 32103 | D35: =D32+D30 -> 38748 | E35: =E32+E30 -> 41847 | F35: =F32+F30 -> 41882.58 | G35: =G32+G30 -> 43889.542 | H35: =H32+H30 -> 46959.938 | I35: =I32+I30 -> 50174.583 | J35: =J32+J30 -> 53370.092 | K35: =K32+K30 -> 56375.645
A36: Assumed blended marketplace take rate (analyst estimate) | C36: 0.25 | D36: 0.25 | E36: 0.25 | F36: 0.25 | G36: 0.25 | H36: 0.25 | I36: 0.25 | J36: 0.25 | K36: 0.25 | M36: Commission 10-20% of transaction value + fulfilment fees (Prospectus); not disclosed
A37: Memo: implied marketplace GMV (illustrative) | C37: =C30/C36 -> 3472 | D37: =D30/D36 -> 13588 | E37: =E30/E36 -> 18960 | F37: =F30/F36 -> 22548.233 | G37: =G30/G36 -> 25455.934 | H37: =H30/H36 -> 28175.963 | I37: =I30/I36 -> 31108.241 | J37: =J30/J36 -> 34156.859 | K37: =K30/K36 -> 36756.92
A38: Memo: implied gross sales (1P revenue + marketplace GMV) | C38: =C32+C37 -> 34707 | D38: =D32+D37 -> 48939 | E38: =E32+E37 -> 56067 | F38: =F32+F37 -> 58793.755 | G38: =G32+G37 -> 62981.492 | H38: =H32+H37 -> 68091.911 | I38: =I32+I37 -> 73505.764 | J38: =J32+J37 -> 78987.736 | K38: =K32+K37 -> 83943.335
A39: YoY growth | D39: =IFERROR(D38/C38-1,0) -> 0.41006137 | E39: =IFERROR(E38/D38-1,0) -> 0.14565071 | F39: =IFERROR(F38/E38-1,0) -> 0.048633865 | G39: =IFERROR(G38/F38-1,0) -> 0.071227587 | H39: =IFERROR(H38/G38-1,0) -> 0.081141589 | I39: =IFERROR(I38/H38-1,0) -> 0.079508029 | J39: =IFERROR(J38/I38-1,0) -> 0.074578803 | K39: =IFERROR(K38/J38-1,0) -> 0.062738837
A40: Net revenues by category (US$m)
A41: Apparel % of net revenues | C41: =IFERROR(C42/C24,0) -> 0.68778619 | D41: =IFERROR(D42/D24,0) -> 0.64694952 | E41: =IFERROR(E42/E24,0) -> 0.63820585 | F41: 0.615 | G41: 0.61 | H41: 0.605 | I41: 0.6 | J41: 0.595 | K41: 0.59 | M41: Category diversification (home, beauty, kids, sport); Q1'26 61.4%
A42: Apparel | C42: 22080 | D42: 25068 | E42: 26707 | F42: =F24*F41 -> 25757.787 | G42: =G24*G41 -> 26772.62 | H42: =H24*H41 -> 28410.763 | I42: =I24*I41 -> 30104.75 | J42: =J24*J41 -> 31755.205 | K42: =K24*K41 -> 33261.63
A43: YoY growth | D43: =IFERROR(D42/C42-1,0) -> 0.13532609 | E43: =IFERROR(E42/D42-1,0) -> 0.065382161 | F43: =IFERROR(F42/E42-1,0) -> -0.035541742 | G43: =IFERROR(G42/F42-1,0) -> 0.039399102 | H43: =IFERROR(H42/G42-1,0) -> 0.061187223 | I43: =IFERROR(I42/H42-1,0) -> 0.059624839 | J43: =IFERROR(J42/I42-1,0) -> 0.054823736 | K43: =IFERROR(K42/J42-1,0) -> 0.047438699
A44: Other categories (footwear, accessories, beauty, home & lifestyle) | C44: 10023 | D44: 13680 | E44: 15140 | F44: =F24-F42 -> 16124.793 | G44: =G24-G42 -> 17116.921 | H44: =H24-H42 -> 18549.176 | I44: =I24-I42 -> 20069.833 | J44: =J24-J42 -> 21614.887 | K44: =K24-K42 -> 23114.014
A45: YoY growth | D45: =IFERROR(D44/C44-1,0) -> 0.36486082 | E45: =IFERROR(E44/D44-1,0) -> 0.10672515 | F45: =IFERROR(F44/E44-1,0) -> 0.065045793 | G45: =IFERROR(G44/F44-1,0) -> 0.061528102 | H45: =IFERROR(H44/G44-1,0) -> 0.083674768 | I45: =IFERROR(I44/H44-1,0) -> 0.081979793 | J45: =IFERROR(J44/I44-1,0) -> 0.076983899 | K45: =IFERROR(K44/J44-1,0) -> 0.069356227
A46: % of net revenues | C46: =IFERROR(C44/C24,0) -> 0.31221381 | D46: =IFERROR(D44/D24,0) -> 0.35305048 | E46: =IFERROR(E44/E24,0) -> 0.36179415 | F46: =IFERROR(F44/F24,0) -> 0.385 | G46: =IFERROR(G44/G24,0) -> 0.39 | H46: =IFERROR(H44/H24,0) -> 0.395 | I46: =IFERROR(I44/I24,0) -> 0.4 | J46: =IFERROR(J44/J24,0) -> 0.405 | K46: =IFERROR(K44/K24,0) -> 0.41
A47: Total net revenues | C47: =C42+C44 -> 32103 | D47: =D42+D44 -> 38748 | E47: =E42+E44 -> 41847 | F47: =F42+F44 -> 41882.58 | G47: =G42+G44 -> 43889.542 | H47: =H42+H44 -> 46959.938 | I47: =I42+I44 -> 50174.583 | J47: =J42+J44 -> 53370.092 | K47: =K42+K44 -> 56375.645
A48: Integrity checks (should be zero)
A49: Geography total less business-model total | C49: =C24-C35 -> 0 | D49: =D24-D35 -> 0 | E49: =E24-E35 -> 0 | F49: =F24-F35 -> 0 | G49: =G24-G35 -> 0 | H49: =H24-H35 -> 0 | I49: =I24-I35 -> 0 | J49: =J24-J35 -> 0 | K49: =K24-K35 -> 0
A50: Geography total less category total | C50: =C24-C47 -> 0 | D50: =D24-D47 -> 0 | E50: =E24-E47 -> 0 | F50: =F24-F47 -> 0 | G50: =G24-G47 -> 0 | H50: =H24-H47 -> 0 | I50: =I24-I47 -> 0 | J50: =J24-J47 -> 0 | K50: =K24-K47 -> 0

Sheet Income Statement
A1: SHEIN Global Holdings Ltd (0625.HK) - Income Statement
A2: IFRS income statement (function of expense) with non-IFRS adjusted earnings. FY2026E = 1H26A + 2H26E.
A4: US$m unless stated | C4: FY2023A | D4: FY2024A | E4: FY2025A | F4: FY2026E | G4: FY2027E | H4: FY2028E | I4: FY2029E | J4: FY2030E | K4: FY2031E
A5: Net revenues (US$m)
A6: Net revenues | C6: ='Revenue Model'!C24 -> 32103 | D6: ='Revenue Model'!D24 -> 38748 | E6: ='Revenue Model'!E24 -> 41847 | F6: ='Revenue Model'!F24 -> 41882.58 | G6: ='Revenue Model'!G24 -> 43889.542 | H6: ='Revenue Model'!H24 -> 46959.938 | I6: ='Revenue Model'!I24 -> 50174.583 | J6: ='Revenue Model'!J24 -> 53370.092 | K6: ='Revenue Model'!K24 -> 56375.645
A7: YoY growth | D7: =IFERROR(D6/C6-1,0) -> 0.20699 | E7: =IFERROR(E6/D6-1,0) -> 0.079978321 | F7: =IFERROR(F6/E6-1,0) -> 0.00085024016 | G7: =IFERROR(G6/F6-1,0) -> 0.047918767 | H7: =IFERROR(H6/G6-1,0) -> 0.069957366 | I7: =IFERROR(I6/H6-1,0) -> 0.068455046 | J7: =IFERROR(J6/I6-1,0) -> 0.063687801 | K7: =IFERROR(K6/J6-1,0) -> 0.056315298
A8: Product revenues | C8: ='Revenue Model'!C32 -> 31235 | D8: ='Revenue Model'!D32 -> 35351 | E8: ='Revenue Model'!E32 -> 37107 | F8: ='Revenue Model'!F32 -> 36245.522 | G8: ='Revenue Model'!G32 -> 37525.558 | H8: ='Revenue Model'!H32 -> 39915.948 | I8: ='Revenue Model'!I32 -> 42397.523 | J8: ='Revenue Model'!J32 -> 44830.877 | K8: ='Revenue Model'!K32 -> 47186.414
A9: Service revenues | C9: ='Revenue Model'!C30 -> 868 | D9: ='Revenue Model'!D30 -> 3397 | E9: ='Revenue Model'!E30 -> 4740 | F9: ='Revenue Model'!F30 -> 5637.0583 | G9: ='Revenue Model'!G30 -> 6363.9835 | H9: ='Revenue Model'!H30 -> 7043.9907 | I9: ='Revenue Model'!I30 -> 7777.0604 | J9: ='Revenue Model'!J30 -> 8539.2147 | K9: ='Revenue Model'!K30 -> 9189.2301
A10: Operating expenses (US$m; shown as positive costs)
A11: Cost of sales | C11: 12777 | D11: 15249 | E11: 13433 | F11: =Interim!K26 -> 12422.257 | G11: =G8*G12 -> 12871.266 | H11: =H8*H12 -> 13651.254 | I11: =I8*I12 -> 14457.555 | J11: =J8*J12 -> 15242.498 | K11: =K8*K12 -> 16043.381
A12: % of product revenues | C12: =IFERROR(C11/C8,0) -> 0.40906035 | D12: =IFERROR(D11/D8,0) -> 0.43135979 | E12: =IFERROR(E11/E8,0) -> 0.36200717 | F12: =IFERROR(F11/F8,0) -> 0.3427253 | G12: =Scenarios!C31 -> 0.343 | H12: =Scenarios!D31 -> 0.342 | I12: =Scenarios!E31 -> 0.341 | J12: =Scenarios!F31 -> 0.34 | K12: =Scenarios!G31 -> 0.34
A13: % of net revenues | C13: =IFERROR(C11/C6,0) -> 0.39800019 | D13: =IFERROR(D11/D6,0) -> 0.39354289 | E13: =IFERROR(E11/E6,0) -> 0.3210027 | F13: =IFERROR(F11/F6,0) -> 0.29659723 | G13: =IFERROR(G11/G6,0) -> 0.293265 | H13: =IFERROR(H11/H6,0) -> 0.2907 | I13: =IFERROR(I11/I6,0) -> 0.288145 | J13: =IFERROR(J11/J6,0) -> 0.2856 | K13: =IFERROR(K11/K6,0) -> 0.28458
A14: Gross profit | C14: =C6-C11 -> 19326 | D14: =D6-D11 -> 23499 | E14: =E6-E11 -> 28414 | F14: =F6-F11 -> 29460.323 | G14: =G6-G11 -> 31018.275 | H14: =H6-H11 -> 33308.684 | I14: =I6-I11 -> 35717.028 | J14: =J6-J11 -> 38127.594 | K14: =K6-K11 -> 40332.264
A15: Gross margin | C15: =IFERROR(C14/C6,0) -> 0.60199981 | D15: =IFERROR(D14/D6,0) -> 0.60645711 | E15: =IFERROR(E14/E6,0) -> 0.6789973 | F15: =IFERROR(F14/F6,0) -> 0.70340277 | G15: =IFERROR(G14/G6,0) -> 0.706735 | H15: =IFERROR(H14/H6,0) -> 0.7093 | I15: =IFERROR(I14/I6,0) -> 0.711855 | J15: =IFERROR(J14/J6,0) -> 0.7144 | K15: =IFERROR(K14/K6,0) -> 0.71542
A16: Fulfilment expenses (logistics, warehousing, duties on direct shipments) | C16: 13501 | D16: 16847 | E16: 19072 | F16: =Interim!K30 -> 21000.776 | G16: =G6*G17 -> 22164.219 | H16: =H6*H17 -> 23573.889 | I16: =I6*I17 -> 25087.292 | J16: =J6*J17 -> 26685.046 | K16: =K6*K17 -> 28187.822
A17: % of net revenues | C17: =IFERROR(C16/C6,0) -> 0.4205526 | D17: =IFERROR(D16/D6,0) -> 0.43478373 | E17: =IFERROR(E16/E6,0) -> 0.45575549 | F17: =IFERROR(F16/F6,0) -> 0.5014203 | G17: =Scenarios!C36 -> 0.505 | H17: =Scenarios!D36 -> 0.502 | I17: =Scenarios!E36 -> 0.5 | J17: =Scenarios!F36 -> 0.5 | K17: =Scenarios!G36 -> 0.5
A18: per order (US$) | C18: =C16/'Revenue Model'!C9 -> 18.882517 | D18: =D16/'Revenue Model'!D9 -> 18.331882 | E18: =E16/'Revenue Model'!E9 -> 17.692022 | F18: =F16/'Revenue Model'!F9 -> 18.362779 | G18: =G16/'Revenue Model'!G9 -> 18.103585 | H18: =H16/'Revenue Model'!H9 -> 18.102986 | I18: =I16/'Revenue Model'!I9 -> 18.289714 | J18: =J16/'Revenue Model'!J9 -> 18.472466 | K18: =K16/'Revenue Model'!K9 -> 18.852897
A19: Contribution after fulfilment | C19: =C14-C16 -> 5825 | D19: =D14-D16 -> 6652 | E19: =E14-E16 -> 9342 | F19: =F14-F16 -> 8459.5468 | G19: =G14-G16 -> 8854.0567 | H19: =H14-H16 -> 9734.7952 | I19: =I14-I16 -> 10629.736 | J19: =J14-J16 -> 11442.548 | K19: =K14-K16 -> 12144.441
A20: Contribution margin | C20: =IFERROR(C19/C6,0) -> 0.18144722 | D20: =IFERROR(D19/D6,0) -> 0.17167338 | E20: =IFERROR(E19/E6,0) -> 0.22324181 | F20: =IFERROR(F19/F6,0) -> 0.20198247 | G20: =IFERROR(G19/G6,0) -> 0.201735 | H20: =IFERROR(H19/H6,0) -> 0.2073 | I20: =IFERROR(I19/I6,0) -> 0.211855 | J20: =IFERROR(J19/J6,0) -> 0.2144 | K20: =IFERROR(K19/K6,0) -> 0.21542
A21: Marketing expenses | C21: 3453 | D21: 4159 | E21: 6191 | F21: =Interim!K33 -> 5877.0583 | G21: =G6*G22 -> 5925.0881 | H21: =H6*H22 -> 6245.6718 | I21: =I6*I22 -> 6623.045 | J21: =J6*J22 -> 7044.8521 | K21: =K6*K22 -> 7441.5851
A22: % of net revenues | C22: =IFERROR(C21/C6,0) -> 0.10756004 | D22: =IFERROR(D21/D6,0) -> 0.10733457 | E22: =IFERROR(E21/E6,0) -> 0.1479437 | F22: =IFERROR(F21/F6,0) -> 0.14032226 | G22: =Scenarios!C41 -> 0.135 | H22: =Scenarios!D41 -> 0.133 | I22: =Scenarios!E41 -> 0.132 | J22: =Scenarios!F41 -> 0.132 | K22: =Scenarios!G41 -> 0.132
A23: Technology & content expenses | C23: 668 | D23: 849 | E23: 896 | F23: =Interim!K35 -> 999.21734 | G23: =G6*G24 -> 1053.349 | H23: =H6*H24 -> 1127.0385 | I23: =I6*I24 -> 1204.19 | J23: =J6*J24 -> 1280.8822 | K23: =K6*K24 -> 1353.0155
A24: % of net revenues | C24: =IFERROR(C23/C6,0) -> 0.020808024 | D24: =IFERROR(D23/D6,0) -> 0.021910808 | E24: =IFERROR(E23/E6,0) -> 0.021411332 | F24: =IFERROR(F23/F6,0) -> 0.023857588 | G24: =Scenarios!C46 -> 0.024 | H24: =Scenarios!D46 -> 0.024 | I24: =Scenarios!E46 -> 0.024 | J24: =Scenarios!F46 -> 0.024 | K24: =Scenarios!G46 -> 0.024
A25: General & administrative expenses | C25: 328 | D25: 678 | E25: 548 | F25: =Interim!K37 -> 548.73154 | G25: =G6*G26 -> 570.56404 | H25: =H6*H26 -> 610.4792 | I25: =I6*I26 -> 652.26958 | J25: =J6*J26 -> 693.81119 | K25: =K6*K26 -> 732.88338
A26: % of net revenues | C26: =IFERROR(C25/C6,0) -> 0.010217114 | D26: =IFERROR(D25/D6,0) -> 0.017497677 | E26: =IFERROR(E25/E6,0) -> 0.013095323 | F26: =IFERROR(F25/F6,0) -> 0.013101665 | G26: =Scenarios!C51 -> 0.013 | H26: =Scenarios!D51 -> 0.013 | I26: =Scenarios!E51 -> 0.013 | J26: =Scenarios!F51 -> 0.013 | K26: =Scenarios!G51 -> 0.013
A27: Total operating expenses | C27: =C11+C16+C21+C23+C25 -> 30727 | D27: =D11+D16+D21+D23+D25 -> 37782 | E27: =E11+E16+E21+E23+E25 -> 40140 | F27: =F11+F16+F21+F23+F25 -> 40848.04 | G27: =G11+G16+G21+G23+G25 -> 42584.486 | H27: =H11+H16+H21+H23+H25 -> 45208.333 | I27: =I11+I16+I21+I23+I25 -> 48024.351 | J27: =J11+J16+J21+J23+J25 -> 50947.09 | K27: =K11+K16+K21+K23+K25 -> 53758.687
A28: % of net revenues | C28: =IFERROR(C27/C6,0) -> 0.95713796 | D28: =IFERROR(D27/D6,0) -> 0.97506968 | E28: =IFERROR(E27/E6,0) -> 0.95920855 | F28: =IFERROR(F27/F6,0) -> 0.97529905 | G28: =IFERROR(G27/G6,0) -> 0.970265 | H28: =IFERROR(H27/H6,0) -> 0.9627 | I28: =IFERROR(I27/I6,0) -> 0.957145 | J28: =IFERROR(J27/J6,0) -> 0.9546 | K28: =IFERROR(K27/K6,0) -> 0.95358
A29: Operating income (EBIT, IFRS) | C29: =C6-C27 -> 1376 | D29: =D6-D27 -> 966 | E29: =E6-E27 -> 1707 | F29: =F6-F27 -> 1034.5396 | G29: =G6-G27 -> 1305.0555 | H29: =H6-H27 -> 1751.6057 | I29: =I6-I27 -> 2150.2318 | J29: =J6-J27 -> 2423.0022 | K29: =K6-K27 -> 2616.9574
A30: Operating margin | C30: =IFERROR(C29/C6,0) -> 0.042862038 | D30: =IFERROR(D29/D6,0) -> 0.024930319 | E30: =IFERROR(E29/E6,0) -> 0.040791455 | F30: =IFERROR(F29/F6,0) -> 0.024700953 | G30: =IFERROR(G29/G6,0) -> 0.029735 | H30: =IFERROR(H29/H6,0) -> 0.0373 | I30: =IFERROR(I29/I6,0) -> 0.042855 | J30: =IFERROR(J29/J6,0) -> 0.0454 | K30: =IFERROR(K29/K6,0) -> 0.04642
A31: YoY growth | D31: =IFERROR(D29/C29-1,0) -> -0.29796512 | E31: =IFERROR(E29/D29-1,0) -> 0.76708075 | F31: =IFERROR(F29/E29-1,0) -> -0.3939428 | G31: =IFERROR(G29/F29-1,0) -> 0.2614843 | H31: =IFERROR(H29/G29-1,0) -> 0.34216949 | I31: =IFERROR(I29/H29-1,0) -> 0.22757751 | J31: =IFERROR(J29/I29-1,0) -> 0.12685629 | K31: =IFERROR(K29/J29-1,0) -> 0.080047492
A32: Share-based compensation (included above) | C32: 49 | D32: 71 | E32: 85 | F32: =Interim!K41 -> 90 | G32: 100 | H32: 105 | I32: 110 | J32: 115 | K32: 120 | M32: Post-IPO share scheme grants
A33: Adjusted EBIT (non-IFRS) | C33: =C29+C32 -> 1425 | D33: =D29+D32 -> 1037 | E33: =E29+E32 -> 1792 | F33: =F29+F32 -> 1124.5396 | G33: =G29+G32 -> 1405.0555 | H33: =H29+H32 -> 1856.6057 | I33: =I29+I32 -> 2260.2318 | J33: =J29+J32 -> 2538.0022 | K33: =K29+K32 -> 2736.9574
A34: Adjusted EBIT margin | C34: =IFERROR(C33/C6,0) -> 0.044388375 | D34: =IFERROR(D33/D6,0) -> 0.026762672 | E34: =IFERROR(E33/E6,0) -> 0.042822664 | F34: =IFERROR(F33/F6,0) -> 0.026849818 | G34: =IFERROR(G33/G6,0) -> 0.032013447 | H34: =IFERROR(H33/H6,0) -> 0.039535948 | I34: =IFERROR(I33/I6,0) -> 0.045047345 | J34: =IFERROR(J33/J6,0) -> 0.047554765 | K34: =IFERROR(K33/K6,0) -> 0.048548579
A35: D&A of PP&E and intangibles, % of revenues | C35: =IFERROR(C36/C6,0) -> 0.0018066847 | D35: =IFERROR(D36/D6,0) -> 0.0032001652 | E35: =IFERROR(E36/E6,0) -> 0.0036083829 | F35: 0.0043 | G35: 0.0043 | H35: 0.0043 | I35: 0.0043 | J35: 0.0043 | K35: 0.0043
A36: D&A of property, equipment & intangibles | C36: 58 | D36: 124 | E36: 151 | F36: =F6*F35 -> 180.09509 | G36: =G6*G35 -> 188.72503 | H36: =H6*H35 -> 201.92773 | I36: =I6*I35 -> 215.75071 | J36: =J6*J35 -> 229.4914 | K36: =K6*K35 -> 242.41527
A37: Right-of-use depreciation, % of revenues | C37: =IFERROR(C38/C6,0) -> 0.0037068187 | D37: =IFERROR(D38/D6,0) -> 0.0051615567 | E37: =IFERROR(E38/E6,0) -> 0.0059024542 | F37: 0.0068 | G37: 0.0068 | H37: 0.0068 | I37: 0.0068 | J37: 0.0068 | K37: 0.0068
A38: Depreciation of right-of-use assets (warehouse & office leases) | C38: 119 | D38: 200 | E38: 247 | F38: =F6*F37 -> 284.80154 | G38: =G6*G37 -> 298.44888 | H38: =H6*H37 -> 319.32758 | I38: =I6*I37 -> 341.18716 | J38: =J6*J37 -> 362.91662 | K38: =K6*K37 -> 383.35438
A39: EBITDA (IFRS 16) | C39: =C29+C36+C38 -> 1553 | D39: =D29+D36+D38 -> 1290 | E39: =E29+E36+E38 -> 2105 | F39: =F29+F36+F38 -> 1499.4363 | G39: =G29+G36+G38 -> 1792.2294 | H39: =H29+H36+H38 -> 2272.861 | I39: =I29+I36+I38 -> 2707.1696 | J39: =J29+J36+J38 -> 3015.4102 | K39: =K29+K36+K38 -> 3242.7271
A40: EBITDA margin | C40: =IFERROR(C39/C6,0) -> 0.048375541 | D40: =IFERROR(D39/D6,0) -> 0.033292041 | E40: =IFERROR(E39/E6,0) -> 0.050302292 | F40: =IFERROR(F39/F6,0) -> 0.035800953 | G40: =IFERROR(G39/G6,0) -> 0.040835 | H40: =IFERROR(H39/H6,0) -> 0.0484 | I40: =IFERROR(I39/I6,0) -> 0.053955 | J40: =IFERROR(J39/J6,0) -> 0.0565 | K40: =IFERROR(K39/K6,0) -> 0.05752
A41: Adjusted EBITDA (ex SBC) | C41: =C39+C32 -> 1602 | D41: =D39+D32 -> 1361 | E41: =E39+E32 -> 2190 | F41: =F39+F32 -> 1589.4363 | G41: =G39+G32 -> 1892.2294 | H41: =H39+H32 -> 2377.861 | I41: =I39+I32 -> 2817.1696 | J41: =J39+J32 -> 3130.4102 | K41: =K39+K32 -> 3362.7271
A42: Adjusted EBITDA margin | C42: =IFERROR(C41/C6,0) -> 0.049901878 | D42: =IFERROR(D41/D6,0) -> 0.035124394 | E42: =IFERROR(E41/E6,0) -> 0.052333501 | F42: =IFERROR(F41/F6,0) -> 0.037949818 | G42: =IFERROR(G41/G6,0) -> 0.043113447 | H42: =IFERROR(H41/H6,0) -> 0.050635948 | I42: =IFERROR(I41/I6,0) -> 0.056147345 | J42: =IFERROR(J41/J6,0) -> 0.058654765 | K42: =IFERROR(K41/K6,0) -> 0.059648579
A43: Non-operating items (US$m)
A44: FV changes of convertible redeemable preferred shares | C44: 1231 | D44: 2431 | E44: 328 | F44: =Interim!K44 -> 5884.3083 | G44: 0 | H44: 0 | I44: 0 | J44: 0 | K44: 0 | M44: Preferred shares converted to Class B at listing (1-Sep-2026)
A45: Share of income/(losses) from associates | C45: -36 | D45: -171 | E45: 3 | F45: =Interim!K45 -> -15 | G45: 0 | H45: 0 | I45: 0 | J45: 0 | K45: 0 | M45: Mainly SPARC Group (Forever 21 / brands JV)
A46: Interest yield on opening cash resources | D46: =IFERROR(D47/AVERAGE('Balance Sheet'!C56,'Balance Sheet'!D56),0) -> 0.054285065 | E46: =IFERROR(E47/AVERAGE('Balance Sheet'!D56,'Balance Sheet'!E56),0) -> 0.046855548 | F46: =IFERROR(F47/AVERAGE('Balance Sheet'!E56,'Balance Sheet'!F56),0) -> 0.040752395 | G46: 0.036 | H46: 0.034 | I46: 0.033 | J46: 0.033 | K46: 0.033 | M46: Hist./FY26E: on average balance
A47: Interest income | C47: 472 | D47: 597 | E47: 621 | F47: =Interim!K47 -> 584.83526 | G47: =G46*'Balance Sheet'!F56 -> 500.97181 | H47: =H46*'Balance Sheet'!G56 -> 506.90388 | I47: =I46*'Balance Sheet'!H56 -> 534.31559 | J47: =J46*'Balance Sheet'!I56 -> 582.11557 | K47: =K46*'Balance Sheet'!J56 -> 632.58353
A48: Exchange gain/(loss) | C48: -34 | D48: -55 | E48: -95 | F48: =Interim!K48 -> -151 | G48: 0 | H48: 0 | I48: 0 | J48: 0 | K48: 0
A49: Others, net as % of revenues | G49: -0.0015 | H49: -0.0015 | I49: -0.0015 | J49: -0.0015 | K49: -0.0015
A50: Others, net (lease interest, FV of investments, credit losses) | C50: -14 | D50: 1 | E50: -50 | F50: =Interim!K49 -> -70 | G50: =G6*G49 -> -65.834312 | H50: =H6*H49 -> -70.439907 | I50: =I6*I49 -> -75.261875 | J50: =J6*J49 -> -80.055138 | K50: =K6*K49 -> -84.563467
A51: Income before income taxes | C51: =C29+C44+C45+C47+C48+C50 -> 2995 | D51: =D29+D44+D45+D47+D48+D50 -> 3769 | E51: =E29+E44+E45+E47+E48+E50 -> 2514 | F51: =F29+F44+F45+F47+F48+F50 -> 7267.6832 | G51: =G29+G44+G45+G47+G48+G50 -> 1740.193 | H51: =H29+H44+H45+H47+H48+H50 -> 2188.0697 | I51: =I29+I44+I45+I47+I48+I50 -> 2609.2855 | J51: =J29+J44+J45+J47+J48+J50 -> 2925.0626 | K51: =K29+K44+K45+K47+K48+K50 -> 3164.9775
A52: Income tax expense | C52: 206 | D52: 404 | E52: 450 | F52: =Interim!K51 -> 339.09623 | G52: =G53*(G51-G44-G45) -> 382.84246 | H52: =H53*(H51-H44-H45) -> 481.37533 | I52: =I53*(I51-I44-I45) -> 574.0428 | J52: =J53*(J51-J44-J45) -> 643.51377 | K52: =K53*(K51-K44-K45) -> 696.29505
A53: Effective tax rate (ex FV changes & associates) | C53: =IFERROR(C52/(C51-C44-C45),0) -> 0.11444444 | D53: =IFERROR(D52/(D51-D44-D45),0) -> 0.26772697 | E53: =IFERROR(E52/(E51-E44-E45),0) -> 0.20613834 | F53: =IFERROR(F52/(F51-F44-F45),0) -> 0.24249307 | G53: 0.22 | H53: 0.22 | I53: 0.22 | J53: 0.22 | K53: 0.22
A54: Net income (IFRS) | C54: =C51-C52 -> 2789 | D54: =D51-D52 -> 3365 | E54: =E51-E52 -> 2064 | F54: =F51-F52 -> 6928.587 | G54: =G51-G52 -> 1357.3506 | H54: =H51-H52 -> 1706.6943 | I54: =I51-I52 -> 2035.2427 | J54: =J51-J52 -> 2281.5488 | K54: =K51-K52 -> 2468.6824
A55: Net margin | C55: =IFERROR(C54/C6,0) -> 0.086876616 | D55: =IFERROR(D54/D6,0) -> 0.086843192 | E55: =IFERROR(E54/E6,0) -> 0.049322532 | F55: =IFERROR(F54/F6,0) -> 0.16542885 | G55: =IFERROR(G54/G6,0) -> 0.030926515 | H55: =IFERROR(H54/H6,0) -> 0.036343624 | I55: =IFERROR(I54/I6,0) -> 0.04056322 | J55: =IFERROR(J54/J6,0) -> 0.042749577 | K55: =IFERROR(K54/K6,0) -> 0.043789875
A56: Non-IFRS adjusted earnings (company definition)
A57: Impairment / FV changes on long-term investments | C57: 0 | D57: -57 | E57: -2 | F57: =Interim!K54 -> 1 | G57: 0 | H57: 0 | I57: 0 | J57: 0 | K57: 0 | M57: FY24: US$55m impairment less US$112m FV gain
A58: Adjusted net income | C58: =C54+C32-C44-C45+C57 -> 1643 | D58: =D54+D32-D44-D45+D57 -> 1119 | E58: =E54+E32-E44-E45+E57 -> 1816 | F58: =F54+F32-F44-F45+F57 -> 1150.2787 | G58: =G54+G32-G44-G45+G57 -> 1457.3506 | H58: =H54+H32-H44-H45+H57 -> 1811.6943 | I58: =I54+I32-I44-I45+I57 -> 2145.2427 | J58: =J54+J32-J44-J45+J57 -> 2396.5488 | K58: =K54+K32-K44-K45+K57 -> 2588.6824 | M58: NI + SBC - FV of prefs - associates +/- LT investment items
A59: Adjusted net margin | C59: =IFERROR(C58/C6,0) -> 0.051179018 | D59: =IFERROR(D58/D6,0) -> 0.02887891 | E59: =IFERROR(E58/E6,0) -> 0.043396181 | F59: =IFERROR(F58/F6,0) -> 0.02746437 | G59: =IFERROR(G58/G6,0) -> 0.033204962 | H59: =IFERROR(H58/H6,0) -> 0.038579572 | I59: =IFERROR(I58/I6,0) -> 0.042755565 | J59: =IFERROR(J58/J6,0) -> 0.044904341 | K59: =IFERROR(K58/K6,0) -> 0.045918454
A60: YoY growth | D60: =IFERROR(D58/C58-1,0) -> -0.31892879 | E60: =IFERROR(E58/D58-1,0) -> 0.62287757 | F60: =IFERROR(F58/E58-1,0) -> -0.36658663 | G60: =IFERROR(G58/F58-1,0) -> 0.26695434 | H60: =IFERROR(H58/G58-1,0) -> 0.24314245 | I60: =IFERROR(I58/H58-1,0) -> 0.1841085 | J60: =IFERROR(J58/I58-1,0) -> 0.1171458 | K60: =IFERROR(K58/J58-1,0) -> 0.080170954
A61: Per-share data (pro forma post-IPO share base, all years)
A62: Basic shares (m) | C62: =Inputs!$C$14 -> 4246.2026 | D62: =Inputs!$C$14 -> 4246.2026 | E62: =Inputs!$C$14 -> 4246.2026 | F62: =Inputs!$C$14 -> 4246.2026 | G62: =F62*(1+Inputs!$C$18) -> 4267.4336 | H62: =G62*(1+Inputs!$C$18) -> 4288.7708 | I62: =H62*(1+Inputs!$C$18) -> 4310.2146 | J62: =I62*(1+Inputs!$C$18) -> 4331.7657 | K62: =J62*(1+Inputs!$C$18) -> 4353.4245
A63: Diluted shares (m) | C63: =Inputs!$C$17 -> 4419.2349 | D63: =Inputs!$C$17 -> 4419.2349 | E63: =Inputs!$C$17 -> 4419.2349 | F63: =Inputs!$C$17 -> 4419.2349 | G63: =F63*(1+Inputs!$C$18) -> 4441.3311 | H63: =G63*(1+Inputs!$C$18) -> 4463.5377 | I63: =H63*(1+Inputs!$C$18) -> 4485.8554 | J63: =I63*(1+Inputs!$C$18) -> 4508.2847 | K63: =J63*(1+Inputs!$C$18) -> 4530.8261
A64: Diluted EPS, IFRS (US$) | C64: =C54/C63 -> 0.63110472 | D64: =D54/D63 -> 0.76144402 | E64: =E54/E63 -> 0.46704917 | F64: =F54/F63 -> 1.567825 | G64: =G54/G63 -> 0.30561796 | H64: =H54/H63 -> 0.3823636 | I64: =I54/I63 -> 0.45370224 | J64: =J54/J63 -> 0.50607914 | K64: =K54/K63 -> 0.54486364 | M64: FY26E includes ~US$5.9bn non-cash FV gains on preferred shares (1H26A + 2H26E)
A65: Adjusted diluted EPS (US$) | C65: =C58/C63 -> 0.37178381 | D65: =D58/D63 -> 0.25321125 | E65: =E58/E63 -> 0.41093086 | F65: =F58/F63 -> 0.2602891 | G65: =G58/G63 -> 0.32813373 | H65: =H58/H63 -> 0.40588754 | I65: =I58/I63 -> 0.47822376 | J65: =J58/J63 -> 0.53158773 | K65: =K58/K63 -> 0.57134888
A66: Adjusted diluted EPS (HK$) | C66: =C65*Inputs!$C$6 -> 2.916644 | D66: =D65*Inputs!$C$6 -> 1.9864423 | E66: =E65*Inputs!$C$6 -> 3.2237526 | F66: =F65*Inputs!$C$6 -> 2.041968 | G66: =G65*Inputs!$C$6 -> 2.5742091 | H66: =H65*Inputs!$C$6 -> 3.1841877 | I66: =I65*Inputs!$C$6 -> 3.7516654 | J66: =J65*Inputs!$C$6 -> 4.1703057 | K66: =K65*Inputs!$C$6 -> 4.482232
A67: YoY growth | D67: =IFERROR(D65/C65-1,0) -> -0.31892879 | E67: =IFERROR(E65/D65-1,0) -> 0.62287757 | F67: =IFERROR(F65/E65-1,0) -> -0.36658663 | G67: =IFERROR(G65/F65-1,0) -> 0.26065109 | H67: =IFERROR(H65/G65-1,0) -> 0.23695766 | I67: =IFERROR(I65/H65-1,0) -> 0.17821741 | J67: =IFERROR(J65/I65-1,0) -> 0.11158786 | K67: =IFERROR(K65/J65-1,0) -> 0.074796969
A68: Dividend payout ratio (of adj. net income) | C68: 0 | D68: 0 | E68: 0 | F68: =Inputs!$C$60 -> 0.5 | G68: =Inputs!$C$60 -> 0.5 | H68: =Inputs!$C$60 -> 0.5 | I68: =Inputs!$C$60 -> 0.5 | J68: =Inputs!$C$60 -> 0.5 | K68: =Inputs!$C$60 -> 0.5
A69: Dividend declared in respect of year (US$m) | C69: =C58*C68 -> 0 | D69: =D58*D68 -> 0 | E69: =E58*E68 -> 0 | F69: =F58*F68 -> 575.13934 | G69: =G58*G68 -> 728.67528 | H69: =H58*H68 -> 905.84717 | I69: =I58*I68 -> 1072.6213 | J69: =J58*J68 -> 1198.2744 | K69: =K58*K68 -> 1294.3412 | M69: First dividend expected with FY26 results; paid in FY27
A70: DPS declared (HK$) | C70: =C69/C63*Inputs!$C$6 -> 0 | D70: =D69/D63*Inputs!$C$6 -> 0 | E70: =E69/E63*Inputs!$C$6 -> 0 | F70: =F69/F63*Inputs!$C$6 -> 1.020984 | G70: =G69/G63*Inputs!$C$6 -> 1.2871046 | H70: =H69/H63*Inputs!$C$6 -> 1.5920939 | I70: =I69/I63*Inputs!$C$6 -> 1.8758327 | J70: =J69/J63*Inputs!$C$6 -> 2.0851529 | K70: =K69/K63*Inputs!$C$6 -> 2.241116
A71: Valuation at current share price
A72: P/E on adjusted EPS (x) | C72: =IFERROR(Inputs!$C$5/C66,0) -> 10.573796 | D72: =IFERROR(Inputs!$C$5/D66,0) -> 15.525244 | E72: =IFERROR(Inputs!$C$5/E66,0) -> 9.5664909 | F72: =IFERROR(Inputs!$C$5/F66,0) -> 15.103077 | G72: =IFERROR(Inputs!$C$5/G66,0) -> 11.980379 | H72: =IFERROR(Inputs!$C$5/H66,0) -> 9.6853586 | I72: =IFERROR(Inputs!$C$5/I66,0) -> 8.2203492 | J72: =IFERROR(Inputs!$C$5/J66,0) -> 7.3951413 | K72: =IFERROR(Inputs!$C$5/K66,0) -> 6.8805007
A73: Dividend yield | C73: =IFERROR(C70/Inputs!$C$5,0) -> 0 | D73: =IFERROR(D70/Inputs!$C$5,0) -> 0 | E73: =IFERROR(E70/Inputs!$C$5,0) -> 0 | F73: =IFERROR(F70/Inputs!$C$5,0) -> 0.033105836 | G73: =IFERROR(G70/Inputs!$C$5,0) -> 0.041734908 | H73: =IFERROR(H70/Inputs!$C$5,0) -> 0.051624315 | I73: =IFERROR(I70/Inputs!$C$5,0) -> 0.060824666 | J73: =IFERROR(J70/Inputs!$C$5,0) -> 0.067611961 | K73: =IFERROR(K70/Inputs!$C$5,0) -> 0.07266913

Sheet Balance Sheet
A1: SHEIN Global Holdings Ltd (0625.HK) - Balance Sheet
A2: Consolidated balance sheet; FY2026E reflects preferred-share conversion, IPO proceeds and listing payments.
A4: US$m unless stated | C4: FY2023A | D4: FY2024A | E4: FY2025A | F4: FY2026E | G4: FY2027E | H4: FY2028E | I4: FY2029E | J4: FY2030E | K4: FY2031E
A5: Assets (US$m)
A6: Cash and cash equivalents | C6: 3494 | D6: 2905 | E6: 4481 | F6: ='Cash Flow'!F45 -> 1710.8837 | G6: ='Cash Flow'!G45 -> 2703.9375 | H6: ='Cash Flow'!H45 -> 3986.3814 | I6: ='Cash Flow'!I45 -> 5434.8656 | J6: ='Cash Flow'!J45 -> 6964.1978 | K6: ='Cash Flow'!K45 -> 8527.8587
A7: Restricted cash | C7: 437 | D7: 485 | E7: 550 | F7: =Interim!I64 -> 622 | G7: =F7 -> 622 | H7: =G7 -> 622 | I7: =H7 -> 622 | J7: =I7 -> 622 | K7: =J7 -> 622
A8: Short-term investments (time deposits) | C8: 6265 | D8: 8086 | E8: 9723 | F8: =Interim!I66 -> 11545 | G8: =F8 -> 11545 | H8: =G8 -> 11545 | I8: =H8 -> 11545 | J8: =I8 -> 11545 | K8: =J8 -> 11545
A9: Receivables from payment platforms & service providers | C9: 823 | D9: 1303 | E9: 718 | F9: =F62/365*'Income Statement'!F6 -> 803.22756 | G9: =G62/365*'Income Statement'!G6 -> 841.71724 | H9: =H62/365*'Income Statement'!H6 -> 900.60156 | I9: =I62/365*'Income Statement'!I6 -> 962.25228 | J9: =J62/365*'Income Statement'!J6 -> 1023.536 | K9: =K62/365*'Income Statement'!K6 -> 1081.1767
A10: Other receivables and prepayments | C10: 273 | D10: 480 | E10: 534 | F10: =F63*'Income Statement'!F6 -> 544.47354 | G10: =G63*'Income Statement'!G6 -> 570.56404 | H10: =H63*'Income Statement'!H6 -> 610.4792 | I10: =I63*'Income Statement'!I6 -> 652.26958 | J10: =J63*'Income Statement'!J6 -> 693.81119 | K10: =K63*'Income Statement'!K6 -> 732.88338
A11: Inventories | C11: 1637 | D11: 1500 | E11: 1261 | F11: =F64/365*'Income Statement'!F11 -> 1191.1754 | G11: =G64/365*'Income Statement'!G11 -> 1234.231 | H11: =H64/365*'Income Statement'!H11 -> 1309.0244 | I11: =I64/365*'Income Statement'!I11 -> 1386.3409 | J11: =J64/365*'Income Statement'!J11 -> 1461.6094 | K11: =K64/365*'Income Statement'!K11 -> 1538.4064
A12: Other current assets | C12: 88 | D12: 127 | E12: 326 | F12: =F65*'Income Statement'!F6 -> 335.06064 | G12: =G65*'Income Statement'!G6 -> 351.11633 | H12: =H65*'Income Statement'!H6 -> 375.67951 | I12: =I65*'Income Statement'!I6 -> 401.39666 | J12: =J65*'Income Statement'!J6 -> 426.96074 | K12: =K65*'Income Statement'!K6 -> 451.00516
A13: Total current assets | C13: =SUM(C6:C12) -> 13017 | D13: =SUM(D6:D12) -> 14886 | E13: =SUM(E6:E12) -> 17593 | F13: =SUM(F6:F12) -> 16751.821 | G13: =SUM(G6:G12) -> 17868.566 | H13: =SUM(H6:H12) -> 19349.166 | I13: =SUM(I6:I12) -> 21004.125 | J13: =SUM(J6:J12) -> 22737.115 | K13: =SUM(K6:K12) -> 24498.33
A14: Property and equipment | C14: 396 | D14: 551 | E14: 619 | F14: =E14-'Cash Flow'!F27-'Income Statement'!F36 -> 732.08297 | G14: =F14-'Cash Flow'!G27-'Income Statement'!G36 -> 872.5295 | H14: =G14-'Cash Flow'!H27-'Income Statement'!H36 -> 1022.8013 | I14: =H14-'Cash Flow'!I27-'Income Statement'!I36 -> 1183.36 | J14: =I14-'Cash Flow'!J27-'Income Statement'!J36 -> 1354.1443 | K14: =J14-'Cash Flow'!K27-'Income Statement'!K36 -> 1534.5463
A15: Right-of-use assets | C15: 497 | D15: 959 | E15: 1105 | F15: =F70*'Income Statement'!F6 -> 1130.8297 | G15: =G70*'Income Statement'!G6 -> 1185.0176 | H15: =H70*'Income Statement'!H6 -> 1267.9183 | I15: =I70*'Income Statement'!I6 -> 1354.7137 | J15: =J70*'Income Statement'!J6 -> 1440.9925 | K15: =K70*'Income Statement'!K6 -> 1522.1424
A16: Intangible assets & goodwill | C16: 40 | D16: 39 | E16: 38 | F16: =Interim!I71 -> 135 | G16: =F16 -> 135 | H16: =G16 -> 135 | I16: =H16 -> 135 | J16: =I16 -> 135 | K16: =J16 -> 135
A17: Non-current restricted cash | C17: 78 | D17: 34 | E17: 32 | F17: =Interim!I65 -> 38 | G17: =F17 -> 38 | H17: =G17 -> 38 | I17: =H17 -> 38 | J17: =I17 -> 38 | K17: =J17 -> 38
A18: Deferred tax assets | C18: 81 | D18: 94 | E18: 102 | F18: =Interim!I72 -> 125 | G18: =F18 -> 125 | H18: =G18 -> 125 | I18: =H18 -> 125 | J18: =I18 -> 125 | K18: =J18 -> 125
A19: Investments in associates | C19: 470 | D19: 251 | E19: 266 | F19: =E19+'Income Statement'!F45 -> 251 | G19: =F19+'Income Statement'!G45 -> 251 | H19: =G19+'Income Statement'!H45 -> 251 | I19: =H19+'Income Statement'!I45 -> 251 | J19: =I19+'Income Statement'!J45 -> 251 | K19: =J19+'Income Statement'!K45 -> 251
A20: Investments at fair value through profit or loss | C20: 82 | D20: 169 | E20: 158 | F20: =Interim!I74 -> 162 | G20: =F20 -> 162 | H20: =G20 -> 162 | I20: =H20 -> 162 | J20: =I20 -> 162 | K20: =J20 -> 162
A21: Long-term time deposits | C21: 0 | D21: 211 | E21: 0 | F21: =E21 -> 0 | G21: =F21 -> 0 | H21: =G21 -> 0 | I21: =H21 -> 0 | J21: =I21 -> 0 | K21: =J21 -> 0
A22: Other non-current assets | C22: 157 | D22: 127 | E22: 120 | F22: =Interim!I75 -> 109 | G22: =F22 -> 109 | H22: =G22 -> 109 | I22: =H22 -> 109 | J22: =I22 -> 109 | K22: =J22 -> 109
A23: Total non-current assets | C23: =SUM(C14:C22) -> 1801 | D23: =SUM(D14:D22) -> 2435 | E23: =SUM(E14:E22) -> 2440 | F23: =SUM(F14:F22) -> 2682.9126 | G23: =SUM(G14:G22) -> 2877.5471 | H23: =SUM(H14:H22) -> 3110.7196 | I23: =SUM(I14:I22) -> 3358.0737 | J23: =SUM(J14:J22) -> 3615.1367 | K23: =SUM(K14:K22) -> 3876.6887
A24: Total assets | C24: =C13+C23 -> 14818 | D24: =D13+D23 -> 17321 | E24: =E13+E23 -> 20033 | F24: =F13+F23 -> 19434.733 | G24: =G13+G23 -> 20746.113 | H24: =H13+H23 -> 22459.886 | I24: =I13+I23 -> 24362.199 | J24: =J13+J23 -> 26352.252 | K24: =K13+K23 -> 28375.019
A25: Liabilities (US$m)
A26: Accounts payable | C26: 2749 | D26: 2935 | E26: 3019 | F26: =F66/365*('Income Statement'!F11+'Income Statement'!F16) -> 3113.3784 | G26: =G66/365*('Income Statement'!G11+'Income Statement'!G16) -> 3263.5794 | H26: =H66/365*('Income Statement'!H11+'Income Statement'!H16) -> 3467.5476 | I26: =I66/365*('Income Statement'!I11+'Income Statement'!I16) -> 3683.6296 | J26: =J66/365*('Income Statement'!J11+'Income Statement'!J16) -> 3905.5795 | K26: =K66/365*('Income Statement'!K11+'Income Statement'!K16) -> 4120.1669
A27: Accrued expenses & other current liabilities (ex lease) | C27: 1836 | D27: 2623 | E27: 3035 | F27: =F67*'Income Statement'!F6 -> 3057.4283 | G27: =G67*'Income Statement'!G6 -> 3203.9365 | H27: =H67*'Income Statement'!H6 -> 3428.0755 | I27: =I67*'Income Statement'!I6 -> 3662.7446 | J27: =J67*'Income Statement'!J6 -> 3896.0167 | K27: =K67*'Income Statement'!K6 -> 4115.422 | M27: Reported line less current lease liabilities
A28: Lease liabilities - current | C28: 122 | D28: 191 | E28: 233 | F28: =F55*F71 -> 236.63423 | G28: =G55*G71 -> 248.0137 | H28: =H55*H71 -> 265.42285 | I28: =I55*I71 -> 283.64989 | J28: =J55*J71 -> 301.76842 | K28: =K55*K71 -> 318.8099
A29: Contract liabilities (customer prepayments) | C29: 694 | D29: 770 | E29: 789 | F29: =F68*'Income Statement'!F6 -> 795.76902 | G29: =G68*'Income Statement'!G6 -> 833.90129 | H29: =H68*'Income Statement'!H6 -> 892.23883 | I29: =I68*'Income Statement'!I6 -> 953.31708 | J29: =J68*'Income Statement'!J6 -> 1014.0317 | K29: =K68*'Income Statement'!K6 -> 1071.1372
A30: Income tax payable | C30: 707 | D30: 771 | E30: 933 | F30: =F69*'Income Statement'!F6 -> 837.6516 | G30: =G69*'Income Statement'!G6 -> 877.79083 | H30: =H69*'Income Statement'!H6 -> 939.19877 | I30: =I69*'Income Statement'!I6 -> 1003.4917 | J30: =J69*'Income Statement'!J6 -> 1067.4018 | K30: =K69*'Income Statement'!K6 -> 1127.5129
A31: Convertible redeemable preferred shares - current | C31: 0 | D31: 0 | E31: 18048 | F31: 0 | G31: 0 | H31: 0 | I31: 0 | J31: 0 | K31: 0
A32: Total current liabilities | C32: =SUM(C26:C31) -> 6108 | D32: =SUM(D26:D31) -> 7290 | E32: =SUM(E26:E31) -> 26057 | F32: =SUM(F26:F31) -> 8040.8616 | G32: =SUM(G26:G31) -> 8427.2218 | H32: =SUM(H26:H31) -> 8992.4835 | I32: =SUM(I26:I31) -> 9586.8327 | J32: =SUM(J26:J31) -> 10184.798 | K32: =SUM(K26:K31) -> 10753.049
A33: Convertible redeemable preferred shares - non-current | C33: 20807 | D33: 18376 | E33: 0 | F33: 0 | G33: 0 | H33: 0 | I33: 0 | J33: 0 | K33: 0
A34: Deferred tax liabilities | C34: 1 | D34: 7 | E34: 5 | F34: =Interim!I84 -> 15 | G34: =F34 -> 15 | H34: =G34 -> 15 | I34: =H34 -> 15 | J34: =I34 -> 15 | K34: =J34 -> 15
A35: Lease liabilities - non-current | C35: 407 | D35: 744 | E35: 868 | F35: =F55-F28 -> 890.19543 | G35: =G55-G28 -> 933.00392 | H35: =H55-H28 -> 998.49548 | I35: =I55-I28 -> 1067.0639 | J35: =J55-J28 -> 1135.2241 | K35: =K55-K28 -> 1199.3325
A36: Other long-term liabilities | C36: 6 | D36: 1 | E36: 0 | F36: =Interim!I85 -> 31 | G36: =F36 -> 31 | H36: =G36 -> 31 | I36: =H36 -> 31 | J36: =I36 -> 31 | K36: =J36 -> 31
A37: Total non-current liabilities | C37: =SUM(C33:C36) -> 21221 | D37: =SUM(D33:D36) -> 19128 | E37: =SUM(E33:E36) -> 873 | F37: =SUM(F33:F36) -> 936.19543 | G37: =SUM(G33:G36) -> 979.00392 | H37: =SUM(H33:H36) -> 1044.4955 | I37: =SUM(I33:I36) -> 1113.0639 | J37: =SUM(J33:J36) -> 1181.2241 | K37: =SUM(K33:K36) -> 1245.3325
A38: Total liabilities | C38: =C32+C37 -> 27329 | D38: =D32+D37 -> 26418 | E38: =E32+E37 -> 26930 | F38: =F32+F37 -> 8977.0571 | G38: =G32+G37 -> 9406.2257 | H38: =H32+H37 -> 10036.979 | I38: =I32+I37 -> 10699.897 | J38: =J32+J37 -> 11366.022 | K38: =K32+K37 -> 11998.381
A39: Shareholders' equity (US$m)
A40: Total shareholders' equity / (deficit) | C40: -12511 | D40: -9097 | E40: -6897 | F40: =F53 -> 10457.676 | G40: =G53 -> 11339.888 | H40: =H53 -> 12422.907 | I40: =I53 -> 13662.302 | J40: =J53 -> 14986.23 | K40: =K53 -> 16376.638
A41: Total liabilities & shareholders' equity | C41: =C38+C40 -> 14818 | D41: =D38+D40 -> 17321 | E41: =E38+E40 -> 20033 | F41: =F38+F40 -> 19434.733 | G41: =G38+G40 -> 20746.113 | H41: =H38+H40 -> 22459.886 | I41: =I38+I40 -> 24362.199 | J41: =J38+J40 -> 26352.252 | K41: =K38+K40 -> 28375.019
A42: Balance check (assets less liabilities & equity) | C42: =ROUND(C24-C41,3) -> 0 | D42: =ROUND(D24-D41,3) -> 0 | E42: =ROUND(E24-E41,3) -> 0 | F42: =ROUND(F24-F41,3) -> 0 | G42: =ROUND(G24-G41,3) -> 0 | H42: =ROUND(H24-H41,3) -> 0 | I42: =ROUND(I24-I41,3) -> 0 | J42: =ROUND(J24-J41,3) -> 0 | K42: =ROUND(K24-K41,3) -> 0
A43: Equity roll-forward (US$m)
A44: Opening equity | F44: =E40 -> -6897 | G44: =F40 -> 10457.676 | H44: =G40 -> 11339.888 | I44: =H40 -> 12422.907 | J44: =I40 -> 13662.302 | K44: =J40 -> 14986.23
A45: Net income | F45: ='Income Statement'!F54 -> 6928.587 | G45: ='Income Statement'!G54 -> 1357.3506 | H45: ='Income Statement'!H54 -> 1706.6943 | I45: ='Income Statement'!I54 -> 2035.2427 | J45: ='Income Statement'!J54 -> 2281.5488 | K45: ='Income Statement'!K54 -> 2468.6824
A46: Share-based compensation | F46: ='Income Statement'!F32 -> 90 | G46: ='Income Statement'!G32 -> 100 | H46: ='Income Statement'!H32 -> 105 | I46: ='Income Statement'!I32 -> 110 | J46: ='Income Statement'!J32 -> 115 | K46: ='Income Statement'!K32 -> 120
A47: Conversion of preferred shares into Class B shares | F47: =E31+E33-Inputs!$C$27-'Income Statement'!F44 -> 11081.692 | G47: 0 | H47: 0 | I47: 0 | J47: 0 | K47: 0 | M47: FY25 carrying value less 8% distributions less FY26E FV gains = fair value at conversion
A48: Conversion Adjustment cash compensation | F48: =-Inputs!$C$26 -> -2200 | G48: 0 | H48: 0 | I48: 0 | J48: 0 | K48: 0
A49: 12% distribution to preferred holders | F49: =-Inputs!$C$29 -> -230 | G49: 0 | H49: 0 | I49: 0 | J49: 0 | K49: 0
A50: IPO net proceeds | F50: =Inputs!$C$25 -> 1684.3977 | G50: 0 | H50: 0 | I50: 0 | J50: 0 | K50: 0
A51: Dividends paid | F51: ='Cash Flow'!F39 -> 0 | G51: ='Cash Flow'!G39 -> -575.13934 | H51: ='Cash Flow'!H39 -> -728.67528 | I51: ='Cash Flow'!I39 -> -905.84717 | J51: ='Cash Flow'!J39 -> -1072.6213 | K51: ='Cash Flow'!K39 -> -1198.2744
A52: Other comprehensive income / other | F52: 0 | G52: 0 | H52: 0 | I52: 0 | J52: 0 | K52: 0
A53: Closing equity | F53: =SUM(F44:F52) -> 10457.676 | G53: =SUM(G44:G52) -> 11339.888 | H53: =SUM(H44:H52) -> 12422.907 | I53: =SUM(I44:I52) -> 13662.302 | J53: =SUM(J44:J52) -> 14986.23 | K53: =SUM(K44:K52) -> 16376.638
A54: Memo items (US$m)
A55: Total lease liabilities | C55: 529 | D55: 935 | E55: 1101 | F55: =E55+F15-E15 -> 1126.8297 | G55: =F55+G15-F15 -> 1181.0176 | H55: =G55+H15-G15 -> 1263.9183 | I55: =H55+I15-H15 -> 1350.7137 | J55: =I55+J15-I15 -> 1436.9925 | K55: =J55+K15-J15 -> 1518.1424
A56: Cash resources (cash + restricted + ST & LT deposits) | C56: =C6+C7+C17+C8+C21 -> 10274 | D56: =D6+D7+D17+D8+D21 -> 11721 | E56: =E6+E7+E17+E8+E21 -> 14786 | F56: =F6+F7+F17+F8+F21 -> 13915.884 | G56: =G6+G7+G17+G8+G21 -> 14908.938 | H56: =H6+H7+H17+H8+H21 -> 16191.381 | I56: =I6+I7+I17+I8+I21 -> 17639.866 | J56: =J6+J7+J17+J8+J21 -> 19169.198 | K56: =K6+K7+K17+K8+K21 -> 20732.859
A57: Net cash after lease liabilities | C57: =C56-C55 -> 9745 | D57: =D56-D55 -> 10786 | E57: =E56-E55 -> 13685 | F57: =F56-F55 -> 12789.054 | G57: =G56-G55 -> 13727.92 | H57: =H56-H55 -> 14927.463 | I57: =I56-I55 -> 16289.152 | J57: =J56-J55 -> 17732.205 | K57: =K56-K55 -> 19214.716
A58: Operating net working capital | C58: =C9+C10+C11+C12-C26-C27-C29 -> -2458 | D58: =D9+D10+D11+D12-D26-D27-D29 -> -2918 | E58: =E9+E10+E11+E12-E26-E27-E29 -> -4004 | F58: =F9+F10+F11+F12-F26-F27-F29 -> -4092.6387 | G58: =G9+G10+G11+G12-G26-G27-G29 -> -4303.7886 | H58: =H9+H10+H11+H12-H26-H27-H29 -> -4592.0773 | I58: =I9+I10+I11+I12-I26-I27-I29 -> -4897.4318 | J58: =J9+J10+J11+J12-J26-J27-J29 -> -5209.7106 | K58: =K9+K10+K11+K12-K26-K27-K29 -> -5503.2545 | M58: Negative = customers and suppliers fund the business
A59: % of net revenues | C59: =C58/'Income Statement'!C6 -> -0.076566053 | D59: =D58/'Income Statement'!D6 -> -0.075307113 | E59: =E58/'Income Statement'!E6 -> -0.095681889 | F59: =F58/'Income Statement'!F6 -> -0.097716967 | G59: =G58/'Income Statement'!G6 -> -0.098059548 | H59: =H58/'Income Statement'!H6 -> -0.097787123 | I59: =I58/'Income Statement'!I6 -> -0.097607822 | J59: =J58/'Income Statement'!J6 -> -0.097614795 | K59: =K58/'Income Statement'!K6 -> -0.097617589
A60: Return on average equity (adj. NI) | D60: =IF(AND(D40>0,C40>0),'Income Statement'!D58/AVERAGE(D40,C40),"n.m.") -> n.m. | E60: =IF(AND(E40>0,D40>0),'Income Statement'!E58/AVERAGE(E40,D40),"n.m.") -> n.m. | F60: =IF(AND(F40>0,E40>0),'Income Statement'!F58/AVERAGE(F40,E40),"n.m.") -> n.m. | G60: =IF(AND(G40>0,F40>0),'Income Statement'!G58/AVERAGE(G40,F40),"n.m.") -> 0.13371683 | H60: =IF(AND(H40>0,G40>0),'Income Statement'!H58/AVERAGE(H40,G40),"n.m.") -> 0.15248159 | I60: =IF(AND(I40>0,H40>0),'Income Statement'!I58/AVERAGE(I40,H40),"n.m.") -> 0.16447962 | J60: =IF(AND(J40>0,I40>0),'Income Statement'!J58/AVERAGE(J40,I40),"n.m.") -> 0.16730692 | K60: =IF(AND(K40>0,J40>0),'Income Statement'!K58/AVERAGE(K40,J40),"n.m.") -> 0.16507945
A61: Balance sheet drivers
A62: Receivables days (on net revenues) | C62: =C9/'Income Statement'!C6*365 -> 9.3572252 | D62: =D9/'Income Statement'!D6*365 -> 12.274053 | E62: =E9/'Income Statement'!E6*365 -> 6.2625756 | F62: 7 | G62: 7 | H62: 7 | I62: 7 | J62: 7 | K62: 7
A63: Other receivables & prepayments % revenues | C63: =C10/'Income Statement'!C6 -> 0.0085038781 | D63: =D10/'Income Statement'!D6 -> 0.012387736 | E63: =E10/'Income Statement'!E6 -> 0.012760771 | F63: 0.013 | G63: 0.013 | H63: 0.013 | I63: 0.013 | J63: 0.013 | K63: 0.013
A64: Inventory days (on cost of sales, year-end) | C64: =C11/'Income Statement'!C11*365 -> 46.764107 | D64: =D11/'Income Statement'!D11*365 -> 35.903994 | E64: =E11/'Income Statement'!E11*365 -> 34.263753 | F64: 35 | G64: 35 | H64: 35 | I64: 35 | J64: 35 | K64: 35 | M64: Company-reported average turnover 34-38 days
A65: Other current assets % revenues | C65: =C12/'Income Statement'!C6 -> 0.0027411768 | D65: =D12/'Income Statement'!D6 -> 0.0032775885 | E65: =E12/'Income Statement'!E6 -> 0.0077902837 | F65: 0.008 | G65: 0.008 | H65: 0.008 | I65: 0.008 | J65: 0.008 | K65: 0.008
A66: Payable days (on cost of sales + fulfilment) | C66: =C26/('Income Statement'!C11+'Income Statement'!C16)*365 -> 38.183461 | D66: =D26/('Income Statement'!D11+'Income Statement'!D16)*365 -> 33.377212 | E66: =E26/('Income Statement'!E11+'Income Statement'!E16)*365 -> 33.900477 | F66: 34 | G66: 34 | H66: 34 | I66: 34 | J66: 34 | K66: 34 | M66: Company-reported 32-34 days
A67: Accrued expenses (ex lease) % revenues | C67: =C27/'Income Statement'!C6 -> 0.057190917 | D67: =D27/'Income Statement'!D6 -> 0.067693816 | E67: =E27/'Income Statement'!E6 -> 0.072526107 | F67: 0.073 | G67: 0.073 | H67: 0.073 | I67: 0.073 | J67: 0.073 | K67: 0.073
A68: Contract liabilities % revenues | C68: =C29/'Income Statement'!C6 -> 0.021617917 | D68: =D29/'Income Statement'!D6 -> 0.019871993 | E68: =E29/'Income Statement'!E6 -> 0.018854398 | F68: 0.019 | G68: 0.019 | H68: 0.019 | I68: 0.019 | J68: 0.019 | K68: 0.019
A69: Income tax payable % revenues | C69: =C30/'Income Statement'!C6 -> 0.022022864 | D69: =D30/'Income Statement'!D6 -> 0.019897801 | E69: =E30/'Income Statement'!E6 -> 0.022295505 | F69: 0.02 | G69: 0.02 | H69: 0.02 | I69: 0.02 | J69: 0.02 | K69: 0.02
A70: Right-of-use assets % revenues | C70: =C15/'Income Statement'!C6 -> 0.015481419 | D70: =D15/'Income Statement'!D6 -> 0.024749664 | E70: =E15/'Income Statement'!E6 -> 0.026405716 | F70: 0.027 | G70: 0.027 | H70: 0.027 | I70: 0.027 | J70: 0.027 | K70: 0.027
A71: Current share of lease liabilities | C71: =C28/C55 -> 0.23062382 | D71: =D28/D55 -> 0.20427807 | E71: =E28/E55 -> 0.21162579 | F71: 0.21 | G71: 0.21 | H71: 0.21 | I71: 0.21 | J71: 0.21 | K71: 0.21

Sheet Cash Flow
A1: SHEIN Global Holdings Ltd (0625.HK) - Cash Flow
A2: Cash-flow statement (company presentation). Projections derived from balance-sheet movements.
A4: US$m unless stated | C4: FY2023A | D4: FY2024A | E4: FY2025A | F4: FY2026E | G4: FY2027E | H4: FY2028E | I4: FY2029E | J4: FY2030E | K4: FY2031E
A5: Operating activities (US$m; company presentation - interest received shown in investing)
A6: Income before income taxes | C6: 2995 | D6: 3769 | E6: 2514 | F6: ='Income Statement'!F51 -> 7267.6832 | G6: ='Income Statement'!G51 -> 1740.193 | H6: ='Income Statement'!H51 -> 2188.0697 | I6: ='Income Statement'!I51 -> 2609.2855 | J6: ='Income Statement'!J51 -> 2925.0626 | K6: ='Income Statement'!K51 -> 3164.9775
A7: Inventory write-downs, credit losses, impairments & other | C7: 120 | D7: 157 | E7: 181 | F7: 0 | G7: 0 | H7: 0 | I7: 0 | J7: 0 | K7: 0
A8: Depreciation of right-of-use assets | C8: 119 | D8: 200 | E8: 247 | F8: ='Income Statement'!F38 -> 284.80154 | G8: ='Income Statement'!G38 -> 298.44888 | H8: ='Income Statement'!H38 -> 319.32758 | I8: ='Income Statement'!I38 -> 341.18716 | J8: ='Income Statement'!J38 -> 362.91662 | K8: ='Income Statement'!K38 -> 383.35438
A9: D&A of property, equipment & intangibles | C9: 58 | D9: 124 | E9: 151 | F9: ='Income Statement'!F36 -> 180.09509 | G9: ='Income Statement'!G36 -> 188.72503 | H9: ='Income Statement'!H36 -> 201.92773 | I9: ='Income Statement'!I36 -> 215.75071 | J9: ='Income Statement'!J36 -> 229.4914 | K9: ='Income Statement'!K36 -> 242.41527
A10: Interest expense on lease liabilities | C10: 25 | D10: 44 | E10: 56 | F10: 0 | G10: 0 | H10: 0 | I10: 0 | J10: 0 | K10: 0 | M10: Projections: lease cost treated as operating
A11: Interest income (reclassified to investing) | C11: -472 | D11: -597 | E11: -621 | F11: =-'Income Statement'!F47 -> -584.83526 | G11: =-'Income Statement'!G47 -> -500.97181 | H11: =-'Income Statement'!H47 -> -506.90388 | I11: =-'Income Statement'!I47 -> -534.31559 | J11: =-'Income Statement'!J47 -> -582.11557 | K11: =-'Income Statement'!K47 -> -632.58353
A12: Share of (income)/losses from associates | C12: 36 | D12: 171 | E12: -3 | F12: =-'Income Statement'!F45 -> 15 | G12: =-'Income Statement'!G45 -> 0 | H12: =-'Income Statement'!H45 -> 0 | I12: =-'Income Statement'!I45 -> 0 | J12: =-'Income Statement'!J45 -> 0 | K12: =-'Income Statement'!K45 -> 0
A13: Share-based compensation | C13: 49 | D13: 71 | E13: 85 | F13: ='Income Statement'!F32 -> 90 | G13: ='Income Statement'!G32 -> 100 | H13: ='Income Statement'!H32 -> 105 | I13: ='Income Statement'!I32 -> 110 | J13: ='Income Statement'!J32 -> 115 | K13: ='Income Statement'!K32 -> 120
A14: FV changes of convertible redeemable preferred shares | C14: -1231 | D14: -2431 | E14: -328 | F14: =-'Income Statement'!F44 -> -5884.3083 | G14: =-'Income Statement'!G44 -> 0 | H14: =-'Income Statement'!H44 -> 0 | I14: =-'Income Statement'!I44 -> 0 | J14: =-'Income Statement'!J44 -> 0 | K14: =-'Income Statement'!K44 -> 0
A15: Change in receivables from payment platforms | C15: -309 | D15: -542 | E15: 647 | F15: =-('Balance Sheet'!F9-'Balance Sheet'!E9) -> -85.227562 | G15: =-('Balance Sheet'!G9-'Balance Sheet'!F9) -> -38.489675 | H15: =-('Balance Sheet'!H9-'Balance Sheet'!G9) -> -58.88432 | I15: =-('Balance Sheet'!I9-'Balance Sheet'!H9) -> -61.650721 | J15: =-('Balance Sheet'!J9-'Balance Sheet'!I9) -> -61.283732 | K15: =-('Balance Sheet'!K9-'Balance Sheet'!J9) -> -57.640735
A16: Change in other receivables, prepayments & other assets | C16: -163 | D16: -286 | E16: -204 | F16: =-(('Balance Sheet'!F10-'Balance Sheet'!E10)+('Balance Sheet'!F12-'Balance Sheet'!E12)+('Balance Sheet'!F22-'Balance Sheet'!E22)+('Balance Sheet'!F18-'Balance Sheet'!E18)) -> -31.53418 | G16: =-(('Balance Sheet'!G10-'Balance Sheet'!F10)+('Balance Sheet'!G12-'Balance Sheet'!F12)+('Balance Sheet'!G22-'Balance Sheet'!F22)+('Balance Sheet'!G18-'Balance Sheet'!F18)) -> -42.146194 | H16: =-(('Balance Sheet'!H10-'Balance Sheet'!G10)+('Balance Sheet'!H12-'Balance Sheet'!G12)+('Balance Sheet'!H22-'Balance Sheet'!G22)+('Balance Sheet'!H18-'Balance Sheet'!G18)) -> -64.478331 | I16: =-(('Balance Sheet'!I10-'Balance Sheet'!H10)+('Balance Sheet'!I12-'Balance Sheet'!H12)+('Balance Sheet'!I22-'Balance Sheet'!H22)+('Balance Sheet'!I18-'Balance Sheet'!H18)) -> -67.507539 | J16: =-(('Balance Sheet'!J10-'Balance Sheet'!I10)+('Balance Sheet'!J12-'Balance Sheet'!I12)+('Balance Sheet'!J22-'Balance Sheet'!I22)+('Balance Sheet'!J18-'Balance Sheet'!I18)) -> -67.105686 | K16: =-(('Balance Sheet'!K10-'Balance Sheet'!J10)+('Balance Sheet'!K12-'Balance Sheet'!J12)+('Balance Sheet'!K22-'Balance Sheet'!J22)+('Balance Sheet'!K18-'Balance Sheet'!J18)) -> -63.116605
A17: Change in inventories | C17: -862 | D17: -83 | E17: 74 | F17: =-('Balance Sheet'!F11-'Balance Sheet'!E11) -> 69.824635 | G17: =-('Balance Sheet'!G11-'Balance Sheet'!F11) -> -43.055661 | H17: =-('Balance Sheet'!H11-'Balance Sheet'!G11) -> -74.793336 | I17: =-('Balance Sheet'!I11-'Balance Sheet'!H11) -> -77.31655 | J17: =-('Balance Sheet'!J11-'Balance Sheet'!I11) -> -75.268509 | K17: =-('Balance Sheet'!K11-'Balance Sheet'!J11) -> -76.796969
A18: Change in accounts payable | C18: 927 | D18: 228 | E18: 36 | F18: =('Balance Sheet'!F26-'Balance Sheet'!E26) -> 94.378433 | G18: =('Balance Sheet'!G26-'Balance Sheet'!F26) -> 150.20098 | H18: =('Balance Sheet'!H26-'Balance Sheet'!G26) -> 203.96816 | I18: =('Balance Sheet'!I26-'Balance Sheet'!H26) -> 216.08198 | J18: =('Balance Sheet'!J26-'Balance Sheet'!I26) -> 221.9499 | K18: =('Balance Sheet'!K26-'Balance Sheet'!J26) -> 214.58741
A19: Change in contract liabilities | C19: 99 | D19: 99 | E19: -27 | F19: =('Balance Sheet'!F29-'Balance Sheet'!E29) -> 6.76902 | G19: =('Balance Sheet'!G29-'Balance Sheet'!F29) -> 38.13227 | H19: =('Balance Sheet'!H29-'Balance Sheet'!G29) -> 58.337537 | I19: =('Balance Sheet'!I29-'Balance Sheet'!H29) -> 61.07825 | J19: =('Balance Sheet'!J29-'Balance Sheet'!I29) -> 60.714669 | K19: =('Balance Sheet'!K29-'Balance Sheet'!J29) -> 57.1055
A20: Change in accrued expenses & other current liabilities | C20: 725 | D20: 854 | E20: 334 | F20: =('Balance Sheet'!F27-'Balance Sheet'!E27) -> 22.42834 | G20: =('Balance Sheet'!G27-'Balance Sheet'!F27) -> 146.5082 | H20: =('Balance Sheet'!H27-'Balance Sheet'!G27) -> 224.13896 | I20: =('Balance Sheet'!I27-'Balance Sheet'!H27) -> 234.66906 | J20: =('Balance Sheet'!J27-'Balance Sheet'!I27) -> 233.27215 | K20: =('Balance Sheet'!K27-'Balance Sheet'!J27) -> 219.40534
A21: Change in other long-term liabilities & deferred taxes | C21: 6 | D21: -4 | E21: -1 | F21: =('Balance Sheet'!F36-'Balance Sheet'!E36)+('Balance Sheet'!F34-'Balance Sheet'!E34) -> 41 | G21: =('Balance Sheet'!G36-'Balance Sheet'!F36)+('Balance Sheet'!G34-'Balance Sheet'!F34) -> 0 | H21: =('Balance Sheet'!H36-'Balance Sheet'!G36)+('Balance Sheet'!H34-'Balance Sheet'!G34) -> 0 | I21: =('Balance Sheet'!I36-'Balance Sheet'!H36)+('Balance Sheet'!I34-'Balance Sheet'!H34) -> 0 | J21: =('Balance Sheet'!J36-'Balance Sheet'!I36)+('Balance Sheet'!J34-'Balance Sheet'!I34) -> 0 | K21: =('Balance Sheet'!K36-'Balance Sheet'!J36)+('Balance Sheet'!K34-'Balance Sheet'!J34) -> 0
A22: Cash generated from operations | C22: =SUM(C6:C21) -> 2122 | D22: =SUM(D6:D21) -> 1774 | E22: =SUM(E6:E21) -> 3141 | F22: =SUM(F6:F21) -> 1486.075 | G22: =SUM(G6:G21) -> 2037.545 | H22: =SUM(H6:H21) -> 2595.7098 | I22: =SUM(I6:I21) -> 3047.2622 | J22: =SUM(J6:J21) -> 3362.6338 | K22: =SUM(K6:K21) -> 3571.7076
A23: Income taxes paid | C23: -365 | D23: -369 | E23: -303 | F23: =-'Income Statement'!F52+('Balance Sheet'!F30-'Balance Sheet'!E30) -> -434.44463 | G23: =-'Income Statement'!G52+('Balance Sheet'!G30-'Balance Sheet'!F30) -> -342.70323 | H23: =-'Income Statement'!H52+('Balance Sheet'!H30-'Balance Sheet'!G30) -> -419.96739 | I23: =-'Income Statement'!I52+('Balance Sheet'!I30-'Balance Sheet'!H30) -> -509.74991 | J23: =-'Income Statement'!J52+('Balance Sheet'!J30-'Balance Sheet'!I30) -> -579.60359 | K23: =-'Income Statement'!K52+('Balance Sheet'!K30-'Balance Sheet'!J30) -> -636.18399
A24: Net cash from operating activities | C24: =C22+C23 -> 1757 | D24: =D22+D23 -> 1405 | E24: =E22+E23 -> 2838 | F24: =F22+F23 -> 1051.6303 | G24: =G22+G23 -> 1694.8418 | H24: =H22+H23 -> 2175.7424 | I24: =I22+I23 -> 2537.5123 | J24: =J22+J23 -> 2783.0302 | K24: =K22+K23 -> 2935.5236
A25: Investing activities (US$m)
A26: Capex % of net revenues | C26: =-C27/'Income Statement'!C6 -> 0.0096875681 | D26: =-D27/'Income Statement'!D6 -> 0.0073552183 | E26: =-E27/'Income Statement'!E6 -> 0.0053050398 | F26: 0.007 | G26: 0.0075 | H26: 0.0075 | I26: 0.0075 | J26: 0.0075 | K26: 0.0075 | M26: Warehouse automation; IPO proceeds 40% to technology
A27: Capital expenditure (PP&E, land use rights) | C27: -311 | D27: -285 | E27: -222 | F27: =-F26*'Income Statement'!F6 -> -293.17806 | G27: =-G26*'Income Statement'!G6 -> -329.17156 | H27: =-H26*'Income Statement'!H6 -> -352.19954 | I27: =-I26*'Income Statement'!I6 -> -376.30937 | J27: =-J26*'Income Statement'!J6 -> -400.27569 | K27: =-K26*'Income Statement'!K6 -> -422.81733
A28: Interest received | C28: 273 | D28: 578 | E28: 565 | F28: ='Income Statement'!F47 -> 584.83526 | G28: ='Income Statement'!G47 -> 500.97181 | H28: ='Income Statement'!H47 -> 506.90388 | I28: ='Income Statement'!I47 -> 534.31559 | J28: ='Income Statement'!J47 -> 582.11557 | K28: ='Income Statement'!K47 -> 632.58353
A29: Net placement of short/long-term time deposits | C29: -3893 | D29: -2064 | E29: -1368 | F29: =-(('Balance Sheet'!F8-'Balance Sheet'!E8)+('Balance Sheet'!F21-'Balance Sheet'!E21)) -> -1822 | G29: =-(('Balance Sheet'!G8-'Balance Sheet'!F8)+('Balance Sheet'!G21-'Balance Sheet'!F21)) -> 0 | H29: =-(('Balance Sheet'!H8-'Balance Sheet'!G8)+('Balance Sheet'!H21-'Balance Sheet'!G21)) -> 0 | I29: =-(('Balance Sheet'!I8-'Balance Sheet'!H8)+('Balance Sheet'!I21-'Balance Sheet'!H21)) -> 0 | J29: =-(('Balance Sheet'!J8-'Balance Sheet'!I8)+('Balance Sheet'!J21-'Balance Sheet'!I21)) -> 0 | K29: =-(('Balance Sheet'!K8-'Balance Sheet'!J8)+('Balance Sheet'!K21-'Balance Sheet'!J21)) -> 0
A30: Acquisitions (Everlane), investments, loans & other | C30: 3 | D30: -33 | E30: 14 | F30: =-(('Balance Sheet'!F16-'Balance Sheet'!E16)+('Balance Sheet'!F20-'Balance Sheet'!E20))-(('Balance Sheet'!F19-'Balance Sheet'!E19)-'Income Statement'!F45) -> -101 | G30: =-(('Balance Sheet'!G16-'Balance Sheet'!F16)+('Balance Sheet'!G20-'Balance Sheet'!F20))-(('Balance Sheet'!G19-'Balance Sheet'!F19)-'Income Statement'!G45) -> 0 | H30: =-(('Balance Sheet'!H16-'Balance Sheet'!G16)+('Balance Sheet'!H20-'Balance Sheet'!G20))-(('Balance Sheet'!H19-'Balance Sheet'!G19)-'Income Statement'!H45) -> 0 | I30: =-(('Balance Sheet'!I16-'Balance Sheet'!H16)+('Balance Sheet'!I20-'Balance Sheet'!H20))-(('Balance Sheet'!I19-'Balance Sheet'!H19)-'Income Statement'!I45) -> 0 | J30: =-(('Balance Sheet'!J16-'Balance Sheet'!I16)+('Balance Sheet'!J20-'Balance Sheet'!I20))-(('Balance Sheet'!J19-'Balance Sheet'!I19)-'Income Statement'!J45) -> 0 | K30: =-(('Balance Sheet'!K16-'Balance Sheet'!J16)+('Balance Sheet'!K20-'Balance Sheet'!J20))-(('Balance Sheet'!K19-'Balance Sheet'!J19)-'Income Statement'!K45) -> 0
A31: Net change in restricted cash | C31: -240 | D31: -16 | E31: -55 | F31: =-(('Balance Sheet'!F7-'Balance Sheet'!E7)+('Balance Sheet'!F17-'Balance Sheet'!E17)) -> -78 | G31: =-(('Balance Sheet'!G7-'Balance Sheet'!F7)+('Balance Sheet'!G17-'Balance Sheet'!F17)) -> 0 | H31: =-(('Balance Sheet'!H7-'Balance Sheet'!G7)+('Balance Sheet'!H17-'Balance Sheet'!G17)) -> 0 | I31: =-(('Balance Sheet'!I7-'Balance Sheet'!H7)+('Balance Sheet'!I17-'Balance Sheet'!H17)) -> 0 | J31: =-(('Balance Sheet'!J7-'Balance Sheet'!I7)+('Balance Sheet'!J17-'Balance Sheet'!I17)) -> 0 | K31: =-(('Balance Sheet'!K7-'Balance Sheet'!J7)+('Balance Sheet'!K17-'Balance Sheet'!J17)) -> 0
A32: Net cash used in investing activities | C32: =C27+C28+C29+C30+C31 -> -4168 | D32: =D27+D28+D29+D30+D31 -> -1820 | E32: =E27+E28+E29+E30+E31 -> -1066 | F32: =F27+F28+F29+F30+F31 -> -1709.3428 | G32: =G27+G28+G29+G30+G31 -> 171.80025 | H32: =H27+H28+H29+H30+H31 -> 154.70434 | I32: =I27+I28+I29+I30+I31 -> 158.00621 | J32: =J27+J28+J29+J30+J31 -> 181.83988 | K32: =K27+K28+K29+K30+K31 -> 209.76619
A33: Financing activities (US$m)
A34: Issuance of preferred shares, net of costs | C34: 1737 | D34: -18 | E34: 0 | F34: 0 | G34: 0 | H34: 0 | I34: 0 | J34: 0 | K34: 0
A35: IPO net proceeds | C35: 0 | D35: 0 | E35: 0 | F35: =Inputs!$C$25 -> 1684.3977 | G35: 0 | H35: 0 | I35: 0 | J35: 0 | K35: 0
A36: Distributions to preferred holders (8% and 12% p.a.) | C36: 0 | D36: 0 | E36: 0 | F36: =-(Inputs!$C$27+Inputs!$C$29) -> -1312 | G36: 0 | H36: 0 | I36: 0 | J36: 0 | K36: 0
A37: Conversion Adjustment cash compensation | C37: 0 | D37: 0 | E37: 0 | F37: =-Inputs!$C$26 -> -2200 | G37: 0 | H37: 0 | I37: 0 | J37: 0 | K37: 0
A38: Lease payments (principal and interest) | C38: -127 | D38: -188 | E38: -284 | F38: =-'Income Statement'!F38 -> -284.80154 | G38: =-'Income Statement'!G38 -> -298.44888 | H38: =-'Income Statement'!H38 -> -319.32758 | I38: =-'Income Statement'!I38 -> -341.18716 | J38: =-'Income Statement'!J38 -> -362.91662 | K38: =-'Income Statement'!K38 -> -383.35438
A39: Dividends paid | C39: -6 | D39: 0 | E39: 0 | F39: =-'Income Statement'!E69 -> 0 | G39: =-'Income Statement'!F69 -> -575.13934 | H39: =-'Income Statement'!G69 -> -728.67528 | I39: =-'Income Statement'!H69 -> -905.84717 | J39: =-'Income Statement'!I69 -> -1072.6213 | K39: =-'Income Statement'!J69 -> -1198.2744
A40: Other financing | C40: -5 | D40: 0 | E40: 0 | F40: 0 | G40: 0 | H40: 0 | I40: 0 | J40: 0 | K40: 0
A41: Net cash from/(used in) financing activities | C41: =SUM(C34:C40) -> 1599 | D41: =SUM(D34:D40) -> -206 | E41: =SUM(E34:E40) -> -284 | F41: =SUM(F34:F40) -> -2112.4038 | G41: =SUM(G34:G40) -> -873.58822 | H41: =SUM(H34:H40) -> -1048.0029 | I41: =SUM(I34:I40) -> -1247.0343 | J41: =SUM(J34:J40) -> -1435.538 | K41: =SUM(K34:K40) -> -1581.6288
A42: Effect of exchange rate changes | C42: 36 | D42: 32 | E42: 88 | F42: 0 | G42: 0 | H42: 0 | I42: 0 | J42: 0 | K42: 0
A43: Net change in cash and cash equivalents | C43: =C24+C32+C41+C42 -> -776 | D43: =D24+D32+D41+D42 -> -589 | E43: =E24+E32+E41+E42 -> 1576 | F43: =F24+F32+F41+F42 -> -2770.1163 | G43: =G24+G32+G41+G42 -> 993.05384 | H43: =H24+H32+H41+H42 -> 1282.4439 | I43: =I24+I32+I41+I42 -> 1448.4842 | J43: =J24+J32+J41+J42 -> 1529.3322 | K43: =K24+K32+K41+K42 -> 1563.661
A44: Cash and cash equivalents - beginning | C44: 4270 | D44: 3494 | E44: 2905 | F44: =E45 -> 4481 | G44: =F45 -> 1710.8837 | H44: =G45 -> 2703.9375 | I44: =H45 -> 3986.3814 | J44: =I45 -> 5434.8656 | K44: =J45 -> 6964.1978
A45: Cash and cash equivalents - ending | C45: =C44+C43 -> 3494 | D45: =D44+D43 -> 2905 | E45: =E44+E43 -> 4481 | F45: =F44+F43 -> 1710.8837 | G45: =G44+G43 -> 2703.9375 | H45: =H44+H43 -> 3986.3814 | I45: =I44+I43 -> 5434.8656 | J45: =J44+J43 -> 6964.1978 | K45: =K44+K43 -> 8527.8587
A46: Free cash flow (US$m)
A47: Free cash flow (CFO - capex - lease payments) | C47: =C24+C27+C38 -> 1319 | D47: =D24+D27+D38 -> 932 | E47: =E24+E27+E38 -> 2332 | F47: =F24+F27+F38 -> 473.65074 | G47: =G24+G27+G38 -> 1067.2214 | H47: =H24+H27+H38 -> 1504.2153 | I47: =I24+I27+I38 -> 1820.0158 | J47: =J24+J27+J38 -> 2019.8379 | K47: =K24+K27+K38 -> 2129.3518
A48: Free cash flow incl. interest received | C48: =C47+C28 -> 1592 | D48: =D47+D28 -> 1510 | E48: =E47+E28 -> 2897 | F48: =F47+F28 -> 1058.486 | G48: =G47+G28 -> 1568.1932 | H48: =H47+H28 -> 2011.1191 | I48: =I47+I28 -> 2354.3314 | J48: =J47+J28 -> 2601.9535 | K48: =K47+K28 -> 2761.9354
A49: FCF (incl. interest) % of revenues | C49: =C48/'Income Statement'!C6 -> 0.049590381 | D49: =D48/'Income Statement'!D6 -> 0.038969753 | E49: =E48/'Income Statement'!E6 -> 0.06922838 | F49: =F48/'Income Statement'!F6 -> 0.025272703 | G49: =G48/'Income Statement'!G6 -> 0.035730452 | H49: =H48/'Income Statement'!H6 -> 0.042826273 | I49: =I48/'Income Statement'!I6 -> 0.046922789 | J49: =J48/'Income Statement'!J6 -> 0.048753026 | K49: =K48/'Income Statement'!K6 -> 0.048991642
A50: FCF (incl. interest) / adjusted net income | C50: =IFERROR(C48/'Income Statement'!C58,0) -> 0.96895922 | D50: =IFERROR(D48/'Income Statement'!D58,0) -> 1.3494191 | E50: =IFERROR(E48/'Income Statement'!E58,0) -> 1.5952643 | F50: =IFERROR(F48/'Income Statement'!F58,0) -> 0.92019962 | G50: =IFERROR(G48/'Income Statement'!G58,0) -> 1.0760576 | H50: =IFERROR(H48/'Income Statement'!H58,0) -> 1.1100764 | I50: =IFERROR(I48/'Income Statement'!I58,0) -> 1.0974662 | J50: =IFERROR(J48/'Income Statement'!J58,0) -> 1.0857085 | K50: =IFERROR(K48/'Income Statement'!K58,0) -> 1.0669271
A51: FCF yield on current market cap | C51: =C48/Inputs!$C$20 -> 0.091637779 | D51: =D48/Inputs!$C$20 -> 0.086917743 | E51: =E48/Inputs!$C$20 -> 0.16675543 | F51: =F48/Inputs!$C$20 -> 0.060927956 | G51: =G48/Inputs!$C$20 -> 0.090267424 | H51: =H48/Inputs!$C$20 -> 0.11576287 | I51: =I48/Inputs!$C$20 -> 0.13551865 | J51: =J48/Inputs!$C$20 -> 0.14977214 | K51: =K48/Inputs!$C$20 -> 0.15898092

Sheet DCF Inputs
A1: SHEIN Global Holdings Ltd (0625.HK) - DCF Inputs
A2: Unlevered free cash flow for the DCF. SBC treated as a real cost; lease payments as operating.
A4: US$m unless stated | C4: FY2023A | D4: FY2024A | E4: FY2025A | F4: FY2026E | G4: FY2027E | H4: FY2028E | I4: FY2029E | J4: FY2030E | K4: FY2031E | L4: 2H26E stub
A5: Unlevered free cash flow build (US$m); column L = 2H26E stub used in DCF
A6: Net revenues | C6: ='Income Statement'!C6 -> 32103 | D6: ='Income Statement'!D6 -> 38748 | E6: ='Income Statement'!E6 -> 41847 | F6: ='Income Statement'!F6 -> 41882.58 | G6: ='Income Statement'!G6 -> 43889.542 | H6: ='Income Statement'!H6 -> 46959.938 | I6: ='Income Statement'!I6 -> 50174.583 | J6: ='Income Statement'!J6 -> 53370.092 | K6: ='Income Statement'!K6 -> 56375.645 | L6: =Interim!J9 -> 21748.58
A7: EBIT (IFRS operating income, after SBC) | C7: ='Income Statement'!C29 -> 1376 | D7: ='Income Statement'!D29 -> 966 | E7: ='Income Statement'!E29 -> 1707 | F7: ='Income Statement'!F29 -> 1034.5396 | G7: ='Income Statement'!G29 -> 1305.0555 | H7: ='Income Statement'!H29 -> 1751.6057 | I7: ='Income Statement'!I29 -> 2150.2318 | J7: ='Income Statement'!J29 -> 2423.0022 | K7: ='Income Statement'!K29 -> 2616.9574 | L7: =Interim!J39 -> 541.53964
A8: EBIT margin | C8: =C7/C6 -> 0.042862038 | D8: =D7/D6 -> 0.024930319 | E8: =E7/E6 -> 0.040791455 | F8: =F7/F6 -> 0.024700953 | G8: =G7/G6 -> 0.029735 | H8: =H7/H6 -> 0.0373 | I8: =I7/I6 -> 0.042855 | J8: =J7/J6 -> 0.0454 | ... L8: =L7/L6 -> 0.0249
A9: Cash tax rate on EBIT | C9: =Inputs!$C$52 -> 0.22 | D9: =Inputs!$C$52 -> 0.22 | E9: =Inputs!$C$52 -> 0.22 | F9: =Inputs!$C$52 -> 0.22 | G9: =Inputs!$C$52 -> 0.22 | H9: =Inputs!$C$52 -> 0.22 | I9: =Inputs!$C$52 -> 0.22 | J9: =Inputs!$C$52 -> 0.22 | ... L9: =Inputs!$C$52 -> 0.22
A10: Less: taxes on EBIT | C10: =-C7*C9 -> -302.72 | D10: =-D7*D9 -> -212.52 | E10: =-E7*E9 -> -375.54 | F10: =-F7*F9 -> -227.59872 | G10: =-G7*G9 -> -287.11221 | H10: =-H7*H9 -> -385.35325 | I10: =-I7*I9 -> -473.05099 | J10: =-J7*J9 -> -533.06048 | ... L10: =-L7*L9 -> -119.13872
A11: NOPAT | C11: =C7+C10 -> 1073.28 | D11: =D7+D10 -> 753.48 | E11: =E7+E10 -> 1331.46 | F11: =F7+F10 -> 806.94092 | G11: =G7+G10 -> 1017.9433 | H11: =H7+H10 -> 1366.2524 | I11: =I7+I10 -> 1677.1808 | J11: =J7+J10 -> 1889.9417 | ... L11: =L7+L10 -> 422.40092
A12: Plus: D&A of PP&E and intangibles | C12: ='Income Statement'!C36 -> 58 | D12: ='Income Statement'!D36 -> 124 | E12: ='Income Statement'!E36 -> 151 | F12: ='Income Statement'!F36 -> 180.09509 | G12: ='Income Statement'!G36 -> 188.72503 | H12: ='Income Statement'!H36 -> 201.92773 | I12: ='Income Statement'!I36 -> 215.75071 | J12: ='Income Statement'!J36 -> 229.4914 | K12: ='Income Statement'!K36 -> 242.41527 | L12: =Interim!J58 -> 93.095094 | M12: ROU depreciation not added back: lease payments treated as operating cost
A13: Less: capital expenditure | C13: ='Cash Flow'!C27 -> -311 | D13: ='Cash Flow'!D27 -> -285 | E13: ='Cash Flow'!E27 -> -222 | F13: ='Cash Flow'!F27 -> -293.17806 | G13: ='Cash Flow'!G27 -> -329.17156 | H13: ='Cash Flow'!H27 -> -352.19954 | I13: ='Cash Flow'!I27 -> -376.30937 | J13: ='Cash Flow'!J27 -> -400.27569 | K13: ='Cash Flow'!K27 -> -422.81733 | L13: =-Interim!J60 -> -153.17806
A14: Operating net working capital (end of period) | C14: ='Balance Sheet'!C58 -> -2458 | D14: ='Balance Sheet'!D58 -> -2918 | E14: ='Balance Sheet'!E58 -> -4004 | F14: ='Balance Sheet'!F58 -> -4092.6387 | G14: ='Balance Sheet'!G58 -> -4303.7886 | H14: ='Balance Sheet'!H58 -> -4592.0773 | I14: ='Balance Sheet'!I58 -> -4897.4318 | J14: ='Balance Sheet'!J58 -> -5209.7106 | K14: ='Balance Sheet'!K58 -> -5503.2545 | L14: ='Balance Sheet'!F58 -> -4092.6387
A15: Less: increase / plus: decrease in NWC | D15: =-(D14-C14) -> 460 | E15: =-(E14-D14) -> 1086 | F15: =-(F14-E14) -> 88.638686 | G15: =-(G14-F14) -> 211.14992 | H15: =-(H14-G14) -> 288.28867 | I15: =-(I14-H14) -> 305.35449 | J15: =-(J14-I14) -> 312.27879 | K15: =-(K14-J14) -> 293.54394 | L15: =-(L14-Interim!I88) -> -881.36131 | M15: 2H26E: seasonal unwind of 30-Jun payables float
A16: Unlevered free cash flow (FCFF) | D16: =D11+D12+D13+D15 -> 1052.48 | E16: =E11+E12+E13+E15 -> 2346.46 | F16: =F11+F12+F13+F15 -> 782.49664 | G16: =G11+G12+G13+G15 -> 1088.6467 | H16: =H11+H12+H13+H15 -> 1504.2693 | I16: =I11+I12+I13+I15 -> 1821.9766 | J16: =J11+J12+J13+J15 -> 2031.4362 | K16: =K11+K12+K13+K15 -> 2154.3687 | L16: =L11+L12+L13+L15 -> -519.04336
A17: FCFF margin | D17: =D16/D6 -> 0.027162176 | E17: =E16/E6 -> 0.056072359 | F17: =F16/F6 -> 0.018683105 | G17: =G16/G6 -> 0.024804239 | H17: =H16/H6 -> 0.032033034 | I17: =I16/I6 -> 0.03631274 | J17: =J16/J6 -> 0.038063195 | K17: =K16/K6 -> 0.038214528 | L17: =L16/L6 -> -0.023865621
A18: Memo
A19: Share-based compensation (treated as a cash-equivalent cost) | C19: ='Income Statement'!C32 -> 49 | D19: ='Income Statement'!D32 -> 71 | E19: ='Income Statement'!E32 -> 85 | F19: ='Income Statement'!F32 -> 90 | G19: ='Income Statement'!G32 -> 100 | H19: ='Income Statement'!H32 -> 105 | I19: ='Income Statement'!I32 -> 110 | J19: ='Income Statement'!J32 -> 115 | K19: ='Income Statement'!K32 -> 120
A20: EBITDA (IFRS 16) | C20: ='Income Statement'!C39 -> 1553 | D20: ='Income Statement'!D39 -> 1290 | E20: ='Income Statement'!E39 -> 2105 | F20: ='Income Statement'!F39 -> 1499.4363 | G20: ='Income Statement'!G39 -> 1792.2294 | H20: ='Income Statement'!H39 -> 2272.861 | I20: ='Income Statement'!I39 -> 2707.1696 | J20: ='Income Statement'!J39 -> 3015.4102 | K20: ='Income Statement'!K39 -> 3242.7271
A21: Adjusted EBIT | C21: ='Income Statement'!C33 -> 1425 | D21: ='Income Statement'!D33 -> 1037 | E21: ='Income Statement'!E33 -> 1792 | F21: ='Income Statement'!F33 -> 1124.5396 | G21: ='Income Statement'!G33 -> 1405.0555 | H21: ='Income Statement'!H33 -> 1856.6057 | I21: ='Income Statement'!I33 -> 2260.2318 | J21: ='Income Statement'!J33 -> 2538.0022 | K21: ='Income Statement'!K33 -> 2736.9574
A22: Reinvestment rate (capex - D&A + dNWC) / NOPAT | D22: =-(D13+D12+D15)/D11 -> -0.3968254 | E22: =-(E13+E12+E15)/E11 -> -0.76232106 | F22: =-(F13+F12+F15)/F11 -> 0.030292527 | G22: =-(G13+G12+G15)/G11 -> -0.069457099 | H22: =-(H13+H12+H15)/H11 -> -0.10101857 | I22: =-(I13+I12+I15)/I11 -> -0.086332866 | J22: =-(J13+J12+J15)/J11 -> -0.074867122 | K22: =-(K13+K12+K15)/K11 -> -0.055428374 | L22: =-(L13+L12+L15)/L11 -> 2.2287932
A23: Terminal-year (FY2031E) metrics
A24: Net revenues | C24: =K6 -> 56375.645
A25: EBITDA | C25: =K20 -> 3242.7271
A26: EBIT | C26: =K7 -> 2616.9574
A27: NOPAT | C27: =K11 -> 2041.2268
A28: FCFF | C28: =K16 -> 2154.3687
A29: Operating NWC | C29: =K14 -> -5503.2545

Sheet DCF
A1: SHEIN Global Holdings Ltd (0625.HK) - DCF
A2: FCFF discounted at WACC (mid-period); Gordon-growth terminal value; bridge to equity at pro forma listing cash.
A4: Discount rate
A5: Risk-free rate | C5: =Inputs!$C$44 -> 0.04
A6: Equity beta | C6: =Inputs!$C$45 -> 1.2
A7: Equity risk premium | C7: =Inputs!$C$46 -> 0.06
A8: Cost of equity (CAPM) | C8: =C5+C6*C7 -> 0.112
A9: Debt / capital | C9: =Inputs!$C$48 -> 0
A10: WACC | C10: =Inputs!$C$50 -> 0.112
A11: Terminal growth | C11: =Inputs!$C$51 -> 0.025
A12: Valuation date | C12: =Inputs!$C$12 -> 46295
A14: Discounted cash flows (US$m; mid-period convention)
D15: 2H26E | E15: FY2027E | F15: FY2028E | G15: FY2029E | H15: FY2030E | I15: FY2031E
A16: Unlevered free cash flow | D16: ='DCF Inputs'!L16 -> -519.04336 | E16: ='DCF Inputs'!G16 -> 1088.6467 | F16: ='DCF Inputs'!H16 -> 1504.2693 | G16: ='DCF Inputs'!I16 -> 1821.9766 | H16: ='DCF Inputs'!J16 -> 2031.4362 | I16: ='DCF Inputs'!K16 -> 2154.3687
A17: Cash-flow mid-point | D17: 46296 | E17: 46569 | F17: 46935 | G17: 47300 | H17: 47665 | I17: 48030
A18: Years from valuation date | D18: =MAX(0,(D17-$C$12)/365.25) -> 0.0027378508 | E18: =MAX(0,(E17-$C$12)/365.25) -> 0.75017112 | F18: =MAX(0,(F17-$C$12)/365.25) -> 1.7522245 | G18: =MAX(0,(G17-$C$12)/365.25) -> 2.75154 | H18: =MAX(0,(H17-$C$12)/365.25) -> 3.7508556 | I18: =MAX(0,(I17-$C$12)/365.25) -> 4.7501711
A19: Discount factor | D19: =1/(1+$C$10)^D18 -> 0.99970939 | E19: =1/(1+$C$10)^E18 -> 0.92345029 | F19: =1/(1+$C$10)^F18 -> 0.8302599 | G19: =1/(1+$C$10)^G18 -> 0.74669085 | H19: =1/(1+$C$10)^H18 -> 0.67153337 | I19: =1/(1+$C$10)^I18 -> 0.6039408
A20: Present value of FCFF | D20: =D16*D19 -> -518.89252 | E20: =E16*E19 -> 1005.3111 | F20: =F16*F19 -> 1248.9345 | G20: =G16*G19 -> 1360.4533 | H20: =H16*H19 -> 1364.1772 | I20: =I16*I19 -> 1301.1111
A22: Terminal value (Gordon growth on FY2031E)
A23: FY2031E NOPAT + D&A - capex | C23: ='DCF Inputs'!K11+'DCF Inputs'!K12+'DCF Inputs'!K13 -> 1860.8247
A24: FY2031E operating NWC | C24: ='DCF Inputs'!K14 -> -5503.2545
A25: Terminal FCFF (FY2032E) | C25: =C23*(1+C11)-C24*C11 -> 2044.9267 | J25: NWC grows with revenue at g
A26: Terminal value at end-FY2031E | C26: =C25/(C10-C11) -> 23504.905
A27: Years from valuation date to end-FY2031E | C27: =(DATE(2031,12,31)-C12)/365.25 -> 5.2511978
A28: Present value of terminal value | C28: =C26/(1+C10)^C27 -> 13460.25
A29: Implied terminal EV / FY2031E EBITDA | C29: =C26/'DCF Inputs'!K20 -> 7.2484992
A30: Implied terminal EV / FY2031E EBIT | C30: =C26/'DCF Inputs'!K7 -> 8.9817681
A32: Enterprise value to equity value (US$m)
A33: Sum of PV of FCFF (2H26E-FY2031E) | C33: =SUM(D20:I20) -> 5761.0947
A34: PV of terminal value | C34: =C28 -> 13460.25
A35: Operating enterprise value | C35: =C33+C34 -> 19221.345
A36: Terminal value % of EV | C36: =C34/C35 -> 0.70027619
A37: Plus: cash resources at 30-Jun-2026 | C37: =Inputs!$C$22 -> 15248
A38: Less: restricted cash | C38: =-Inputs!$C$23 -> -660
A39: Plus: IPO net proceeds (Sep-2026) | C39: =Inputs!$C$25 -> 1684.3977
A40: Less: Conversion Adjustment cash paid at listing | C40: =-Inputs!$C$26 -> -2200
A41: Less: preferred distributions paid after 30-Jun-2026 | C41: =-(Inputs!$C$28+Inputs!$C$29) -> -587
A42: Less: minimum operating cash | C42: =-Inputs!$C$31 -> -1500
A43: Less: regulatory contingency reserve | C43: =-Inputs!$C$32 -> -1000
A44: Plus: associates & FVTPL investments | C44: =Inputs!$C$33 -> 411
A45: Net cash & investments used in valuation | C45: =SUM(C37:C44) -> 11396.398
A46: Equity value (US$m) | C46: =C35+C45 -> 30617.743
A47: Fully diluted shares (m) | C47: =Inputs!$C$17 -> 4419.2349
A48: DCF value per share (US$) | C48: =C46/C47 -> 6.9282904
A49: DCF value per share (HK$) | C49: =C48*Inputs!$C$6 -> 54.352438
A50: Upside / (downside) vs. current price | C50: =C49/Inputs!$C$5-1 -> 0.76240071
A51: of which net cash & investments per share (HK$) | C51: =C45/C47*Inputs!$C$6 -> 20.230819
A52: Implied P/E on FY2027E adj. EPS | C52: =C49/'Income Statement'!G66 -> 21.114228
A53: Implied operating EV / FY2027E adj. EBIT | C53: =C35/'Income Statement'!G33 -> 13.680132

Sheet Sensitivity
A1: SHEIN Global Holdings Ltd (0625.HK) - Sensitivity
A2: All tables recalculate live from the DCF and Income Statement tabs.
A4: Table 1 - DCF value per share (HK$): WACC vs. terminal growth
B5: WACC \ g | C5: =DCF!$C$11+(-0.01) -> 0.015 | D5: =DCF!$C$11+(-0.005) -> 0.02 | E5: =DCF!$C$11+(0) -> 0.025 | F5: =DCF!$C$11+(0.005) -> 0.03 | G5: =DCF!$C$11+(0.01) -> 0.035
B6: =DCF!$C$10+(-0.015) -> 0.097 | C6: =(SUMPRODUCT(DCF!$D$16:$I$16/(1+$B6)^DCF!$D$18:$I$18)+((DCF!$C$23*(1+C$5)-DCF!$C$24*C$5)/($B6-C$5))/(1+$B6)^DCF!$C$27+DCF!$C$45)/Inputs!$C$17*Inputs!$C$6 -> 57.14707 | D6: =(SUMPRODUCT(DCF!$D$16:$I$16/(1+$B6)^DCF!$D$18:$I$18)+((DCF!$C$23*(1+D$5)-DCF!$C$24*D$5)/($B6-D$5))/(1+$B6)^DCF!$C$27+DCF!$C$45)/Inputs!$C$17*Inputs!$C$6 -> 59.373347 | E6: =(SUMPRODUCT(DCF!$D$16:$I$16/(1+$B6)^DCF!$D$18:$I$18)+((DCF!$C$23*(1+E$5)-DCF!$C$24*E$5)/($B6-E$5))/(1+$B6)^DCF!$C$27+DCF!$C$45)/Inputs!$C$17*Inputs!$C$6 -> 61.90883 | F6: =(SUMPRODUCT(DCF!$D$16:$I$16/(1+$B6)^DCF!$D$18:$I$18)+((DCF!$C$23*(1+F$5)-DCF!$C$24*F$5)/($B6-F$5))/(1+$B6)^DCF!$C$27+DCF!$C$45)/Inputs!$C$17*Inputs!$C$6 -> 64.822742 | G6: =(SUMPRODUCT(DCF!$D$16:$I$16/(1+$B6)^DCF!$D$18:$I$18)+((DCF!$C$23*(1+G$5)-DCF!$C$24*G$5)/($B6-G$5))/(1+$B6)^DCF!$C$27+DCF!$C$45)/Inputs!$C$17*Inputs!$C$6 -> 68.206641
B7: =DCF!$C$10+(-0.01) -> 0.102 | C7: =(SUMPRODUCT(DCF!$D$16:$I$16/(1+$B7)^DCF!$D$18:$I$18)+((DCF!$C$23*(1+C$5)-DCF!$C$24*C$5)/($B7-C$5))/(1+$B7)^DCF!$C$27+DCF!$C$45)/Inputs!$C$17*Inputs!$C$6 -> 54.903945 | D7: =(SUMPRODUCT(DCF!$D$16:$I$16/(1+$B7)^DCF!$D$18:$I$18)+((DCF!$C$23*(1+D$5)-DCF!$C$24*D$5)/($B7-D$5))/(1+$B7)^DCF!$C$27+DCF!$C$45)/Inputs!$C$17*Inputs!$C$6 -> 56.855342 | E7: =(SUMPRODUCT(DCF!$D$16:$I$16/(1+$B7)^DCF!$D$18:$I$18)+((DCF!$C$23*(1+E$5)-DCF!$C$24*E$5)/($B7-E$5))/(1+$B7)^DCF!$C$27+DCF!$C$45)/Inputs!$C$17*Inputs!$C$6 -> 59.060166 | F7: =(SUMPRODUCT(DCF!$D$16:$I$16/(1+$B7)^DCF!$D$18:$I$18)+((DCF!$C$23*(1+F$5)-DCF!$C$24*F$5)/($B7-F$5))/(1+$B7)^DCF!$C$27+DCF!$C$45)/Inputs!$C$17*Inputs!$C$6 -> 61.571217 | G7: =(SUMPRODUCT(DCF!$D$16:$I$16/(1+$B7)^DCF!$D$18:$I$18)+((DCF!$C$23*(1+G$5)-DCF!$C$24*G$5)/($B7-G$5))/(1+$B7)^DCF!$C$27+DCF!$C$45)/Inputs!$C$17*Inputs!$C$6 -> 64.45705
B8: =DCF!$C$10+(-0.005) -> 0.107 | C8: =(SUMPRODUCT(DCF!$D$16:$I$16/(1+$B8)^DCF!$D$18:$I$18)+((DCF!$C$23*(1+C$5)-DCF!$C$24*C$5)/($B8-C$5))/(1+$B8)^DCF!$C$27+DCF!$C$45)/Inputs!$C$17*Inputs!$C$6 -> 52.906728 | D8: =(SUMPRODUCT(DCF!$D$16:$I$16/(1+$B8)^DCF!$D$18:$I$18)+((DCF!$C$23*(1+D$5)-DCF!$C$24*D$5)/($B8-D$5))/(1+$B8)^DCF!$C$27+DCF!$C$45)/Inputs!$C$17*Inputs!$C$6 -> 54.6291 | E8: =(SUMPRODUCT(DCF!$D$16:$I$16/(1+$B8)^DCF!$D$18:$I$18)+((DCF!$C$23*(1+E$5)-DCF!$C$24*E$5)/($B8-E$5))/(1+$B8)^DCF!$C$27+DCF!$C$45)/Inputs!$C$17*Inputs!$C$6 -> 56.561517 | F8: =(SUMPRODUCT(DCF!$D$16:$I$16/(1+$B8)^DCF!$D$18:$I$18)+((DCF!$C$23*(1+F$5)-DCF!$C$24*F$5)/($B8-F$5))/(1+$B8)^DCF!$C$27+DCF!$C$45)/Inputs!$C$17*Inputs!$C$6 -> 58.744898 | G8: =(SUMPRODUCT(DCF!$D$16:$I$16/(1+$B8)^DCF!$D$18:$I$18)+((DCF!$C$23*(1+G$5)-DCF!$C$24*G$5)/($B8-G$5))/(1+$B8)^DCF!$C$27+DCF!$C$45)/Inputs!$C$17*Inputs!$C$6 -> 61.231526
B9: =DCF!$C$10+(0) -> 0.112 | C9: =(SUMPRODUCT(DCF!$D$16:$I$16/(1+$B9)^DCF!$D$18:$I$18)+((DCF!$C$23*(1+C$5)-DCF!$C$24*C$5)/($B9-C$5))/(1+$B9)^DCF!$C$27+DCF!$C$45)/Inputs!$C$17*Inputs!$C$6 -> 51.117313 | D9: =(SUMPRODUCT(DCF!$D$16:$I$16/(1+$B9)^DCF!$D$18:$I$18)+((DCF!$C$23*(1+D$5)-DCF!$C$24*D$5)/($B9-D$5))/(1+$B9)^DCF!$C$27+DCF!$C$45)/Inputs!$C$17*Inputs!$C$6 -> 52.646964 | E9: =(SUMPRODUCT(DCF!$D$16:$I$16/(1+$B9)^DCF!$D$18:$I$18)+((DCF!$C$23*(1+E$5)-DCF!$C$24*E$5)/($B9-E$5))/(1+$B9)^DCF!$C$27+DCF!$C$45)/Inputs!$C$17*Inputs!$C$6 -> 54.352438 | F9: =(SUMPRODUCT(DCF!$D$16:$I$16/(1+$B9)^DCF!$D$18:$I$18)+((DCF!$C$23*(1+F$5)-DCF!$C$24*F$5)/($B9-F$5))/(1+$B9)^DCF!$C$27+DCF!$C$45)/Inputs!$C$17*Inputs!$C$6 -> 56.265896 | G9: =(SUMPRODUCT(DCF!$D$16:$I$16/(1+$B9)^DCF!$D$18:$I$18)+((DCF!$C$23*(1+G$5)-DCF!$C$24*G$5)/($B9-G$5))/(1+$B9)^DCF!$C$27+DCF!$C$45)/Inputs!$C$17*Inputs!$C$6 -> 58.427856
B10: =DCF!$C$10+(0.005) -> 0.117 | C10: =(SUMPRODUCT(DCF!$D$16:$I$16/(1+$B10)^DCF!$D$18:$I$18)+((DCF!$C$23*(1+C$5)-DCF!$C$24*C$5)/($B10-C$5))/(1+$B10)^DCF!$C$27+DCF!$C$45)/Inputs!$C$17*Inputs!$C$6 -> 49.505071 | D10: =(SUMPRODUCT(DCF!$D$16:$I$16/(1+$B10)^DCF!$D$18:$I$18)+((DCF!$C$23*(1+D$5)-DCF!$C$24*D$5)/($B10-D$5))/(1+$B10)^DCF!$C$27+DCF!$C$45)/Inputs!$C$17*Inputs!$C$6 -> 50.871108 | E10: =(SUMPRODUCT(DCF!$D$16:$I$16/(1+$B10)^DCF!$D$18:$I$18)+((DCF!$C$23*(1+E$5)-DCF!$C$24*E$5)/($B10-E$5))/(1+$B10)^DCF!$C$27+DCF!$C$45)/Inputs!$C$17*Inputs!$C$6 -> 52.385628 | F10: =(SUMPRODUCT(DCF!$D$16:$I$16/(1+$B10)^DCF!$D$18:$I$18)+((DCF!$C$23*(1+F$5)-DCF!$C$24*F$5)/($B10-F$5))/(1+$B10)^DCF!$C$27+DCF!$C$45)/Inputs!$C$17*Inputs!$C$6 -> 54.074231 | G10: =(SUMPRODUCT(DCF!$D$16:$I$16/(1+$B10)^DCF!$D$18:$I$18)+((DCF!$C$23*(1+G$5)-DCF!$C$24*G$5)/($B10-G$5))/(1+$B10)^DCF!$C$27+DCF!$C$45)/Inputs!$C$17*Inputs!$C$6 -> 55.968761
B11: =DCF!$C$10+(0.01) -> 0.122 | C11: =(SUMPRODUCT(DCF!$D$16:$I$16/(1+$B11)^DCF!$D$18:$I$18)+((DCF!$C$23*(1+C$5)-DCF!$C$24*C$5)/($B11-C$5))/(1+$B11)^DCF!$C$27+DCF!$C$45)/Inputs!$C$17*Inputs!$C$6 -> 48.0451 | D11: =(SUMPRODUCT(DCF!$D$16:$I$16/(1+$B11)^DCF!$D$18:$I$18)+((DCF!$C$23*(1+D$5)-DCF!$C$24*D$5)/($B11-D$5))/(1+$B11)^DCF!$C$27+DCF!$C$45)/Inputs!$C$17*Inputs!$C$6 -> 49.271125 | E11: =(SUMPRODUCT(DCF!$D$16:$I$16/(1+$B11)^DCF!$D$18:$I$18)+((DCF!$C$23*(1+E$5)-DCF!$C$24*E$5)/($B11-E$5))/(1+$B11)^DCF!$C$27+DCF!$C$45)/Inputs!$C$17*Inputs!$C$6 -> 50.623545 | F11: =(SUMPRODUCT(DCF!$D$16:$I$16/(1+$B11)^DCF!$D$18:$I$18)+((DCF!$C$23*(1+F$5)-DCF!$C$24*F$5)/($B11-F$5))/(1+$B11)^DCF!$C$27+DCF!$C$45)/Inputs!$C$17*Inputs!$C$6 -> 52.122966 | G11: =(SUMPRODUCT(DCF!$D$16:$I$16/(1+$B11)^DCF!$D$18:$I$18)+((DCF!$C$23*(1+G$5)-DCF!$C$24*G$5)/($B11-G$5))/(1+$B11)^DCF!$C$27+DCF!$C$45)/Inputs!$C$17*Inputs!$C$6 -> 53.794735
B12: =DCF!$C$10+(0.015) -> 0.127 | C12: =(SUMPRODUCT(DCF!$D$16:$I$16/(1+$B12)^DCF!$D$18:$I$18)+((DCF!$C$23*(1+C$5)-DCF!$C$24*C$5)/($B12-C$5))/(1+$B12)^DCF!$C$27+DCF!$C$45)/Inputs!$C$17*Inputs!$C$6 -> 46.716949 | D12: =(SUMPRODUCT(DCF!$D$16:$I$16/(1+$B12)^DCF!$D$18:$I$18)+((DCF!$C$23*(1+D$5)-DCF!$C$24*D$5)/($B12-D$5))/(1+$B12)^DCF!$C$27+DCF!$C$45)/Inputs!$C$17*Inputs!$C$6 -> 47.822295 | E12: =(SUMPRODUCT(DCF!$D$16:$I$16/(1+$B12)^DCF!$D$18:$I$18)+((DCF!$C$23*(1+E$5)-DCF!$C$24*E$5)/($B12-E$5))/(1+$B12)^DCF!$C$27+DCF!$C$45)/Inputs!$C$17*Inputs!$C$6 -> 49.036008 | F12: =(SUMPRODUCT(DCF!$D$16:$I$16/(1+$B12)^DCF!$D$18:$I$18)+((DCF!$C$23*(1+F$5)-DCF!$C$24*F$5)/($B12-F$5))/(1+$B12)^DCF!$C$27+DCF!$C$45)/Inputs!$C$17*Inputs!$C$6 -> 50.374846 | G12: =(SUMPRODUCT(DCF!$D$16:$I$16/(1+$B12)^DCF!$D$18:$I$18)+((DCF!$C$23*(1+G$5)-DCF!$C$24*G$5)/($B12-G$5))/(1+$B12)^DCF!$C$27+DCF!$C$45)/Inputs!$C$17*Inputs!$C$6 -> 51.85921
A14: Table 2 - DCF value per share (HK$): revenue CAGR FY26E-31E vs. FY2031E EBIT margin (simplified re-computation)
B15: CAGR \ margin | C15: =$C$24+(-0.02) -> 0.02642 | D15: =$C$24+(-0.01) -> 0.03642 | E15: =$C$24+(0) -> 0.04642 | F15: =$C$24+(0.01) -> 0.05642 | G15: =$C$24+(0.02) -> 0.06642
B16: =$C$25+(-0.04) -> 0.021235132 | C16: =(DCF!$D$20+SUMPRODUCT(($C$22*(1+$B16)^$C$21:$G$21*(($C$23+(C$15-$C$23)*$C$21:$G$21/5)*(1-Inputs!$C$52)+$C$26)-$C$27*$C$22*(1+$B16)^($C$21:$G$21-1)*$B16)*DCF!$E$19:$I$19)+(($C$22*(1+$B16)^5*(C$15*(1-Inputs!$C$52)+$C$26)*(1+DCF!$C$11)-$C$27*$C$22*(1+$B16)^5*DCF!$C$11)/(DCF!$C$10-DCF!$C$11))/(1+DCF!$C$10)^DCF!$C$27+DCF!$C$45)/Inputs!$C$17*Inputs!$C$6 -> 35.951072 | D16: =(DCF!$D$20+SUMPRODUCT(($C$22*(1+$B16)^$C$21:$G$21*(($C$23+(D$15-$C$23)*$C$21:$G$21/5)*(1-Inputs!$C$52)+$C$26)-$C$27*$C$22*(1+$B16)^($C$21:$G$21-1)*$B16)*DCF!$E$19:$I$19)+(($C$22*(1+$B16)^5*(D$15*(1-Inputs!$C$52)+$C$26)*(1+DCF!$C$11)-$C$27*$C$22*(1+$B16)^5*DCF!$C$11)/(DCF!$C$10-DCF!$C$11))/(1+DCF!$C$10)^DCF!$C$27+DCF!$C$45)/Inputs!$C$17*Inputs!$C$6 -> 41.612073 | E16: =(DCF!$D$20+SUMPRODUCT(($C$22*(1+$B16)^$C$21:$G$21*(($C$23+(E$15-$C$23)*$C$21:$G$21/5)*(1-Inputs!$C$52)+$C$26)-$C$27*$C$22*(1+$B16)^($C$21:$G$21-1)*$B16)*DCF!$E$19:$I$19)+(($C$22*(1+$B16)^5*(E$15*(1-Inputs!$C$52)+$C$26)*(1+DCF!$C$11)-$C$27*$C$22*(1+$B16)^5*DCF!$C$11)/(DCF!$C$10-DCF!$C$11))/(1+DCF!$C$10)^DCF!$C$27+DCF!$C$45)/Inputs!$C$17*Inputs!$C$6 -> 47.273074 | F16: =(DCF!$D$20+SUMPRODUCT(($C$22*(1+$B16)^$C$21:$G$21*(($C$23+(F$15-$C$23)*$C$21:$G$21/5)*(1-Inputs!$C$52)+$C$26)-$C$27*$C$22*(1+$B16)^($C$21:$G$21-1)*$B16)*DCF!$E$19:$I$19)+(($C$22*(1+$B16)^5*(F$15*(1-Inputs!$C$52)+$C$26)*(1+DCF!$C$11)-$C$27*$C$22*(1+$B16)^5*DCF!$C$11)/(DCF!$C$10-DCF!$C$11))/(1+DCF!$C$10)^DCF!$C$27+DCF!$C$45)/Inputs!$C$17*Inputs!$C$6 -> 52.934074 | G16: =(DCF!$D$20+SUMPRODUCT(($C$22*(1+$B16)^$C$21:$G$21*(($C$23+(G$15-$C$23)*$C$21:$G$21/5)*(1-Inputs!$C$52)+$C$26)-$C$27*$C$22*(1+$B16)^($C$21:$G$21-1)*$B16)*DCF!$E$19:$I$19)+(($C$22*(1+$B16)^5*(G$15*(1-Inputs!$C$52)+$C$26)*(1+DCF!$C$11)-$C$27*$C$22*(1+$B16)^5*DCF!$C$11)/(DCF!$C$10-DCF!$C$11))/(1+DCF!$C$10)^DCF!$C$27+DCF!$C$45)/Inputs!$C$17*Inputs!$C$6 -> 58.595075
B17: =$C$25+(-0.02) -> 0.041235132 | C17: =(DCF!$D$20+SUMPRODUCT(($C$22*(1+$B17)^$C$21:$G$21*(($C$23+(C$15-$C$23)*$C$21:$G$21/5)*(1-Inputs!$C$52)+$C$26)-$C$27*$C$22*(1+$B17)^($C$21:$G$21-1)*$B17)*DCF!$E$19:$I$19)+(($C$22*(1+$B17)^5*(C$15*(1-Inputs!$C$52)+$C$26)*(1+DCF!$C$11)-$C$27*$C$22*(1+$B17)^5*DCF!$C$11)/(DCF!$C$10-DCF!$C$11))/(1+DCF!$C$10)^DCF!$C$27+DCF!$C$45)/Inputs!$C$17*Inputs!$C$6 -> 37.974053 | D17: =(DCF!$D$20+SUMPRODUCT(($C$22*(1+$B17)^$C$21:$G$21*(($C$23+(D$15-$C$23)*$C$21:$G$21/5)*(1-Inputs!$C$52)+$C$26)-$C$27*$C$22*(1+$B17)^($C$21:$G$21-1)*$B17)*DCF!$E$19:$I$19)+(($C$22*(1+$B17)^5*(D$15*(1-Inputs!$C$52)+$C$26)*(1+DCF!$C$11)-$C$27*$C$22*(1+$B17)^5*DCF!$C$11)/(DCF!$C$10-DCF!$C$11))/(1+DCF!$C$10)^DCF!$C$27+DCF!$C$45)/Inputs!$C$17*Inputs!$C$6 -> 44.171246 | E17: =(DCF!$D$20+SUMPRODUCT(($C$22*(1+$B17)^$C$21:$G$21*(($C$23+(E$15-$C$23)*$C$21:$G$21/5)*(1-Inputs!$C$52)+$C$26)-$C$27*$C$22*(1+$B17)^($C$21:$G$21-1)*$B17)*DCF!$E$19:$I$19)+(($C$22*(1+$B17)^5*(E$15*(1-Inputs!$C$52)+$C$26)*(1+DCF!$C$11)-$C$27*$C$22*(1+$B17)^5*DCF!$C$11)/(DCF!$C$10-DCF!$C$11))/(1+DCF!$C$10)^DCF!$C$27+DCF!$C$45)/Inputs!$C$17*Inputs!$C$6 -> 50.368438 | F17: =(DCF!$D$20+SUMPRODUCT(($C$22*(1+$B17)^$C$21:$G$21*(($C$23+(F$15-$C$23)*$C$21:$G$21/5)*(1-Inputs!$C$52)+$C$26)-$C$27*$C$22*(1+$B17)^($C$21:$G$21-1)*$B17)*DCF!$E$19:$I$19)+(($C$22*(1+$B17)^5*(F$15*(1-Inputs!$C$52)+$C$26)*(1+DCF!$C$11)-$C$27*$C$22*(1+$B17)^5*DCF!$C$11)/(DCF!$C$10-DCF!$C$11))/(1+DCF!$C$10)^DCF!$C$27+DCF!$C$45)/Inputs!$C$17*Inputs!$C$6 -> 56.565631 | G17: =(DCF!$D$20+SUMPRODUCT(($C$22*(1+$B17)^$C$21:$G$21*(($C$23+(G$15-$C$23)*$C$21:$G$21/5)*(1-Inputs!$C$52)+$C$26)-$C$27*$C$22*(1+$B17)^($C$21:$G$21-1)*$B17)*DCF!$E$19:$I$19)+(($C$22*(1+$B17)^5*(G$15*(1-Inputs!$C$52)+$C$26)*(1+DCF!$C$11)-$C$27*$C$22*(1+$B17)^5*DCF!$C$11)/(DCF!$C$10-DCF!$C$11))/(1+DCF!$C$10)^DCF!$C$27+DCF!$C$45)/Inputs!$C$17*Inputs!$C$6 -> 62.762824
B18: =$C$25+(0) -> 0.061235132 | C18: =(DCF!$D$20+SUMPRODUCT(($C$22*(1+$B18)^$C$21:$G$21*(($C$23+(C$15-$C$23)*$C$21:$G$21/5)*(1-Inputs!$C$52)+$C$26)-$C$27*$C$22*(1+$B18)^($C$21:$G$21-1)*$B18)*DCF!$E$19:$I$19)+(($C$22*(1+$B18)^5*(C$15*(1-Inputs!$C$52)+$C$26)*(1+DCF!$C$11)-$C$27*$C$22*(1+$B18)^5*DCF!$C$11)/(DCF!$C$10-DCF!$C$11))/(1+DCF!$C$10)^DCF!$C$27+DCF!$C$45)/Inputs!$C$17*Inputs!$C$6 -> 40.145365 | D18: =(DCF!$D$20+SUMPRODUCT(($C$22*(1+$B18)^$C$21:$G$21*(($C$23+(D$15-$C$23)*$C$21:$G$21/5)*(1-Inputs!$C$52)+$C$26)-$C$27*$C$22*(1+$B18)^($C$21:$G$21-1)*$B18)*DCF!$E$19:$I$19)+(($C$22*(1+$B18)^5*(D$15*(1-Inputs!$C$52)+$C$26)*(1+DCF!$C$11)-$C$27*$C$22*(1+$B18)^5*DCF!$C$11)/(DCF!$C$10-DCF!$C$11))/(1+DCF!$C$10)^DCF!$C$27+DCF!$C$45)/Inputs!$C$17*Inputs!$C$6 -> 46.91968 | E18: =(DCF!$D$20+SUMPRODUCT(($C$22*(1+$B18)^$C$21:$G$21*(($C$23+(E$15-$C$23)*$C$21:$G$21/5)*(1-Inputs!$C$52)+$C$26)-$C$27*$C$22*(1+$B18)^($C$21:$G$21-1)*$B18)*DCF!$E$19:$I$19)+(($C$22*(1+$B18)^5*(E$15*(1-Inputs!$C$52)+$C$26)*(1+DCF!$C$11)-$C$27*$C$22*(1+$B18)^5*DCF!$C$11)/(DCF!$C$10-DCF!$C$11))/(1+DCF!$C$10)^DCF!$C$27+DCF!$C$45)/Inputs!$C$17*Inputs!$C$6 -> 53.693994 | F18: =(DCF!$D$20+SUMPRODUCT(($C$22*(1+$B18)^$C$21:$G$21*(($C$23+(F$15-$C$23)*$C$21:$G$21/5)*(1-Inputs!$C$52)+$C$26)-$C$27*$C$22*(1+$B18)^($C$21:$G$21-1)*$B18)*DCF!$E$19:$I$19)+(($C$22*(1+$B18)^5*(F$15*(1-Inputs!$C$52)+$C$26)*(1+DCF!$C$11)-$C$27*$C$22*(1+$B18)^5*DCF!$C$11)/(DCF!$C$10-DCF!$C$11))/(1+DCF!$C$10)^DCF!$C$27+DCF!$C$45)/Inputs!$C$17*Inputs!$C$6 -> 60.468309 | G18: =(DCF!$D$20+SUMPRODUCT(($C$22*(1+$B18)^$C$21:$G$21*(($C$23+(G$15-$C$23)*$C$21:$G$21/5)*(1-Inputs!$C$52)+$C$26)-$C$27*$C$22*(1+$B18)^($C$21:$G$21-1)*$B18)*DCF!$E$19:$I$19)+(($C$22*(1+$B18)^5*(G$15*(1-Inputs!$C$52)+$C$26)*(1+DCF!$C$11)-$C$27*$C$22*(1+$B18)^5*DCF!$C$11)/(DCF!$C$10-DCF!$C$11))/(1+DCF!$C$10)^DCF!$C$27+DCF!$C$45)/Inputs!$C$17*Inputs!$C$6 -> 67.242624
B19: =$C$25+(0.02) -> 0.081235132 | C19: =(DCF!$D$20+SUMPRODUCT(($C$22*(1+$B19)^$C$21:$G$21*(($C$23+(C$15-$C$23)*$C$21:$G$21/5)*(1-Inputs!$C$52)+$C$26)-$C$27*$C$22*(1+$B19)^($C$21:$G$21-1)*$B19)*DCF!$E$19:$I$19)+(($C$22*(1+$B19)^5*(C$15*(1-Inputs!$C$52)+$C$26)*(1+DCF!$C$11)-$C$27*$C$22*(1+$B19)^5*DCF!$C$11)/(DCF!$C$10-DCF!$C$11))/(1+DCF!$C$10)^DCF!$C$27+DCF!$C$45)/Inputs!$C$17*Inputs!$C$6 -> 42.473356 | D19: =(DCF!$D$20+SUMPRODUCT(($C$22*(1+$B19)^$C$21:$G$21*(($C$23+(D$15-$C$23)*$C$21:$G$21/5)*(1-Inputs!$C$52)+$C$26)-$C$27*$C$22*(1+$B19)^($C$21:$G$21-1)*$B19)*DCF!$E$19:$I$19)+(($C$22*(1+$B19)^5*(D$15*(1-Inputs!$C$52)+$C$26)*(1+DCF!$C$11)-$C$27*$C$22*(1+$B19)^5*DCF!$C$11)/(DCF!$C$10-DCF!$C$11))/(1+DCF!$C$10)^DCF!$C$27+DCF!$C$45)/Inputs!$C$17*Inputs!$C$6 -> 49.86806 | E19: =(DCF!$D$20+SUMPRODUCT(($C$22*(1+$B19)^$C$21:$G$21*(($C$23+(E$15-$C$23)*$C$21:$G$21/5)*(1-Inputs!$C$52)+$C$26)-$C$27*$C$22*(1+$B19)^($C$21:$G$21-1)*$B19)*DCF!$E$19:$I$19)+(($C$22*(1+$B19)^5*(E$15*(1-Inputs!$C$52)+$C$26)*(1+DCF!$C$11)-$C$27*$C$22*(1+$B19)^5*DCF!$C$11)/(DCF!$C$10-DCF!$C$11))/(1+DCF!$C$10)^DCF!$C$27+DCF!$C$45)/Inputs!$C$17*Inputs!$C$6 -> 57.262765 | F19: =(DCF!$D$20+SUMPRODUCT(($C$22*(1+$B19)^$C$21:$G$21*(($C$23+(F$15-$C$23)*$C$21:$G$21/5)*(1-Inputs!$C$52)+$C$26)-$C$27*$C$22*(1+$B19)^($C$21:$G$21-1)*$B19)*DCF!$E$19:$I$19)+(($C$22*(1+$B19)^5*(F$15*(1-Inputs!$C$52)+$C$26)*(1+DCF!$C$11)-$C$27*$C$22*(1+$B19)^5*DCF!$C$11)/(DCF!$C$10-DCF!$C$11))/(1+DCF!$C$10)^DCF!$C$27+DCF!$C$45)/Inputs!$C$17*Inputs!$C$6 -> 64.657469 | G19: =(DCF!$D$20+SUMPRODUCT(($C$22*(1+$B19)^$C$21:$G$21*(($C$23+(G$15-$C$23)*$C$21:$G$21/5)*(1-Inputs!$C$52)+$C$26)-$C$27*$C$22*(1+$B19)^($C$21:$G$21-1)*$B19)*DCF!$E$19:$I$19)+(($C$22*(1+$B19)^5*(G$15*(1-Inputs!$C$52)+$C$26)*(1+DCF!$C$11)-$C$27*$C$22*(1+$B19)^5*DCF!$C$11)/(DCF!$C$10-DCF!$C$11))/(1+DCF!$C$10)^DCF!$C$27+DCF!$C$45)/Inputs!$C$17*Inputs!$C$6 -> 72.052173
B20: =$C$25+(0.04) -> 0.10123513 | C20: =(DCF!$D$20+SUMPRODUCT(($C$22*(1+$B20)^$C$21:$G$21*(($C$23+(C$15-$C$23)*$C$21:$G$21/5)*(1-Inputs!$C$52)+$C$26)-$C$27*$C$22*(1+$B20)^($C$21:$G$21-1)*$B20)*DCF!$E$19:$I$19)+(($C$22*(1+$B20)^5*(C$15*(1-Inputs!$C$52)+$C$26)*(1+DCF!$C$11)-$C$27*$C$22*(1+$B20)^5*DCF!$C$11)/(DCF!$C$10-DCF!$C$11))/(1+DCF!$C$10)^DCF!$C$27+DCF!$C$45)/Inputs!$C$17*Inputs!$C$6 -> 44.966689 | D20: =(DCF!$D$20+SUMPRODUCT(($C$22*(1+$B20)^$C$21:$G$21*(($C$23+(D$15-$C$23)*$C$21:$G$21/5)*(1-Inputs!$C$52)+$C$26)-$C$27*$C$22*(1+$B20)^($C$21:$G$21-1)*$B20)*DCF!$E$19:$I$19)+(($C$22*(1+$B20)^5*(D$15*(1-Inputs!$C$52)+$C$26)*(1+DCF!$C$11)-$C$27*$C$22*(1+$B20)^5*DCF!$C$11)/(DCF!$C$10-DCF!$C$11))/(1+DCF!$C$10)^DCF!$C$27+DCF!$C$45)/Inputs!$C$17*Inputs!$C$6 -> 53.027474 | E20: =(DCF!$D$20+SUMPRODUCT(($C$22*(1+$B20)^$C$21:$G$21*(($C$23+(E$15-$C$23)*$C$21:$G$21/5)*(1-Inputs!$C$52)+$C$26)-$C$27*$C$22*(1+$B20)^($C$21:$G$21-1)*$B20)*DCF!$E$19:$I$19)+(($C$22*(1+$B20)^5*(E$15*(1-Inputs!$C$52)+$C$26)*(1+DCF!$C$11)-$C$27*$C$22*(1+$B20)^5*DCF!$C$11)/(DCF!$C$10-DCF!$C$11))/(1+DCF!$C$10)^DCF!$C$27+DCF!$C$45)/Inputs!$C$17*Inputs!$C$6 -> 61.08826 | F20: =(DCF!$D$20+SUMPRODUCT(($C$22*(1+$B20)^$C$21:$G$21*(($C$23+(F$15-$C$23)*$C$21:$G$21/5)*(1-Inputs!$C$52)+$C$26)-$C$27*$C$22*(1+$B20)^($C$21:$G$21-1)*$B20)*DCF!$E$19:$I$19)+(($C$22*(1+$B20)^5*(F$15*(1-Inputs!$C$52)+$C$26)*(1+DCF!$C$11)-$C$27*$C$22*(1+$B20)^5*DCF!$C$11)/(DCF!$C$10-DCF!$C$11))/(1+DCF!$C$10)^DCF!$C$27+DCF!$C$45)/Inputs!$C$17*Inputs!$C$6 -> 69.149045 | G20: =(DCF!$D$20+SUMPRODUCT(($C$22*(1+$B20)^$C$21:$G$21*(($C$23+(G$15-$C$23)*$C$21:$G$21/5)*(1-Inputs!$C$52)+$C$26)-$C$27*$C$22*(1+$B20)^($C$21:$G$21-1)*$B20)*DCF!$E$19:$I$19)+(($C$22*(1+$B20)^5*(G$15*(1-Inputs!$C$52)+$C$26)*(1+DCF!$C$11)-$C$27*$C$22*(1+$B20)^5*DCF!$C$11)/(DCF!$C$10-DCF!$C$11))/(1+DCF!$C$10)^DCF!$C$27+DCF!$C$45)/Inputs!$C$17*Inputs!$C$6 -> 77.20983
A21: Helper: year index k (FY2027E..FY2031E) | C21: 1 | D21: 2 | E21: 3 | F21: 4 | G21: 5
A22: Helper: FY2026E revenue | C22: ='Income Statement'!F6 -> 41882.58
A23: Helper: FY2026E EBIT margin | C23: ='Income Statement'!F30 -> 0.024700953
A24: Helper: FY2031E EBIT margin (base) | C24: ='Income Statement'!K30 -> 0.04642
A25: Helper: FY2026E-31E revenue CAGR (base) | C25: =('Income Statement'!K6/'Income Statement'!F6)^(1/5)-1 -> 0.061235132
A26: Helper: FY2031E (D&A + capex) % revenue | C26: =('DCF Inputs'!K12+'DCF Inputs'!K13)/'Income Statement'!K6 -> -0.0032
A27: Helper: FY2031E NWC % revenue | C27: ='Balance Sheet'!K58/'Income Statement'!K6 -> -0.097617589
A29: Table 3 - P/E value per share (HK$): target multiple vs. FY2027E adj. EPS
B30: P/E \ EPS chg | C30: -0.2 | D30: -0.1 | E30: 0 | F30: 0.1 | G30: 0.2
B31: 10 | C31: =$B31*'Income Statement'!$G$66*(1+C$30) -> 20.593673 | D31: =$B31*'Income Statement'!$G$66*(1+D$30) -> 23.167882 | E31: =$B31*'Income Statement'!$G$66*(1+E$30) -> 25.742091 | F31: =$B31*'Income Statement'!$G$66*(1+F$30) -> 28.316301 | G31: =$B31*'Income Statement'!$G$66*(1+G$30) -> 30.89051
B32: 12 | C32: =$B32*'Income Statement'!$G$66*(1+C$30) -> 24.712408 | D32: =$B32*'Income Statement'!$G$66*(1+D$30) -> 27.801459 | E32: =$B32*'Income Statement'!$G$66*(1+E$30) -> 30.89051 | F32: =$B32*'Income Statement'!$G$66*(1+F$30) -> 33.979561 | G32: =$B32*'Income Statement'!$G$66*(1+G$30) -> 37.068612
B33: 14 | C33: =$B33*'Income Statement'!$G$66*(1+C$30) -> 28.831142 | D33: =$B33*'Income Statement'!$G$66*(1+D$30) -> 32.435035 | E33: =$B33*'Income Statement'!$G$66*(1+E$30) -> 36.038928 | F33: =$B33*'Income Statement'!$G$66*(1+F$30) -> 39.642821 | G33: =$B33*'Income Statement'!$G$66*(1+G$30) -> 43.246714
B34: 16 | C34: =$B34*'Income Statement'!$G$66*(1+C$30) -> 32.949877 | D34: =$B34*'Income Statement'!$G$66*(1+D$30) -> 37.068612 | E34: =$B34*'Income Statement'!$G$66*(1+E$30) -> 41.187346 | F34: =$B34*'Income Statement'!$G$66*(1+F$30) -> 45.306081 | G34: =$B34*'Income Statement'!$G$66*(1+G$30) -> 49.424816
B35: 18 | C35: =$B35*'Income Statement'!$G$66*(1+C$30) -> 37.068612 | D35: =$B35*'Income Statement'!$G$66*(1+D$30) -> 41.702188 | E35: =$B35*'Income Statement'!$G$66*(1+E$30) -> 46.335765 | F35: =$B35*'Income Statement'!$G$66*(1+F$30) -> 50.969341 | G35: =$B35*'Income Statement'!$G$66*(1+G$30) -> 55.602918

Sheet Comps
A1: SHEIN Global Holdings Ltd (0625.HK) - Comps
A2: Trading comparables. Peer data: stockanalysis.com (29/30-Sep-2026); LTM = last reported 12 months; NTM P/E = consensus.
A4: FX (approximate, late-Sep-2026)
A5: EUR / USD | C5: 1.14
A6: USD / SEK | C6: 9.9
A7: USD / JPY | C7: 157.6
A8: GBP / USD | C8: 1.325
A10: Company | B10: Ticker | C10: Segment | D10: Ccy | E10: Price (local) | F10: Mkt cap (bn, local) | G10: Local per US$ | H10: Mkt cap (US$bn) | I10: EV (bn, local) | J10: EV (US$bn) | K10: EV/Sales LTM | L10: EV/EBITDA LTM | M10: EV/EBIT LTM | N10: P/E LTM | O10: P/E NTM | P10: EBITDA margin LTM | Q10: Net margin LTM | R10: Revenue LTM (bn, local) | S10: EBITDA LTM (bn, local) | T10: NI LTM (bn, local)
A11: Inditex | B11: ITX SM | C11: Global apparel | D11: EUR | E11: 54.02 | F11: 165.97 | G11: =1/Comps!$C$5 -> 0.87719298 | H11: =F11/G11 -> 189.2058 | I11: 161.77 | J11: =I11/G11 -> 184.4178 | K11: 3.92 | L11: 14.09 | M11: 19.22 | N11: 25.93 | O11: 23.51 | P11: =S11/R11 -> 0.23679108 | Q11: =T11/R11 -> 0.15535628 | R11: 41.26 | S11: 9.77 | T11: 6.41
A12: H&M | B12: HMB SS | C12: Global apparel | D12: SEK | E12: 159.15 | F12: 250.55 | G12: =Comps!$C$6 -> 9.9 | H12: =F12/G12 -> 25.308081 | I12: 303.49 | J12: =I12/G12 -> 30.655556 | K12: 1.37 | L12: 8.22 | M12: 15.3 | N12: 19.01 | O12: 19.33 | P12: =S12/R12 -> 0.11306317 | Q12: =T12/R12 -> 0.059769074 | R12: 220.85 | S12: 24.97 | T12: 13.2
A13: Fast Retailing | B13: 9983 JP | C13: Global apparel | D13: JPY | E13: 70860 | F13: 21850 | G13: =Comps!$C$7 -> 157.6 | H13: =F13/G13 -> 138.64213 | I13: 20640 | J13: =I13/G13 -> 130.96447 | K13: 5.36 | L13: 22.62 | M13: 29.03 | N13: 42.08 | O13: 38.81 | P13: =S13/R13 -> 0.20126234 | Q13: =T13/R13 -> 0.13506234 | R13: 3850 | S13: 774.86 | T13: 519.99
A14: Zalando | B14: ZAL GY | C14: Online fashion | D14: EUR | E14: 22.44 | F14: 5.27 | G14: =1/Comps!$C$5 -> 0.87719298 | H14: =F14/G14 -> 6.0078 | I14: 5.18 | J14: =I14/G14 -> 5.9052 | K14: 0.38 | L14: 6.38 | M14: 12.36 | N14: 59.31 | O14: 12.87 | P14: =S14/R14 -> 0.048408586 | Q14: =T14/R14 -> 0.0070170244 | R14: 13.51 | S14: 0.654 | T14: 0.0948
A15: ASOS | B15: ASC LN | C15: Online fashion | D15: GBP | E15: 4.915 | F15: 0.584 | G15: =1/Comps!$C$8 -> 0.75471698 | H15: =F15/G15 -> 0.7738 | I15: 1.1 | J15: =I15/G15 -> 1.4575 | K15: 0.48 | L15: n.m. | M15: n.m. | N15: n.m. | O15: n.m. | P15: =S15/R15 -> -0.031834061 | Q15: =T15/R15 -> -0.10082969 | R15: 2.29 | S15: -0.0729 | T15: -0.2309
A16: Revolve | B16: RVLV US | C16: Online fashion | D16: USD | E16: 21.27 | F16: 1.51 | G16: =1 -> 1 | H16: =F16/G16 -> 1.51 | I16: 1.23 | J16: =I16/G16 -> 1.23 | K16: 0.94 | L16: 14.12 | M16: 15.02 | N16: 20.98 | O16: 21.2 | P16: =S16/R16 -> 0.066564885 | Q16: =T16/R16 -> 0.055419847 | R16: 1.31 | S16: 0.0872 | T16: 0.0726
A17: PDD Holdings (Temu) | B17: PDD US | C17: E-commerce platforms | D17: USD | E17: 77.5 | F17: 110.31 | G17: =1 -> 1 | H17: =F17/G17 -> 110.31 | I17: 43.84 | J17: =I17/G17 -> 43.84 | K17: 0.66 | L17: 3 | M17: 3.02 | N17: 8.46 | O17: 6.8 | P17: =S17/R17 -> 0.21986136 | Q17: =T17/R17 -> 0.20418927 | R17: 66.36 | S17: 14.59 | T17: 13.55
A18: Alibaba (AliExpress) | B18: BABA US | C18: E-commerce platforms | D18: USD | E18: 107.74 | F18: 267.8 | G18: =1 -> 1 | H18: =F18/G18 -> 267.8 | I18: 250.26 | J18: =I18/G18 -> 250.26 | K18: 1.63 | L18: 17.08 | M18: 35.7 | N18: 24.59 | O18: 13.63 | P18: =S18/R18 -> 0.095228809 | Q18: =T18/R18 -> 0.070137806 | R18: 153.84 | S18: 14.65 | T18: 10.79
A19: JD.com | B19: JD US | C19: E-commerce platforms | D19: USD | E19: 26.3 | F19: 35.35 | G19: =1 -> 1 | H19: =F19/G19 -> 35.35 | I19: 12.57 | J19: =I19/G19 -> 12.57 | K19: 0.06 | L19: 7.23 | M19: 38.98 | N19: 18.12 | O19: 6.39 | P19: =S19/R19 -> 0.0089987588 | Q19: =T19/R19 -> 0.011274307 | R19: 193.36 | S19: 1.74 | T19: 2.18
A20: Amazon | B20: AMZN US | C20: E-commerce platforms | D20: USD | E20: 246.67 | F20: 2660 | G20: =1 -> 1 | H20: =F20/G20 -> 2660 | I20: 2790 | J20: =I20/G20 -> 2790 | K20: 3.6 | L20: 16.51 | M20: 29.76 | N20: 19.84 | O20: 26.3 | P20: =S20/R20 -> 0.21775732 | Q20: =T20/R20 -> 0.17440182 | R20: 775.68 | S20: 168.91 | T20: 135.28
A21: MercadoLibre | B21: MELI US | C21: E-commerce platforms | D21: USD | E21: 1724.9 | F21: 87.45 | G21: =1 -> 1 | H21: =F21/G21 -> 87.45 | I21: 94.91 | J21: =I21/G21 -> 94.91 | K21: 2.7 | L21: 24.39 | M21: 32.65 | N21: 46.94 | O21: 40.95 | P21: =S21/R21 -> 0.11057419 | Q21: =T21/R21 -> 0.052870949 | R21: 35.18 | S21: 3.89 | T21: 1.86
A22: SHEIN (at current price) | B22: 0625 HK | C22: Subject | D22: HKD | E22: =Inputs!$C$5 -> 30.84 | F22: =Inputs!$C$19/1000 -> 136.2892 | G22: =Inputs!$C$6 -> 7.845 | H22: =F22/G22 -> 17.372748 | I22: =J22*G22 -> 27.271965 | J22: =C43/1000 -> 3.4763499 | K22: =J22*1000/C37 -> 0.082689514 | L22: =J22*1000/C39 -> 2.2002214 | M22: =J22*1000/C38 -> 3.0124349 | N22: =H22*1000/C40 -> 14.574453 | O22: =H22*1000/C41 -> 12.583635 | P22: =S22/R22 -> 0.03758236 | Q22: =T22/R22 -> 0.028353274 | R22: =C37/1000*G22 -> 329.81164 | S22: =C39/1000*G22 -> 12.3951 | T22: =C40/1000*G22 -> 9.35124
A24: Statistical summary (11 peers)
A25: Maximum | H25: =MAX(H11:H21) -> 2660 | J25: =MAX(J11:J21) -> 2790 | K25: =MAX(K11:K21) -> 5.36 | L25: =MAX(L11:L21) -> 24.39 | M25: =MAX(M11:M21) -> 38.98 | N25: =MAX(N11:N21) -> 59.31 | O25: =MAX(O11:O21) -> 40.95 | P25: =MAX(P11:P21) -> 0.23679108 | Q25: =MAX(Q11:Q21) -> 0.20418927
A26: 75th percentile | H26: =QUARTILE(H11:H21,3) -> 163.92397 | J26: =QUARTILE(J11:J21,3) -> 157.69113 | K26: =QUARTILE(K11:K21,3) -> 3.15 | L26: =QUARTILE(L11:L21,3) -> 16.9375 | M26: =QUARTILE(M11:M21,3) -> 31.9275 | N26: =QUARTILE(N11:N21,3) -> 38.0425 | O26: =QUARTILE(O11:O21,3) -> 25.6025 | P26: =QUARTILE(P11:P21,3) -> 0.20950983 | Q26: =QUARTILE(Q11:Q21,3) -> 0.14520931
A27: Median | H27: =MEDIAN(H11:H21) -> 87.45 | J27: =MEDIAN(J11:J21) -> 43.84 | K27: =MEDIAN(K11:K21) -> 1.37 | L27: =MEDIAN(L11:L21) -> 14.105 | M27: =MEDIAN(M11:M21) -> 24.125 | N27: =MEDIAN(N11:N21) -> 22.785 | O27: =MEDIAN(O11:O21) -> 20.265 | P27: =MEDIAN(P11:P21) -> 0.11057419 | Q27: =MEDIAN(Q11:Q21) -> 0.059769074
A28: 25th percentile | H28: =QUARTILE(H11:H21,1) -> 15.65794 | J28: =QUARTILE(J11:J21,1) -> 9.2376 | K28: =QUARTILE(K11:K21,1) -> 0.57 | L28: =QUARTILE(L11:L21,1) -> 7.4775 | M28: =QUARTILE(M11:M21,1) -> 15.09 | N28: =QUARTILE(N11:N21,1) -> 19.2175 | O28: =QUARTILE(O11:O21,1) -> 13.06 | P28: =QUARTILE(P11:P21,1) -> 0.057486736 | Q28: =QUARTILE(Q11:Q21,1) -> 0.032072628
A29: Minimum | H29: =MIN(H11:H21) -> 0.7738 | J29: =MIN(J11:J21) -> 1.23 | K29: =MIN(K11:K21) -> 0.06 | L29: =MIN(L11:L21) -> 3 | M29: =MIN(M11:M21) -> 3.02 | N29: =MIN(N11:N21) -> 8.46 | O29: =MIN(O11:O21) -> 6.39 | P29: =MIN(P11:P21) -> -0.031834061 | Q29: =MIN(Q11:Q21) -> -0.10082969
A31: Segment medians
A32: Global apparel | K32: =MEDIAN(K11,K12,K13) -> 3.92 | L32: =MEDIAN(L11,L12,L13) -> 14.09 | M32: =MEDIAN(M11,M12,M13) -> 19.22 | N32: =MEDIAN(N11,N12,N13) -> 25.93 | O32: =MEDIAN(O11,O12,O13) -> 23.51 | P32: =MEDIAN(P11,P12,P13) -> 0.20126234 | Q32: =MEDIAN(Q11,Q12,Q13) -> 0.13506234
A33: Online fashion | K33: =MEDIAN(K14,K15,K16) -> 0.48 | L33: =MEDIAN(L14,L15,L16) -> 10.25 | M33: =MEDIAN(M14,M15,M16) -> 13.69 | N33: =MEDIAN(N14,N15,N16) -> 40.145 | O33: =MEDIAN(O14,O15,O16) -> 17.035 | P33: =MEDIAN(P14,P15,P16) -> 0.048408586 | Q33: =MEDIAN(Q14,Q15,Q16) -> 0.0070170244
A34: E-commerce platforms | K34: =MEDIAN(K17,K18,K19,K20,K21) -> 1.63 | L34: =MEDIAN(L17,L18,L19,L20,L21) -> 16.51 | M34: =MEDIAN(M17,M18,M19,M20,M21) -> 32.65 | N34: =MEDIAN(N17,N18,N19,N20,N21) -> 19.84 | O34: =MEDIAN(O17,O18,O19,O20,O21) -> 13.63 | P34: =MEDIAN(P17,P18,P19,P20,P21) -> 0.11057419 | Q34: =MEDIAN(Q17,Q18,Q19,Q20,Q21) -> 0.070137806
A36: SHEIN LTM (12 months to 30-Jun-2026) and NTM inputs (US$m)
A37: LTM net revenues | C37: ='Income Statement'!E6-Interim!D9+Interim!I9 -> 42041
A38: LTM EBIT | C38: ='Income Statement'!E29-Interim!D39+Interim!I39 -> 1154
A39: LTM EBITDA (IFRS 16) | C39: =C38+'Income Statement'!E36-Interim!D58+Interim!I58+'Income Statement'!E38-Interim!D59+Interim!I59 -> 1580
A40: LTM adjusted net income | C40: ='Income Statement'!E58-Interim!D55+Interim!I55 -> 1192
A41: NTM adjusted net income (0.25 x FY26E + 0.75 x FY27E) | C41: =0.25*'Income Statement'!F58+0.75*'Income Statement'!G58 -> 1380.5826
A42: NTM adjusted EPS (HK$) | C42: =C41/Inputs!$C$17*Inputs!$C$6 -> 2.4508021
A43: SHEIN EV for comps (mkt cap - pro forma cash - investments) | C43: =Inputs!$C$20-Inputs!$C$30-Inputs!$C$33 -> 3476.3499
A45: Implied SHEIN value per share from peer multiples (HK$)
A46: Method | C46: Multiple | D46: HK$/sh | E46: vs. price
A47: All-peer median P/E NTM x SHEIN NTM EPS | C47: =O27 -> 20.265 | D47: =C47*C42 -> 49.665505 | E47: =D47/Inputs!$C$5-1 -> 0.61042495
A48: Global apparel median P/E NTM x NTM EPS | C48: =O32 -> 23.51 | D48: =C48*C42 -> 57.618358 | E48: =D48/Inputs!$C$5-1 -> 0.86829956
A49: Online fashion median P/E NTM x NTM EPS | C49: =O33 -> 17.035 | D49: =C49*C42 -> 41.749414 | E49: =D49/Inputs!$C$5-1 -> 0.35374236
A50: E-commerce platforms median P/E NTM x NTM EPS | C50: =O34 -> 13.63 | D50: =C50*C42 -> 33.404433 | E50: =D50/Inputs!$C$5-1 -> 0.083152827
A51: All-peer median EV/EBIT LTM x FY2027E adj. EBIT + net cash | C51: =M27 -> 24.125 | D51: =(C51*'Income Statement'!G33+Inputs!$C$30+Inputs!$C$33)/Inputs!$C$17*Inputs!$C$6 -> 84.842497 | E51: =D51/Inputs!$C$5-1 -> 1.7510537

Sheet Valuation Summary
A1: SHEIN Global Holdings Ltd (0625.HK) - Valuation Summary
A2: Price target = weighted DCF and P/E; rating from upside thresholds on the Inputs tab.
A4: Price target derivation
A5: Current share price (HK$, 30-Sep-2026) | C5: =Inputs!$C$5 -> 30.84
A6: DCF value per share (HK$) | C6: =DCF!C49 -> 54.352438 | D6: =Inputs!$C$55 -> 0.5 | E6: Weight in column D
A7: P/E value per share (HK$): target P/E x FY2027E adj. EPS | C7: =Inputs!$C$54*'Income Statement'!G66 -> 36.038928 | D7: =Inputs!$C$56 -> 0.5
A8: Weighted value per share (HK$) | C8: =C6*D6+C7*D7 -> 45.195683
A9: 12-month price target (HK$, rounded to nearest HK$0.50) | C9: =ROUND(C8*2,0)/2 -> 45
A10: Upside / (downside) | C10: =C9/C5-1 -> 0.45914397
A11: Rating | C11: =IF(C10>Inputs!$C$57,"BUY",IF(C10<Inputs!$C$58,"SELL","HOLD")) -> BUY
A12: Implied P/E at target (FY2026E / FY2027E adj. EPS) | C12: =C9/'Income Statement'!F66 -> 22.037564 | D12: =C9/'Income Statement'!G66 -> 17.481097
A13: Implied market cap at target (US$m) | C13: =C9*Inputs!$C$17/Inputs!$C$6 -> 25349.34
A14: Implied EV at target, ex pro forma cash (US$m) | C14: =C13-Inputs!$C$30-Inputs!$C$33 -> 11452.942
A15: Implied EV / FY2027E adj. EBIT at target | C15: =C14/'Income Statement'!G33 -> 8.1512381
A17: Valuation football field (HK$ per share)
C18: Low | D18: High | E18: Basis
A19: Trading range since listing | C19: =Inputs!$C$11 -> 29.9 | D19: =Inputs!$C$10 -> 48.56 | E19: 1-30 Sep 2026
A20: IPO indicative price range | C20: =Inputs!$C$8 -> 47.6 | D20: =Inputs!$C$9 -> 49.5 | E20: Final HK$48.56
A21: DCF (WACC +/-0.5pp, g +/-0.5pp) | C21: =MIN(Sensitivity!D8:F10) -> 50.871108 | D21: =MAX(Sensitivity!D8:F10) -> 58.744898 | E21: Sensitivity tab
A22: P/E 12x-16x FY2027E adj. EPS | C22: =12*'Income Statement'!G66 -> 30.89051 | D22: =16*'Income Statement'!G66 -> 41.187346 | E22: Target 14x
A23: Peer P/E NTM, 25th-75th percentile x NTM EPS | C23: =Comps!O28*Comps!C42 -> 32.007476 | D23: =Comps!O26*Comps!C42 -> 62.746662 | E23: Comps tab
A24: EV / FY2027E adj. EBIT 8x-12x + valuation net cash | C24: =(8*'Income Statement'!G33+Inputs!$C$35)/Inputs!$C$17*Inputs!$C$6 -> 40.184789 | D24: =(12*'Income Statement'!G33+Inputs!$C$35)/Inputs!$C$17*Inputs!$C$6 -> 50.161775 | E24: ~50% discount to peer median EV/EBIT
A25: Scenario blended value (Bear to Bull) | C25: =Scenarios!E76 -> 29.638547 | D25: =Scenarios!C76 -> 61.324625 | E25: Scenarios tab
A26: Current price | C26: =Inputs!$C$5 -> 30.84 | D26: =Inputs!$C$5 -> 30.84
A27: Price target | C27: =C9 -> 45 | D27: =C9 -> 45
A29: Key financials and valuation (US$m unless stated)
C30: FY2024A | D30: FY2025A | E30: FY2026E | F30: FY2027E | G30: FY2028E | H30: FY2029E
A31: Net revenues | C31: ='Income Statement'!D6 -> 38748 | D31: ='Income Statement'!E6 -> 41847 | E31: ='Income Statement'!F6 -> 41882.58 | F31: ='Income Statement'!G6 -> 43889.542 | G31: ='Income Statement'!H6 -> 46959.938 | H31: ='Income Statement'!I6 -> 50174.583
A32: YoY growth | C32: ='Income Statement'!D7 -> 0.20699 | D32: ='Income Statement'!E7 -> 0.079978321 | E32: ='Income Statement'!F7 -> 0.00085024016 | F32: ='Income Statement'!G7 -> 0.047918767 | G32: ='Income Statement'!H7 -> 0.069957366 | H32: ='Income Statement'!I7 -> 0.068455046
A33: Adjusted EBIT | C33: ='Income Statement'!D33 -> 1037 | D33: ='Income Statement'!E33 -> 1792 | E33: ='Income Statement'!F33 -> 1124.5396 | F33: ='Income Statement'!G33 -> 1405.0555 | G33: ='Income Statement'!H33 -> 1856.6057 | H33: ='Income Statement'!I33 -> 2260.2318
A34: Adjusted EBIT margin | C34: ='Income Statement'!D34 -> 0.026762672 | D34: ='Income Statement'!E34 -> 0.042822664 | E34: ='Income Statement'!F34 -> 0.026849818 | F34: ='Income Statement'!G34 -> 0.032013447 | G34: ='Income Statement'!H34 -> 0.039535948 | H34: ='Income Statement'!I34 -> 0.045047345
A35: Net income (IFRS) | C35: ='Income Statement'!D54 -> 3365 | D35: ='Income Statement'!E54 -> 2064 | E35: ='Income Statement'!F54 -> 6928.587 | F35: ='Income Statement'!G54 -> 1357.3506 | G35: ='Income Statement'!H54 -> 1706.6943 | H35: ='Income Statement'!I54 -> 2035.2427
A36: Adjusted net income | C36: ='Income Statement'!D58 -> 1119 | D36: ='Income Statement'!E58 -> 1816 | E36: ='Income Statement'!F58 -> 1150.2787 | F36: ='Income Statement'!G58 -> 1457.3506 | G36: ='Income Statement'!H58 -> 1811.6943 | H36: ='Income Statement'!I58 -> 2145.2427
A37: Adjusted diluted EPS (HK$) | C37: ='Income Statement'!D66 -> 1.9864423 | D37: ='Income Statement'!E66 -> 3.2237526 | E37: ='Income Statement'!F66 -> 2.041968 | F37: ='Income Statement'!G66 -> 2.5742091 | G37: ='Income Statement'!H66 -> 3.1841877 | H37: ='Income Statement'!I66 -> 3.7516654
A38: DPS declared (HK$) | C38: ='Income Statement'!D70 -> 0 | D38: ='Income Statement'!E70 -> 0 | E38: ='Income Statement'!F70 -> 1.020984 | F38: ='Income Statement'!G70 -> 1.2871046 | G38: ='Income Statement'!H70 -> 1.5920939 | H38: ='Income Statement'!I70 -> 1.8758327
A39: FCF incl. interest | C39: ='Cash Flow'!D48 -> 1510 | D39: ='Cash Flow'!E48 -> 2897 | E39: ='Cash Flow'!F48 -> 1058.486 | F39: ='Cash Flow'!G48 -> 1568.1932 | G39: ='Cash Flow'!H48 -> 2011.1191 | H39: ='Cash Flow'!I48 -> 2354.3314
A40: Cash resources (year-end) | C40: ='Balance Sheet'!D56 -> 11721 | D40: ='Balance Sheet'!E56 -> 14786 | E40: ='Balance Sheet'!F56 -> 13915.884 | F40: ='Balance Sheet'!G56 -> 14908.938 | G40: ='Balance Sheet'!H56 -> 16191.381 | H40: ='Balance Sheet'!I56 -> 17639.866
A41: P/E on adjusted EPS (x) | C41: =Inputs!$C$5/'Income Statement'!D66 -> 15.525244 | D41: =Inputs!$C$5/'Income Statement'!E66 -> 9.5664909 | E41: =Inputs!$C$5/'Income Statement'!F66 -> 15.103077 | F41: =Inputs!$C$5/'Income Statement'!G66 -> 11.980379 | G41: =Inputs!$C$5/'Income Statement'!H66 -> 9.6853586 | H41: =Inputs!$C$5/'Income Statement'!I66 -> 8.2203492
A42: EV / adjusted EBIT (x); EV = mkt cap - pro forma cash | C42: =(Inputs!$C$20-Inputs!$C$30-Inputs!$C$33)/'Income Statement'!D33 -> 3.3523142 | D42: =(Inputs!$C$20-Inputs!$C$30-Inputs!$C$33)/'Income Statement'!E33 -> 1.9399274 | E42: =(Inputs!$C$20-Inputs!$C$30-Inputs!$C$33)/'Income Statement'!F33 -> 3.0913538 | F42: =(Inputs!$C$20-Inputs!$C$30-Inputs!$C$33)/'Income Statement'!G33 -> 2.4741726 | G42: =(Inputs!$C$20-Inputs!$C$30-Inputs!$C$33)/'Income Statement'!H33 -> 1.8724223 | H42: =(Inputs!$C$20-Inputs!$C$30-Inputs!$C$33)/'Income Statement'!I33 -> 1.5380502
A43: Dividend yield (declared basis) | C43: ='Income Statement'!D70/Inputs!$C$5 -> 0 | D43: ='Income Statement'!E70/Inputs!$C$5 -> 0 | E43: ='Income Statement'!F70/Inputs!$C$5 -> 0.033105836 | F43: ='Income Statement'!G70/Inputs!$C$5 -> 0.041734908 | G43: ='Income Statement'!H70/Inputs!$C$5 -> 0.051624315 | H43: ='Income Statement'!I70/Inputs!$C$5 -> 0.060824666
A44: FCF yield (incl. interest) | C44: ='Cash Flow'!D48/Inputs!$C$20 -> 0.086917743 | D44: ='Cash Flow'!E48/Inputs!$C$20 -> 0.16675543 | E44: ='Cash Flow'!F48/Inputs!$C$20 -> 0.060927956 | F44: ='Cash Flow'!G48/Inputs!$C$20 -> 0.090267424 | G44: ='Cash Flow'!H48/Inputs!$C$20 -> 0.11576287 | H44: ='Cash Flow'!I48/Inputs!$C$20 -> 0.13551865

Sheet Checks
A1: SHEIN Global Holdings Ltd (0625.HK) - Checks
A2: TRUE = pass. Overall flag feeds the Cover tab.
C4: FY2023A | D4: FY2024A | E4: FY2025A | F4: FY2026E | G4: FY2027E | H4: FY2028E | I4: FY2029E | J4: FY2030E | K4: FY2031E
A5: Balance sheet balances | C5: =ABS('Balance Sheet'!C42)<0.5 -> TRUE | D5: =ABS('Balance Sheet'!D42)<0.5 -> TRUE | E5: =ABS('Balance Sheet'!E42)<0.5 -> TRUE | F5: =ABS('Balance Sheet'!F42)<0.5 -> TRUE | G5: =ABS('Balance Sheet'!G42)<0.5 -> TRUE | H5: =ABS('Balance Sheet'!H42)<0.5 -> TRUE | I5: =ABS('Balance Sheet'!I42)<0.5 -> TRUE | J5: =ABS('Balance Sheet'!J42)<0.5 -> TRUE | K5: =ABS('Balance Sheet'!K42)<0.5 -> TRUE
A6: Cash-flow ending cash = balance-sheet cash | C6: =ABS('Cash Flow'!C45-'Balance Sheet'!C6)<0.5 -> TRUE | D6: =ABS('Cash Flow'!D45-'Balance Sheet'!D6)<0.5 -> TRUE | E6: =ABS('Cash Flow'!E45-'Balance Sheet'!E6)<0.5 -> TRUE | F6: =ABS('Cash Flow'!F45-'Balance Sheet'!F6)<0.5 -> TRUE | G6: =ABS('Cash Flow'!G45-'Balance Sheet'!G6)<0.5 -> TRUE | H6: =ABS('Cash Flow'!H45-'Balance Sheet'!H6)<0.5 -> TRUE | I6: =ABS('Cash Flow'!I45-'Balance Sheet'!I6)<0.5 -> TRUE | J6: =ABS('Cash Flow'!J45-'Balance Sheet'!J6)<0.5 -> TRUE | K6: =ABS('Cash Flow'!K45-'Balance Sheet'!K6)<0.5 -> TRUE
A7: Revenue: geography = business model | C7: =ABS('Revenue Model'!C49)<0.5 -> TRUE | D7: =ABS('Revenue Model'!D49)<0.5 -> TRUE | E7: =ABS('Revenue Model'!E49)<0.5 -> TRUE | F7: =ABS('Revenue Model'!F49)<0.5 -> TRUE | G7: =ABS('Revenue Model'!G49)<0.5 -> TRUE | H7: =ABS('Revenue Model'!H49)<0.5 -> TRUE | I7: =ABS('Revenue Model'!I49)<0.5 -> TRUE | J7: =ABS('Revenue Model'!J49)<0.5 -> TRUE | K7: =ABS('Revenue Model'!K49)<0.5 -> TRUE
A8: Revenue: geography = category | C8: =ABS('Revenue Model'!C50)<0.5 -> TRUE | D8: =ABS('Revenue Model'!D50)<0.5 -> TRUE | E8: =ABS('Revenue Model'!E50)<0.5 -> TRUE | F8: =ABS('Revenue Model'!F50)<0.5 -> TRUE | G8: =ABS('Revenue Model'!G50)<0.5 -> TRUE | H8: =ABS('Revenue Model'!H50)<0.5 -> TRUE | I8: =ABS('Revenue Model'!I50)<0.5 -> TRUE | J8: =ABS('Revenue Model'!J50)<0.5 -> TRUE | K8: =ABS('Revenue Model'!K50)<0.5 -> TRUE
A9: Historical net income ties to Accountants' Report | C9: =ABS('Income Statement'!C54-CHOOSE(COLUMN()-2,2789,3365,2064))<0.5 -> TRUE | D9: =ABS('Income Statement'!D54-CHOOSE(COLUMN()-2,2789,3365,2064))<0.5 -> TRUE | E9: =ABS('Income Statement'!E54-CHOOSE(COLUMN()-2,2789,3365,2064))<0.5 -> TRUE
A10: Historical operating income ties to Accountants' Report | C10: =ABS('Income Statement'!C29-CHOOSE(COLUMN()-2,1376,966,1707))<0.5 -> TRUE | D10: =ABS('Income Statement'!D29-CHOOSE(COLUMN()-2,1376,966,1707))<0.5 -> TRUE | E10: =ABS('Income Statement'!E29-CHOOSE(COLUMN()-2,1376,966,1707))<0.5 -> TRUE
A11: Historical CFO ties to Accountants' Report | C11: =ABS('Cash Flow'!C24-CHOOSE(COLUMN()-2,1757,1405,2838))<0.5 -> TRUE | D11: =ABS('Cash Flow'!D24-CHOOSE(COLUMN()-2,1757,1405,2838))<0.5 -> TRUE | E11: =ABS('Cash Flow'!E24-CHOOSE(COLUMN()-2,1757,1405,2838))<0.5 -> TRUE
A12: Historical CFI ties to Accountants' Report | C12: =ABS('Cash Flow'!C32-CHOOSE(COLUMN()-2,-4168,-1820,-1066))<0.5 -> TRUE | D12: =ABS('Cash Flow'!D32-CHOOSE(COLUMN()-2,-4168,-1820,-1066))<0.5 -> TRUE | E12: =ABS('Cash Flow'!E32-CHOOSE(COLUMN()-2,-4168,-1820,-1066))<0.5 -> TRUE
A13: Historical total assets tie to Accountants' Report | C13: =ABS('Balance Sheet'!C24-CHOOSE(COLUMN()-2,14818,17321,20033))<0.5 -> TRUE | D13: =ABS('Balance Sheet'!D24-CHOOSE(COLUMN()-2,14818,17321,20033))<0.5 -> TRUE | E13: =ABS('Balance Sheet'!E24-CHOOSE(COLUMN()-2,14818,17321,20033))<0.5 -> TRUE
A14: 1H26 revenue / op. income / NI / adj. NI tie to Interim Report | C14: =AND(ABS(Interim!I9-20134)<0.5,ABS(Interim!I39-493)<0.5,ABS(Interim!I53-2299)<0.5,ABS(Interim!I55-499)<0.5) -> TRUE
A15: 1H25 revenue / op. income / NI / adj. NI tie to Interim Report | C15: =AND(ABS(Interim!D9-19940)<0.5,ABS(Interim!D39-1046)<0.5,ABS(Interim!D53-1086)<0.5,ABS(Interim!D55-1123)<0.5) -> TRUE
A16: 30-Jun-2026 cash resources tie to Interim Report (US$15,248m) | C16: =ABS(Interim!I87-15248)<0.5 -> TRUE
A17: FY2026E = 1H26A + 2H26E (revenue) | F17: =ABS('Income Statement'!F6-Interim!I9-Interim!J9)<0.5 -> TRUE
A18: Scenario selector is 1, 2 or 3 | C18: =OR(Scenarios!C4=1,Scenarios!C4=2,Scenarios!C4=3) -> TRUE
A19: Net equity from conversion = converted shares x IPO price | F19: =ABS('Balance Sheet'!F47+'Balance Sheet'!F48+'Balance Sheet'!F49-Inputs!$C$39*Inputs!$C$7/Inputs!$C$6)<0.5 -> TRUE
A20: ALL CHECKS PASS | C20: =AND(C5:K19) -> TRUE
